Workbook
Name p_ke: Inputs!$D$6
Name p_kd: Inputs!$D$7
Name p_wacc: Inputs!$D$8
Name p_tir: Inputs!$D$9
Name p_rcsd: Inputs!$D$10
Name p_crsd: Inputs!$D$11
Name p_ir: Inputs!$D$12
Name p_pt: Inputs!$D$13
Name p_arr: Inputs!$D$14
Name p_ipm: Inputs!$D$15
Name p_fx: Inputs!$D$16
Name p_ref: Inputs!$D$17
Name p_precio: Inputs!$D$18
Name p_margen_om: Inputs!$D$19

Sheet Resumen
B2: Resumen del modelo, APP autofinanciada por hitos
B3: No hay PPDI ni PPDMO: el proyecto se paga con la tarifa al usuario.
B6: Tarifa al usuario, S/ miles por kg DBO5 | D6: =p_precio
B7: Referencia mensual de ingreso | D7: =p_ref
B8: Ingreso tarifario, primer ano de operacion | D8: 30961.252
B9: Activo intangible al termino de obra | D9: ='Activo intangible'!$D$8
B10: Amortizacion lineal mensual | D10: ='Activo intangible'!$D$10
B11: Saldo final del intangible, debe ser cero | D11: ='Activo intangible'!$AC$16
B12: VAN financiero, debe ser cero | D12: =Flujo!$D$29
B13: Ke | D13: =p_ke
B14: Kd | D14: =p_kd
B15: WACC | D15: =p_wacc

Sheet Inputs
B2: Parametros del modelo
B3: Las celdas en ambar son de entrada. Las dos ultimas las resuelve el cierre.
B6: Ke, costo del patrimonio | D6: 0.12622649 | E6: CAPM en USD + riesgo pais + devaluacion
B7: Kd, costo de la deuda | D7: 0.10092957 | E7: soberano a vida media + spread
B8: WACC | D8: 0.097303479 | E8: despues de impuestos
B9: TIR objetivo del cierre | D9: 0.1262 | E9: Ke redondeado a 4 decimales, Control!M12
B10: Cobertura minima, RCSD | D10: 1.25 | E10: dimensiona la amortizacion
B11: Cuenta de reserva, CRSD | D11: 0.5 | E11: del servicio del ano siguiente
B12: Impuesto a la Renta | D12: 0.295
B13: Participacion de trabajadores | D13: 0.05
B14: Arrastre de perdidas | D14: 0.5 | E14: sistema B
B15: IPM, reajuste | D15: 0.0267 | E15: anual
B16: Tipo de cambio | D16: 0 | E16: solo entra por los reembolsos en dolares
B17: PPDMO referencia mensual | D17: 3109.2149 | E17: S/ - LA CIERRA Solver
B18: Tarifa al usuario | D18: 0.011688778 | E18: S/ por kg DBO5, derivada de la referencia
B19: Margen del operador | D19: 0.15 | E19: sobre todo el costo de O&M; aca no hay pata fija y variable

Sheet Hitos
B2: Hitos funcionales
B3: Sin PPDI los hitos solo reparten la inversion: no hay cuota que cobrar y no escalonan el inicio de la operacion.
B5: Hito | C5: % del CAPEX | D5: Inversion del hito
B6: Hito 1 | C6: 0.45 | D6: ='Activo intangible'!$D$7*C6
B7: Hito 2 | C7: 0.2 | D7: ='Activo intangible'!$D$7*C7
B8: Hito 3 | C8: 0.2 | D8: ='Activo intangible'!$D$7*C8
B9: Hito 4 | C9: 0.15 | D9: ='Activo intangible'!$D$7*C9
B10: Total | C10: =SUM(C6:C9) | D10: =SUM(D6:D9)

Sheet Activo intangible
B2: Activo intangible de la concesion
B3: CINIIF 12 p.17 y p.22. La amortizacion es gasto deducible y NO es caja.
B6: Inversion capitalizada | D6: 212556.28 | E6: CAPEX, otros del periodo D+C+PM y comisiones
B7: Intereses capitalizados | D7: 16738.228 | E7: solo los del periodo de obra, NIC 23 via CINIIF 12 p.22
B8: Activo intangible al termino de obra | D8: =$D$6+$D$7
B9: Meses de operacion | D9: 240
B10: Amortizacion lineal mensual | D10: =$D$8/$D$9
B13: Ano | D13: 2027 | E13: 2028 | F13: 2029 | G13: 2030 | H13: 2031 | I13: 2032 | J13: 2033 | K13: 2034 | L13: 2035 | M13: 2036 | N13: 2037 | O13: 2038 | P13: 2039 | Q13: 2040 | R13: 2041 | S13: 2042 | T13: 2043 | U13: 2044 | V13: 2045 | W13: 2046 | X13: 2047 | Y13: 2048 | Z13: 2049 | AA13: 2050 | AB13: 2051 | AC13: 2052
B14: Meses de operacion del ano | D14: 0 | E14: 0 | F14: 0 | G14: 0 | H14: 9 | I14: 12 | J14: 12 | K14: 12 | L14: 12 | M14: 12 | N14: 12 | O14: 12 | P14: 12 | Q14: 12 | R14: 12 | S14: 12 | T14: 12 | U14: 12 | V14: 12 | W14: 12 | X14: 12 | Y14: 12 | Z14: 12 | AA14: 12 | AB14: 3 | AC14: 0
B15: Amortizacion del intangible | D15: =$D$10*D14 | E15: =$D$10*E14 | F15: =$D$10*F14 | G15: =$D$10*G14 | H15: =$D$10*H14 | I15: =$D$10*I14 | J15: =$D$10*J14 | K15: =$D$10*K14 | ... AC15: =$D$10*AC14
B16: Saldo del intangible | D16: =$D$8-D15 | E16: =D16-E15 | F16: =E16-F15 | G16: =F16-G15 | H16: =G16-H15 | I16: =H16-I15 | J16: =I16-J15 | K16: =J16-K15 | L16: =K16-L15 | ... AC16: =AB16-AC15
B18: Amortizacion acumulada | D18: =SUM($D$15:$AC$15)
B19: Saldo final, debe ser cero | D19: =$AC$16

Sheet Flujo
B2: Flujo de caja anual
B3: El VAN de la ultima fila es la celda que Solver lleva a cero.
B5: Ano | D5: 2027 | E5: 2028 | F5: 2029 | G5: 2030 | H5: 2031 | I5: 2032 | J5: 2033 | K5: 2034 | L5: 2035 | M5: 2036 | N5: 2037 | O5: 2038 | P5: 2039 | Q5: 2040 | R5: 2041 | S5: 2042 | T5: 2043 | U5: 2044 | V5: 2045 | W5: 2046 | X5: 2047 | Y5: 2048 | Z5: 2049 | AA5: 2050 | AB5: 2051 | AC5: 2052
B7: Ingreso tarifario al usuario | D7: =p_ref*0.0 | E7: =p_ref*0.0 | F7: =p_ref*0.0 | G7: =p_ref*0.0 | H7: =p_ref*9.9579 | I7: =p_ref*13.744518480000002 | J7: =p_ref*14.30081908992 | K7: =p_ref*14.880690528795517 | L7: =p_ref*15.445243318387915 | M7: =p_ref*16.030840588540457 | N7: =p_ref*16.638225864607215 | O7: =p_ref*17.26818551405517 | P7: =p_ref*17.921550555133035 | Q7: =p_ref*18.64692705728342 | R7: =p_ref*19.402995712438283 | S7: =p_ref*20.139201087606008 | T7: =p_ref*20.902801117067543 | U7: =p_ref*21.69476607654472 | V7: =p_ref*22.516141102493965 | W7: =p_ref*23.36802576972516 | X7: =p_ref*24.31383340783509 | Y7: =p_ref*25.299723714425618 | Z7: =p_ref*26.25965211526544 | AA7: =p_ref*27.255282600663655 | AB7: =p_ref*6.98244754421381 | AC7: =p_ref*0.0
B8: Pago por Obras | D8: 0 | E8: 0 | F8: 0 | G8: 0 | H8: 0 | I8: 0 | J8: 0 | K8: 0 | L8: 0 | M8: 0 | N8: 0 | O8: 0 | P8: 0 | Q8: 0 | R8: 0 | S8: 0 | T8: 0 | U8: 0 | V8: 0 | W8: 0 | X8: 0 | Y8: 0 | Z8: 0 | AA8: 0 | AB8: 0 | AC8: 0
B9: CAPEX | D9: -4767.216 | E9: -34643.068 | F9: -82277.849 | G9: -68292.304 | H9: -10758.632 | I9: 0 | J9: 0 | K9: 0 | L9: 0 | M9: 0 | N9: 0 | O9: 0 | P9: 0 | Q9: 0 | R9: 0 | S9: 0 | T9: 0 | U9: 0 | V9: 0 | W9: 0 | X9: 0 | Y9: 0 | Z9: 0 | AA9: 0 | AB9: 0 | AC9: 0
B10: Otros costos del periodo D+C+PM | D10: -6232.2761 | E10: -773.71694 | F10: 0 | G10: 0 | H10: 0 | I10: 0 | J10: 0 | K10: 0 | L10: 0 | M10: 0 | N10: 0 | O10: 0 | P10: 0 | Q10: 0 | R10: 0 | S10: 0 | T10: 0 | U10: 0 | V10: 0 | W10: 0 | X10: 0 | Y10: 0 | Z10: 0 | AA10: 0 | AB10: 0 | AC10: 0
B11: Variacion de IGV del periodo D+C+PM | D11: 0 | E11: 0 | F11: 0 | G11: 0 | H11: 0 | I11: 0 | J11: 0 | K11: 0 | L11: 0 | M11: 0 | N11: 0 | O11: 0 | P11: 0 | Q11: 0 | R11: 0 | S11: 0 | T11: 0 | U11: 0 | V11: 0 | W11: 0 | X11: 0 | Y11: 0 | Z11: 0 | AA11: 0 | AB11: 0 | AC11: 0
B12: Costos de cierre de la laguna SJS | D12: 0 | E12: 0 | F12: 0 | G12: 0 | H12: 0 | I12: 0 | J12: 0 | K12: 0 | L12: 0 | M12: 0 | N12: 0 | O12: 0 | P12: 0 | Q12: 0 | R12: 0 | S12: 0 | T12: 0 | U12: 0 | V12: 0 | W12: 0 | X12: 0 | Y12: 0 | Z12: 0 | AA12: 0 | AB12: 0 | AC12: 0
B13: Costos de operacion y mantenimiento | D13: 0 | E13: 0 | F13: 0 | G13: 0 | H13: -7401.4395 | I13: -10136.979 | J13: -10447.214 | K13: -10767.276 | L13: -11097.489 | M13: -11438.186 | N13: -11789.711 | O13: -12152.422 | P13: -12526.687 | Q13: -12912.889 | R13: -13311.421 | S13: -13722.691 | T13: -14147.122 | U13: -14585.15 | V13: -15037.225 | W13: -15503.816 | X13: -15985.405 | Y13: -16482.492 | Z13: -16995.593 | AA13: -17525.244 | AB13: -4473.4544 | AC13: 0
B14: Reposiciones | D14: 0 | E14: 0 | F14: 0 | G14: 0 | H14: 0 | I14: 0 | J14: 0 | K14: 0 | L14: 0 | M14: 0 | N14: 0 | O14: 0 | P14: 0 | Q14: -5121.2104 | R14: 0 | S14: 0 | T14: 0 | U14: 0 | V14: -5842.3885 | W14: 0 | X14: 0 | Y14: 0 | Z14: 0 | AA14: -6665.1241 | AB14: 0 | AC14: 0
B15: Variacion del capital de trabajo | D15: 0 | E15: 0 | F15: 0 | G15: 0 | H15: -9913.1916 | I15: -7.7084195 | J15: -324.57892 | K15: -452.91375 | L15: -472.73908 | M15: -493.48884 | N15: -515.0928 | O15: -537.67832 | P15: -276.10629 | Q15: -424.75394 | R15: -592.09883 | S15: -618.10275 | T15: -645.12367 | U15: -673.30044 | V15: -702.77919 | W15: -361.79715 | X15: -555.66242 | Y15: -773.96191 | Z15: -807.85822 | AA15: -843.12673 | AB15: 19992.063 | AC15: 0
B16: Otros del periodo operativo | D16: 0 | E16: 0 | F16: 0 | G16: -1200 | H16: 1200 | I16: 0 | J16: 0 | K16: 0 | L16: 0 | M16: 0 | N16: 0 | O16: 0 | P16: 0 | Q16: 0 | R16: 0 | S16: 0 | T16: 0 | U16: 0 | V16: 0 | W16: 0 | X16: 0 | Y16: 0 | Z16: 0 | AA16: 0 | AB16: 0 | AC16: 0
B17: Participacion de trabajadores | D17: 0 | E17: 0 | F17: 0 | G17: 0 | H17: -119.86387 | I17: -231.44149 | J17: -348.98038 | K17: -477.44719 | L17: -610.68483 | M17: -751.48397 | N17: -903.65814 | O17: -1068.6675 | P17: -1247.824 | Q17: -1190.6432 | R17: -1655.2372 | S17: -1853.3666 | T17: -1968.9727 | U17: -2070.1908 | V17: -1883.1592 | W17: -2284.3837 | X17: -2407.3402 | Y17: -2535.7531 | Z17: -2659.3292 | AA17: -2454.372 | AB17: -718.51473 | AC17: 0
B18: Impuesto a la Renta | D18: 0 | E18: 0 | F18: 0 | G18: 0 | H18: -335.91849 | I18: -648.61476 | J18: -978.01752 | K18: -1338.0458 | L18: -3242.7637 | M18: -4212.0676 | N18: -5065.0039 | O18: -5989.8811 | P18: -6994.0533 | Q18: -6673.5553 | R18: -9277.6044 | S18: -10388.12 | T18: -11036.092 | U18: -11603.419 | V18: -10555.107 | W18: -12803.97 | X18: -13493.142 | Y18: -14212.896 | Z18: -14905.54 | AA18: -13756.755 | AB18: -4027.2751 | AC18: 0
B19: Desembolsos de deuda | D19: 0 | E19: 0 | F19: 64382.861 | G19: 79338.187 | H19: 22016.147 | I19: 0 | J19: 0 | K19: 0 | L19: 0 | M19: 0 | N19: 0 | O19: 0 | P19: 0 | Q19: 0 | R19: 0 | S19: 0 | T19: 0 | U19: 0 | V19: 0 | W19: 0 | X19: 0 | Y19: 0 | Z19: 0 | AA19: 0 | AB19: 0 | AC19: 0
... B24: Cuenta de reserva CRSD | D24: 0 | E24: 0 | F24: 0 | G24: 0 | H24: -12683.967 | I24: -262.24447 | J24: -346.42104 | K24: 253.07108 | L24: -139.67936 | M24: -204.10063 | N24: -193.39873 | O24: -294.1721 | P24: 1209.2117 | Q24: -1534.9882 | R24: 11622.051 | S24: 2574.6386 | T24: 0 | U24: 0 | V24: 0 | W24: 0 | X24: 0 | Y24: 0 | Z24: 0 | AA24: 0 | AB24: 0 | AC24: 0
B26: Flujo de caja financiero | D26: =SUM(D7:D24) | E26: =SUM(E7:E24) | F26: =SUM(F7:F24) | G26: =SUM(G7:G24) | H26: =SUM(H7:H24) | I26: =SUM(I7:I24) | J26: =SUM(J7:J24) | K26: =SUM(K7:K24) | ... AC26: =SUM(AC7:AC24)
B27: Periodo de descuento | D27: 0.91666667 | E27: 1.9166667 | F27: 2.9166667 | G27: 3.9166667 | H27: 4.9166667 | I27: 5.9166667 | J27: 6.9166667 | K27: 7.9166667 | L27: 8.9166667 | M27: 9.9166667 | N27: 10.916667 | O27: 11.916667 | P27: 12.916667 | Q27: 13.916667 | R27: 14.916667 | S27: 15.916667 | T27: 16.916667 | U27: 17.916667 | V27: 18.916667 | W27: 19.916667 | X27: 20.916667 | Y27: 21.916667 | Z27: 22.916667 | AA27: 23.916667 | AB27: 24.166667 | AC27: 24.166667
B29: VAN del flujo de caja financiero | D29: =SUMPRODUCT(D26:AC26,1/(1+p_tir)^D27:AC27)
B31: Memoria: amortizacion del intangible (no es caja) | D31: ='Activo intangible'!D15 | E31: ='Activo intangible'!E15 | F31: ='Activo intangible'!F15 | G31: ='Activo intangible'!G15 | H31: ='Activo intangible'!H15 | I31: ='Activo intangible'!I15 | J31: ='Activo intangible'!J15 | K31: ='Activo intangible'!K15 | ... AC31: ='Activo intangible'!AC15

Sheet Reparto de la tarifa
B2: Reparto de la tarifa
B3: De lo que recauda la tarifa, cuanto paga la operacion y cuanto repaga la inversion. Las dos partes suman el ingreso.
B5: Ano | D5: 2027 | E5: 2028 | F5: 2029 | G5: 2030 | H5: 2031 | I5: 2032 | J5: 2033 | K5: 2034 | L5: 2035 | M5: 2036 | N5: 2037 | O5: 2038 | P5: 2039 | Q5: 2040 | R5: 2041 | S5: 2042 | T5: 2043 | U5: 2044 | V5: 2045 | W5: 2046 | X5: 2047 | Y5: 2048 | Z5: 2049 | AA5: 2050 | AB5: 2051 | AC5: 2052
B7: Ingreso tarifario | D7: =Flujo!D7 | E7: =Flujo!E7 | F7: =Flujo!F7 | G7: =Flujo!G7 | H7: =Flujo!H7 | I7: =Flujo!I7 | J7: =Flujo!J7 | K7: =Flujo!K7 | ... AC7: =Flujo!AC7
B8: Costo de operacion y mantenimiento | D8: =-Flujo!D13 | E8: =-Flujo!E13 | F8: =-Flujo!F13 | G8: =-Flujo!G13 | H8: =-Flujo!H13 | I8: =-Flujo!I13 | J8: =-Flujo!J13 | K8: =-Flujo!K13 | ... AC8: =-Flujo!AC13
B9: Margen del operador | D9: =p_margen_om*D8 | E9: =p_margen_om*E8 | F9: =p_margen_om*F8 | G9: =p_margen_om*G8 | H9: =p_margen_om*H8 | I9: =p_margen_om*I8 | J9: =p_margen_om*J8 | K9: =p_margen_om*K8 | ... AC9: =p_margen_om*AC8
B10: Operacion y mantenimiento | D10: =D8+D9 | E10: =E8+E9 | F10: =F8+F9 | G10: =G8+G9 | H10: =H8+H9 | I10: =I8+I9 | J10: =J8+J9 | K10: =K8+K9 | ... AC10: =AC8+AC9
B11: Disponible para repagar la inversion | D11: =D7-D10 | E11: =E7-E10 | F11: =F7-F10 | G11: =G7-G10 | H11: =H7-H10 | I11: =I7-I10 | J11: =J7-J10 | K11: =K7-K10 | ... AC11: =AC7-AC10
B13: VAN del ingreso tarifario | D13: =SUMPRODUCT($D$7:$AC$7,1/(1+p_tir)^Flujo!$D$27:$AC$27)
B14: VAN del costo de O&M, sin margen | D14: =SUMPRODUCT($D$8:$AC$8,1/(1+p_tir)^Flujo!$D$27:$AC$27)
B15: VAN de la operacion, con margen | D15: =SUMPRODUCT($D$10:$AC$10,1/(1+p_tir)^Flujo!$D$27:$AC$27)
B16: VAN para la inversion | D16: =SUMPRODUCT($D$11:$AC$11,1/(1+p_tir)^Flujo!$D$27:$AC$27)
B17: Participacion de la operacion | D17: =$D$15/$D$13
B18: Participacion de la inversion | D18: =$D$16/$D$13
B19: Las dos partes menos el total, debe ser cero | D19: =$D$15+$D$16-$D$13
B20: Check del reparto | D20: =IF(ROUND($D$19,2)=0,"OK","ERROR")
