Workbook
Name p_ke: Inputs!$D$6
Name p_kd: Inputs!$D$7
Name p_wacc: Inputs!$D$8
Name p_tir: Inputs!$D$9
Name p_rcsd: Inputs!$D$10
Name p_crsd: Inputs!$D$11
Name p_ir: Inputs!$D$12
Name p_pt: Inputs!$D$13
Name p_arr: Inputs!$D$14
Name p_ipm: Inputs!$D$15
Name p_fx: Inputs!$D$16
Name p_cuotas: Inputs!$D$17
Name p_ppdi: Inputs!$D$18
Name p_ref: Inputs!$D$19

Sheet Resumen
B2: Resumen del modelo
B3: San Martin paga el PPDI por hitos funcionales y cierra todo el PPDMO a la vez.
B6: PPD Inversiones, anual | D6: =p_ppdi
B7: PPD Inversiones, cuota trimestral | D7: =p_ppdi/4
B8: PPD MO, referencia mensual | D8: =p_ref
B9: PPD MO fijo, anual | D9: =Hitos!E10*12
B10: Precio unitario, S/ por kg DBO | D10: 3.647797
B11: VAN financiero, debe ser cero | D11: =Flujo!$D$31
B12: Ke | D12: =p_ke
B13: Kd | D13: =p_kd
B14: WACC | D14: =p_wacc

Sheet Inputs
B2: Parametros del modelo
B3: Las celdas en ambar son de entrada. Las dos ultimas las resuelve el cierre.
B6: Ke, costo del patrimonio | D6: 0.11973267 | E6: CAPM en USD + riesgo pais + devaluacion
B7: Kd, costo de la deuda | D7: 0.10002309 | E7: soberano a vida media + spread
B8: WACC | D8: 0.098635786 | E8: despues de impuestos
B9: TIR objetivo del cierre | D9: 0.1197 | E9: Ke redondeado a 4 decimales, Control!M12
B10: Cobertura minima, RCSD | D10: 1.25 | E10: dimensiona la amortizacion
B11: Cuenta de reserva, CRSD | D11: 0.5 | E11: del servicio del ano siguiente
B12: Impuesto a la Renta | D12: 0.295
B13: Participacion de trabajadores | D13: 0.05
B14: Arrastre de perdidas | D14: 0.5 | E14: sistema B
B15: IPM, reajuste | D15: 0.0267 | E15: anual
B16: Tipo de cambio | D16: 3.3805 | E16: solo entra por los reembolsos en dolares
B17: Cuotas del PPDI | D17: 60 | E17: trimestrales
B18: PPDI anual | D18: 96490727 | E18: S/ - LA CIERRA Solver
B19: PPDMO referencia mensual | D19: 5479810.1 | E19: S/ - LA CIERRA Solver

Sheet Hitos
B2: Hitos funcionales
B3: El PPDI se reparte por la participacion de cada hito en el CAPEX, y el PPDMO fijo por el VAN de su operacion y mantenimiento.
B5: Hito | C5: % del CAPEX | D5: Cuota trimestral del PPDI | E5: PPDMO fijo mensual
B6: Hito 1 | C6: 0.7596494 | D6: =p_ppdi*C6/4 | E6: 2683129.2
B7: Hito 2 | C7: 0.062513374 | D7: =p_ppdi*C7/4 | E7: 179543.05
B8: Hito 3 | C8: 0.022824984 | D8: =p_ppdi*C8/4 | E8: 56494.397
B9: Hito 4 | C9: 0.15501225 | D9: =p_ppdi*C9/4 | E9: 1047025.7
B10: Total | C10: =SUM(C6:C9) | D10: =SUM(D6:D9) | E10: =SUM(E6:E9)

Sheet Flujo
B2: Flujo de caja anual
B3: El VAN de la ultima fila es la celda que Solver lleva a cero.
B5: Ano | D5: 2025 | E5: 2026 | F5: 2027 | G5: 2028 | H5: 2029 | I5: 2030 | J5: 2031 | K5: 2032 | L5: 2033 | M5: 2034 | N5: 2035 | O5: 2036 | P5: 2037 | Q5: 2038 | R5: 2039 | S5: 2040 | T5: 2041 | U5: 2042 | V5: 2043 | W5: 2044 | X5: 2045 | Y5: 2046 | Z5: 2047 | AA5: 2048 | AB5: 2049 | AC5: 2050 | AD5: 2051 | AE5: 2052
B7: PPD Inversiones | D7: =p_ppdi*0.0 | E7: =p_ppdi*0.0 | F7: =p_ppdi*0.0 | G7: =p_ppdi*0.0 | H7: =p_ppdi*0.0 | I7: =p_ppdi*0.9999999999999993 | J7: =p_ppdi*0.9999999999999993 | K7: =p_ppdi*0.9999999999999993 | L7: =p_ppdi*0.9999999999999993 | M7: =p_ppdi*0.9999999999999993 | N7: =p_ppdi*0.9999999999999993 | O7: =p_ppdi*0.9999999999999993 | P7: =p_ppdi*0.9999999999999993 | ... W7: =p_ppdi*0.9999999999999993 | X7: =p_ppdi*0.0 | Y7: =p_ppdi*0.0 | Z7: =p_ppdi*0.0 | AA7: =p_ppdi*0.0 | AB7: =p_ppdi*0.0 | AC7: =p_ppdi*0.0 | AD7: =p_ppdi*0.0 | AE7: =p_ppdi*0.0
B8: PPD MO fijo | D8: =p_ref*0.0 | E8: =p_ref*0.0 | F8: =p_ref*0.0 | G8: =p_ref*0.0 | H8: =p_ref*0.0 | I8: =p_ref*9.65859213679519 | J8: =p_ref*9.90551788154506 | K8: =p_ref*10.15850892627442 | L8: =p_ref*10.417695551889748 | M8: =p_ref*10.738273435770067 | N8: =p_ref*11.013672796414117 | O8: =p_ref*11.295846764195161 | P8: =p_ref*11.584969046988517 | Q8: =p_ref*11.881184401356936 | R8: =p_ref*12.184637583863173 | S8: =p_ref*12.49550230238254 | T8: =p_ref*12.880091538313742 | U8: =p_ref*13.21042601452385 | V8: =p_ref*13.548866858248306 | W8: =p_ref*13.895631204331263 | X8: =p_ref*14.25090723630429 | Y8: =p_ref*14.61488313769898 | Z8: =p_ref*14.98777604335946 | AA8: =p_ref*15.449057306238997 | AB8: =p_ref*13.170418968913564 | AC8: =p_ref*0.0 | AD8: =p_ref*0.0 | AE8: =p_ref*0.0
B9: PPD MO variable | D9: =p_ref*0.0 | E9: =p_ref*0.0 | F9: =p_ref*0.0 | G9: =p_ref*0.0 | H9: =p_ref*0.0 | I9: =p_ref*2.6408549964385943 | J9: =p_ref*2.767157216392784 | K9: =p_ref*2.9002645881229294 | L9: =p_ref*3.067679145441892 | M9: =p_ref*3.2226668386049213 | N9: =p_ref*3.3694941867331294 | O9: =p_ref*3.523806464247716 | P9: =p_ref*3.686023759558088 | Q9: =p_ref*3.856581011820298 | R9: =p_ref*4.035937078427676 | S9: =p_ref*4.224586201540354 | T9: =p_ref*4.4458811485058085 | U9: =p_ref*4.656652872173741 | V9: =p_ref*4.902550310447827 | W9: =p_ref*5.162887901064566 | X9: =p_ref*5.4385727636957135 | Y9: =p_ref*5.577476862301027 | Z9: =p_ref*5.719783956640543 | AA9: =p_ref*5.895822693761001 | AB9: =p_ref*5.026226099368686 | AC9: =p_ref*0.0 | AD9: =p_ref*0.0 | AE9: =p_ref*0.0
B10: Pago por Obras | D10: 0 | E10: 0 | F10: 0 | G10: 0 | H10: 0 | I10: 0 | J10: 6738784.8 | K10: 0 | L10: 0 | M10: 0 | N10: 0 | O10: 0 | P10: 0 | Q10: 0 | R10: 0 | S10: 0 | T10: 0 | U10: 0 | V10: 0 | W10: 0 | X10: 0 | Y10: 0 | Z10: 0 | AA10: 0 | AB10: 0 | AC10: 0 | AD10: 0 | AE10: 0
B11: CAPEX | D11: -5843750.2 | E11: -24597552 | F11: -1.1508684e+08 | G11: -2.7059553e+08 | H11: -1.3920017e+08 | I11: 0 | J11: 0 | K11: 0 | L11: 0 | M11: 0 | N11: 0 | O11: 0 | P11: 0 | Q11: 0 | R11: 0 | S11: 0 | T11: 0 | U11: 0 | V11: 0 | W11: 0 | X11: 0 | Y11: 0 | Z11: 0 | AA11: 0 | AB11: 0 | AC11: 0 | AD11: 0 | AE11: 0
B12: Otros costos del periodo D+C+PM | D12: -4272486.9 | E12: -2619055.1 | F12: -2976119.7 | G12: -3475883 | H12: -3504061.8 | I12: 0 | J12: 0 | K12: 0 | L12: 0 | M12: 0 | N12: 0 | O12: 0 | P12: 0 | Q12: 0 | R12: 0 | S12: 0 | T12: 0 | U12: 0 | V12: 0 | W12: 0 | X12: 0 | Y12: 0 | Z12: 0 | AA12: 0 | AB12: 0 | AC12: 0 | AD12: 0 | AE12: 0
B13: Variacion de IGV del periodo D+C+PM | D13: -531330.44 | E13: 476308.42 | F13: -2439521.3 | G13: -1603943.4 | H13: 3915109.6 | I13: 183377.14 | J13: 0 | K13: 0 | L13: 0 | M13: 0 | N13: 0 | O13: 0 | P13: 0 | Q13: 0 | R13: 0 | S13: 0 | T13: 0 | U13: 0 | V13: 0 | W13: 0 | X13: 0 | Y13: 0 | Z13: 0 | AA13: 0 | AB13: 0 | AC13: 0 | AD13: 0 | AE13: 0
B14: Costos de cierre de la laguna SJS | D14: 0 | E14: 0 | F14: 0 | G14: 0 | H14: 0 | I14: -6738784.8 | J14: 0 | K14: 0 | L14: 0 | M14: 0 | N14: 0 | O14: 0 | P14: 0 | Q14: 0 | R14: 0 | S14: 0 | T14: 0 | U14: 0 | V14: 0 | W14: 0 | X14: 0 | Y14: 0 | Z14: 0 | AA14: 0 | AB14: 0 | AC14: 0 | AD14: 0 | AE14: 0
B15: Costos de operacion y mantenimiento | D15: 0 | E15: 0 | F15: 0 | G15: 0 | H15: 0 | I15: -58208696 | J15: -59374669 | K15: -60155937 | L15: -61830243 | M15: -63555824 | N15: -63623040 | O15: -65421949 | P15: -67327680 | Q15: -69201749 | R15: -71174318 | S15: -73920856 | T15: -76011263 | U15: -78156659 | V15: -80365049 | W15: -82667692 | X15: -83719126 | Y15: -86133142 | Z15: -88683405 | AA15: -91310040 | AB15: -79951487 | AC15: 0 | AD15: 0 | AE15: 0
B16: Reposiciones | D16: 0 | E16: 0 | F16: 0 | G16: 0 | H16: 0 | I16: 0 | J16: 0 | K16: 0 | L16: 0 | M16: 0 | N16: 0 | O16: 0 | P16: 0 | Q16: 0 | R16: 0 | S16: -213408.11 | T16: -169841.01 | U16: -72880.522 | V16: 0 | W16: -5260935.2 | X16: 0 | Y16: -6936190.9 | Z16: 0 | AA16: 0 | AB16: 0 | AC16: 0 | AD16: 0 | AE16: 0
B17: Variacion del capital de trabajo | D17: 0 | E17: 0 | F17: 0 | G17: 0 | H17: 0 | I17: -37700931 | J17: -363762.48 | K17: -1180797.1 | L17: -1177360 | M17: -605195 | N17: -1322499.5 | O17: -640546.26 | P17: -1010134.1 | Q17: -1563330.2 | R17: -182179.29 | S17: -1293761.1 | T17: -1296760.5 | U17: -892660.19 | V17: -1611916.3 | W17: -497143.01 | X17: 29611935 | Y17: -1031965.5 | Z17: -210723.75 | AA17: -793327.56 | AB17: 23763058 | AC17: 0 | AD17: 0 | AE17: 0
B18: Otros del periodo operativo | D18: 0 | E18: 0 | F18: 0 | G18: 0 | H18: -10133000 | I18: 10133000 | J18: 0 | K18: 0 | L18: 0 | M18: 0 | N18: 0 | O18: 0 | P18: 0 | Q18: 0 | R18: 0 | S18: 0 | T18: 0 | U18: 0 | V18: 0 | W18: 0 | X18: 0 | Y18: 0 | Z18: 0 | AA18: 0 | AB18: 0 | AC18: 0 | AD18: 0 | AE18: 0
B19: Participacion de trabajadores | D19: 0 | E19: 0 | F19: 0 | G19: 0 | H19: 0 | I19: -4084.931 | J19: -770202.9 | K19: -665623.23 | L19: -863409.8 | M19: -1089283 | N19: -1401176.3 | O19: -1641336.1 | P19: -1896607.1 | Q19: -2174636.5 | R19: -2471992.7 | S19: -3062720.7 | T19: -3424088.5 | U19: -3769926.7 | V19: -4010717.5 | W19: -3798878.7 | X19: -1208774.2 | Y19: -879048.22 | Z19: -1239504.5 | AA19: -1282792.4 | AB19: -988133.58 | AC19: 0 | AD19: 0 | AE19: 0
B20: Impuesto a la Renta | D20: 0 | E20: 0 | F20: 0 | G20: 0 | H20: 0 | I20: -11448.019 | J20: -2158493.6 | K20: -1865409.1 | L20: -2419706 | M20: -3052715.5 | N20: -6966983.5 | O20: -9199689.1 | P20: -10630483 | Q20: -12188837 | R20: -13855519 | S20: -17166550 | T20: -19192016 | U20: -21130439 | V20: -22480072 | W20: -21292715 | X20: -6775179.6 | Y20: -4927065.3 | Z20: -6947422.8 | AA20: -7190051.4 | AB20: -5538488.7 | AC20: 0 | AD20: 0 | AE20: 0
B21: Desembolsos de deuda | D21: 0 | E21: 0 | F21: 33313426 | G21: 2.9776691e+08 | H21: 2.2436618e+08 | I21: 0 | J21: 0 | K21: 0 | L21: 0 | M21: 0 | N21: 0 | O21: 0 | P21: 0 | Q21: 0 | R21: 0 | S21: 0 | T21: 0 | U21: 0 | V21: 0 | W21: 0 | X21: 0 | Y21: 0 | Z21: 0 | AA21: 0 | AB21: 0 | AC21: 0 | AD21: 0 | AE21: 0
... B26: Cuenta de reserva CRSD | D26: 0 | E26: 0 | F26: 0 | G26: 0 | H26: -28616717 | I26: -15385777 | J26: 2329470.8 | K26: 34103.863 | L26: -237484.41 | M26: 1078784.2 | N26: 479183.55 | O26: 595251.41 | P26: 682329.42 | Q26: -36098.659 | R26: 2094418.1 | S26: 446617.37 | T26: 9671975.1 | U26: 26863944 | V26: 0 | W26: 0 | X26: 0 | Y26: 0 | Z26: 0 | AA26: 0 | AB26: 0 | AC26: 0 | AD26: 0 | AE26: 0
B28: Flujo de caja financiero | D28: =SUM(D7:D26) | E28: =SUM(E7:E26) | F28: =SUM(F7:F26) | G28: =SUM(G7:G26) | H28: =SUM(H7:H26) | I28: =SUM(I7:I26) | J28: =SUM(J7:J26) | K28: =SUM(K7:K26) | ... AE28: =SUM(AE7:AE26)
B29: Periodo de descuento | D29: 0.16666667 | E29: 1.1666667 | F29: 2.1666667 | G29: 3.1666667 | H29: 4.1666667 | I29: 5.1666667 | J29: 6.1666667 | K29: 7.1666667 | L29: 8.1666667 | M29: 9.1666667 | N29: 10.166667 | O29: 11.166667 | P29: 12.166667 | Q29: 13.166667 | R29: 14.166667 | S29: 15.166667 | T29: 16.166667 | U29: 17.166667 | V29: 18.166667 | W29: 19.166667 | X29: 20.166667 | Y29: 21.166667 | Z29: 22.166667 | AA29: 23.166667 | AB29: 24 | AC29: 24 | AD29: 24 | AE29: 24
B31: VAN del flujo de caja financiero | D31: =SUMPRODUCT(D28:AE28,1/(1+p_tir)^D29:AE29)

Sheet Activo financiero
B2: Activo financiero del PPDI
B3: CINIIF 12 p.16: el cobro es incondicional, asi que la obra es cuenta por cobrar. Se reconoce por el servicio de construccion, no por la necesidad de financiamiento.
B5: Ano | D5: 2025 | E5: 2026 | F5: 2027 | G5: 2028 | H5: 2029 | I5: 2030 | J5: 2031 | K5: 2032 | L5: 2033 | M5: 2034 | N5: 2035 | O5: 2036 | P5: 2037 | Q5: 2038 | R5: 2039 | S5: 2040 | T5: 2041 | U5: 2042 | V5: 2043 | W5: 2044 | X5: 2045 | Y5: 2046 | Z5: 2047 | AA5: 2048 | AB5: 2049 | AC5: 2050 | AD5: 2051 | AE5: 2052
B7: Servicio de construccion (CAPEX) | D7: =-Flujo!D11 | E7: =-Flujo!E11 | F7: =-Flujo!F11 | G7: =-Flujo!G11 | H7: =-Flujo!H11 | I7: =-Flujo!I11 | J7: =-Flujo!J11 | K7: =-Flujo!K11 | ... AE7: =-Flujo!AE11
B8: Otros costos del periodo D+C+PM | D8: =-Flujo!D12 | E8: =-Flujo!E12 | F8: =-Flujo!F12 | G8: =-Flujo!G12 | H8: =-Flujo!H12 | I8: =-Flujo!I12 | J8: =-Flujo!J12 | K8: =-Flujo!K12 | ... AE8: =-Flujo!AE12
B9: PPD Inversiones cobrado | D9: =-Flujo!D7 | E9: =-Flujo!E7 | F9: =-Flujo!F7 | G9: =-Flujo!G7 | H9: =-Flujo!H7 | I9: =-Flujo!I7 | J9: =-Flujo!J7 | K9: =-Flujo!K7 | ... AE9: =-Flujo!AE7
B10: Total del periodo | D10: =SUM(D7:D9) | E10: =SUM(E7:E9) | F10: =SUM(F7:F9) | G10: =SUM(G7:G9) | H10: =SUM(H7:H9) | I10: =SUM(I7:I9) | J10: =SUM(J7:J9) | K10: =SUM(K7:K9) | ... AE10: =SUM(AE7:AE9)
B12: Tasa implicita anual | D12: =IFERROR(IRR($D$10:$AE$10),0)
B14: Saldo inicial del activo | D14: 0 | E14: =D16 | F14: =E16 | G14: =F16 | H14: =G16 | I14: =H16 | J14: =I16 | K14: =J16 | L14: =K16 | ... AE14: =AD16
B15: Ingreso financiero devengado | D15: =D14*$D$12 | E15: =E14*$D$12 | F15: =F14*$D$12 | G15: =G14*$D$12 | H15: =H14*$D$12 | I15: =I14*$D$12 | J15: =J14*$D$12 | K15: =K14*$D$12 | ... AE15: =AE14*$D$12
B16: Saldo final del activo | D16: =D14+D10+D15 | E16: =E14+E10+E15 | F16: =F14+F10+F15 | G16: =G14+G10+G15 | H16: =H14+H10+H15 | I16: =I14+I10+I15 | J16: =J14+J10+J15 | K16: =K14+K10+K15 | ... AE16: =AE14+AE10+AE15
B18: Saldo maximo del activo | D18: =MAX($D$16:$AE$16)
B19: Ingreso financiero acumulado | D19: =SUM($D$15:$AE$15)
B20: Saldo final, debe ser cero | D20: =AE16
B21: Check AF | D21: =IF(ROUND(AE16,2)=0,"OK","ERROR")
B22: Anos con saldo negativo | D22: =SUMPRODUCT(--(ROUND($D$16:$AE$16,2)<0))
