Workbook
Name p_costo_obra: Inputs!$D$6
Name p_tamano_deuda: Inputs!$D$7
Name p_kd: Inputs!$D$8
Name p_spread: Inputs!$D$9
Name p_ke: Inputs!$D$10
Name p_wacc: Inputs!$D$11
Name p_pagos: Inputs!$D$12
Name p_ipm: Inputs!$D$13
Name p_gatillo: Inputs!$D$14
Name p_ipc: Inputs!$D$15
Name p_ir: Inputs!$D$16
Name p_part: Inputs!$D$17
Name p_superv: Inputs!$D$18
Name p_margen_cf: Inputs!$D$19
Name p_fijo_base: Inputs!$D$20
Name p_tarifa: Inputs!$D$21
Name p_ppdi_anual: Inputs!$D$22

Sheet Resumen
B2: Resumen del modelo
B3: S/ miles sin IGV, primer mes de operacion anualizado.
B6: PPD Inversiones, anual | D6: =p_ppdi_anual
B7: PPD MO fijo, anual | D7: =SUMPRODUCT(PPDMO!$D$21:$LI$21,PPDMO!$D$15:$LI$15)*12
B8: PPD MO variable, anual | D8: =SUMPRODUCT(PPDMO!$D$21:$LI$21,PPDMO!$D$16:$LI$16)*12
B9: PPD MO total, anual | D9: =D7+D8
B10: PPD total, anual | D10: =D6+D9
B11: Tarifa unitaria, S/ por kg DBO5 | D11: =p_tarifa
B12: VAN financiero, debe ser cero | D12: =Flujo!$D$34
B13: WACC | D13: =p_wacc
B14: Kd | D14: =p_kd
B15: Ke | D15: =p_ke
B16: Activo financiero, saldo maximo | D16: =MAX('Activo financiero'!$D$17:$LC$17)
B17: Activo financiero, amortizacion acumulada | D17: =SUM('Activo financiero'!$D$16:$LC$16)
B18: Activo financiero, saldo final | D18: ='Activo financiero'!$LC$17
B19: Tasa implicita del activo, anual | D19: =(1+'Activo financiero'!$D$7)^12-1

Sheet Inputs
B2: Parametros del modelo
B3: Las celdas en ambar son de entrada. Las dos ultimas las resuelve el cierre.
B6: Costo de obra a financiar | D6: 261144.81 | E6: S/ miles
B7: Tamano de deuda | D7: 0.8 | E7: % del costo de obra
B8: Kd, costo de la deuda | D8: 0.10092957 | E8: soberano a vida media + spread
B9: Spread de deuda | D9: 0.035 | E9: sondeo de mercado
B10: Ke, costo del patrimonio | D10: 0.12622649 | E10: CAPM en USD + riesgo pais + devaluacion
B11: WACC | D11: 0.097303479 | E11: despues de impuestos
B12: Numero de pagos de la deuda | D12: 144 | E12: meses
B13: IPM, reajuste de ingresos | D13: 0.0267 | E13: anual
B14: Gatillo del reajuste | D14: 0.03 | E14: acumulado que dispara el ajuste
B15: IPC, reajuste de costos | D15: 0.02 | E15: anual, sin gatillo
B16: Tasa de Impuesto a la Renta | D16: 0.295
B17: Participacion de trabajadores | D17: 0.05
B18: Supervision SUNASS | D18: 0.01 | E18: % del PPD
B19: Margen del costo fijo | D19: 0.15 | E19: pass-through de costos
B20: PPDMO fijo base mensual | D20: 556.65918 | E20: S/ miles, calculado de costos
B21: Tarifa variable | D21: 3.8583316 | E21: S/ por kg DBO5 - LA CIERRA Buscar Objetivo
B22: PPDI anual | D22: 46362.146 | E22: S/ miles - LA CIERRA Buscar Objetivo

Sheet Deuda
B2: Deuda financiera
B3: Cuota constante: el servicio sale de PMT y la amortizacion es el residuo.
B6: Mes | D6: 2026-10-31 | E6: 2026-11-30 | F6: 2026-12-31 | G6: 2027-01-31 | H6: 2027-02-28 | I6: 2027-03-31 | J6: 2027-04-30 | K6: 2027-05-31 | L6: 2027-06-30 | M6: 2027-07-31 | N6: 2027-08-31 | O6: 2027-09-30 | P6: 2027-10-31 | Q6: 2027-11-30 | R6: 2027-12-31 | S6: 2028-01-31 | T6: 2028-02-29 | U6: 2028-03-31 | V6: 2028-04-30 | W6: 2028-05-31 | X6: 2028-06-30 | Y6: 2028-07-31 | Z6: 2028-08-31 | AA6: 2028-09-30 | AB6: 2028-10-31 | AC6: 2028-11-30 | AD6: 2028-12-31 | AE6: 2029-01-31 | AF6: 2029-02-28 | AG6: 2029-03-31 | AH6: 2029-04-30 | AI6: 2029-05-31 | AJ6: 2029-06-30 | AK6: 2029-07-31 | AL6: 2029-08-31 | AM6: 2029-09-30 | AN6: 2029-10-31 | AO6: 2029-11-30 | AP6: 2029-12-31 | AQ6: 2030-01-31 | AR6: 2030-02-28 | AS6: 2030-03-31 | AT6: 2030-04-30 | AU6: 2030-05-31 | AV6: 2030-06-30 | AW6: 2030-07-31 | AX6: 2030-08-31 | AY6: 2030-09-30 | AZ6: 2030-10-31 | BA6: 2030-11-30 | BB6: 2030-12-31 | BC6: 2031-01-31 | BD6: 2031-02-28 | BE6: 2031-03-31 | BF6: 2031-04-30 | BG6: 2031-05-31 | BH6: 2031-06-30 | BI6: 2031-07-31 | BJ6: 2031-08-31 | BK6: 2031-09-30 | BL6: 2031-10-31 | BM6: 2031-11-30 | BN6: 2031-12-31 | BO6: 2032-01-31 | BP6: 2032-02-29 | BQ6: 2032-03-31 | BR6: 2032-04-30 | BS6: 2032-05-31 | BT6: 2032-06-30 | BU6: 2032-07-31 | BV6: 2032-08-31 | BW6: 2032-09-30 | BX6: 2032-10-31 | BY6: 2032-11-30 | BZ6: 2032-12-31 | CA6: 2033-01-31 | CB6: 2033-02-28 | CC6: 2033-03-31 | CD6: 2033-04-30 | CE6: 2033-05-31 | CF6: 2033-06-30 | CG6: 2033-07-31 | CH6: 2033-08-31 | CI6: 2033-09-30 | CJ6: 2033-10-31 | CK6: 2033-11-30 | CL6: 2033-12-31 | CM6: 2034-01-31 | CN6: 2034-02-28 | CO6: 2034-03-31 | CP6: 2034-04-30 | CQ6: 2034-05-31 | CR6: 2034-06-30 | CS6: 2034-07-31 | CT6: 2034-08-31 | CU6: 2034-09-30 | CV6: 2034-10-31 | CW6: 2034-11-30 | CX6: 2034-12-31 | CY6: 2035-01-31 | CZ6: 2035-02-28 | DA6: 2035-03-31 | DB6: 2035-04-30 | DC6: 2035-05-31 | DD6: 2035-06-30 | DE6: 2035-07-31 | DF6: 2035-08-31 | DG6: 2035-09-30 | DH6: 2035-10-31 | DI6: 2035-11-30 | DJ6: 2035-12-31 | DK6: 2036-01-31 | DL6: 2036-02-29 | DM6: 2036-03-31 | DN6: 2036-04-30 | DO6: 2036-05-31 | DP6: 2036-06-30 | DQ6: 2036-07-31 | DR6: 2036-08-31 | DS6: 2036-09-30 | DT6: 2036-10-31 | DU6: 2036-11-30 | DV6: 2036-12-31 | DW6: 2037-01-31 | DX6: 2037-02-28 | DY6: 2037-03-31 | DZ6: 2037-04-30 | EA6: 2037-05-31 | EB6: 2037-06-30 | EC6: 2037-07-31 | ED6: 2037-08-31 | EE6: 2037-09-30 | EF6: 2037-10-31 | EG6: 2037-11-30 | EH6: 2037-12-31 | EI6: 2038-01-31 | EJ6: 2038-02-28 | EK6: 2038-03-31 | EL6: 2038-04-30 | EM6: 2038-05-31 | EN6: 2038-06-30 | EO6: 2038-07-31 | EP6: 2038-08-31 | EQ6: 2038-09-30 | ER6: 2038-10-31 | ES6: 2038-11-30 | ET6: 2038-12-31 | EU6: 2039-01-31 | EV6: 2039-02-28 | EW6: 2039-03-31 | EX6: 2039-04-30 | EY6: 2039-05-31 | EZ6: 2039-06-30 | FA6: 2039-07-31 | FB6: 2039-08-31 | FC6: 2039-09-30 | FD6: 2039-10-31 | FE6: 2039-11-30 | FF6: 2039-12-31 | FG6: 2040-01-31 | FH6: 2040-02-29 | FI6: 2040-03-31 | FJ6: 2040-04-30 | FK6: 2040-05-31 | FL6: 2040-06-30 | FM6: 2040-07-31 | FN6: 2040-08-31 | FO6: 2040-09-30 | FP6: 2040-10-31 | FQ6: 2040-11-30 | FR6: 2040-12-31 | FS6: 2041-01-31 | FT6: 2041-02-28 | FU6: 2041-03-31 | FV6: 2041-04-30 | FW6: 2041-05-31 | FX6: 2041-06-30 | FY6: 2041-07-31 | FZ6: 2041-08-31 | GA6: 2041-09-30 | GB6: 2041-10-31 | GC6: 2041-11-30 | GD6: 2041-12-31 | GE6: 2042-01-31 | GF6: 2042-02-28 | GG6: 2042-03-31 | GH6: 2042-04-30 | GI6: 2042-05-31 | GJ6: 2042-06-30 | GK6: 2042-07-31 | GL6: 2042-08-31 | GM6: 2042-09-30 | GN6: 2042-10-31 | GO6: 2042-11-30 | GP6: 2042-12-31 | GQ6: 2043-01-31 | GR6: 2043-02-28 | GS6: 2043-03-31 | GT6: 2043-04-30 | GU6: 2043-05-31 | GV6: 2043-06-30 | GW6: 2043-07-31 | GX6: 2043-08-31 | GY6: 2043-09-30 | GZ6: 2043-10-31 | HA6: 2043-11-30 | HB6: 2043-12-31 | HC6: 2044-01-31 | HD6: 2044-02-29 | HE6: 2044-03-31 | HF6: 2044-04-30 | HG6: 2044-05-31 | HH6: 2044-06-30 | HI6: 2044-07-31 | HJ6: 2044-08-31 | HK6: 2044-09-30 | HL6: 2044-10-31 | HM6: 2044-11-30 | HN6: 2044-12-31 | HO6: 2045-01-31 | HP6: 2045-02-28 | HQ6: 2045-03-31 | HR6: 2045-04-30 | HS6: 2045-05-31 | HT6: 2045-06-30 | HU6: 2045-07-31 | HV6: 2045-08-31 | HW6: 2045-09-30 | HX6: 2045-10-31 | HY6: 2045-11-30 | HZ6: 2045-12-31 | IA6: 2046-01-31 | IB6: 2046-02-28 | IC6: 2046-03-31 | ID6: 2046-04-30 | IE6: 2046-05-31 | IF6: 2046-06-30 | IG6: 2046-07-31 | IH6: 2046-08-31 | II6: 2046-09-30 | IJ6: 2046-10-31 | IK6: 2046-11-30 | IL6: 2046-12-31 | IM6: 2047-01-31 | IN6: 2047-02-28 | IO6: 2047-03-31 | IP6: 2047-04-30 | IQ6: 2047-05-31 | IR6: 2047-06-30 | IS6: 2047-07-31 | IT6: 2047-08-31 | IU6: 2047-09-30 | IV6: 2047-10-31 | IW6: 2047-11-30 | IX6: 2047-12-31 | IY6: 2048-01-31 | IZ6: 2048-02-29 | JA6: 2048-03-31 | JB6: 2048-04-30 | JC6: 2048-05-31 | JD6: 2048-06-30 | JE6: 2048-07-31 | JF6: 2048-08-31 | JG6: 2048-09-30 | JH6: 2048-10-31 | JI6: 2048-11-30 | JJ6: 2048-12-31 | JK6: 2049-01-31 | JL6: 2049-02-28 | JM6: 2049-03-31 | JN6: 2049-04-30 | JO6: 2049-05-31 | JP6: 2049-06-30 | JQ6: 2049-07-31 | JR6: 2049-08-31 | JS6: 2049-09-30 | JT6: 2049-10-31 | JU6: 2049-11-30 | JV6: 2049-12-31 | JW6: 2050-01-31 | JX6: 2050-02-28 | JY6: 2050-03-31 | JZ6: 2050-04-30 | KA6: 2050-05-31 | KB6: 2050-06-30 | KC6: 2050-07-31 | KD6: 2050-08-31 | KE6: 2050-09-30 | KF6: 2050-10-31 | KG6: 2050-11-30 | KH6: 2050-12-31 | KI6: 2051-01-31 | KJ6: 2051-02-28 | KK6: 2051-03-31 | KL6: 2051-04-30 | KM6: 2051-05-31 | KN6: 2051-06-30 | KO6: 2051-07-31 | KP6: 2051-08-31 | KQ6: 2051-09-30 | KR6: 2051-10-31 | KS6: 2051-11-30 | KT6: 2051-12-31 | KU6: 2052-01-31 | KV6: 2052-02-29 | KW6: 2052-03-31 | KX6: 2052-04-30 | KY6: 2052-05-31 | KZ6: 2052-06-30 | LA6: 2052-07-31 | LB6: 2052-08-31 | LC6: 2052-09-30 | LD6: 2052-10-31 | LE6: 2052-11-30 | LF6: 2052-12-31 | LG6: 2053-01-31 | LH6: 2053-02-28 | LI6: 2053-03-31
B7: Flag obra y puesta en marcha | D7: 0 | E7: 0 | F7: 0 | G7: 0 | H7: 0 | I7: 0 | J7: 0 | K7: 0 | L7: 0 | M7: 0 | N7: 0 | O7: 0 | P7: 0 | Q7: 0 | R7: 0 | S7: 0 | T7: 0 | U7: 0 | V7: 0 | W7: 0 | X7: 0 | Y7: 1 | Z7: 1 | AA7: 1 | AB7: 1 | AC7: 1 | AD7: 1 | AE7: 1 | AF7: 1 | AG7: 1 | AH7: 1 | AI7: 1 | AJ7: 1 | AK7: 1 | AL7: 1 | AM7: 1 | AN7: 1 | AO7: 1 | AP7: 1 | AQ7: 1 | AR7: 1 | AS7: 1 | AT7: 1 | AU7: 1 | AV7: 1 | AW7: 1 | AX7: 1 | AY7: 1 | AZ7: 0 | BA7: 0 | BB7: 0 | BC7: 0 | BD7: 0 | BE7: 0 | BF7: 0 | BG7: 0 | BH7: 0 | BI7: 0 | BJ7: 0 | BK7: 0 | BL7: 0 | BM7: 0 | BN7: 0 | BO7: 0 | BP7: 0 | BQ7: 0 | BR7: 0 | BS7: 0 | BT7: 0 | BU7: 0 | BV7: 0 | BW7: 0 | BX7: 0 | BY7: 0 | BZ7: 0 | CA7: 0 | CB7: 0 | CC7: 0 | CD7: 0 | CE7: 0 | CF7: 0 | CG7: 0 | CH7: 0 | CI7: 0 | CJ7: 0 | CK7: 0 | CL7: 0 | CM7: 0 | CN7: 0 | CO7: 0 | CP7: 0 | CQ7: 0 | CR7: 0 | CS7: 0 | CT7: 0 | CU7: 0 | CV7: 0 | CW7: 0 | CX7: 0 | CY7: 0 | CZ7: 0 | DA7: 0 | DB7: 0 | DC7: 0 | DD7: 0 | DE7: 0 | DF7: 0 | DG7: 0 | DH7: 0 | DI7: 0 | DJ7: 0 | DK7: 0 | DL7: 0 | DM7: 0 | DN7: 0 | DO7: 0 | DP7: 0 | DQ7: 0 | DR7: 0 | DS7: 0 | DT7: 0 | DU7: 0 | DV7: 0 | DW7: 0 | DX7: 0 | DY7: 0 | DZ7: 0 | EA7: 0 | EB7: 0 | EC7: 0 | ED7: 0 | EE7: 0 | EF7: 0 | EG7: 0 | EH7: 0 | EI7: 0 | EJ7: 0 | EK7: 0 | EL7: 0 | EM7: 0 | EN7: 0 | EO7: 0 | EP7: 0 | EQ7: 0 | ER7: 0 | ES7: 0 | ET7: 0 | EU7: 0 | EV7: 0 | EW7: 0 | EX7: 0 | EY7: 0 | EZ7: 0 | FA7: 0 | FB7: 0 | FC7: 0 | FD7: 0 | FE7: 0 | FF7: 0 | FG7: 0 | FH7: 0 | FI7: 0 | FJ7: 0 | FK7: 0 | FL7: 0 | FM7: 0 | FN7: 0 | FO7: 0 | FP7: 0 | FQ7: 0 | FR7: 0 | FS7: 0 | FT7: 0 | FU7: 0 | FV7: 0 | FW7: 0 | FX7: 0 | FY7: 0 | FZ7: 0 | GA7: 0 | GB7: 0 | GC7: 0 | GD7: 0 | GE7: 0 | GF7: 0 | GG7: 0 | GH7: 0 | GI7: 0 | GJ7: 0 | GK7: 0 | GL7: 0 | GM7: 0 | GN7: 0 | GO7: 0 | GP7: 0 | GQ7: 0 | GR7: 0 | GS7: 0 | GT7: 0 | GU7: 0 | GV7: 0 | GW7: 0 | GX7: 0 | GY7: 0 | GZ7: 0 | HA7: 0 | HB7: 0 | HC7: 0 | HD7: 0 | HE7: 0 | HF7: 0 | HG7: 0 | HH7: 0 | HI7: 0 | HJ7: 0 | HK7: 0 | HL7: 0 | HM7: 0 | HN7: 0 | HO7: 0 | HP7: 0 | HQ7: 0 | HR7: 0 | HS7: 0 | HT7: 0 | HU7: 0 | HV7: 0 | HW7: 0 | HX7: 0 | HY7: 0 | HZ7: 0 | IA7: 0 | IB7: 0 | IC7: 0 | ID7: 0 | IE7: 0 | IF7: 0 | IG7: 0 | IH7: 0 | II7: 0 | IJ7: 0 | IK7: 0 | IL7: 0 | IM7: 0 | IN7: 0 | IO7: 0 | IP7: 0 | IQ7: 0 | IR7: 0 | IS7: 0 | IT7: 0 | IU7: 0 | IV7: 0 | IW7: 0 | IX7: 0 | IY7: 0 | IZ7: 0 | JA7: 0 | JB7: 0 | JC7: 0 | JD7: 0 | JE7: 0 | JF7: 0 | JG7: 0 | JH7: 0 | JI7: 0 | JJ7: 0 | JK7: 0 | JL7: 0 | JM7: 0 | JN7: 0 | JO7: 0 | JP7: 0 | JQ7: 0 | JR7: 0 | JS7: 0 | JT7: 0 | JU7: 0 | JV7: 0 | JW7: 0 | JX7: 0 | JY7: 0 | JZ7: 0 | KA7: 0 | KB7: 0 | KC7: 0 | KD7: 0 | KE7: 0 | KF7: 0 | KG7: 0 | KH7: 0 | KI7: 0 | KJ7: 0 | KK7: 0 | KL7: 0 | KM7: 0 | KN7: 0 | KO7: 0 | KP7: 0 | KQ7: 0 | KR7: 0 | KS7: 0 | KT7: 0 | KU7: 0 | KV7: 0 | KW7: 0 | KX7: 0 | KY7: 0 | KZ7: 0 | LA7: 0 | LB7: 0 | LC7: 0 | LD7: 0 | LE7: 0 | LF7: 0 | LG7: 0 | LH7: 0 | LI7: 0
B8: Flag de pago de deuda | D8: 0 | E8: 0 | F8: 0 | G8: 0 | H8: 0 | I8: 0 | J8: 0 | K8: 0 | L8: 0 | M8: 0 | N8: 0 | O8: 0 | P8: 0 | Q8: 0 | R8: 0 | S8: 0 | T8: 0 | U8: 0 | V8: 0 | W8: 0 | X8: 0 | Y8: 0 | Z8: 0 | AA8: 0 | AB8: 0 | AC8: 0 | AD8: 0 | AE8: 0 | AF8: 0 | AG8: 0 | AH8: 0 | AI8: 0 | AJ8: 0 | AK8: 0 | AL8: 0 | AM8: 0 | AN8: 0 | AO8: 0 | AP8: 0 | AQ8: 0 | AR8: 0 | AS8: 0 | AT8: 0 | AU8: 0 | AV8: 0 | AW8: 0 | AX8: 0 | AY8: 0 | AZ8: 1 | BA8: 1 | BB8: 1 | BC8: 1 | BD8: 1 | BE8: 1 | BF8: 1 | BG8: 1 | BH8: 1 | BI8: 1 | BJ8: 1 | BK8: 1 | BL8: 1 | BM8: 1 | BN8: 1 | BO8: 1 | BP8: 1 | BQ8: 1 | BR8: 1 | BS8: 1 | BT8: 1 | BU8: 1 | BV8: 1 | BW8: 1 | BX8: 1 | BY8: 1 | BZ8: 1 | CA8: 1 | CB8: 1 | CC8: 1 | CD8: 1 | CE8: 1 | CF8: 1 | CG8: 1 | CH8: 1 | CI8: 1 | CJ8: 1 | CK8: 1 | CL8: 1 | CM8: 1 | CN8: 1 | CO8: 1 | CP8: 1 | CQ8: 1 | CR8: 1 | CS8: 1 | CT8: 1 | CU8: 1 | CV8: 1 | CW8: 1 | CX8: 1 | CY8: 1 | CZ8: 1 | DA8: 1 | DB8: 1 | DC8: 1 | DD8: 1 | DE8: 1 | DF8: 1 | DG8: 1 | DH8: 1 | DI8: 1 | DJ8: 1 | DK8: 1 | DL8: 1 | DM8: 1 | DN8: 1 | DO8: 1 | DP8: 1 | DQ8: 1 | DR8: 1 | DS8: 1 | DT8: 1 | DU8: 1 | DV8: 1 | DW8: 1 | DX8: 1 | DY8: 1 | DZ8: 1 | EA8: 1 | EB8: 1 | EC8: 1 | ED8: 1 | EE8: 1 | EF8: 1 | EG8: 1 | EH8: 1 | EI8: 1 | EJ8: 1 | EK8: 1 | EL8: 1 | EM8: 1 | EN8: 1 | EO8: 1 | EP8: 1 | EQ8: 1 | ER8: 1 | ES8: 1 | ET8: 1 | EU8: 1 | EV8: 1 | EW8: 1 | EX8: 1 | EY8: 1 | EZ8: 1 | FA8: 1 | FB8: 1 | FC8: 1 | FD8: 1 | FE8: 1 | FF8: 1 | FG8: 1 | FH8: 1 | FI8: 1 | FJ8: 1 | FK8: 1 | FL8: 1 | FM8: 1 | FN8: 1 | FO8: 1 | FP8: 1 | FQ8: 1 | FR8: 1 | FS8: 1 | FT8: 1 | FU8: 1 | FV8: 1 | FW8: 1 | FX8: 1 | FY8: 1 | FZ8: 1 | GA8: 1 | GB8: 1 | GC8: 1 | GD8: 1 | GE8: 1 | GF8: 1 | GG8: 1 | GH8: 1 | GI8: 1 | GJ8: 1 | GK8: 1 | GL8: 1 | GM8: 1 | GN8: 0 | GO8: 0 | GP8: 0 | GQ8: 0 | GR8: 0 | GS8: 0 | GT8: 0 | GU8: 0 | GV8: 0 | GW8: 0 | GX8: 0 | GY8: 0 | GZ8: 0 | HA8: 0 | HB8: 0 | HC8: 0 | HD8: 0 | HE8: 0 | HF8: 0 | HG8: 0 | HH8: 0 | HI8: 0 | HJ8: 0 | HK8: 0 | HL8: 0 | HM8: 0 | HN8: 0 | HO8: 0 | HP8: 0 | HQ8: 0 | HR8: 0 | HS8: 0 | HT8: 0 | HU8: 0 | HV8: 0 | HW8: 0 | HX8: 0 | HY8: 0 | HZ8: 0 | IA8: 0 | IB8: 0 | IC8: 0 | ID8: 0 | IE8: 0 | IF8: 0 | IG8: 0 | IH8: 0 | II8: 0 | IJ8: 0 | IK8: 0 | IL8: 0 | IM8: 0 | IN8: 0 | IO8: 0 | IP8: 0 | IQ8: 0 | IR8: 0 | IS8: 0 | IT8: 0 | IU8: 0 | IV8: 0 | IW8: 0 | IX8: 0 | IY8: 0 | IZ8: 0 | JA8: 0 | JB8: 0 | JC8: 0 | JD8: 0 | JE8: 0 | JF8: 0 | JG8: 0 | JH8: 0 | JI8: 0 | JJ8: 0 | JK8: 0 | JL8: 0 | JM8: 0 | JN8: 0 | JO8: 0 | JP8: 0 | JQ8: 0 | JR8: 0 | JS8: 0 | JT8: 0 | JU8: 0 | JV8: 0 | JW8: 0 | JX8: 0 | JY8: 0 | JZ8: 0 | KA8: 0 | KB8: 0 | KC8: 0 | KD8: 0 | KE8: 0 | KF8: 0 | KG8: 0 | KH8: 0 | KI8: 0 | KJ8: 0 | KK8: 0 | KL8: 0 | KM8: 0 | KN8: 0 | KO8: 0 | KP8: 0 | KQ8: 0 | KR8: 0 | KS8: 0 | KT8: 0 | KU8: 0 | KV8: 0 | KW8: 0 | KX8: 0 | KY8: 0 | KZ8: 0 | LA8: 0 | LB8: 0 | LC8: 0 | LD8: 0 | LE8: 0 | LF8: 0 | LG8: 0 | LH8: 0 | LI8: 0
B9: Inversion a financiarse | D9: 0 | E9: 0 | F9: 0 | G9: 0 | H9: 0 | I9: 0 | J9: 0 | K9: 0 | L9: 0 | M9: 0 | N9: 0 | O9: 0 | P9: 0 | Q9: 0 | R9: 0 | S9: 0 | T9: 0 | U9: 0 | V9: 0 | W9: 0 | X9: 0 | Y9: 42887.065 | Z9: 6255.7562 | AA9: 6266.0881 | AB9: 6276.4371 | AC9: 6286.8031 | AD9: 6297.1863 | AE9: 15790.504 | AF9: 15816.583 | AG9: 15842.705 | AH9: 15868.871 | AI9: 15642.805 | AJ9: 15633.192 | AK9: 13673.055 | AL9: 13671.281 | AM9: 13091.902 | AN9: 13113.525 | AO9: 14842.491 | AP9: 14831.203 | AQ9: 2451.2709 | AR9: 2455.3194 | AS9: 1600.067 | AT9: 1602.7096 | AU9: 188.97311 | AV9: 189.28521 | AW9: 189.59783 | AX9: 189.91097 | AY9: 190.22462 | AZ9: 0 | BA9: 0 | BB9: 0 | BC9: 0 | BD9: 0 | BE9: 0 | BF9: 0 | BG9: 0 | BH9: 0 | BI9: 0 | BJ9: 0 | BK9: 0 | BL9: 0 | BM9: 0 | BN9: 0 | BO9: 0 | BP9: 0 | BQ9: 0 | BR9: 0 | BS9: 0 | BT9: 0 | BU9: 0 | BV9: 0 | BW9: 0 | BX9: 0 | BY9: 0 | BZ9: 0 | CA9: 0 | CB9: 0 | CC9: 0 | CD9: 0 | CE9: 0 | CF9: 0 | CG9: 0 | CH9: 0 | CI9: 0 | CJ9: 0 | CK9: 0 | CL9: 0 | CM9: 0 | CN9: 0 | CO9: 0 | CP9: 0 | CQ9: 0 | CR9: 0 | CS9: 0 | CT9: 0 | CU9: 0 | CV9: 0 | CW9: 0 | CX9: 0 | CY9: 0 | CZ9: 0 | DA9: 0 | DB9: 0 | DC9: 0 | DD9: 0 | DE9: 0 | DF9: 0 | DG9: 0 | DH9: 0 | DI9: 0 | DJ9: 0 | DK9: 0 | DL9: 0 | DM9: 0 | DN9: 0 | DO9: 0 | DP9: 0 | DQ9: 0 | DR9: 0 | DS9: 0 | DT9: 0 | DU9: 0 | DV9: 0 | DW9: 0 | DX9: 0 | DY9: 0 | DZ9: 0 | EA9: 0 | EB9: 0 | EC9: 0 | ED9: 0 | EE9: 0 | EF9: 0 | EG9: 0 | EH9: 0 | EI9: 0 | EJ9: 0 | EK9: 0 | EL9: 0 | EM9: 0 | EN9: 0 | EO9: 0 | EP9: 0 | EQ9: 0 | ER9: 0 | ES9: 0 | ET9: 0 | EU9: 0 | EV9: 0 | EW9: 0 | EX9: 0 | EY9: 0 | EZ9: 0 | FA9: 0 | FB9: 0 | FC9: 0 | FD9: 0 | FE9: 0 | FF9: 0 | FG9: 0 | FH9: 0 | FI9: 0 | FJ9: 0 | FK9: 0 | FL9: 0 | FM9: 0 | FN9: 0 | FO9: 0 | FP9: 0 | FQ9: 0 | FR9: 0 | FS9: 0 | FT9: 0 | FU9: 0 | FV9: 0 | FW9: 0 | FX9: 0 | FY9: 0 | FZ9: 0 | GA9: 0 | GB9: 0 | GC9: 0 | GD9: 0 | GE9: 0 | GF9: 0 | GG9: 0 | GH9: 0 | GI9: 0 | GJ9: 0 | GK9: 0 | GL9: 0 | GM9: 0 | GN9: 0 | GO9: 0 | GP9: 0 | GQ9: 0 | GR9: 0 | GS9: 0 | GT9: 0 | GU9: 0 | GV9: 0 | GW9: 0 | GX9: 0 | GY9: 0 | GZ9: 0 | HA9: 0 | HB9: 0 | HC9: 0 | HD9: 0 | HE9: 0 | HF9: 0 | HG9: 0 | HH9: 0 | HI9: 0 | HJ9: 0 | HK9: 0 | HL9: 0 | HM9: 0 | HN9: 0 | HO9: 0 | HP9: 0 | HQ9: 0 | HR9: 0 | HS9: 0 | HT9: 0 | HU9: 0 | HV9: 0 | HW9: 0 | HX9: 0 | HY9: 0 | HZ9: 0 | IA9: 0 | IB9: 0 | IC9: 0 | ID9: 0 | IE9: 0 | IF9: 0 | IG9: 0 | IH9: 0 | II9: 0 | IJ9: 0 | IK9: 0 | IL9: 0 | IM9: 0 | IN9: 0 | IO9: 0 | IP9: 0 | IQ9: 0 | IR9: 0 | IS9: 0 | IT9: 0 | IU9: 0 | IV9: 0 | IW9: 0 | IX9: 0 | IY9: 0 | IZ9: 0 | JA9: 0 | JB9: 0 | JC9: 0 | JD9: 0 | JE9: 0 | JF9: 0 | JG9: 0 | JH9: 0 | JI9: 0 | JJ9: 0 | JK9: 0 | JL9: 0 | JM9: 0 | JN9: 0 | JO9: 0 | JP9: 0 | JQ9: 0 | JR9: 0 | JS9: 0 | JT9: 0 | JU9: 0 | JV9: 0 | JW9: 0 | JX9: 0 | JY9: 0 | JZ9: 0 | KA9: 0 | KB9: 0 | KC9: 0 | KD9: 0 | KE9: 0 | KF9: 0 | KG9: 0 | KH9: 0 | KI9: 0 | KJ9: 0 | KK9: 0 | KL9: 0 | KM9: 0 | KN9: 0 | KO9: 0 | KP9: 0 | KQ9: 0 | KR9: 0 | KS9: 0 | KT9: 0 | KU9: 0 | KV9: 0 | KW9: 0 | KX9: 0 | KY9: 0 | KZ9: 0 | LA9: 0 | LB9: 0 | LC9: 0 | LD9: 0 | LE9: 0 | LF9: 0 | LG9: 0 | LH9: 0 | LI9: 0
B10: Desembolsos | D10: =D7*D9*p_tamano_deuda | E10: =E7*E9*p_tamano_deuda | F10: =F7*F9*p_tamano_deuda | G10: =G7*G9*p_tamano_deuda | H10: =H7*H9*p_tamano_deuda | I10: =I7*I9*p_tamano_deuda | J10: =J7*J9*p_tamano_deuda | K10: =K7*K9*p_tamano_deuda | ... LI10: =LI7*LI9*p_tamano_deuda
B11: Tasa mensual | D11: =(1+p_kd)^(1/12)-1
B12: Saldo de obra capitalizado (base de la cuota) | D12: =0*(1+$D$11)+D10 | E12: =D12*(1+$D$11)+E10 | F12: =E12*(1+$D$11)+F10 | G12: =F12*(1+$D$11)+G10 | H12: =G12*(1+$D$11)+H10 | I12: =H12*(1+$D$11)+I10 | J12: =I12*(1+$D$11)+J10 | K12: =J12*(1+$D$11)+K10 | L12: =K12*(1+$D$11)+L10 | ... AY12: =AX12*(1+$D$11)+AY10 | AZ12: 0 | BA12: 0 | BB12: 0 | BC12: 0 | BD12: 0 | BE12: 0 | BF12: 0 | BG12: 0 | BH12: 0 | BI12: 0 | BJ12: 0 | BK12: 0 | BL12: 0 | BM12: 0 | BN12: 0 | BO12: 0 | BP12: 0 | BQ12: 0 | BR12: 0 | BS12: 0 | BT12: 0 | BU12: 0 | BV12: 0 | BW12: 0 | BX12: 0 | BY12: 0 | BZ12: 0 | CA12: 0 | CB12: 0 | CC12: 0 | CD12: 0 | CE12: 0 | CF12: 0 | CG12: 0 | CH12: 0 | CI12: 0 | CJ12: 0 | CK12: 0 | CL12: 0 | CM12: 0 | CN12: 0 | CO12: 0 | CP12: 0 | CQ12: 0 | CR12: 0 | CS12: 0 | CT12: 0 | CU12: 0 | CV12: 0 | CW12: 0 | CX12: 0 | CY12: 0 | CZ12: 0 | DA12: 0 | DB12: 0 | DC12: 0 | DD12: 0 | DE12: 0 | DF12: 0 | DG12: 0 | DH12: 0 | DI12: 0 | DJ12: 0 | DK12: 0 | DL12: 0 | DM12: 0 | DN12: 0 | DO12: 0 | DP12: 0 | DQ12: 0 | DR12: 0 | DS12: 0 | DT12: 0 | DU12: 0 | DV12: 0 | DW12: 0 | DX12: 0 | DY12: 0 | DZ12: 0 | EA12: 0 | EB12: 0 | EC12: 0 | ED12: 0 | EE12: 0 | EF12: 0 | EG12: 0 | EH12: 0 | EI12: 0 | EJ12: 0 | EK12: 0 | EL12: 0 | EM12: 0 | EN12: 0 | EO12: 0 | EP12: 0 | EQ12: 0 | ER12: 0 | ES12: 0 | ET12: 0 | EU12: 0 | EV12: 0 | EW12: 0 | EX12: 0 | EY12: 0 | EZ12: 0 | FA12: 0 | FB12: 0 | FC12: 0 | FD12: 0 | FE12: 0 | FF12: 0 | FG12: 0 | FH12: 0 | FI12: 0 | FJ12: 0 | FK12: 0 | FL12: 0 | FM12: 0 | FN12: 0 | FO12: 0 | FP12: 0 | FQ12: 0 | FR12: 0 | FS12: 0 | FT12: 0 | FU12: 0 | FV12: 0 | FW12: 0 | FX12: 0 | FY12: 0 | FZ12: 0 | GA12: 0 | GB12: 0 | GC12: 0 | GD12: 0 | GE12: 0 | GF12: 0 | GG12: 0 | GH12: 0 | GI12: 0 | GJ12: 0 | GK12: 0 | GL12: 0 | GM12: 0 | GN12: 0 | GO12: 0 | GP12: 0 | GQ12: 0 | GR12: 0 | GS12: 0 | GT12: 0 | GU12: 0 | GV12: 0 | GW12: 0 | GX12: 0 | GY12: 0 | GZ12: 0 | HA12: 0 | HB12: 0 | HC12: 0 | HD12: 0 | HE12: 0 | HF12: 0 | HG12: 0 | HH12: 0 | HI12: 0 | HJ12: 0 | HK12: 0 | HL12: 0 | HM12: 0 | HN12: 0 | HO12: 0 | HP12: 0 | HQ12: 0 | HR12: 0 | HS12: 0 | HT12: 0 | HU12: 0 | HV12: 0 | HW12: 0 | HX12: 0 | HY12: 0 | HZ12: 0 | IA12: 0 | IB12: 0 | IC12: 0 | ID12: 0 | IE12: 0 | IF12: 0 | IG12: 0 | IH12: 0 | II12: 0 | IJ12: 0 | IK12: 0 | IL12: 0 | IM12: 0 | IN12: 0 | IO12: 0 | IP12: 0 | IQ12: 0 | IR12: 0 | IS12: 0 | IT12: 0 | IU12: 0 | IV12: 0 | IW12: 0 | IX12: 0 | IY12: 0 | IZ12: 0 | JA12: 0 | JB12: 0 | JC12: 0 | JD12: 0 | JE12: 0 | JF12: 0 | JG12: 0 | JH12: 0 | JI12: 0 | JJ12: 0 | JK12: 0 | JL12: 0 | JM12: 0 | JN12: 0 | JO12: 0 | JP12: 0 | JQ12: 0 | JR12: 0 | JS12: 0 | JT12: 0 | JU12: 0 | JV12: 0 | JW12: 0 | JX12: 0 | JY12: 0 | JZ12: 0 | KA12: 0 | KB12: 0 | KC12: 0 | KD12: 0 | KE12: 0 | KF12: 0 | KG12: 0 | KH12: 0 | KI12: 0 | KJ12: 0 | KK12: 0 | KL12: 0 | KM12: 0 | KN12: 0 | KO12: 0 | KP12: 0 | KQ12: 0 | KR12: 0 | KS12: 0 | KT12: 0 | KU12: 0 | KV12: 0 | KW12: 0 | KX12: 0 | KY12: 0 | KZ12: 0 | LA12: 0 | LB12: 0 | LC12: 0 | LD12: 0 | LE12: 0 | LF12: 0 | LG12: 0 | LH12: 0 | LI12: 0
B13: Cuota constante | D13: =-PMT($D$11,p_pagos,AY12)
B14: Interes | D14: 0 | E14: =D17*$D$11 | F14: =E17*$D$11 | G14: =F17*$D$11 | H14: =G17*$D$11 | I14: =H17*$D$11 | J14: =I17*$D$11 | K14: =J17*$D$11 | L14: =K17*$D$11 | ... LI14: =LH17*$D$11
B15: Amortizacion | D15: =D16-D14 | E15: =E16-E14 | F15: =F16-F14 | G15: =G16-G14 | H15: =H16-H14 | I15: =I16-I14 | J15: =J16-J14 | K15: =K16-K14 | ... LI15: =LI16-LI14
B16: Servicio de deuda | D16: =D8*$D$13 | E16: =E8*$D$13 | F16: =F8*$D$13 | G16: =G8*$D$13 | H16: =H8*$D$13 | I16: =I8*$D$13 | J16: =J8*$D$13 | K16: =K8*$D$13 | ... LI16: =LI8*$D$13
B17: Saldo deudor | D17: =0+D10-D15 | E17: =D17+E10-E15 | F17: =E17+F10-F15 | G17: =F17+G10-G15 | H17: =G17+H10-H15 | I17: =H17+I10-I15 | J17: =I17+J10-J15 | K17: =J17+K10-K15 | L17: =K17+L10-L15 | ... LI17: =LH17+LI10-LI15

Sheet Activo financiero
B2: Activo financiero del PPDI
B3: CINIIF 12 p.16: derecho incondicional de cobro, no intangible. Amortizacion = cobro del mes menos ingreso financiero devengado.
B6: Mes | D6: 2026-10-31 | E6: 2026-11-30 | F6: 2026-12-31 | G6: 2027-01-31 | H6: 2027-02-28 | I6: 2027-03-31 | J6: 2027-04-30 | K6: 2027-05-31 | L6: 2027-06-30 | M6: 2027-07-31 | N6: 2027-08-31 | O6: 2027-09-30 | P6: 2027-10-31 | Q6: 2027-11-30 | R6: 2027-12-31 | S6: 2028-01-31 | T6: 2028-02-29 | U6: 2028-03-31 | V6: 2028-04-30 | W6: 2028-05-31 | X6: 2028-06-30 | Y6: 2028-07-31 | Z6: 2028-08-31 | AA6: 2028-09-30 | AB6: 2028-10-31 | AC6: 2028-11-30 | AD6: 2028-12-31 | AE6: 2029-01-31 | AF6: 2029-02-28 | AG6: 2029-03-31 | AH6: 2029-04-30 | AI6: 2029-05-31 | AJ6: 2029-06-30 | AK6: 2029-07-31 | AL6: 2029-08-31 | AM6: 2029-09-30 | AN6: 2029-10-31 | AO6: 2029-11-30 | AP6: 2029-12-31 | AQ6: 2030-01-31 | AR6: 2030-02-28 | AS6: 2030-03-31 | AT6: 2030-04-30 | AU6: 2030-05-31 | AV6: 2030-06-30 | AW6: 2030-07-31 | AX6: 2030-08-31 | AY6: 2030-09-30 | AZ6: 2030-10-31 | BA6: 2030-11-30 | BB6: 2030-12-31 | BC6: 2031-01-31 | BD6: 2031-02-28 | BE6: 2031-03-31 | BF6: 2031-04-30 | BG6: 2031-05-31 | BH6: 2031-06-30 | BI6: 2031-07-31 | BJ6: 2031-08-31 | BK6: 2031-09-30 | BL6: 2031-10-31 | BM6: 2031-11-30 | BN6: 2031-12-31 | BO6: 2032-01-31 | BP6: 2032-02-29 | BQ6: 2032-03-31 | BR6: 2032-04-30 | BS6: 2032-05-31 | BT6: 2032-06-30 | BU6: 2032-07-31 | BV6: 2032-08-31 | BW6: 2032-09-30 | BX6: 2032-10-31 | BY6: 2032-11-30 | BZ6: 2032-12-31 | CA6: 2033-01-31 | CB6: 2033-02-28 | CC6: 2033-03-31 | CD6: 2033-04-30 | CE6: 2033-05-31 | CF6: 2033-06-30 | CG6: 2033-07-31 | CH6: 2033-08-31 | CI6: 2033-09-30 | CJ6: 2033-10-31 | CK6: 2033-11-30 | CL6: 2033-12-31 | CM6: 2034-01-31 | CN6: 2034-02-28 | CO6: 2034-03-31 | CP6: 2034-04-30 | CQ6: 2034-05-31 | CR6: 2034-06-30 | CS6: 2034-07-31 | CT6: 2034-08-31 | CU6: 2034-09-30 | CV6: 2034-10-31 | CW6: 2034-11-30 | CX6: 2034-12-31 | CY6: 2035-01-31 | CZ6: 2035-02-28 | DA6: 2035-03-31 | DB6: 2035-04-30 | DC6: 2035-05-31 | DD6: 2035-06-30 | DE6: 2035-07-31 | DF6: 2035-08-31 | DG6: 2035-09-30 | DH6: 2035-10-31 | DI6: 2035-11-30 | DJ6: 2035-12-31 | DK6: 2036-01-31 | DL6: 2036-02-29 | DM6: 2036-03-31 | DN6: 2036-04-30 | DO6: 2036-05-31 | DP6: 2036-06-30 | DQ6: 2036-07-31 | DR6: 2036-08-31 | DS6: 2036-09-30 | DT6: 2036-10-31 | DU6: 2036-11-30 | DV6: 2036-12-31 | DW6: 2037-01-31 | DX6: 2037-02-28 | DY6: 2037-03-31 | DZ6: 2037-04-30 | EA6: 2037-05-31 | EB6: 2037-06-30 | EC6: 2037-07-31 | ED6: 2037-08-31 | EE6: 2037-09-30 | EF6: 2037-10-31 | EG6: 2037-11-30 | EH6: 2037-12-31 | EI6: 2038-01-31 | EJ6: 2038-02-28 | EK6: 2038-03-31 | EL6: 2038-04-30 | EM6: 2038-05-31 | EN6: 2038-06-30 | EO6: 2038-07-31 | EP6: 2038-08-31 | EQ6: 2038-09-30 | ER6: 2038-10-31 | ES6: 2038-11-30 | ET6: 2038-12-31 | EU6: 2039-01-31 | EV6: 2039-02-28 | EW6: 2039-03-31 | EX6: 2039-04-30 | EY6: 2039-05-31 | EZ6: 2039-06-30 | FA6: 2039-07-31 | FB6: 2039-08-31 | FC6: 2039-09-30 | FD6: 2039-10-31 | FE6: 2039-11-30 | FF6: 2039-12-31 | FG6: 2040-01-31 | FH6: 2040-02-29 | FI6: 2040-03-31 | FJ6: 2040-04-30 | FK6: 2040-05-31 | FL6: 2040-06-30 | FM6: 2040-07-31 | FN6: 2040-08-31 | FO6: 2040-09-30 | FP6: 2040-10-31 | FQ6: 2040-11-30 | FR6: 2040-12-31 | FS6: 2041-01-31 | FT6: 2041-02-28 | FU6: 2041-03-31 | FV6: 2041-04-30 | FW6: 2041-05-31 | FX6: 2041-06-30 | FY6: 2041-07-31 | FZ6: 2041-08-31 | GA6: 2041-09-30 | GB6: 2041-10-31 | GC6: 2041-11-30 | GD6: 2041-12-31 | GE6: 2042-01-31 | GF6: 2042-02-28 | GG6: 2042-03-31 | GH6: 2042-04-30 | GI6: 2042-05-31 | GJ6: 2042-06-30 | GK6: 2042-07-31 | GL6: 2042-08-31 | GM6: 2042-09-30 | GN6: 2042-10-31 | GO6: 2042-11-30 | GP6: 2042-12-31 | GQ6: 2043-01-31 | GR6: 2043-02-28 | GS6: 2043-03-31 | GT6: 2043-04-30 | GU6: 2043-05-31 | GV6: 2043-06-30 | GW6: 2043-07-31 | GX6: 2043-08-31 | GY6: 2043-09-30 | GZ6: 2043-10-31 | HA6: 2043-11-30 | HB6: 2043-12-31 | HC6: 2044-01-31 | HD6: 2044-02-29 | HE6: 2044-03-31 | HF6: 2044-04-30 | HG6: 2044-05-31 | HH6: 2044-06-30 | HI6: 2044-07-31 | HJ6: 2044-08-31 | HK6: 2044-09-30 | HL6: 2044-10-31 | HM6: 2044-11-30 | HN6: 2044-12-31 | HO6: 2045-01-31 | HP6: 2045-02-28 | HQ6: 2045-03-31 | HR6: 2045-04-30 | HS6: 2045-05-31 | HT6: 2045-06-30 | HU6: 2045-07-31 | HV6: 2045-08-31 | HW6: 2045-09-30 | HX6: 2045-10-31 | HY6: 2045-11-30 | HZ6: 2045-12-31 | IA6: 2046-01-31 | IB6: 2046-02-28 | IC6: 2046-03-31 | ID6: 2046-04-30 | IE6: 2046-05-31 | IF6: 2046-06-30 | IG6: 2046-07-31 | IH6: 2046-08-31 | II6: 2046-09-30 | IJ6: 2046-10-31 | IK6: 2046-11-30 | IL6: 2046-12-31 | IM6: 2047-01-31 | IN6: 2047-02-28 | IO6: 2047-03-31 | IP6: 2047-04-30 | IQ6: 2047-05-31 | IR6: 2047-06-30 | IS6: 2047-07-31 | IT6: 2047-08-31 | IU6: 2047-09-30 | IV6: 2047-10-31 | IW6: 2047-11-30 | IX6: 2047-12-31 | IY6: 2048-01-31 | IZ6: 2048-02-29 | JA6: 2048-03-31 | JB6: 2048-04-30 | JC6: 2048-05-31 | JD6: 2048-06-30 | JE6: 2048-07-31 | JF6: 2048-08-31 | JG6: 2048-09-30 | JH6: 2048-10-31 | JI6: 2048-11-30 | JJ6: 2048-12-31 | JK6: 2049-01-31 | JL6: 2049-02-28 | JM6: 2049-03-31 | JN6: 2049-04-30 | JO6: 2049-05-31 | JP6: 2049-06-30 | JQ6: 2049-07-31 | JR6: 2049-08-31 | JS6: 2049-09-30 | JT6: 2049-10-31 | JU6: 2049-11-30 | JV6: 2049-12-31 | JW6: 2050-01-31 | JX6: 2050-02-28 | JY6: 2050-03-31 | JZ6: 2050-04-30 | KA6: 2050-05-31 | KB6: 2050-06-30 | KC6: 2050-07-31 | KD6: 2050-08-31 | KE6: 2050-09-30 | KF6: 2050-10-31 | KG6: 2050-11-30 | KH6: 2050-12-31 | KI6: 2051-01-31 | KJ6: 2051-02-28 | KK6: 2051-03-31 | KL6: 2051-04-30 | KM6: 2051-05-31 | KN6: 2051-06-30 | KO6: 2051-07-31 | KP6: 2051-08-31 | KQ6: 2051-09-30 | KR6: 2051-10-31 | KS6: 2051-11-30 | KT6: 2051-12-31 | KU6: 2052-01-31 | KV6: 2052-02-29 | KW6: 2052-03-31 | KX6: 2052-04-30 | KY6: 2052-05-31 | KZ6: 2052-06-30 | LA6: 2052-07-31 | LB6: 2052-08-31 | LC6: 2052-09-30
B7: Tasa implicita mensual | C7: TIR del activo | D7: 0.0086694967
B8: Flag de devengo del PPDI | D8: 0 | E8: 0 | F8: 0 | G8: 0 | H8: 0 | I8: 0 | J8: 0 | K8: 0 | L8: 0 | M8: 0 | N8: 0 | O8: 0 | P8: 0 | Q8: 0 | R8: 0 | S8: 0 | T8: 0 | U8: 0 | V8: 0 | W8: 0 | X8: 0 | Y8: 0 | Z8: 0 | AA8: 0 | AB8: 0 | AC8: 0 | AD8: 0 | AE8: 0 | AF8: 0 | AG8: 0 | AH8: 0 | AI8: 0 | AJ8: 0 | AK8: 0 | AL8: 0 | AM8: 0 | AN8: 0 | AO8: 0 | AP8: 0 | AQ8: 0 | AR8: 0 | AS8: 0 | AT8: 0 | AU8: 0 | AV8: 0 | AW8: 0 | AX8: 0 | AY8: 0 | AZ8: 1 | BA8: 1 | BB8: 1 | BC8: 1 | BD8: 1 | BE8: 1 | BF8: 1 | BG8: 1 | BH8: 1 | BI8: 1 | BJ8: 1 | BK8: 1 | BL8: 1 | BM8: 1 | BN8: 1 | BO8: 1 | BP8: 1 | BQ8: 1 | BR8: 1 | BS8: 1 | BT8: 1 | BU8: 1 | BV8: 1 | BW8: 1 | BX8: 1 | BY8: 1 | BZ8: 1 | CA8: 1 | CB8: 1 | CC8: 1 | CD8: 1 | CE8: 1 | CF8: 1 | CG8: 1 | CH8: 1 | CI8: 1 | CJ8: 1 | CK8: 1 | CL8: 1 | CM8: 1 | CN8: 1 | CO8: 1 | CP8: 1 | CQ8: 1 | CR8: 1 | CS8: 1 | CT8: 1 | CU8: 1 | CV8: 1 | CW8: 1 | CX8: 1 | CY8: 1 | CZ8: 1 | DA8: 1 | DB8: 1 | DC8: 1 | DD8: 1 | DE8: 1 | DF8: 1 | DG8: 1 | DH8: 1 | DI8: 1 | DJ8: 1 | DK8: 1 | DL8: 1 | DM8: 1 | DN8: 1 | DO8: 1 | DP8: 1 | DQ8: 1 | DR8: 1 | DS8: 1 | DT8: 1 | DU8: 1 | DV8: 1 | DW8: 1 | DX8: 1 | DY8: 1 | DZ8: 1 | EA8: 1 | EB8: 1 | EC8: 1 | ED8: 1 | EE8: 1 | EF8: 1 | EG8: 1 | EH8: 1 | EI8: 1 | EJ8: 1 | EK8: 1 | EL8: 1 | EM8: 1 | EN8: 1 | EO8: 1 | EP8: 1 | EQ8: 1 | ER8: 1 | ES8: 1 | ET8: 1 | EU8: 1 | EV8: 1 | EW8: 1 | EX8: 1 | EY8: 1 | EZ8: 1 | FA8: 1 | FB8: 1 | FC8: 1 | FD8: 1 | FE8: 1 | FF8: 1 | FG8: 1 | FH8: 1 | FI8: 1 | FJ8: 1 | FK8: 1 | FL8: 1 | FM8: 1 | FN8: 1 | FO8: 1 | FP8: 1 | FQ8: 1 | FR8: 1 | FS8: 1 | FT8: 1 | FU8: 1 | FV8: 1 | FW8: 1 | FX8: 1 | FY8: 1 | FZ8: 1 | GA8: 1 | GB8: 1 | GC8: 1 | GD8: 1 | GE8: 1 | GF8: 1 | GG8: 1 | GH8: 1 | GI8: 1 | GJ8: 1 | GK8: 1 | GL8: 1 | GM8: 1 | GN8: 1 | GO8: 1 | GP8: 1 | GQ8: 1 | GR8: 1 | GS8: 1 | GT8: 1 | GU8: 1 | GV8: 1 | GW8: 1 | GX8: 1 | GY8: 1 | GZ8: 1 | HA8: 1 | HB8: 1 | HC8: 1 | HD8: 1 | HE8: 1 | HF8: 1 | HG8: 1 | HH8: 1 | HI8: 1 | HJ8: 1 | HK8: 1 | HL8: 1 | HM8: 1 | HN8: 1 | HO8: 1 | HP8: 1 | HQ8: 1 | HR8: 1 | HS8: 1 | HT8: 1 | HU8: 1 | HV8: 1 | HW8: 1 | HX8: 0 | HY8: 0 | HZ8: 0 | IA8: 0 | IB8: 0 | IC8: 0 | ID8: 0 | IE8: 0 | IF8: 0 | IG8: 0 | IH8: 0 | II8: 0 | IJ8: 0 | IK8: 0 | IL8: 0 | IM8: 0 | IN8: 0 | IO8: 0 | IP8: 0 | IQ8: 0 | IR8: 0 | IS8: 0 | IT8: 0 | IU8: 0 | IV8: 0 | IW8: 0 | IX8: 0 | IY8: 0 | IZ8: 0 | JA8: 0 | JB8: 0 | JC8: 0 | JD8: 0 | JE8: 0 | JF8: 0 | JG8: 0 | JH8: 0 | JI8: 0 | JJ8: 0 | JK8: 0 | JL8: 0 | JM8: 0 | JN8: 0 | JO8: 0 | JP8: 0 | JQ8: 0 | JR8: 0 | JS8: 0 | JT8: 0 | JU8: 0 | JV8: 0 | JW8: 0 | JX8: 0 | JY8: 0 | JZ8: 0 | KA8: 0 | KB8: 0 | KC8: 0 | KD8: 0 | KE8: 0 | KF8: 0 | KG8: 0 | KH8: 0 | KI8: 0 | KJ8: 0 | KK8: 0 | KL8: 0 | KM8: 0 | KN8: 0 | KO8: 0 | KP8: 0 | KQ8: 0 | KR8: 0 | KS8: 0 | KT8: 0 | KU8: 0 | KV8: 0 | KW8: 0 | KX8: 0 | KY8: 0 | KZ8: 0 | LA8: 0 | LB8: 0 | LC8: 0
B9: Flag de cobro (cierre de trimestre) | D9: 0 | E9: 0 | F9: 0 | G9: 0 | H9: 0 | I9: 0 | J9: 0 | K9: 0 | L9: 0 | M9: 0 | N9: 0 | O9: 0 | P9: 0 | Q9: 0 | R9: 0 | S9: 0 | T9: 0 | U9: 0 | V9: 0 | W9: 0 | X9: 0 | Y9: 0 | Z9: 0 | AA9: 0 | AB9: 0 | AC9: 0 | AD9: 0 | AE9: 0 | AF9: 0 | AG9: 0 | AH9: 0 | AI9: 0 | AJ9: 0 | AK9: 0 | AL9: 0 | AM9: 0 | AN9: 0 | AO9: 0 | AP9: 0 | AQ9: 0 | AR9: 0 | AS9: 0 | AT9: 0 | AU9: 0 | AV9: 0 | AW9: 0 | AX9: 0 | AY9: 0 | AZ9: 0 | BA9: 0 | BB9: 1 | BC9: 0 | BD9: 0 | BE9: 1 | BF9: 0 | BG9: 0 | BH9: 1 | BI9: 0 | BJ9: 0 | BK9: 1 | BL9: 0 | BM9: 0 | BN9: 1 | BO9: 0 | BP9: 0 | BQ9: 1 | BR9: 0 | BS9: 0 | BT9: 1 | BU9: 0 | BV9: 0 | BW9: 1 | BX9: 0 | BY9: 0 | BZ9: 1 | CA9: 0 | CB9: 0 | CC9: 1 | CD9: 0 | CE9: 0 | CF9: 1 | CG9: 0 | CH9: 0 | CI9: 1 | CJ9: 0 | CK9: 0 | CL9: 1 | CM9: 0 | CN9: 0 | CO9: 1 | CP9: 0 | CQ9: 0 | CR9: 1 | CS9: 0 | CT9: 0 | CU9: 1 | CV9: 0 | CW9: 0 | CX9: 1 | CY9: 0 | CZ9: 0 | DA9: 1 | DB9: 0 | DC9: 0 | DD9: 1 | DE9: 0 | DF9: 0 | DG9: 1 | DH9: 0 | DI9: 0 | DJ9: 1 | DK9: 0 | DL9: 0 | DM9: 1 | DN9: 0 | DO9: 0 | DP9: 1 | DQ9: 0 | DR9: 0 | DS9: 1 | DT9: 0 | DU9: 0 | DV9: 1 | DW9: 0 | DX9: 0 | DY9: 1 | DZ9: 0 | EA9: 0 | EB9: 1 | EC9: 0 | ED9: 0 | EE9: 1 | EF9: 0 | EG9: 0 | EH9: 1 | EI9: 0 | EJ9: 0 | EK9: 1 | EL9: 0 | EM9: 0 | EN9: 1 | EO9: 0 | EP9: 0 | EQ9: 1 | ER9: 0 | ES9: 0 | ET9: 1 | EU9: 0 | EV9: 0 | EW9: 1 | EX9: 0 | EY9: 0 | EZ9: 1 | FA9: 0 | FB9: 0 | FC9: 1 | FD9: 0 | FE9: 0 | FF9: 1 | FG9: 0 | FH9: 0 | FI9: 1 | FJ9: 0 | FK9: 0 | FL9: 1 | FM9: 0 | FN9: 0 | FO9: 1 | FP9: 0 | FQ9: 0 | FR9: 1 | FS9: 0 | FT9: 0 | FU9: 1 | FV9: 0 | FW9: 0 | FX9: 1 | FY9: 0 | FZ9: 0 | GA9: 1 | GB9: 0 | GC9: 0 | GD9: 1 | GE9: 0 | GF9: 0 | GG9: 1 | GH9: 0 | GI9: 0 | GJ9: 1 | GK9: 0 | GL9: 0 | GM9: 1 | GN9: 0 | GO9: 0 | GP9: 1 | GQ9: 0 | GR9: 0 | GS9: 1 | GT9: 0 | GU9: 0 | GV9: 1 | GW9: 0 | GX9: 0 | GY9: 1 | GZ9: 0 | HA9: 0 | HB9: 1 | HC9: 0 | HD9: 0 | HE9: 1 | HF9: 0 | HG9: 0 | HH9: 1 | HI9: 0 | HJ9: 0 | HK9: 1 | HL9: 0 | HM9: 0 | HN9: 1 | HO9: 0 | HP9: 0 | HQ9: 1 | HR9: 0 | HS9: 0 | HT9: 1 | HU9: 0 | HV9: 0 | HW9: 1 | HX9: 0 | HY9: 0 | HZ9: 0 | IA9: 0 | IB9: 0 | IC9: 0 | ID9: 0 | IE9: 0 | IF9: 0 | IG9: 0 | IH9: 0 | II9: 0 | IJ9: 0 | IK9: 0 | IL9: 0 | IM9: 0 | IN9: 0 | IO9: 0 | IP9: 0 | IQ9: 0 | IR9: 0 | IS9: 0 | IT9: 0 | IU9: 0 | IV9: 0 | IW9: 0 | IX9: 0 | IY9: 0 | IZ9: 0 | JA9: 0 | JB9: 0 | JC9: 0 | JD9: 0 | JE9: 0 | JF9: 0 | JG9: 0 | JH9: 0 | JI9: 0 | JJ9: 0 | JK9: 0 | JL9: 0 | JM9: 0 | JN9: 0 | JO9: 0 | JP9: 0 | JQ9: 0 | JR9: 0 | JS9: 0 | JT9: 0 | JU9: 0 | JV9: 0 | JW9: 0 | JX9: 0 | JY9: 0 | JZ9: 0 | KA9: 0 | KB9: 0 | KC9: 0 | KD9: 0 | KE9: 0 | KF9: 0 | KG9: 0 | KH9: 0 | KI9: 0 | KJ9: 0 | KK9: 0 | KL9: 0 | KM9: 0 | KN9: 0 | KO9: 0 | KP9: 0 | KQ9: 0 | KR9: 0 | KS9: 0 | KT9: 0 | KU9: 0 | KV9: 0 | KW9: 0 | KX9: 0 | KY9: 0 | KZ9: 0 | LA9: 0 | LB9: 0 | LC9: 0
B10: PPDI devengado | D10: =D8*p_ppdi_anual/12 | E10: =E8*p_ppdi_anual/12 | F10: =F8*p_ppdi_anual/12 | G10: =G8*p_ppdi_anual/12 | H10: =H8*p_ppdi_anual/12 | I10: =I8*p_ppdi_anual/12 | J10: =J8*p_ppdi_anual/12 | K10: =K8*p_ppdi_anual/12 | ... LC10: =LC8*p_ppdi_anual/12
B11: PPDI cobrado | D11: =IF(D9=1,0+D10,0) | E11: =IF(E9=1,D12+E10,0) | F11: =IF(F9=1,E12+F10,0) | G11: =IF(G9=1,F12+G10,0) | H11: =IF(H9=1,G12+H10,0) | I11: =IF(I9=1,H12+I10,0) | J11: =IF(J9=1,I12+J10,0) | K11: =IF(K9=1,J12+K10,0) | L11: =IF(L9=1,K12+L10,0) | ... LC11: =IF(LC9=1,LB12+LC10,0)
B12: Devengado pendiente de cobro | D12: =0+D10-D11 | E12: =D12+E10-E11 | F12: =E12+F10-F11 | G12: =F12+G10-G11 | H12: =G12+H10-H11 | I12: =H12+I10-I11 | J12: =I12+J10-J11 | K12: =J12+K10-K11 | L12: =K12+L10-L11 | ... LC12: =LB12+LC10-LC11
B13: Saldo inicial del activo | D13: 0 | E13: =D17 | F13: =E17 | G13: =F17 | H13: =G17 | I13: =H17 | J13: =I17 | K13: =J17 | L13: =K17 | ... LC13: =LB17
B14: Servicio de construccion del periodo | D14: 9871.0611 | E14: 1436.3191 | F14: 1438.6913 | G14: 1441.0674 | H14: 1443.4474 | I14: 1445.8314 | J14: 1456.5526 | K14: 1458.9445 | L14: 1461.3403 | M14: 1381.0649 | N14: 1383.3321 | O14: 1385.603 | P14: 49.876039 | Q14: 49.94465 | R14: 50.013374 | S14: 133.57997 | T14: 8.3333333 | U14: 8.3333333 | V14: 8.3333333 | W14: 8.3333333 | X14: 8.3333333 | Y14: 47218.558 | Z14: 6404.7806 | AA14: 6410.9541 | AB14: 6417.1378 | AC14: 6423.3317 | AD14: 6429.5359 | AE14: 15912.374 | AF14: 15927.957 | AG14: 15943.566 | AH14: 15959.2 | AI14: 15722.754 | AJ14: 15702.765 | AK14: 13733.555 | AL14: 13722.708 | AM14: 13134.641 | AN14: 13147.561 | AO14: 14866.677 | AP14: 14845.547 | AQ14: 2463.9882 | AR14: 2466.4073 | AS14: 1610.093 | AT14: 1611.6721 | AU14: 197.81015 | AV14: 197.99664 | AW14: 198.18343 | AX14: 198.37054 | AY14: 198.55795 | AZ14: 0 | BA14: 0 | BB14: 0 | BC14: 0 | BD14: 0 | BE14: 0 | BF14: 0 | BG14: 0 | BH14: 0 | BI14: 0 | BJ14: 0 | BK14: 0 | BL14: 0 | BM14: 0 | BN14: 0 | BO14: 0 | BP14: 0 | BQ14: 0 | BR14: 0 | BS14: 0 | BT14: 0 | BU14: 0 | BV14: 0 | BW14: 0 | BX14: 0 | BY14: 0 | BZ14: 0 | CA14: 0 | CB14: 0 | CC14: 0 | CD14: 0 | CE14: 0 | CF14: 0 | CG14: 0 | CH14: 0 | CI14: 0 | CJ14: 0 | CK14: 0 | CL14: 0 | CM14: 0 | CN14: 0 | CO14: 0 | CP14: 0 | CQ14: 0 | CR14: 0 | CS14: 0 | CT14: 0 | CU14: 0 | CV14: 0 | CW14: 0 | CX14: 0 | CY14: 0 | CZ14: 0 | DA14: 0 | DB14: 0 | DC14: 0 | DD14: 0 | DE14: 0 | DF14: 0 | DG14: 0 | DH14: 0 | DI14: 0 | DJ14: 0 | DK14: 0 | DL14: 0 | DM14: 0 | DN14: 0 | DO14: 0 | DP14: 0 | DQ14: 0 | DR14: 0 | DS14: 0 | DT14: 0 | DU14: 0 | DV14: 0 | DW14: 0 | DX14: 0 | DY14: 0 | DZ14: 0 | EA14: 0 | EB14: 0 | EC14: 0 | ED14: 0 | EE14: 0 | EF14: 0 | EG14: 0 | EH14: 0 | EI14: 0 | EJ14: 0 | EK14: 0 | EL14: 0 | EM14: 0 | EN14: 0 | EO14: 0 | EP14: 0 | EQ14: 0 | ER14: 0 | ES14: 0 | ET14: 0 | EU14: 0 | EV14: 0 | EW14: 0 | EX14: 0 | EY14: 0 | EZ14: 0 | FA14: 0 | FB14: 0 | FC14: 0 | FD14: 0 | FE14: 0 | FF14: 0 | FG14: 0 | FH14: 0 | FI14: 0 | FJ14: 0 | FK14: 0 | FL14: 0 | FM14: 0 | FN14: 0 | FO14: 0 | FP14: 0 | FQ14: 0 | FR14: 0 | FS14: 0 | FT14: 0 | FU14: 0 | FV14: 0 | FW14: 0 | FX14: 0 | FY14: 0 | FZ14: 0 | GA14: 0 | GB14: 0 | GC14: 0 | GD14: 0 | GE14: 0 | GF14: 0 | GG14: 0 | GH14: 0 | GI14: 0 | GJ14: 0 | GK14: 0 | GL14: 0 | GM14: 0 | GN14: 0 | GO14: 0 | GP14: 0 | GQ14: 0 | GR14: 0 | GS14: 0 | GT14: 0 | GU14: 0 | GV14: 0 | GW14: 0 | GX14: 0 | GY14: 0 | GZ14: 0 | HA14: 0 | HB14: 0 | HC14: 0 | HD14: 0 | HE14: 0 | HF14: 0 | HG14: 0 | HH14: 0 | HI14: 0 | HJ14: 0 | HK14: 0 | HL14: 0 | HM14: 0 | HN14: 0 | HO14: 0 | HP14: 0 | HQ14: 0 | HR14: 0 | HS14: 0 | HT14: 0 | HU14: 0 | HV14: 0 | HW14: 0 | HX14: 0 | HY14: 0 | HZ14: 0 | IA14: 0 | IB14: 0 | IC14: 0 | ID14: 0 | IE14: 0 | IF14: 0 | IG14: 0 | IH14: 0 | II14: 0 | IJ14: 0 | IK14: 0 | IL14: 0 | IM14: 0 | IN14: 0 | IO14: 0 | IP14: 0 | IQ14: 0 | IR14: 0 | IS14: 0 | IT14: 0 | IU14: 0 | IV14: 0 | IW14: 0 | IX14: 0 | IY14: 0 | IZ14: 0 | JA14: 0 | JB14: 0 | JC14: 0 | JD14: 0 | JE14: 0 | JF14: 0 | JG14: 0 | JH14: 0 | JI14: 0 | JJ14: 0 | JK14: 0 | JL14: 0 | JM14: 0 | JN14: 0 | JO14: 0 | JP14: 0 | JQ14: 0 | JR14: 0 | JS14: 0 | JT14: 0 | JU14: 0 | JV14: 0 | JW14: 0 | JX14: 0 | JY14: 0 | JZ14: 0 | KA14: 0 | KB14: 0 | KC14: 0 | KD14: 0 | KE14: 0 | KF14: 0 | KG14: 0 | KH14: 0 | KI14: 0 | KJ14: 0 | KK14: 0 | KL14: 0 | KM14: 0 | KN14: 0 | KO14: 0 | KP14: 0 | KQ14: 0 | KR14: 0 | KS14: 0 | KT14: 0 | KU14: 0 | KV14: 0 | KW14: 0 | KX14: 0 | KY14: 0 | KZ14: 0 | LA14: 0 | LB14: 0 | LC14: 0
B15: Ingreso financiero devengado | D15: =D13*$D$7 | E15: =E13*$D$7 | F15: =F13*$D$7 | G15: =G13*$D$7 | H15: =H13*$D$7 | I15: =I13*$D$7 | J15: =J13*$D$7 | K15: =K13*$D$7 | ... LC15: =LC13*$D$7
B16: Amortizacion del activo (cobro - ingreso financiero) | D16: =D11-D15 | E16: =E11-E15 | F16: =F11-F15 | G16: =G11-G15 | H16: =H11-H15 | I16: =I11-I15 | J16: =J11-J15 | K16: =K11-K15 | ... LC16: =LC11-LC15
B17: Saldo final del activo | D17: =D13+D14+D15-D11 | E17: =E13+E14+E15-E11 | F17: =F13+F14+F15-F11 | G17: =G13+G14+G15-G11 | H17: =H13+H14+H15-H11 | I17: =I13+I14+I15-I11 | J17: =J13+J14+J15-J11 | K17: =K13+K14+K15-K11 | ... LC17: =LC13+LC14+LC15-LC11
B19: Saldo maximo del activo | D19: =MAX($D$17:$LC$17)
B20: Amortizacion acumulada | D20: =SUM($D$16:$LC$16)
B21: Saldo final, debe ser cero | D21: =$LC$17
B22: Meses con amortizacion negativa (el activo crece) | D22: =COUNTIF($D$16:$LC$16,"<0")

Sheet PPDMO
B2: PPD de operacion y mantenimiento
B3: Ingresos reajustados por IPM con gatillo; la pata fija es costo mas margen.
B6: Mes | D6: 2026-10-31 | E6: 2026-11-30 | F6: 2026-12-31 | G6: 2027-01-31 | H6: 2027-02-28 | I6: 2027-03-31 | J6: 2027-04-30 | K6: 2027-05-31 | L6: 2027-06-30 | M6: 2027-07-31 | N6: 2027-08-31 | O6: 2027-09-30 | P6: 2027-10-31 | Q6: 2027-11-30 | R6: 2027-12-31 | S6: 2028-01-31 | T6: 2028-02-29 | U6: 2028-03-31 | V6: 2028-04-30 | W6: 2028-05-31 | X6: 2028-06-30 | Y6: 2028-07-31 | Z6: 2028-08-31 | AA6: 2028-09-30 | AB6: 2028-10-31 | AC6: 2028-11-30 | AD6: 2028-12-31 | AE6: 2029-01-31 | AF6: 2029-02-28 | AG6: 2029-03-31 | AH6: 2029-04-30 | AI6: 2029-05-31 | AJ6: 2029-06-30 | AK6: 2029-07-31 | AL6: 2029-08-31 | AM6: 2029-09-30 | AN6: 2029-10-31 | AO6: 2029-11-30 | AP6: 2029-12-31 | AQ6: 2030-01-31 | AR6: 2030-02-28 | AS6: 2030-03-31 | AT6: 2030-04-30 | AU6: 2030-05-31 | AV6: 2030-06-30 | AW6: 2030-07-31 | AX6: 2030-08-31 | AY6: 2030-09-30 | AZ6: 2030-10-31 | BA6: 2030-11-30 | BB6: 2030-12-31 | BC6: 2031-01-31 | BD6: 2031-02-28 | BE6: 2031-03-31 | BF6: 2031-04-30 | BG6: 2031-05-31 | BH6: 2031-06-30 | BI6: 2031-07-31 | BJ6: 2031-08-31 | BK6: 2031-09-30 | BL6: 2031-10-31 | BM6: 2031-11-30 | BN6: 2031-12-31 | BO6: 2032-01-31 | BP6: 2032-02-29 | BQ6: 2032-03-31 | BR6: 2032-04-30 | BS6: 2032-05-31 | BT6: 2032-06-30 | BU6: 2032-07-31 | BV6: 2032-08-31 | BW6: 2032-09-30 | BX6: 2032-10-31 | BY6: 2032-11-30 | BZ6: 2032-12-31 | CA6: 2033-01-31 | CB6: 2033-02-28 | CC6: 2033-03-31 | CD6: 2033-04-30 | CE6: 2033-05-31 | CF6: 2033-06-30 | CG6: 2033-07-31 | CH6: 2033-08-31 | CI6: 2033-09-30 | CJ6: 2033-10-31 | CK6: 2033-11-30 | CL6: 2033-12-31 | CM6: 2034-01-31 | CN6: 2034-02-28 | CO6: 2034-03-31 | CP6: 2034-04-30 | CQ6: 2034-05-31 | CR6: 2034-06-30 | CS6: 2034-07-31 | CT6: 2034-08-31 | CU6: 2034-09-30 | CV6: 2034-10-31 | CW6: 2034-11-30 | CX6: 2034-12-31 | CY6: 2035-01-31 | CZ6: 2035-02-28 | DA6: 2035-03-31 | DB6: 2035-04-30 | DC6: 2035-05-31 | DD6: 2035-06-30 | DE6: 2035-07-31 | DF6: 2035-08-31 | DG6: 2035-09-30 | DH6: 2035-10-31 | DI6: 2035-11-30 | DJ6: 2035-12-31 | DK6: 2036-01-31 | DL6: 2036-02-29 | DM6: 2036-03-31 | DN6: 2036-04-30 | DO6: 2036-05-31 | DP6: 2036-06-30 | DQ6: 2036-07-31 | DR6: 2036-08-31 | DS6: 2036-09-30 | DT6: 2036-10-31 | DU6: 2036-11-30 | DV6: 2036-12-31 | DW6: 2037-01-31 | DX6: 2037-02-28 | DY6: 2037-03-31 | DZ6: 2037-04-30 | EA6: 2037-05-31 | EB6: 2037-06-30 | EC6: 2037-07-31 | ED6: 2037-08-31 | EE6: 2037-09-30 | EF6: 2037-10-31 | EG6: 2037-11-30 | EH6: 2037-12-31 | EI6: 2038-01-31 | EJ6: 2038-02-28 | EK6: 2038-03-31 | EL6: 2038-04-30 | EM6: 2038-05-31 | EN6: 2038-06-30 | EO6: 2038-07-31 | EP6: 2038-08-31 | EQ6: 2038-09-30 | ER6: 2038-10-31 | ES6: 2038-11-30 | ET6: 2038-12-31 | EU6: 2039-01-31 | EV6: 2039-02-28 | EW6: 2039-03-31 | EX6: 2039-04-30 | EY6: 2039-05-31 | EZ6: 2039-06-30 | FA6: 2039-07-31 | FB6: 2039-08-31 | FC6: 2039-09-30 | FD6: 2039-10-31 | FE6: 2039-11-30 | FF6: 2039-12-31 | FG6: 2040-01-31 | FH6: 2040-02-29 | FI6: 2040-03-31 | FJ6: 2040-04-30 | FK6: 2040-05-31 | FL6: 2040-06-30 | FM6: 2040-07-31 | FN6: 2040-08-31 | FO6: 2040-09-30 | FP6: 2040-10-31 | FQ6: 2040-11-30 | FR6: 2040-12-31 | FS6: 2041-01-31 | FT6: 2041-02-28 | FU6: 2041-03-31 | FV6: 2041-04-30 | FW6: 2041-05-31 | FX6: 2041-06-30 | FY6: 2041-07-31 | FZ6: 2041-08-31 | GA6: 2041-09-30 | GB6: 2041-10-31 | GC6: 2041-11-30 | GD6: 2041-12-31 | GE6: 2042-01-31 | GF6: 2042-02-28 | GG6: 2042-03-31 | GH6: 2042-04-30 | GI6: 2042-05-31 | GJ6: 2042-06-30 | GK6: 2042-07-31 | GL6: 2042-08-31 | GM6: 2042-09-30 | GN6: 2042-10-31 | GO6: 2042-11-30 | GP6: 2042-12-31 | GQ6: 2043-01-31 | GR6: 2043-02-28 | GS6: 2043-03-31 | GT6: 2043-04-30 | GU6: 2043-05-31 | GV6: 2043-06-30 | GW6: 2043-07-31 | GX6: 2043-08-31 | GY6: 2043-09-30 | GZ6: 2043-10-31 | HA6: 2043-11-30 | HB6: 2043-12-31 | HC6: 2044-01-31 | HD6: 2044-02-29 | HE6: 2044-03-31 | HF6: 2044-04-30 | HG6: 2044-05-31 | HH6: 2044-06-30 | HI6: 2044-07-31 | HJ6: 2044-08-31 | HK6: 2044-09-30 | HL6: 2044-10-31 | HM6: 2044-11-30 | HN6: 2044-12-31 | HO6: 2045-01-31 | HP6: 2045-02-28 | HQ6: 2045-03-31 | HR6: 2045-04-30 | HS6: 2045-05-31 | HT6: 2045-06-30 | HU6: 2045-07-31 | HV6: 2045-08-31 | HW6: 2045-09-30 | HX6: 2045-10-31 | HY6: 2045-11-30 | HZ6: 2045-12-31 | IA6: 2046-01-31 | IB6: 2046-02-28 | IC6: 2046-03-31 | ID6: 2046-04-30 | IE6: 2046-05-31 | IF6: 2046-06-30 | IG6: 2046-07-31 | IH6: 2046-08-31 | II6: 2046-09-30 | IJ6: 2046-10-31 | IK6: 2046-11-30 | IL6: 2046-12-31 | IM6: 2047-01-31 | IN6: 2047-02-28 | IO6: 2047-03-31 | IP6: 2047-04-30 | IQ6: 2047-05-31 | IR6: 2047-06-30 | IS6: 2047-07-31 | IT6: 2047-08-31 | IU6: 2047-09-30 | IV6: 2047-10-31 | IW6: 2047-11-30 | IX6: 2047-12-31 | IY6: 2048-01-31 | IZ6: 2048-02-29 | JA6: 2048-03-31 | JB6: 2048-04-30 | JC6: 2048-05-31 | JD6: 2048-06-30 | JE6: 2048-07-31 | JF6: 2048-08-31 | JG6: 2048-09-30 | JH6: 2048-10-31 | JI6: 2048-11-30 | JJ6: 2048-12-31 | JK6: 2049-01-31 | JL6: 2049-02-28 | JM6: 2049-03-31 | JN6: 2049-04-30 | JO6: 2049-05-31 | JP6: 2049-06-30 | JQ6: 2049-07-31 | JR6: 2049-08-31 | JS6: 2049-09-30 | JT6: 2049-10-31 | JU6: 2049-11-30 | JV6: 2049-12-31 | JW6: 2050-01-31 | JX6: 2050-02-28 | JY6: 2050-03-31 | JZ6: 2050-04-30 | KA6: 2050-05-31 | KB6: 2050-06-30 | KC6: 2050-07-31 | KD6: 2050-08-31 | KE6: 2050-09-30 | KF6: 2050-10-31 | KG6: 2050-11-30 | KH6: 2050-12-31 | KI6: 2051-01-31 | KJ6: 2051-02-28 | KK6: 2051-03-31 | KL6: 2051-04-30 | KM6: 2051-05-31 | KN6: 2051-06-30 | KO6: 2051-07-31 | KP6: 2051-08-31 | KQ6: 2051-09-30 | KR6: 2051-10-31 | KS6: 2051-11-30 | KT6: 2051-12-31 | KU6: 2052-01-31 | KV6: 2052-02-29 | KW6: 2052-03-31 | KX6: 2052-04-30 | KY6: 2052-05-31 | KZ6: 2052-06-30 | LA6: 2052-07-31 | LB6: 2052-08-31 | LC6: 2052-09-30 | LD6: 2052-10-31 | LE6: 2052-11-30 | LF6: 2052-12-31 | LG6: 2053-01-31 | LH6: 2053-02-28 | LI6: 2053-03-31
B7: Flag de operacion | D7: 0 | E7: 0 | F7: 0 | G7: 0 | H7: 0 | I7: 0 | J7: 0 | K7: 0 | L7: 0 | M7: 0 | N7: 0 | O7: 0 | P7: 0 | Q7: 0 | R7: 0 | S7: 0 | T7: 0 | U7: 0 | V7: 0 | W7: 0 | X7: 0 | Y7: 0 | Z7: 0 | AA7: 0 | AB7: 0 | AC7: 0 | AD7: 0 | AE7: 0 | AF7: 0 | AG7: 0 | AH7: 0 | AI7: 0 | AJ7: 0 | AK7: 0 | AL7: 0 | AM7: 0 | AN7: 0 | AO7: 0 | AP7: 0 | AQ7: 0 | AR7: 0 | AS7: 0 | AT7: 0 | AU7: 0 | AV7: 0 | AW7: 0 | AX7: 0 | AY7: 0 | AZ7: 1 | BA7: 1 | BB7: 1 | BC7: 1 | BD7: 1 | BE7: 1 | BF7: 1 | BG7: 1 | BH7: 1 | BI7: 1 | BJ7: 1 | BK7: 1 | BL7: 1 | BM7: 1 | BN7: 1 | BO7: 1 | BP7: 1 | BQ7: 1 | BR7: 1 | BS7: 1 | BT7: 1 | BU7: 1 | BV7: 1 | BW7: 1 | BX7: 1 | BY7: 1 | BZ7: 1 | CA7: 1 | CB7: 1 | CC7: 1 | CD7: 1 | CE7: 1 | CF7: 1 | CG7: 1 | CH7: 1 | CI7: 1 | CJ7: 1 | CK7: 1 | CL7: 1 | CM7: 1 | CN7: 1 | CO7: 1 | CP7: 1 | CQ7: 1 | CR7: 1 | CS7: 1 | CT7: 1 | CU7: 1 | CV7: 1 | CW7: 1 | CX7: 1 | CY7: 1 | CZ7: 1 | DA7: 1 | DB7: 1 | DC7: 1 | DD7: 1 | DE7: 1 | DF7: 1 | DG7: 1 | DH7: 1 | DI7: 1 | DJ7: 1 | DK7: 1 | DL7: 1 | DM7: 1 | DN7: 1 | DO7: 1 | DP7: 1 | DQ7: 1 | DR7: 1 | DS7: 1 | DT7: 1 | DU7: 1 | DV7: 1 | DW7: 1 | DX7: 1 | DY7: 1 | DZ7: 1 | EA7: 1 | EB7: 1 | EC7: 1 | ED7: 1 | EE7: 1 | EF7: 1 | EG7: 1 | EH7: 1 | EI7: 1 | EJ7: 1 | EK7: 1 | EL7: 1 | EM7: 1 | EN7: 1 | EO7: 1 | EP7: 1 | EQ7: 1 | ER7: 1 | ES7: 1 | ET7: 1 | EU7: 1 | EV7: 1 | EW7: 1 | EX7: 1 | EY7: 1 | EZ7: 1 | FA7: 1 | FB7: 1 | FC7: 1 | FD7: 1 | FE7: 1 | FF7: 1 | FG7: 1 | FH7: 1 | FI7: 1 | FJ7: 1 | FK7: 1 | FL7: 1 | FM7: 1 | FN7: 1 | FO7: 1 | FP7: 1 | FQ7: 1 | FR7: 1 | FS7: 1 | FT7: 1 | FU7: 1 | FV7: 1 | FW7: 1 | FX7: 1 | FY7: 1 | FZ7: 1 | GA7: 1 | GB7: 1 | GC7: 1 | GD7: 1 | GE7: 1 | GF7: 1 | GG7: 1 | GH7: 1 | GI7: 1 | GJ7: 1 | GK7: 1 | GL7: 1 | GM7: 1 | GN7: 1 | GO7: 1 | GP7: 1 | GQ7: 1 | GR7: 1 | GS7: 1 | GT7: 1 | GU7: 1 | GV7: 1 | GW7: 1 | GX7: 1 | GY7: 1 | GZ7: 1 | HA7: 1 | HB7: 1 | HC7: 1 | HD7: 1 | HE7: 1 | HF7: 1 | HG7: 1 | HH7: 1 | HI7: 1 | HJ7: 1 | HK7: 1 | HL7: 1 | HM7: 1 | HN7: 1 | HO7: 1 | HP7: 1 | HQ7: 1 | HR7: 1 | HS7: 1 | HT7: 1 | HU7: 1 | HV7: 1 | HW7: 1 | HX7: 1 | HY7: 1 | HZ7: 1 | IA7: 1 | IB7: 1 | IC7: 1 | ID7: 1 | IE7: 1 | IF7: 1 | IG7: 1 | IH7: 1 | II7: 1 | IJ7: 1 | IK7: 1 | IL7: 1 | IM7: 1 | IN7: 1 | IO7: 1 | IP7: 1 | IQ7: 1 | IR7: 1 | IS7: 1 | IT7: 1 | IU7: 1 | IV7: 1 | IW7: 1 | IX7: 1 | IY7: 1 | IZ7: 1 | JA7: 1 | JB7: 1 | JC7: 1 | JD7: 1 | JE7: 1 | JF7: 1 | JG7: 1 | JH7: 1 | JI7: 1 | JJ7: 1 | JK7: 1 | JL7: 1 | JM7: 1 | JN7: 1 | JO7: 1 | JP7: 1 | JQ7: 1 | JR7: 1 | JS7: 1 | JT7: 1 | JU7: 1 | JV7: 1 | JW7: 1 | JX7: 1 | JY7: 1 | JZ7: 1 | KA7: 1 | KB7: 1 | KC7: 1 | KD7: 1 | KE7: 1 | KF7: 1 | KG7: 1 | KH7: 1 | KI7: 1 | KJ7: 1 | KK7: 1 | KL7: 1 | KM7: 1 | KN7: 1 | KO7: 1 | KP7: 1 | KQ7: 1 | KR7: 1 | KS7: 1 | KT7: 1 | KU7: 1 | KV7: 1 | KW7: 1 | KX7: 1 | KY7: 1 | KZ7: 1 | LA7: 1 | LB7: 1 | LC7: 1 | LD7: 0 | LE7: 0 | LF7: 0 | LG7: 0 | LH7: 0 | LI7: 0
B8: Flag trimestral | D8: 0 | E8: 0 | F8: 0 | G8: 0 | H8: 0 | I8: 0 | J8: 0 | K8: 0 | L8: 0 | M8: 0 | N8: 0 | O8: 0 | P8: 0 | Q8: 0 | R8: 0 | S8: 0 | T8: 0 | U8: 0 | V8: 0 | W8: 0 | X8: 0 | Y8: 0 | Z8: 0 | AA8: 0 | AB8: 0 | AC8: 0 | AD8: 0 | AE8: 0 | AF8: 0 | AG8: 0 | AH8: 0 | AI8: 0 | AJ8: 0 | AK8: 0 | AL8: 0 | AM8: 0 | AN8: 0 | AO8: 0 | AP8: 0 | AQ8: 0 | AR8: 0 | AS8: 0 | AT8: 0 | AU8: 0 | AV8: 0 | AW8: 0 | AX8: 0 | AY8: 0 | AZ8: 0 | BA8: 0 | BB8: 1 | BC8: 0 | BD8: 0 | BE8: 1 | BF8: 0 | BG8: 0 | BH8: 1 | BI8: 0 | BJ8: 0 | BK8: 1 | BL8: 0 | BM8: 0 | BN8: 1 | BO8: 0 | BP8: 0 | BQ8: 1 | BR8: 0 | BS8: 0 | BT8: 1 | BU8: 0 | BV8: 0 | BW8: 1 | BX8: 0 | BY8: 0 | BZ8: 1 | CA8: 0 | CB8: 0 | CC8: 1 | CD8: 0 | CE8: 0 | CF8: 1 | CG8: 0 | CH8: 0 | CI8: 1 | CJ8: 0 | CK8: 0 | CL8: 1 | CM8: 0 | CN8: 0 | CO8: 1 | CP8: 0 | CQ8: 0 | CR8: 1 | CS8: 0 | CT8: 0 | CU8: 1 | CV8: 0 | CW8: 0 | CX8: 1 | CY8: 0 | CZ8: 0 | DA8: 1 | DB8: 0 | DC8: 0 | DD8: 1 | DE8: 0 | DF8: 0 | DG8: 1 | DH8: 0 | DI8: 0 | DJ8: 1 | DK8: 0 | DL8: 0 | DM8: 1 | DN8: 0 | DO8: 0 | DP8: 1 | DQ8: 0 | DR8: 0 | DS8: 1 | DT8: 0 | DU8: 0 | DV8: 1 | DW8: 0 | DX8: 0 | DY8: 1 | DZ8: 0 | EA8: 0 | EB8: 1 | EC8: 0 | ED8: 0 | EE8: 1 | EF8: 0 | EG8: 0 | EH8: 1 | EI8: 0 | EJ8: 0 | EK8: 1 | EL8: 0 | EM8: 0 | EN8: 1 | EO8: 0 | EP8: 0 | EQ8: 1 | ER8: 0 | ES8: 0 | ET8: 1 | EU8: 0 | EV8: 0 | EW8: 1 | EX8: 0 | EY8: 0 | EZ8: 1 | FA8: 0 | FB8: 0 | FC8: 1 | FD8: 0 | FE8: 0 | FF8: 1 | FG8: 0 | FH8: 0 | FI8: 1 | FJ8: 0 | FK8: 0 | FL8: 1 | FM8: 0 | FN8: 0 | FO8: 1 | FP8: 0 | FQ8: 0 | FR8: 1 | FS8: 0 | FT8: 0 | FU8: 1 | FV8: 0 | FW8: 0 | FX8: 1 | FY8: 0 | FZ8: 0 | GA8: 1 | GB8: 0 | GC8: 0 | GD8: 1 | GE8: 0 | GF8: 0 | GG8: 1 | GH8: 0 | GI8: 0 | GJ8: 1 | GK8: 0 | GL8: 0 | GM8: 1 | GN8: 0 | GO8: 0 | GP8: 1 | GQ8: 0 | GR8: 0 | GS8: 1 | GT8: 0 | GU8: 0 | GV8: 1 | GW8: 0 | GX8: 0 | GY8: 1 | GZ8: 0 | HA8: 0 | HB8: 1 | HC8: 0 | HD8: 0 | HE8: 1 | HF8: 0 | HG8: 0 | HH8: 1 | HI8: 0 | HJ8: 0 | HK8: 1 | HL8: 0 | HM8: 0 | HN8: 1 | HO8: 0 | HP8: 0 | HQ8: 1 | HR8: 0 | HS8: 0 | HT8: 1 | HU8: 0 | HV8: 0 | HW8: 1 | HX8: 0 | HY8: 0 | HZ8: 1 | IA8: 0 | IB8: 0 | IC8: 1 | ID8: 0 | IE8: 0 | IF8: 1 | IG8: 0 | IH8: 0 | II8: 1 | IJ8: 0 | IK8: 0 | IL8: 1 | IM8: 0 | IN8: 0 | IO8: 1 | IP8: 0 | IQ8: 0 | IR8: 1 | IS8: 0 | IT8: 0 | IU8: 1 | IV8: 0 | IW8: 0 | IX8: 1 | IY8: 0 | IZ8: 0 | JA8: 1 | JB8: 0 | JC8: 0 | JD8: 1 | JE8: 0 | JF8: 0 | JG8: 1 | JH8: 0 | JI8: 0 | JJ8: 1 | JK8: 0 | JL8: 0 | JM8: 1 | JN8: 0 | JO8: 0 | JP8: 1 | JQ8: 0 | JR8: 0 | JS8: 1 | JT8: 0 | JU8: 0 | JV8: 1 | JW8: 0 | JX8: 0 | JY8: 1 | JZ8: 0 | KA8: 0 | KB8: 1 | KC8: 0 | KD8: 0 | KE8: 1 | KF8: 0 | KG8: 0 | KH8: 1 | KI8: 0 | KJ8: 0 | KK8: 1 | KL8: 0 | KM8: 0 | KN8: 1 | KO8: 0 | KP8: 0 | KQ8: 1 | KR8: 0 | KS8: 0 | KT8: 1 | KU8: 0 | KV8: 0 | KW8: 1 | KX8: 0 | KY8: 0 | KZ8: 1 | LA8: 0 | LB8: 0 | LC8: 1 | LD8: 0 | LE8: 0 | LF8: 0 | LG8: 0 | LH8: 0 | LI8: 0
B9: Flag de pago del PPDMO | D9: 0 | E9: 0 | F9: 0 | G9: 0 | H9: 0 | I9: 0 | J9: 0 | K9: 0 | L9: 0 | M9: 0 | N9: 0 | O9: 0 | P9: 0 | Q9: 0 | R9: 0 | S9: 0 | T9: 0 | U9: 0 | V9: 0 | W9: 0 | X9: 0 | Y9: 0 | Z9: 0 | AA9: 0 | AB9: 0 | AC9: 0 | AD9: 0 | AE9: 0 | AF9: 0 | AG9: 0 | AH9: 0 | AI9: 0 | AJ9: 0 | AK9: 0 | AL9: 0 | AM9: 0 | AN9: 0 | AO9: 0 | AP9: 0 | AQ9: 0 | AR9: 0 | AS9: 0 | AT9: 0 | AU9: 0 | AV9: 0 | AW9: 0 | AX9: 0 | AY9: 0 | AZ9: 0 | BA9: 0 | BB9: 0 | BC9: 1 | BD9: 1 | BE9: 1 | BF9: 1 | BG9: 1 | BH9: 1 | BI9: 1 | BJ9: 1 | BK9: 1 | BL9: 1 | BM9: 1 | BN9: 1 | BO9: 1 | BP9: 1 | BQ9: 1 | BR9: 1 | BS9: 1 | BT9: 1 | BU9: 1 | BV9: 1 | BW9: 1 | BX9: 1 | BY9: 1 | BZ9: 1 | CA9: 1 | CB9: 1 | CC9: 1 | CD9: 1 | CE9: 1 | CF9: 1 | CG9: 1 | CH9: 1 | CI9: 1 | CJ9: 1 | CK9: 1 | CL9: 1 | CM9: 1 | CN9: 1 | CO9: 1 | CP9: 1 | CQ9: 1 | CR9: 1 | CS9: 1 | CT9: 1 | CU9: 1 | CV9: 1 | CW9: 1 | CX9: 1 | CY9: 1 | CZ9: 1 | DA9: 1 | DB9: 1 | DC9: 1 | DD9: 1 | DE9: 1 | DF9: 1 | DG9: 1 | DH9: 1 | DI9: 1 | DJ9: 1 | DK9: 1 | DL9: 1 | DM9: 1 | DN9: 1 | DO9: 1 | DP9: 1 | DQ9: 1 | DR9: 1 | DS9: 1 | DT9: 1 | DU9: 1 | DV9: 1 | DW9: 1 | DX9: 1 | DY9: 1 | DZ9: 1 | EA9: 1 | EB9: 1 | EC9: 1 | ED9: 1 | EE9: 1 | EF9: 1 | EG9: 1 | EH9: 1 | EI9: 1 | EJ9: 1 | EK9: 1 | EL9: 1 | EM9: 1 | EN9: 1 | EO9: 1 | EP9: 1 | EQ9: 1 | ER9: 1 | ES9: 1 | ET9: 1 | EU9: 1 | EV9: 1 | EW9: 1 | EX9: 1 | EY9: 1 | EZ9: 1 | FA9: 1 | FB9: 1 | FC9: 1 | FD9: 1 | FE9: 1 | FF9: 1 | FG9: 1 | FH9: 1 | FI9: 1 | FJ9: 1 | FK9: 1 | FL9: 1 | FM9: 1 | FN9: 1 | FO9: 1 | FP9: 1 | FQ9: 1 | FR9: 1 | FS9: 1 | FT9: 1 | FU9: 1 | FV9: 1 | FW9: 1 | FX9: 1 | FY9: 1 | FZ9: 1 | GA9: 1 | GB9: 1 | GC9: 1 | GD9: 1 | GE9: 1 | GF9: 1 | GG9: 1 | GH9: 1 | GI9: 1 | GJ9: 1 | GK9: 1 | GL9: 1 | GM9: 1 | GN9: 1 | GO9: 1 | GP9: 1 | GQ9: 1 | GR9: 1 | GS9: 1 | GT9: 1 | GU9: 1 | GV9: 1 | GW9: 1 | GX9: 1 | GY9: 1 | GZ9: 1 | HA9: 1 | HB9: 1 | HC9: 1 | HD9: 1 | HE9: 1 | HF9: 1 | HG9: 1 | HH9: 1 | HI9: 1 | HJ9: 1 | HK9: 1 | HL9: 1 | HM9: 1 | HN9: 1 | HO9: 1 | HP9: 1 | HQ9: 1 | HR9: 1 | HS9: 1 | HT9: 1 | HU9: 1 | HV9: 1 | HW9: 1 | HX9: 1 | HY9: 1 | HZ9: 1 | IA9: 1 | IB9: 1 | IC9: 1 | ID9: 1 | IE9: 1 | IF9: 1 | IG9: 1 | IH9: 1 | II9: 1 | IJ9: 1 | IK9: 1 | IL9: 1 | IM9: 1 | IN9: 1 | IO9: 1 | IP9: 1 | IQ9: 1 | IR9: 1 | IS9: 1 | IT9: 1 | IU9: 1 | IV9: 1 | IW9: 1 | IX9: 1 | IY9: 1 | IZ9: 1 | JA9: 1 | JB9: 1 | JC9: 1 | JD9: 1 | JE9: 1 | JF9: 1 | JG9: 1 | JH9: 1 | JI9: 1 | JJ9: 1 | JK9: 1 | JL9: 1 | JM9: 1 | JN9: 1 | JO9: 1 | JP9: 1 | JQ9: 1 | JR9: 1 | JS9: 1 | JT9: 1 | JU9: 1 | JV9: 1 | JW9: 1 | JX9: 1 | JY9: 1 | JZ9: 1 | KA9: 1 | KB9: 1 | KC9: 1 | KD9: 1 | KE9: 1 | KF9: 1 | KG9: 1 | KH9: 1 | KI9: 1 | KJ9: 1 | KK9: 1 | KL9: 1 | KM9: 1 | KN9: 1 | KO9: 1 | KP9: 1 | KQ9: 1 | KR9: 1 | KS9: 1 | KT9: 1 | KU9: 1 | KV9: 1 | KW9: 1 | KX9: 1 | KY9: 1 | KZ9: 1 | LA9: 1 | LB9: 1 | LC9: 1 | LD9: 1 | LE9: 1 | LF9: 1 | LG9: 0 | LH9: 0 | LI9: 0
B10: Produccion efectiva, kg DBO5 | D10: 0 | E10: 0 | F10: 0 | G10: 0 | H10: 0 | I10: 0 | J10: 0 | K10: 0 | L10: 0 | M10: 0 | N10: 0 | O10: 0 | P10: 0 | Q10: 0 | R10: 0 | S10: 0 | T10: 0 | U10: 0 | V10: 0 | W10: 0 | X10: 0 | Y10: 0 | Z10: 0 | AA10: 0 | AB10: 0 | AC10: 0 | AD10: 0 | AE10: 0 | AF10: 0 | AG10: 0 | AH10: 0 | AI10: 0 | AJ10: 0 | AK10: 0 | AL10: 0 | AM10: 0 | AN10: 0 | AO10: 0 | AP10: 0 | AQ10: 0 | AR10: 0 | AS10: 0 | AT10: 0 | AU10: 0 | AV10: 0 | AW10: 0 | AX10: 0 | AY10: 0 | AZ10: 558467.34 | BA10: 558467.34 | BB10: 558467.34 | BC10: 565769.15 | BD10: 565769.15 | BE10: 565769.15 | BF10: 565769.15 | BG10: 565769.15 | BH10: 565769.15 | BI10: 565769.15 | BJ10: 565769.15 | BK10: 565769.15 | BL10: 565769.15 | BM10: 565769.15 | BN10: 565769.15 | BO10: 571854 | BP10: 571854 | BQ10: 571854 | BR10: 571854 | BS10: 571854 | BT10: 571854 | BU10: 571854 | BV10: 571854 | BW10: 571854 | BX10: 571854 | BY10: 571854 | BZ10: 571854 | CA10: 576721.88 | CB10: 576721.88 | CC10: 576721.88 | CD10: 576721.88 | CE10: 576721.88 | CF10: 576721.88 | CG10: 576721.88 | CH10: 576721.88 | CI10: 576721.88 | CJ10: 576721.88 | CK10: 576721.88 | CL10: 576721.88 | CM10: 581589.76 | CN10: 581589.76 | CO10: 581589.76 | CP10: 581589.76 | CQ10: 581589.76 | CR10: 581589.76 | CS10: 581589.76 | CT10: 581589.76 | CU10: 581589.76 | CV10: 581589.76 | CW10: 581589.76 | CX10: 581589.76 | CY10: 586457.64 | CZ10: 586457.64 | DA10: 586457.64 | DB10: 586457.64 | DC10: 586457.64 | DD10: 586457.64 | DE10: 586457.64 | DF10: 586457.64 | DG10: 586457.64 | DH10: 586457.64 | DI10: 586457.64 | DJ10: 586457.64 | DK10: 591325.51 | DL10: 591325.51 | DM10: 591325.51 | DN10: 591325.51 | DO10: 591325.51 | DP10: 591325.51 | DQ10: 591325.51 | DR10: 591325.51 | DS10: 591325.51 | DT10: 591325.51 | DU10: 591325.51 | DV10: 591325.51 | DW10: 620532.78 | DX10: 620532.78 | DY10: 620532.78 | DZ10: 620532.78 | EA10: 620532.78 | EB10: 620532.78 | EC10: 620532.78 | ED10: 620532.78 | EE10: 620532.78 | EF10: 620532.78 | EG10: 620532.78 | EH10: 620532.78 | EI10: 626617.63 | EJ10: 626617.63 | EK10: 626617.63 | EL10: 626617.63 | EM10: 626617.63 | EN10: 626617.63 | EO10: 626617.63 | EP10: 626617.63 | EQ10: 626617.63 | ER10: 626617.63 | ES10: 626617.63 | ET10: 626617.63 | EU10: 632702.48 | EV10: 632702.48 | EW10: 632702.48 | EX10: 632702.48 | EY10: 632702.48 | EZ10: 632702.48 | FA10: 632702.48 | FB10: 632702.48 | FC10: 632702.48 | FD10: 632702.48 | FE10: 632702.48 | FF10: 632702.48 | FG10: 640004.3 | FH10: 640004.3 | FI10: 640004.3 | FJ10: 640004.3 | FK10: 640004.3 | FL10: 640004.3 | FM10: 640004.3 | FN10: 640004.3 | FO10: 640004.3 | FP10: 640004.3 | FQ10: 640004.3 | FR10: 640004.3 | FS10: 646089.14 | FT10: 646089.14 | FU10: 646089.14 | FV10: 646089.14 | FW10: 646089.14 | FX10: 646089.14 | FY10: 646089.14 | FZ10: 646089.14 | GA10: 646089.14 | GB10: 646089.14 | GC10: 646089.14 | GD10: 646089.14 | GE10: 653390.96 | GF10: 653390.96 | GG10: 653390.96 | GH10: 653390.96 | GI10: 653390.96 | GJ10: 653390.96 | GK10: 653390.96 | GL10: 653390.96 | GM10: 653390.96 | GN10: 653390.96 | GO10: 653390.96 | GP10: 653390.96 | GQ10: 659475.81 | GR10: 659475.81 | GS10: 659475.81 | GT10: 659475.81 | GU10: 659475.81 | GV10: 659475.81 | GW10: 659475.81 | GX10: 659475.81 | GY10: 659475.81 | GZ10: 659475.81 | HA10: 659475.81 | HB10: 659475.81 | HC10: 666777.63 | HD10: 666777.63 | HE10: 666777.63 | HF10: 666777.63 | HG10: 666777.63 | HH10: 666777.63 | HI10: 666777.63 | HJ10: 666777.63 | HK10: 666777.63 | HL10: 666777.63 | HM10: 666777.63 | HN10: 666777.63 | HO10: 674079.44 | HP10: 674079.44 | HQ10: 674079.44 | HR10: 674079.44 | HS10: 674079.44 | HT10: 674079.44 | HU10: 674079.44 | HV10: 674079.44 | HW10: 674079.44 | HX10: 674079.44 | HY10: 674079.44 | HZ10: 674079.44 | IA10: 681381.26 | IB10: 681381.26 | IC10: 681381.26 | ID10: 681381.26 | IE10: 681381.26 | IF10: 681381.26 | IG10: 681381.26 | IH10: 681381.26 | II10: 681381.26 | IJ10: 681381.26 | IK10: 681381.26 | IL10: 681381.26 | IM10: 688683.08 | IN10: 688683.08 | IO10: 688683.08 | IP10: 688683.08 | IQ10: 688683.08 | IR10: 688683.08 | IS10: 688683.08 | IT10: 688683.08 | IU10: 688683.08 | IV10: 688683.08 | IW10: 688683.08 | IX10: 688683.08 | IY10: 695984.9 | IZ10: 695984.9 | JA10: 695984.9 | JB10: 695984.9 | JC10: 695984.9 | JD10: 695984.9 | JE10: 695984.9 | JF10: 695984.9 | JG10: 695984.9 | JH10: 695984.9 | JI10: 695984.9 | JJ10: 695984.9 | JK10: 703286.71 | JL10: 703286.71 | JM10: 703286.71 | JN10: 703286.71 | JO10: 703286.71 | JP10: 703286.71 | JQ10: 703286.71 | JR10: 703286.71 | JS10: 703286.71 | JT10: 703286.71 | JU10: 703286.71 | JV10: 703286.71 | JW10: 711805.5 | JX10: 711805.5 | JY10: 711805.5 | JZ10: 711805.5 | KA10: 711805.5 | KB10: 711805.5 | KC10: 711805.5 | KD10: 711805.5 | KE10: 711805.5 | KF10: 711805.5 | KG10: 711805.5 | KH10: 711805.5 | KI10: 720324.29 | KJ10: 720324.29 | KK10: 720324.29 | KL10: 720324.29 | KM10: 720324.29 | KN10: 720324.29 | KO10: 720324.29 | KP10: 720324.29 | KQ10: 720324.29 | KR10: 720324.29 | KS10: 720324.29 | KT10: 720324.29 | KU10: 720324.29 | KV10: 720324.29 | KW10: 720324.29 | KX10: 720324.29 | KY10: 720324.29 | KZ10: 720324.29 | LA10: 720324.29 | LB10: 720324.29 | LC10: 720324.29 | LD10: 0 | LE10: 0 | LF10: 0 | LG10: 0 | LH10: 0 | LI10: 0
B11: IPM mensual | D11: =((1+p_ipm)^(1/12)-1)*D7 | E11: =((1+p_ipm)^(1/12)-1)*E7 | F11: =((1+p_ipm)^(1/12)-1)*F7 | G11: =((1+p_ipm)^(1/12)-1)*G7 | H11: =((1+p_ipm)^(1/12)-1)*H7 | I11: =((1+p_ipm)^(1/12)-1)*I7 | J11: =((1+p_ipm)^(1/12)-1)*J7 | K11: =((1+p_ipm)^(1/12)-1)*K7 | ... LI11: =((1+p_ipm)^(1/12)-1)*LI7
B12: Acumulado pendiente | D12: =IF($D11=0,0,$D11) | E12: =IF(E11=0,0,SUM($D11:E11)-SUM($D13:D13)) | F12: =IF(F11=0,0,SUM($D11:F11)-SUM($D13:E13)) | G12: =IF(G11=0,0,SUM($D11:G11)-SUM($D13:F13)) | H12: =IF(H11=0,0,SUM($D11:H11)-SUM($D13:G13)) | I12: =IF(I11=0,0,SUM($D11:I11)-SUM($D13:H13)) | J12: =IF(J11=0,0,SUM($D11:J11)-SUM($D13:I13)) | K12: =IF(K11=0,0,SUM($D11:K11)-SUM($D13:J13)) | L12: =IF(L11=0,0,SUM($D11:L11)-SUM($D13:K13)) | ... LI12: =IF(LI11=0,0,SUM($D11:LI11)-SUM($D13:LH13))
B13: Ajuste liberado | D13: =IF(D12>=p_gatillo,D12,0) | E13: =IF(E12>=p_gatillo,E12,0) | F13: =IF(F12>=p_gatillo,F12,0) | G13: =IF(G12>=p_gatillo,G12,0) | H13: =IF(H12>=p_gatillo,H12,0) | I13: =IF(I12>=p_gatillo,I12,0) | J13: =IF(J12>=p_gatillo,J12,0) | K13: =IF(K12>=p_gatillo,K12,0) | ... LI13: =IF(LI12>=p_gatillo,LI12,0)
B14: Factor de reajuste | D14: =TRUNC(IF(D7=0,1,1*(1+D13)*D7),5) | E14: =TRUNC(IF(E7=0,1,D14*(1+E13)*E7),5) | F14: =TRUNC(IF(F7=0,1,E14*(1+F13)*F7),5) | G14: =TRUNC(IF(G7=0,1,F14*(1+G13)*G7),5) | H14: =TRUNC(IF(H7=0,1,G14*(1+H13)*H7),5) | I14: =TRUNC(IF(I7=0,1,H14*(1+I13)*I7),5) | J14: =TRUNC(IF(J7=0,1,I14*(1+J13)*J7),5) | K14: =TRUNC(IF(K7=0,1,J14*(1+K13)*K7),5) | L14: =TRUNC(IF(L7=0,1,K14*(1+L13)*L7),5) | ... LI14: =TRUNC(IF(LI7=0,1,LH14*(1+LI13)*LI7),5)
B15: PPDMO fijo mensual | D15: =p_fijo_base*D14*D7 | E15: =p_fijo_base*E14*E7 | F15: =p_fijo_base*F14*F7 | G15: =p_fijo_base*G14*G7 | H15: =p_fijo_base*H14*H7 | I15: =p_fijo_base*I14*I7 | J15: =p_fijo_base*J14*J7 | K15: =p_fijo_base*K14*K7 | ... LI15: =p_fijo_base*LI14*LI7
B16: PPDMO variable mensual | D16: =IF(D7=0,0,p_tarifa*D10*D14)/1000 | E16: =IF(E7=0,0,p_tarifa*E10*E14)/1000 | F16: =IF(F7=0,0,p_tarifa*F10*F14)/1000 | G16: =IF(G7=0,0,p_tarifa*G10*G14)/1000 | H16: =IF(H7=0,0,p_tarifa*H10*H14)/1000 | I16: =IF(I7=0,0,p_tarifa*I10*I14)/1000 | J16: =IF(J7=0,0,p_tarifa*J10*J14)/1000 | K16: =IF(K7=0,0,p_tarifa*K10*K14)/1000 | ... LI16: =IF(LI7=0,0,p_tarifa*LI10*LI14)/1000
B17: Fijo trimestral | D17: =SUM(D15:D15)*D8 | E17: =SUM(D15:E15)*E8 | F17: =SUM(D15:F15)*F8 | G17: =SUM(E15:G15)*G8 | H17: =SUM(F15:H15)*H8 | I17: =SUM(G15:I15)*I8 | J17: =SUM(H15:J15)*J8 | K17: =SUM(I15:K15)*K8 | L17: =SUM(J15:L15)*L8 | M17: =SUM(K15:M15)*M8 | ... LI17: =SUM(LG15:LI15)*LI8
B18: Variable trimestral | D18: =SUM(D16:D16)*D8 | E18: =SUM(D16:E16)*E8 | F18: =SUM(D16:F16)*F8 | G18: =SUM(E16:G16)*G8 | H18: =SUM(F16:H16)*H8 | I18: =SUM(G16:I16)*I8 | J18: =SUM(H16:J16)*J8 | K18: =SUM(I16:K16)*K8 | L18: =SUM(J16:L16)*L8 | M18: =SUM(K16:M16)*M8 | ... LI18: =SUM(LG16:LI16)*LI8
B19: Fijo a cobrar | D19: 0 | E19: 0 | F19: 0 | G19: =G9*D17 | H19: =H9*E17 | I19: =I9*F17 | J19: =J9*G17 | K19: =K9*H17 | L19: =L9*I17 | M19: =M9*J17 | N19: =N9*K17 | ... LI19: =LI9*LF17
B20: Variable a cobrar | D20: 0 | E20: 0 | F20: 0 | G20: =G9*D18 | H20: =H9*E18 | I20: =I9*F18 | J20: =J9*G18 | K20: =K9*H18 | L20: =L9*I18 | M20: =M9*J18 | N20: =N9*K18 | ... LI20: =LI9*LF18
B21: Primer mes de operacion | D21: =IF(AND(D7=1,0=0),1,0) | E21: =IF(AND(E7=1,SUM($D7:D7)=0),1,0) | F21: =IF(AND(F7=1,SUM($D7:E7)=0),1,0) | G21: =IF(AND(G7=1,SUM($D7:F7)=0),1,0) | H21: =IF(AND(H7=1,SUM($D7:G7)=0),1,0) | I21: =IF(AND(I7=1,SUM($D7:H7)=0),1,0) | J21: =IF(AND(J7=1,SUM($D7:I7)=0),1,0) | K21: =IF(AND(K7=1,SUM($D7:J7)=0),1,0) | L21: =IF(AND(L7=1,SUM($D7:K7)=0),1,0) | ... LI21: =IF(AND(LI7=1,SUM($D7:LH7)=0),1,0)

Sheet Flujo
B2: Flujo de caja financiero
B3: El VAN de la ultima fila es la celda que Buscar Objetivo lleva a cero.
B6: Ano | D6: 2026 | E6: 2027 | F6: 2027 | G6: 2027 | H6: 2027 | I6: 2028 | J6: 2028 | K6: 2028 | L6: 2028 | M6: 2029 | N6: 2029 | O6: 2029 | P6: 2029 | Q6: 2030 | R6: 2030 | S6: 2030 | T6: 2030 | U6: 2031 | V6: 2031 | W6: 2031 | X6: 2031 | Y6: 2032 | Z6: 2032 | AA6: 2032 | AB6: 2032 | AC6: 2033 | AD6: 2033 | AE6: 2033 | AF6: 2033 | AG6: 2034 | AH6: 2034 | AI6: 2034 | AJ6: 2034 | AK6: 2035 | AL6: 2035 | AM6: 2035 | AN6: 2035 | AO6: 2036 | AP6: 2036 | AQ6: 2036 | AR6: 2036 | AS6: 2037 | AT6: 2037 | AU6: 2037 | AV6: 2037 | AW6: 2038 | AX6: 2038 | AY6: 2038 | AZ6: 2038 | BA6: 2039 | BB6: 2039 | BC6: 2039 | BD6: 2039 | BE6: 2040 | BF6: 2040 | BG6: 2040 | BH6: 2040 | BI6: 2041 | BJ6: 2041 | BK6: 2041 | BL6: 2041 | BM6: 2042 | BN6: 2042 | BO6: 2042 | BP6: 2042 | BQ6: 2043 | BR6: 2043 | BS6: 2043 | BT6: 2043 | BU6: 2044 | BV6: 2044 | BW6: 2044 | BX6: 2044 | BY6: 2045 | BZ6: 2045 | CA6: 2045 | CB6: 2045 | CC6: 2046 | CD6: 2046 | CE6: 2046 | CF6: 2046 | CG6: 2047 | CH6: 2047 | CI6: 2047 | CJ6: 2047 | CK6: 2048 | CL6: 2048 | CM6: 2048 | CN6: 2048 | CO6: 2049 | CP6: 2049 | CQ6: 2049 | CR6: 2049 | CS6: 2050 | CT6: 2050 | CU6: 2050 | CV6: 2050 | CW6: 2051 | CX6: 2051 | CY6: 2051 | CZ6: 2051 | DA6: 2052 | DB6: 2052 | DC6: 2052 | DD6: 2052 | DE6: 2053
B7: Trimestre | D7: 1 | E7: 2 | F7: 3 | G7: 4 | H7: 5 | I7: 6 | J7: 7 | K7: 8 | L7: 9 | M7: 10 | N7: 11 | O7: 12 | P7: 13 | Q7: 14 | R7: 15 | S7: 16 | T7: 17 | U7: 18 | V7: 19 | W7: 20 | X7: 21 | Y7: 22 | Z7: 23 | AA7: 24 | AB7: 25 | AC7: 26 | AD7: 27 | AE7: 28 | AF7: 29 | AG7: 30 | AH7: 31 | AI7: 32 | AJ7: 33 | AK7: 34 | AL7: 35 | AM7: 36 | AN7: 37 | AO7: 38 | AP7: 39 | AQ7: 40 | AR7: 41 | AS7: 42 | AT7: 43 | AU7: 44 | AV7: 45 | AW7: 46 | AX7: 47 | AY7: 48 | AZ7: 49 | BA7: 50 | BB7: 51 | BC7: 52 | BD7: 53 | BE7: 54 | BF7: 55 | BG7: 56 | BH7: 57 | BI7: 58 | BJ7: 59 | BK7: 60 | BL7: 61 | BM7: 62 | BN7: 63 | BO7: 64 | BP7: 65 | BQ7: 66 | BR7: 67 | BS7: 68 | BT7: 69 | BU7: 70 | BV7: 71 | BW7: 72 | BX7: 73 | BY7: 74 | BZ7: 75 | CA7: 76 | CB7: 77 | CC7: 78 | CD7: 79 | CE7: 80 | CF7: 81 | CG7: 82 | CH7: 83 | CI7: 84 | CJ7: 85 | CK7: 86 | CL7: 87 | CM7: 88 | CN7: 89 | CO7: 90 | CP7: 91 | CQ7: 92 | CR7: 93 | CS7: 94 | CT7: 95 | CU7: 96 | CV7: 97 | CW7: 98 | CX7: 99 | CY7: 100 | CZ7: 101 | DA7: 102 | DB7: 103 | DC7: 104 | DD7: 105 | DE7: 106
B8: Meses vivos | D8: 3 | E8: 3 | F8: 3 | G8: 3 | H8: 3 | I8: 3 | J8: 3 | K8: 3 | L8: 3 | M8: 3 | N8: 3 | O8: 3 | P8: 3 | Q8: 3 | R8: 3 | S8: 3 | T8: 3 | U8: 3 | V8: 3 | W8: 3 | X8: 3 | Y8: 3 | Z8: 3 | AA8: 3 | AB8: 3 | AC8: 3 | AD8: 3 | AE8: 3 | AF8: 3 | AG8: 3 | AH8: 3 | AI8: 3 | AJ8: 3 | AK8: 3 | AL8: 3 | AM8: 3 | AN8: 3 | AO8: 3 | AP8: 3 | AQ8: 3 | AR8: 3 | AS8: 3 | AT8: 3 | AU8: 3 | AV8: 3 | AW8: 3 | AX8: 3 | AY8: 3 | AZ8: 3 | BA8: 3 | BB8: 3 | BC8: 3 | BD8: 3 | BE8: 3 | BF8: 3 | BG8: 3 | BH8: 3 | BI8: 3 | BJ8: 3 | BK8: 3 | BL8: 3 | BM8: 3 | BN8: 3 | BO8: 3 | BP8: 3 | BQ8: 3 | BR8: 3 | BS8: 3 | BT8: 3 | BU8: 3 | BV8: 3 | BW8: 3 | BX8: 3 | BY8: 3 | BZ8: 3 | CA8: 3 | CB8: 3 | CC8: 3 | CD8: 3 | CE8: 3 | CF8: 3 | CG8: 3 | CH8: 3 | CI8: 3 | CJ8: 3 | CK8: 3 | CL8: 3 | CM8: 3 | CN8: 3 | CO8: 3 | CP8: 3 | CQ8: 3 | CR8: 3 | CS8: 3 | CT8: 3 | CU8: 3 | CV8: 3 | CW8: 3 | CX8: 3 | CY8: 3 | CZ8: 3 | DA8: 3 | DB8: 3 | DC8: 3 | DD8: 3 | DE8: 0
B9: PPD Inversiones | D9: =p_ppdi_anual*0.0 | E9: =p_ppdi_anual*0.0 | F9: =p_ppdi_anual*0.0 | G9: =p_ppdi_anual*0.0 | H9: =p_ppdi_anual*0.0 | I9: =p_ppdi_anual*0.0 | J9: =p_ppdi_anual*0.0 | K9: =p_ppdi_anual*0.0 | ... S9: =p_ppdi_anual*0.0 | T9: =p_ppdi_anual*0.25 | U9: =p_ppdi_anual*0.25 | V9: =p_ppdi_anual*0.25 | W9: =p_ppdi_anual*0.25 | X9: =p_ppdi_anual*0.25 | Y9: =p_ppdi_anual*0.25 | Z9: =p_ppdi_anual*0.25 | AA9: =p_ppdi_anual*0.25 | ... CA9: =p_ppdi_anual*0.25 | CB9: =p_ppdi_anual*0.0 | CC9: =p_ppdi_anual*0.0 | CD9: =p_ppdi_anual*0.0 | CE9: =p_ppdi_anual*0.0 | CF9: =p_ppdi_anual*0.0 | CG9: =p_ppdi_anual*0.0 | CH9: =p_ppdi_anual*0.0 | CI9: =p_ppdi_anual*0.0 | ... DE9: =p_ppdi_anual*0.0
B10: PPD MO fijo | D10: 0 | E10: 0 | F10: 0 | G10: 0 | H10: 0 | I10: 0 | J10: 0 | K10: 0 | L10: 0 | M10: 0 | N10: 0 | O10: 0 | P10: 0 | Q10: 0 | R10: 0 | S10: 0 | T10: 0 | U10: 1669.9775 | V10: 1669.9775 | W10: 1669.9775 | X10: 1669.9775 | Y10: 1704.2343 | Z10: 1721.3627 | AA10: 1721.3627 | AB10: 1721.3627 | AC10: 1721.3627 | AD10: 1774.3344 | AE10: 1774.3344 | AF10: 1774.3344 | AG10: 1774.3344 | AH10: 1792.5316 | AI10: 1828.926 | AJ10: 1828.926 | AK10: 1828.926 | AL10: 1828.926 | AM10: 1866.4448 | AN10: 1885.2042 | AO10: 1885.2042 | AP10: 1885.2042 | AQ10: 1885.2042 | AR10: 1943.2193 | AS10: 1943.2193 | AT10: 1943.2193 | AU10: 1943.2193 | AV10: 1963.1532 | AW10: 2003.0211 | AX10: 2003.0211 | AY10: 2003.0211 | AZ10: 2003.0211 | BA10: 2044.1137 | BB10: 2064.66 | BC10: 2064.66 | BD10: 2064.66 | BE10: 2064.66 | BF10: 2128.186 | BG10: 2128.186 | BH10: 2128.186 | BI10: 2128.186 | BJ10: 2150.0126 | BK10: 2193.6658 | BL10: 2193.6658 | BM10: 2193.6658 | BN10: 2193.6658 | BO10: 2238.6661 | BP10: 2261.1663 | BQ10: 2261.1663 | BR10: 2261.1663 | BS10: 2261.1663 | BT10: 2330.7375 | BU10: 2330.7375 | BV10: 2330.7375 | BW10: 2330.7375 | BX10: 2354.646 | BY10: 2402.4631 | BZ10: 2402.4631 | CA10: 2402.4631 | CB10: 2402.4631 | CC10: 2451.7497 | CD10: 2476.393 | CE10: 2476.393 | CF10: 2476.393 | CG10: 2476.393 | CH10: 2552.594 | CI10: 2552.594 | CJ10: 2552.594 | CK10: 2552.594 | CL10: 2578.7793 | CM10: 2631.1498 | CN10: 2631.1498 | CO10: 2631.1498 | CP10: 2631.1498 | CQ10: 2685.1235 | CR10: 2712.1103 | CS10: 2712.1103 | CT10: 2712.1103 | CU10: 2712.1103 | CV10: 2795.5758 | CW10: 2795.5758 | CX10: 2795.5758 | CY10: 2795.5758 | CZ10: 2824.2493 | DA10: 2881.5963 | DB10: 2881.5963 | DC10: 2881.5963 | DD10: 2881.5963 | DE10: 0
B11: PPD MO variable | D11: 0 | E11: 0 | F11: 0 | G11: 0 | H11: 0 | I11: 0 | J11: 0 | K11: 0 | L11: 0 | M11: 0 | N11: 0 | O11: 0 | P11: 0 | Q11: 0 | R11: 0 | S11: 0 | T11: 0 | U11: 6464.2564 | V11: 6548.7749 | W11: 6548.7749 | X11: 6548.7749 | Y11: 6683.1121 | Z11: 6822.88 | AA11: 6822.88 | AB11: 6822.88 | AC11: 6822.88 | AD11: 7092.708 | AE11: 7092.708 | AF11: 7092.708 | AG11: 7092.708 | AH11: 7225.9299 | AI11: 7372.6404 | AJ11: 7372.6404 | AK11: 7372.6404 | AL11: 7434.3491 | AM11: 7586.8583 | AN11: 7663.1129 | AO11: 7663.1129 | AP11: 7726.7204 | AQ11: 7726.7204 | AR11: 7964.5014 | AS11: 7964.5014 | AT11: 8357.8911 | AU11: 8357.8911 | AV11: 8443.6281 | AW11: 8615.1023 | AX11: 8699.5806 | AY11: 8699.5806 | AZ11: 8699.5806 | BA11: 8878.0551 | BB11: 9054.3704 | BC11: 9054.3704 | BD11: 9054.3704 | BE11: 9054.3704 | BF11: 9440.6661 | BG11: 9440.6661 | BH11: 9440.6661 | BI11: 9440.6661 | BJ11: 9628.167 | BK11: 9823.6544 | BL11: 9823.6544 | BM11: 9823.6544 | BN11: 9934.6771 | BO11: 10138.475 | BP11: 10240.373 | BQ11: 10240.373 | BR11: 10335.739 | BS11: 10335.739 | BT11: 10653.748 | BU11: 10653.748 | BV11: 10771.708 | BW11: 10771.708 | BX11: 10882.203 | BY11: 11103.194 | BZ11: 11224.784 | CA11: 11224.784 | CB11: 11224.784 | CC11: 11455.06 | CD11: 11695.53 | CE11: 11695.53 | CF11: 11695.53 | CG11: 11695.53 | CH11: 12184.602 | CI11: 12184.602 | CJ11: 12184.602 | CK11: 12184.602 | CL11: 12440.108 | CM11: 12692.745 | CN11: 12692.745 | CO11: 12692.745 | CP11: 12825.909 | CQ11: 13089.011 | CR11: 13220.563 | CS11: 13220.563 | CT11: 13380.701 | CU11: 13380.701 | CV11: 13792.493 | CW11: 13792.493 | CX11: 13957.56 | CY11: 13957.56 | CZ11: 14100.719 | DA11: 14387.037 | DB11: 14387.037 | DC11: 14387.037 | DD11: 14387.037 | DE11: 0
B12: Flag de supervision | D12: 0 | E12: 0 | F12: 0 | G12: 0 | H12: 0 | I12: 0 | J12: 0 | K12: 0 | L12: 0 | M12: 0 | N12: 0 | O12: 0 | P12: 0 | Q12: 0 | R12: 0 | S12: 0 | T12: 1 | U12: 1 | V12: 1 | W12: 1 | X12: 1 | Y12: 1 | Z12: 1 | AA12: 1 | AB12: 1 | AC12: 1 | AD12: 1 | AE12: 1 | AF12: 1 | AG12: 1 | AH12: 1 | AI12: 1 | AJ12: 1 | AK12: 1 | AL12: 1 | AM12: 1 | AN12: 1 | AO12: 1 | AP12: 1 | AQ12: 1 | AR12: 1 | AS12: 1 | AT12: 1 | AU12: 1 | AV12: 1 | AW12: 1 | AX12: 1 | AY12: 1 | AZ12: 1 | BA12: 1 | BB12: 1 | BC12: 1 | BD12: 1 | BE12: 1 | BF12: 1 | BG12: 1 | BH12: 1 | BI12: 1 | BJ12: 1 | BK12: 1 | BL12: 1 | BM12: 1 | BN12: 1 | BO12: 1 | BP12: 1 | BQ12: 1 | BR12: 1 | BS12: 1 | BT12: 1 | BU12: 1 | BV12: 1 | BW12: 1 | BX12: 1 | BY12: 1 | BZ12: 1 | CA12: 1 | CB12: 1 | CC12: 1 | CD12: 1 | CE12: 1 | CF12: 1 | CG12: 1 | CH12: 1 | CI12: 1 | CJ12: 1 | CK12: 1 | CL12: 1 | CM12: 1 | CN12: 1 | CO12: 1 | CP12: 1 | CQ12: 1 | CR12: 1 | CS12: 1 | CT12: 1 | CU12: 1 | CV12: 1 | CW12: 1 | CX12: 1 | CY12: 1 | CZ12: 1 | DA12: 1 | DB12: 1 | DC12: 1 | DD12: 0 | DE12: 0
B13: Supervision SUNASS | D13: =-p_superv*SUM(D9:D11)*D12 | E13: =-p_superv*SUM(E9:E11)*E12 | F13: =-p_superv*SUM(F9:F11)*F12 | G13: =-p_superv*SUM(G9:G11)*G12 | H13: =-p_superv*SUM(H9:H11)*H12 | I13: =-p_superv*SUM(I9:I11)*I12 | J13: =-p_superv*SUM(J9:J11)*J12 | K13: =-p_superv*SUM(K9:K11)*K12 | ... DE13: =-p_superv*SUM(DE9:DE11)*DE12
B14: Costo fijo (del motor) | D14: 0 | E14: 0 | F14: 0 | G14: 0 | H14: 0 | I14: 0 | J14: 0 | K14: 0 | L14: 0 | M14: 0 | N14: 0 | O14: 0 | P14: 0 | Q14: 0 | R14: 0 | S14: 0 | T14: -2185.32 | U14: -2196.17 | V14: -2207.07 | W14: -2218.02 | X14: -2229.03 | Y14: -2240.1 | Z14: -2251.21 | AA14: -2262.38 | AB14: -2273.61 | AC14: -2284.89 | AD14: -2296.23 | AE14: -2307.63 | AF14: -2319.08 | AG14: -2330.59 | AH14: -2342.16 | AI14: -2353.78 | AJ14: -2365.47 | AK14: -2377.2 | AL14: -2389 | AM14: -2400.87 | AN14: -2412.78 | AO14: -2424.75 | AP14: -2436.78 | AQ14: -2448.88 | AR14: -2461.03 | AS14: -2473.24 | AT14: -2485.52 | AU14: -2497.85 | AV14: -2510.25 | AW14: -2522.71 | AX14: -2535.23 | AY14: -2547.81 | AZ14: -2560.45 | BA14: -2573.17 | BB14: -2585.94 | BC14: -2598.77 | BD14: -2611.66 | BE14: -2624.62 | BF14: -2637.66 | BG14: -2650.74 | BH14: -2663.89 | BI14: -2677.12 | BJ14: -2690.4 | BK14: -2703.76 | BL14: -2717.17 | BM14: -2730.66 | BN14: -2744.22 | BO14: -2757.83 | BP14: -2771.52 | BQ14: -2785.27 | BR14: -2799.09 | BS14: -2812.99 | BT14: -2826.95 | BU14: -2840.98 | BV14: -2855.07 | BW14: -2869.25 | BX14: -2883.49 | BY14: -2897.8 | BZ14: -2912.19 | CA14: -2926.62 | CB14: -2941.15 | CC14: -2955.76 | CD14: -2970.43 | CE14: -2985.16 | CF14: -2999.97 | CG14: -3014.88 | CH14: -3029.83 | CI14: -3044.87 | CJ14: -3059.98 | CK14: -3075.16 | CL14: -3090.42 | CM14: -3105.76 | CN14: -3121.18 | CO14: -3136.67 | CP14: -3152.23 | CQ14: -3167.88 | CR14: -3183.6 | CS14: -3199.41 | CT14: -3215.28 | CU14: -3231.24 | CV14: -3247.27 | CW14: -3263.39 | CX14: -3279.58 | CY14: -3295.86 | CZ14: -3312.22 | DA14: -3328.65 | DB14: -3345.18 | DC14: -3361.77 | DD14: 0 | DE14: 0
B15: Costo variable (del motor) | D15: 0 | E15: 0 | F15: 0 | G15: 0 | H15: 0 | I15: 0 | J15: 0 | K15: 0 | L15: 0 | M15: 0 | N15: 0 | O15: 0 | P15: 0 | Q15: 0 | R15: 0 | S15: 0 | T15: -4129.23 | U15: -4195.86 | V15: -4216.68 | W15: -4237.62 | X15: -4258.65 | Y15: -4319.01 | Z15: -4340.44 | AA15: -4361.99 | AB15: -4383.63 | AC15: -4437.39 | AD15: -4459.42 | AE15: -4481.56 | AF15: -4503.79 | AG15: -4558.8 | AH15: -4581.42 | AI15: -4604.16 | AJ15: -4627 | AK15: -4683.28 | AL15: -4706.52 | AM15: -4729.87 | AN15: -4753.36 | AO15: -4810.9 | AP15: -4834.79 | AQ15: -4858.78 | AR15: -4882.9 | AS15: -5115.01 | AT15: -5140.39 | AU15: -5165.91 | AV15: -5191.54 | AW15: -5261.49 | AX15: -5287.6 | AY15: -5313.85 | AZ15: -5340.22 | BA15: -5411.77 | BB15: -5438.64 | BC15: -5465.62 | BD15: -5492.76 | BE15: -5575.17 | BF15: -5602.84 | BG15: -5630.64 | BH15: -5658.58 | BI15: -5733.55 | BJ15: -5762.01 | BK15: -5790.61 | BL15: -5819.34 | BM15: -5905.6 | BN15: -5934.91 | BO15: -5964.36 | BP15: -5993.97 | BQ15: -6072.48 | BR15: -6102.63 | BS15: -6132.91 | BT15: -6163.35 | BU15: -6253.64 | BV15: -6284.68 | BW15: -6315.87 | BX15: -6347.21 | BY15: -6439.6 | BZ15: -6471.57 | CA15: -6503.68 | CB15: -6535.96 | CC15: -6630.51 | CD15: -6663.41 | CE15: -6696.49 | CF15: -6729.72 | CG15: -6826.48 | CH15: -6860.35 | CI15: -6894.4 | CJ15: -6928.62 | CK15: -7027.63 | CL15: -7062.49 | CM15: -7097.55 | CN15: -7132.78 | CO15: -7234.08 | CP15: -7269.99 | CQ15: -7306.07 | CR15: -7342.32 | CS15: -7457.2 | CT15: -7494.21 | CU15: -7531.41 | CV15: -7568.79 | CW15: -7686.36 | CX15: -7724.5 | CY15: -7762.83 | CZ15: -7801.36 | DA15: -7840.08 | DB15: -7878.99 | DC15: -7918.09 | DD15: 0 | DE15: 0
B16: Gastos SPV (del motor) | D16: 0 | E16: 0 | F16: 0 | G16: 0 | H16: 0 | I16: 0 | J16: 0 | K16: 0 | L16: 0 | M16: 0 | N16: 0 | O16: 0 | P16: 0 | Q16: 0 | R16: 0 | S16: 0 | T16: -491.07 | U16: -493.5 | V16: -495.94 | W16: -498.4 | X16: -500.88 | Y16: -503.37 | Z16: -505.86 | AA16: -508.38 | AB16: -510.9 | AC16: -513.43 | AD16: -515.98 | AE16: -518.54 | AF16: -521.11 | AG16: -523.7 | AH16: -526.29 | AI16: -528.9 | AJ16: -531.54 | AK16: -534.17 | AL16: -536.83 | AM16: -539.49 | AN16: -542.16 | AO16: -544.86 | AP16: -547.56 | AQ16: -550.28 | AR16: -553.01 | AS16: -555.76 | AT16: -558.51 | AU16: -561.28 | AV16: -564.06 | AW16: -566.87 | AX16: -569.68 | AY16: -572.51 | AZ16: -575.35 | BA16: -578.21 | BB16: -581.07 | BC16: -583.95 | BD16: -586.86 | BE16: -589.78 | BF16: -592.7 | BG16: -595.64 | BH16: -598.59 | BI16: -601.56 | BJ16: -604.56 | BK16: -607.55 | BL16: -610.57 | BM16: -613.6 | BN16: -616.65 | BO16: -619.71 | BP16: -622.78 | BQ16: -625.87 | BR16: -628.97 | BS16: -632.1 | BT16: -635.23 | BU16: -638.39 | BV16: -641.56 | BW16: -644.74 | BX16: -647.94 | BY16: -651.15 | BZ16: -654.39 | CA16: -657.63 | CB16: -660.9 | CC16: -664.18 | CD16: -667.47 | CE16: -670.79 | CF16: -674.12 | CG16: -677.46 | CH16: -680.83 | CI16: -684.2 | CJ16: -687.6 | CK16: -691.02 | CL16: -694.44 | CM16: -697.89 | CN16: -701.35 | CO16: -704.83 | CP16: -708.33 | CQ16: -711.84 | CR16: -715.38 | CS16: -718.93 | CT16: -722.49 | CU16: -726.09 | CV16: -729.69 | CW16: -733.31 | CX16: -736.94 | CY16: -740.61 | CZ16: -744.27 | DA16: -747.97 | DB16: -751.69 | DC16: -755.42 | DD16: 0 | DE16: 0
B17: Seguros (del motor) | D17: 0 | E17: 0 | F17: 0 | G17: 0 | H17: 0 | I17: 0 | J17: 0 | K17: 0 | L17: 0 | M17: 0 | N17: 0 | O17: 0 | P17: 0 | Q17: 0 | R17: 0 | S17: 0 | T17: -178.20478 | U17: -178.20478 | V17: -178.20478 | W17: -178.20478 | X17: -178.20478 | Y17: -178.20478 | Z17: -178.20478 | AA17: -178.20478 | AB17: -178.20478 | AC17: -178.20478 | AD17: -178.20478 | AE17: -178.20478 | AF17: -178.20478 | AG17: -178.20478 | AH17: -178.20478 | AI17: -178.20478 | AJ17: -178.20478 | AK17: -178.20478 | AL17: -178.20478 | AM17: -178.20478 | AN17: -178.20478 | AO17: -178.20478 | AP17: -178.20478 | AQ17: -178.20478 | AR17: -178.20478 | AS17: -178.20478 | AT17: -178.20478 | AU17: -178.20478 | AV17: -178.20478 | AW17: -178.20478 | AX17: -178.20478 | AY17: -178.20478 | AZ17: -178.20478 | BA17: -178.20478 | BB17: -178.20478 | BC17: -178.20478 | BD17: -178.20478 | BE17: -178.20478 | BF17: -178.20478 | BG17: -178.20478 | BH17: -178.20478 | BI17: -178.20478 | BJ17: -178.20478 | BK17: -178.20478 | BL17: -178.20478 | BM17: -178.20478 | BN17: -178.20478 | BO17: -178.20478 | BP17: -178.20478 | BQ17: -178.20478 | BR17: -178.20478 | BS17: -178.20478 | BT17: -178.20478 | BU17: -178.20478 | BV17: -178.20478 | BW17: -178.20478 | BX17: -178.20478 | BY17: -178.20478 | BZ17: -178.20478 | CA17: -178.20478 | CB17: -178.20478 | CC17: -178.20478 | CD17: -178.20478 | CE17: -178.20478 | CF17: -178.20478 | CG17: -178.20478 | CH17: -178.20478 | CI17: -178.20478 | CJ17: -178.20478 | CK17: -178.20478 | CL17: -178.20478 | CM17: -178.20478 | CN17: -178.20478 | CO17: -178.20478 | CP17: -178.20478 | CQ17: -178.20478 | CR17: -178.20478 | CS17: -178.20478 | CT17: -178.20478 | CU17: -178.20478 | CV17: -178.20478 | CW17: -178.20478 | CX17: -178.20478 | CY17: -178.20478 | CZ17: -178.20478 | DA17: -178.20478 | DB17: -178.20478 | DC17: -178.20478 | DD17: 0 | DE17: 0
B18: Fianzas (del motor) | D18: 0 | E18: 0 | F18: 0 | G18: 0 | H18: 0 | I18: 0 | J18: 0 | K18: 0 | L18: 0 | M18: 0 | N18: 0 | O18: 0 | P18: 0 | Q18: 0 | R18: 0 | S18: 0 | T18: -191.57902 | U18: -191.57902 | V18: -191.57902 | W18: -191.57902 | X18: -191.57902 | Y18: -191.57902 | Z18: -191.57902 | AA18: -191.57902 | AB18: -52.323497 | AC18: -52.323497 | AD18: -52.323497 | AE18: -52.323497 | AF18: -52.323497 | AG18: -52.323497 | AH18: -52.323497 | AI18: -52.323497 | AJ18: -52.323497 | AK18: -52.323497 | AL18: -52.323497 | AM18: -52.323497 | AN18: -52.323497 | AO18: -52.323497 | AP18: -52.323497 | AQ18: -52.323497 | AR18: -52.323497 | AS18: -52.323497 | AT18: -52.323497 | AU18: -52.323497 | AV18: -52.323497 | AW18: -52.323497 | AX18: -52.323497 | AY18: -52.323497 | AZ18: -52.323497 | BA18: -52.323497 | BB18: -52.323497 | BC18: -52.323497 | BD18: -52.323497 | BE18: -52.323497 | BF18: -52.323497 | BG18: -52.323497 | BH18: -52.323497 | BI18: -52.323497 | BJ18: -52.323497 | BK18: -52.323497 | BL18: -52.323497 | BM18: -52.323497 | BN18: -52.323497 | BO18: -52.323497 | BP18: -52.323497 | BQ18: -52.323497 | BR18: -52.323497 | BS18: -52.323497 | BT18: -52.323497 | BU18: -52.323497 | BV18: -52.323497 | BW18: -52.323497 | BX18: -52.323497 | BY18: -52.323497 | BZ18: -52.323497 | CA18: -52.323497 | CB18: -52.323497 | CC18: -52.323497 | CD18: -52.323497 | CE18: -52.323497 | CF18: -52.323497 | CG18: -52.323497 | CH18: -52.323497 | CI18: -52.323497 | CJ18: -52.323497 | CK18: -52.323497 | CL18: -52.323497 | CM18: -52.323497 | CN18: -52.323497 | CO18: -52.323497 | CP18: -52.323497 | CQ18: -52.323497 | CR18: -52.323497 | CS18: -52.323497 | CT18: -52.323497 | CU18: -52.323497 | CV18: -52.323497 | CW18: -52.323497 | CX18: -52.323497 | CY18: -52.323497 | CZ18: -52.323497 | DA18: -52.323497 | DB18: -52.323497 | DC18: -52.323497 | DD18: -418.58798 | DE18: 0
B19: Gastos de promocion (del motor) | D19: 0 | E19: 0 | F19: 0 | G19: 0 | H19: 0 | I19: 0 | J19: 0 | K19: 0 | L19: 0 | M19: 0 | N19: 0 | O19: 0 | P19: 0 | Q19: 0 | R19: 0 | S19: 0 | T19: 0 | U19: 0 | V19: 0 | W19: 0 | X19: 0 | Y19: 0 | Z19: 0 | AA19: 0 | AB19: 0 | AC19: 0 | AD19: 0 | AE19: 0 | AF19: 0 | AG19: 0 | AH19: 0 | AI19: 0 | AJ19: 0 | AK19: 0 | AL19: 0 | AM19: 0 | AN19: 0 | AO19: 0 | AP19: 0 | AQ19: 0 | AR19: 0 | AS19: 0 | AT19: 0 | AU19: 0 | AV19: 0 | AW19: 0 | AX19: 0 | AY19: 0 | AZ19: 0 | BA19: 0 | BB19: 0 | BC19: 0 | BD19: 0 | BE19: 0 | BF19: 0 | BG19: 0 | BH19: 0 | BI19: 0 | BJ19: 0 | BK19: 0 | BL19: 0 | BM19: 0 | BN19: 0 | BO19: 0 | BP19: 0 | BQ19: 0 | BR19: 0 | BS19: 0 | BT19: 0 | BU19: 0 | BV19: 0 | BW19: 0 | BX19: 0 | BY19: 0 | BZ19: 0 | CA19: 0 | CB19: 0 | CC19: 0 | CD19: 0 | CE19: 0 | CF19: 0 | CG19: 0 | CH19: 0 | CI19: 0 | CJ19: 0 | CK19: 0 | CL19: 0 | CM19: 0 | CN19: 0 | CO19: 0 | CP19: 0 | CQ19: 0 | CR19: 0 | CS19: 0 | CT19: 0 | CU19: 0 | CV19: 0 | CW19: 0 | CX19: 0 | CY19: 0 | CZ19: 0 | DA19: 0 | DB19: 0 | DC19: 0 | DD19: 0 | DE19: 0
B20: Fideicomiso (del motor) | D20: 0 | E20: 0 | F20: 0 | G20: 0 | H20: 0 | I20: 0 | J20: 0 | K20: 0 | L20: 0 | M20: 0 | N20: 0 | O20: 0 | P20: 0 | Q20: 0 | R20: 0 | S20: 0 | T20: -25 | U20: -25 | V20: -25 | W20: -25 | X20: -25 | Y20: -25 | Z20: -25 | AA20: -25 | AB20: -25 | AC20: -25 | AD20: -25 | AE20: -25 | AF20: -25 | AG20: -25 | AH20: -25 | AI20: -25 | AJ20: -25 | AK20: -25 | AL20: -25 | AM20: -25 | AN20: -25 | AO20: -25 | AP20: -25 | AQ20: -25 | AR20: -25 | AS20: -25 | AT20: -25 | AU20: -25 | AV20: -25 | AW20: -25 | AX20: -25 | AY20: -25 | AZ20: -25 | BA20: -25 | BB20: -25 | BC20: -25 | BD20: -25 | BE20: -25 | BF20: -25 | BG20: -25 | BH20: -25 | BI20: -25 | BJ20: -25 | BK20: -25 | BL20: -25 | BM20: -25 | BN20: -25 | BO20: -25 | BP20: -25 | BQ20: -25 | BR20: -25 | BS20: -25 | BT20: -25 | BU20: -25 | BV20: -25 | BW20: -25 | BX20: -25 | BY20: -25 | BZ20: -25 | CA20: -25 | CB20: -25 | CC20: -25 | CD20: -25 | CE20: -25 | CF20: -25 | CG20: -25 | CH20: -25 | CI20: -25 | CJ20: -25 | CK20: -25 | CL20: -25 | CM20: -25 | CN20: -25 | CO20: -25 | CP20: -25 | CQ20: -25 | CR20: -25 | CS20: -25 | CT20: -25 | CU20: -25 | CV20: -25 | CW20: -25 | CX20: -25 | CY20: -25 | CZ20: -25 | DA20: -25 | DB20: -25 | DC20: -25 | DD20: -200 | DE20: 0
B21: Efecto ITAN (del motor) | D21: 0 | E21: 0 | F21: 0 | G21: 0 | H21: 0 | I21: 0 | J21: 0 | K21: 0 | L21: 0 | M21: 0 | N21: 0 | O21: 0 | P21: 0 | Q21: 0 | R21: 0 | S21: 0 | T21: 0 | U21: 0 | V21: 0 | W21: 0 | X21: 0 | Y21: 0 | Z21: 0 | AA21: 0 | AB21: 0 | AC21: 0 | AD21: 0 | AE21: 0 | AF21: 0 | AG21: 0 | AH21: 0 | AI21: 0 | AJ21: 0 | AK21: 0 | AL21: 0 | AM21: 0 | AN21: 0 | AO21: 0 | AP21: 0 | AQ21: 0 | AR21: 0 | AS21: 0 | AT21: 0 | AU21: 0 | AV21: 0 | AW21: 0 | AX21: 0 | AY21: 0 | AZ21: 0 | BA21: 0 | BB21: 0 | BC21: 0 | BD21: 0 | BE21: 0 | BF21: 0 | BG21: 0 | BH21: 0 | BI21: 0 | BJ21: 0 | BK21: 0 | BL21: 0 | BM21: 0 | BN21: 0 | BO21: 0 | BP21: 0 | BQ21: 0 | BR21: 0 | BS21: 0 | BT21: 0 | BU21: 0 | BV21: 0 | BW21: 0 | BX21: 0 | BY21: 0 | BZ21: 0 | CA21: 0 | CB21: 0 | CC21: 0 | CD21: 0 | CE21: 0 | CF21: 0 | CG21: 0 | CH21: 0 | CI21: 0 | CJ21: 0 | CK21: 0 | CL21: 0 | CM21: 0 | CN21: 0 | CO21: 0 | CP21: 0 | CQ21: 0 | CR21: 0 | CS21: 0 | CT21: 0 | CU21: 0 | CV21: 0 | CW21: 0 | CX21: 0 | CY21: 0 | CZ21: 0 | DA21: 0 | DB21: 0 | DC21: 0 | DD21: 0 | DE21: 0
B22: CAPEX (del motor) | D22: -12746.071 | E22: -4330.3462 | F22: -4376.8374 | G22: -4150.0001 | H22: -149.83406 | I22: -150.24664 | J22: -25 | K22: -60034.293 | L22: -19270.005 | M22: -47783.897 | N22: -47384.719 | O22: -40590.904 | P22: -42859.785 | Q22: -6540.4886 | R22: -2007.4789 | S22: -595.11193 | T22: 0 | U22: 0 | V22: 0 | W22: 0 | X22: 0 | Y22: 0 | Z22: 0 | AA22: 0 | AB22: 0 | AC22: 0 | AD22: 0 | AE22: 0 | AF22: 0 | AG22: 0 | AH22: 0 | AI22: 0 | AJ22: 0 | AK22: 0 | AL22: 0 | AM22: 0 | AN22: 0 | AO22: 0 | AP22: 0 | AQ22: 0 | AR22: 0 | AS22: 0 | AT22: 0 | AU22: 0 | AV22: 0 | AW22: 0 | AX22: 0 | AY22: 0 | AZ22: 0 | BA22: 0 | BB22: 0 | BC22: 0 | BD22: 0 | BE22: 0 | BF22: 0 | BG22: 0 | BH22: 0 | BI22: 0 | BJ22: 0 | BK22: 0 | BL22: 0 | BM22: 0 | BN22: 0 | BO22: 0 | BP22: 0 | BQ22: 0 | BR22: 0 | BS22: 0 | BT22: 0 | BU22: 0 | BV22: 0 | BW22: 0 | BX22: 0 | BY22: 0 | BZ22: 0 | CA22: 0 | CB22: 0 | CC22: 0 | CD22: 0 | CE22: 0 | CF22: 0 | CG22: 0 | CH22: 0 | CI22: 0 | CJ22: 0 | CK22: 0 | CL22: 0 | CM22: 0 | CN22: 0 | CO22: 0 | CP22: 0 | CQ22: 0 | CR22: 0 | CS22: 0 | CT22: 0 | CU22: 0 | CV22: 0 | CW22: 0 | CX22: 0 | CY22: 0 | CZ22: 0 | DA22: 0 | DB22: 0 | DC22: 0 | DD22: 0 | DE22: 0
B23: Flujo de caja de IGV (del motor) | D23: -258.96443 | E23: -1.2852227 | F23: -2.7916012 | G23: 13.632703 | H23: 240.40614 | I23: 7.5024074 | J23: 0 | K23: -1127.8959 | L23: -5.59767 | M23: -1718.1934 | N23: 37.712467 | O23: 457.43208 | P23: -313.07405 | Q23: 2381.6044 | R23: 253.94072 | S23: -0.16909372 | T23: 35.740432 | U23: 0 | V23: 0 | W23: 0 | X23: 0 | Y23: 0 | Z23: 0 | AA23: 0 | AB23: 0 | AC23: 0 | AD23: 0 | AE23: 0 | AF23: 0 | AG23: 0 | AH23: 0 | AI23: 0 | AJ23: 0 | AK23: 0 | AL23: 0 | AM23: 0 | AN23: 0 | AO23: 0 | AP23: 0 | AQ23: 0 | AR23: 0 | AS23: 0 | AT23: 0 | AU23: 0 | AV23: 0 | AW23: 0 | AX23: 0 | AY23: 0 | AZ23: 0 | BA23: 0 | BB23: 0 | BC23: 0 | BD23: 0 | BE23: 0 | BF23: 0 | BG23: 0 | BH23: 0 | BI23: 0 | BJ23: 0 | BK23: 0 | BL23: 0 | BM23: 0 | BN23: 0 | BO23: 0 | BP23: 0 | BQ23: 0 | BR23: 0 | BS23: 0 | BT23: 0 | BU23: 0 | BV23: 0 | BW23: 0 | BX23: 0 | BY23: 0 | BZ23: 0 | CA23: 0 | CB23: 0 | CC23: 0 | CD23: 0 | CE23: 0 | CF23: 0 | CG23: 0 | CH23: 0 | CI23: 0 | CJ23: 0 | CK23: 0 | CL23: 0 | CM23: 0 | CN23: 0 | CO23: 0 | CP23: 0 | CQ23: 0 | CR23: 0 | CS23: 0 | CT23: 0 | CU23: 0 | CV23: 0 | CW23: 0 | CX23: 0 | CY23: 0 | CZ23: 0 | DA23: 0 | DB23: 0 | DC23: 0 | DD23: 0 | DE23: 0
B24: Intereses de la deuda | D24: 0 | E24: 0 | F24: 0 | G24: 0 | H24: 0 | I24: 0 | J24: 0 | K24: -594.53209 | L24: -1214.5217 | M24: -1795.4636 | N24: -2762.6036 | O24: -3706.3772 | P24: -4583.9102 | Q24: -5310.7234 | R24: -5541.0255 | S24: -5696.1392 | T24: -5773.8537 | U24: -5708.3639 | V24: -5641.2807 | W24: -5572.5655 | X24: -5502.1783 | Y24: -5430.0787 | Z24: -5356.2249 | AA24: -5280.5742 | AB24: -5203.0829 | AC24: -5123.7063 | AD24: -5042.3984 | AE24: -4959.1123 | AF24: -4873.7999 | AG24: -4786.4118 | AH24: -4696.8976 | AI24: -4605.2054 | AJ24: -4511.2825 | AK24: -4415.0743 | AL24: -4316.5255 | AM24: -4215.5789 | AN24: -4112.1763 | AO24: -4006.258 | AP24: -3897.7626 | AQ24: -3786.6276 | AR24: -3672.7886 | AS24: -3556.1799 | AT24: -3436.7342 | AU24: -3314.3823 | AV24: -3189.0536 | AW24: -3060.6757 | AX24: -2929.1743 | AY24: -2794.4736 | AZ24: -2656.4955 | BA24: -2515.1605 | BB24: -2370.3867 | BC24: -2222.0906 | BD24: -2070.1865 | BE24: -1914.5866 | BF24: -1755.2009 | BG24: -1591.9374 | BH24: -1424.7016 | BI24: -1253.3971 | BJ24: -1077.9246 | BK24: -898.183 | BL24: -714.06823 | BM24: -525.47396 | BN24: -332.29119 | BO24: -134.40829 | BP24: 6.7932924e-12 | BQ24: 6.9585731e-12 | BR24: 7.127875e-12 | BS24: 7.3012961e-12 | BT24: 7.4789365e-12 | BU24: 7.6608989e-12 | BV24: 7.8472884e-12 | BW24: 8.0382128e-12 | BX24: 8.2337823e-12 | BY24: 8.4341101e-12 | BZ24: 8.6393118e-12 | CA24: 8.8495061e-12 | CB24: 9.0648144e-12 | CC24: 9.2853612e-12 | CD24: 9.5112738e-12 | CE24: 9.7426829e-12 | CF24: 9.9797222e-12 | CG24: 1.0222529e-11 | CH24: 1.0471243e-11 | CI24: 1.0726008e-11 | CJ24: 1.0986971e-11 | CK24: 1.1254284e-11 | CL24: 1.1528101e-11 | CM24: 1.1808579e-11 | CN24: 1.2095882e-11 | CO24: 1.2390174e-11 | CP24: 1.2691627e-11 | CQ24: 1.3000414e-11 | CR24: 1.3316714e-11 | CS24: 1.3640709e-11 | CT24: 1.3972587e-11 | CU24: 1.431254e-11 | CV24: 1.4660764e-11 | CW24: 1.501746e-11 | CX24: 1.5382834e-11 | CY24: 1.5757098e-11 | CZ24: 1.6140468e-11 | DA24: 1.6533166e-11 | DB24: 1.6935417e-11 | DC24: 1.7347456e-11 | DD24: 1.7769519e-11 | DE24: 1.8201851e-11
B25: Utilidad antes de impuestos | D25: =SUM(D9:D11)+D13+SUM(D14:D20)-D24 | E25: =SUM(E9:E11)+E13+SUM(E14:E20)-E24 | F25: =SUM(F9:F11)+F13+SUM(F14:F20)-F24 | G25: =SUM(G9:G11)+G13+SUM(G14:G20)-G24 | H25: =SUM(H9:H11)+H13+SUM(H14:H20)-H24 | I25: =SUM(I9:I11)+I13+SUM(I14:I20)-I24 | J25: =SUM(J9:J11)+J13+SUM(J14:J20)-J24 | K25: =SUM(K9:K11)+K13+SUM(K14:K20)-K24 | ... DE25: =SUM(DE9:DE11)+DE13+SUM(DE14:DE20)-DE24
B26: Participacion e Impuesto a la Renta (del motor) | D26: 0 | E26: 0 | F26: 0 | G26: 0 | H26: 0 | I26: 0 | J26: 0 | K26: 0 | L26: 0 | M26: 0 | N26: 0 | O26: 0 | P26: 0 | Q26: 0 | R26: 0 | S26: 0 | T26: 0 | U26: 0 | V26: 0 | W26: 0 | X26: 0 | Y26: 0 | Z26: 0 | AA26: 0 | AB26: -1704.2105 | AC26: 0 | AD26: 0 | AE26: 0 | AF26: -7353.1399 | AG26: 0 | AH26: 0 | AI26: 0 | AJ26: -7492.899 | AK26: 0 | AL26: 0 | AM26: 0 | AN26: -7634.5254 | AO26: 0 | AP26: 0 | AQ26: 0 | AR26: -7777.4129 | AS26: 0 | AT26: 0 | AU26: 0 | AV26: -8124.4819 | AW26: 0 | AX26: 0 | AY26: 0 | AZ26: -8282.9387 | BA26: 0 | BB26: 0 | BC26: 0 | BD26: -8441.7539 | BE26: 0 | BF26: 0 | BG26: 0 | BH26: -8688.5711 | BI26: 0 | BJ26: 0 | BK26: 0 | BL26: -8848.3458 | BM26: 0 | BN26: 0 | BO26: 0 | BP26: -8993.0965 | BQ26: 0 | BR26: 0 | BS26: 0 | BT26: -8371.9523 | BU26: 0 | BV26: 0 | BW26: 0 | BX26: -7316.4898 | BY26: 0 | BZ26: 0 | CA26: 0 | CB26: -6166.3989 | CC26: 0 | CD26: 0 | CE26: 0 | CF26: -4555.252 | CG26: 0 | CH26: 0 | CI26: 0 | CJ26: -4938.3388 | CK26: 0 | CL26: 0 | CM26: 0 | CN26: -5239.9944 | CO26: 0 | CP26: 0 | CQ26: 0 | CR26: -5553.5925 | CS26: 0 | CT26: 0 | CU26: 0 | CV26: -5895.152 | CW26: 0 | CX26: 0 | CY26: 0 | CZ26: -6250.4229 | DA26: 0 | DB26: 0 | DC26: 0 | DD26: -4615.1874 | DE26: 0
B27: Desembolsos de deuda | D27: 0 | E27: 0 | F27: 0 | G27: 0 | H27: 0 | I27: 0 | J27: 0 | K27: 44327.128 | L27: 15088.341 | M27: 37959.834 | N27: 37715.894 | O27: 32348.991 | P27: 34229.775 | Q27: 5205.3258 | R27: 1584.7744 | S27: 455.78674 | T27: 0 | U27: 0 | V27: 0 | W27: 0 | X27: 0 | Y27: 0 | Z27: 0 | AA27: 0 | AB27: 0 | AC27: 0 | AD27: 0 | AE27: 0 | AF27: 0 | AG27: 0 | AH27: 0 | AI27: 0 | AJ27: 0 | AK27: 0 | AL27: 0 | AM27: 0 | AN27: 0 | AO27: 0 | AP27: 0 | AQ27: 0 | AR27: 0 | AS27: 0 | AT27: 0 | AU27: 0 | AV27: 0 | AW27: 0 | AX27: 0 | AY27: 0 | AZ27: 0 | BA27: 0 | BB27: 0 | BC27: 0 | BD27: 0 | BE27: 0 | BF27: 0 | BG27: 0 | BH27: 0 | BI27: 0 | BJ27: 0 | BK27: 0 | BL27: 0 | BM27: 0 | BN27: 0 | BO27: 0 | BP27: 0 | BQ27: 0 | BR27: 0 | BS27: 0 | BT27: 0 | BU27: 0 | BV27: 0 | BW27: 0 | BX27: 0 | BY27: 0 | BZ27: 0 | CA27: 0 | CB27: 0 | CC27: 0 | CD27: 0 | CE27: 0 | CF27: 0 | CG27: 0 | CH27: 0 | CI27: 0 | CJ27: 0 | CK27: 0 | CL27: 0 | CM27: 0 | CN27: 0 | CO27: 0 | CP27: 0 | CQ27: 0 | CR27: 0 | CS27: 0 | CT27: 0 | CU27: 0 | CV27: 0 | CW27: 0 | CX27: 0 | CY27: 0 | CZ27: 0 | DA27: 0 | DB27: 0 | DC27: 0 | DD27: 0 | DE27: 0
B28: Servicio de deuda | D28: 0 | E28: 0 | F28: 0 | G28: 0 | H28: 0 | I28: 0 | J28: 0 | K28: 0 | L28: 0 | M28: 0 | N28: 0 | O28: 0 | P28: 0 | Q28: 0 | R28: 0 | S28: 0 | T28: -8465.5858 | U28: -8465.5858 | V28: -8465.5858 | W28: -8465.5858 | X28: -8465.5858 | Y28: -8465.5858 | Z28: -8465.5858 | AA28: -8465.5858 | AB28: -8465.5858 | AC28: -8465.5858 | AD28: -8465.5858 | AE28: -8465.5858 | AF28: -8465.5858 | AG28: -8465.5858 | AH28: -8465.5858 | AI28: -8465.5858 | AJ28: -8465.5858 | AK28: -8465.5858 | AL28: -8465.5858 | AM28: -8465.5858 | AN28: -8465.5858 | AO28: -8465.5858 | AP28: -8465.5858 | AQ28: -8465.5858 | AR28: -8465.5858 | AS28: -8465.5858 | AT28: -8465.5858 | AU28: -8465.5858 | AV28: -8465.5858 | AW28: -8465.5858 | AX28: -8465.5858 | AY28: -8465.5858 | AZ28: -8465.5858 | BA28: -8465.5858 | BB28: -8465.5858 | BC28: -8465.5858 | BD28: -8465.5858 | BE28: -8465.5858 | BF28: -8465.5858 | BG28: -8465.5858 | BH28: -8465.5858 | BI28: -8465.5858 | BJ28: -8465.5858 | BK28: -8465.5858 | BL28: -8465.5858 | BM28: -8465.5858 | BN28: -8465.5858 | BO28: -8465.5858 | BP28: 0 | BQ28: 0 | BR28: 0 | BS28: 0 | BT28: 0 | BU28: 0 | BV28: 0 | BW28: 0 | BX28: 0 | BY28: 0 | BZ28: 0 | CA28: 0 | CB28: 0 | CC28: 0 | CD28: 0 | CE28: 0 | CF28: 0 | CG28: 0 | CH28: 0 | CI28: 0 | CJ28: 0 | CK28: 0 | CL28: 0 | CM28: 0 | CN28: 0 | CO28: 0 | CP28: 0 | CQ28: 0 | CR28: 0 | CS28: 0 | CT28: 0 | CU28: 0 | CV28: 0 | CW28: 0 | CX28: 0 | CY28: 0 | CZ28: 0 | DA28: 0 | DB28: 0 | DC28: 0 | DD28: 0 | DE28: 0
B29: Deuda complementaria, desembolsos (del motor) | D29: 0 | E29: 0 | F29: 0 | G29: 0 | H29: 0 | I29: 0 | J29: 0 | K29: 0 | L29: 0 | M29: 0 | N29: 0 | O29: 0 | P29: 0 | Q29: 0 | R29: 0 | S29: 0 | T29: 0 | U29: 0 | V29: 0 | W29: 0 | X29: 0 | Y29: 0 | Z29: 0 | AA29: 0 | AB29: 0 | AC29: 0 | AD29: 0 | AE29: 0 | AF29: 0 | AG29: 0 | AH29: 0 | AI29: 0 | AJ29: 0 | AK29: 0 | AL29: 0 | AM29: 0 | AN29: 0 | AO29: 0 | AP29: 0 | AQ29: 0 | AR29: 0 | AS29: 0 | AT29: 0 | AU29: 0 | AV29: 0 | AW29: 0 | AX29: 0 | AY29: 0 | AZ29: 0 | BA29: 0 | BB29: 0 | BC29: 0 | BD29: 0 | BE29: 0 | BF29: 0 | BG29: 0 | BH29: 0 | BI29: 0 | BJ29: 0 | BK29: 0 | BL29: 0 | BM29: 0 | BN29: 0 | BO29: 0 | BP29: 0 | BQ29: 0 | BR29: 0 | BS29: 0 | BT29: 0 | BU29: 0 | BV29: 0 | BW29: 0 | BX29: 0 | BY29: 0 | BZ29: 0 | CA29: 0 | CB29: 0 | CC29: 0 | CD29: 0 | CE29: 0 | CF29: 0 | CG29: 0 | CH29: 0 | CI29: 0 | CJ29: 0 | CK29: 0 | CL29: 0 | CM29: 0 | CN29: 0 | CO29: 0 | CP29: 0 | CQ29: 0 | CR29: 0 | CS29: 0 | CT29: 0 | CU29: 0 | CV29: 0 | CW29: 0 | CX29: 0 | CY29: 0 | CZ29: 0 | DA29: 0 | DB29: 0 | DC29: 0 | DD29: 0 | DE29: 0
B30: Deuda complementaria, servicio (del motor) | D30: 0 | E30: 0 | F30: 0 | G30: 0 | H30: 0 | I30: 0 | J30: 0 | K30: 0 | L30: 0 | M30: 0 | N30: 0 | O30: 0 | P30: 0 | Q30: 0 | R30: 0 | S30: 0 | T30: 0 | U30: 0 | V30: 0 | W30: 0 | X30: 0 | Y30: 0 | Z30: 0 | AA30: 0 | AB30: 0 | AC30: 0 | AD30: 0 | AE30: 0 | AF30: 0 | AG30: 0 | AH30: 0 | AI30: 0 | AJ30: 0 | AK30: 0 | AL30: 0 | AM30: 0 | AN30: 0 | AO30: 0 | AP30: 0 | AQ30: 0 | AR30: 0 | AS30: 0 | AT30: 0 | AU30: 0 | AV30: 0 | AW30: 0 | AX30: 0 | AY30: 0 | AZ30: 0 | BA30: 0 | BB30: 0 | BC30: 0 | BD30: 0 | BE30: 0 | BF30: 0 | BG30: 0 | BH30: 0 | BI30: 0 | BJ30: 0 | BK30: 0 | BL30: 0 | BM30: 0 | BN30: 0 | BO30: 0 | BP30: 0 | BQ30: 0 | BR30: 0 | BS30: 0 | BT30: 0 | BU30: 0 | BV30: 0 | BW30: 0 | BX30: 0 | BY30: 0 | BZ30: 0 | CA30: 0 | CB30: 0 | CC30: 0 | CD30: 0 | CE30: 0 | CF30: 0 | CG30: 0 | CH30: 0 | CI30: 0 | CJ30: 0 | CK30: 0 | CL30: 0 | CM30: 0 | CN30: 0 | CO30: 0 | CP30: 0 | CQ30: 0 | CR30: 0 | CS30: 0 | CT30: 0 | CU30: 0 | CV30: 0 | CW30: 0 | CX30: 0 | CY30: 0 | CZ30: 0 | DA30: 0 | DB30: 0 | DC30: 0 | DD30: 0 | DE30: 0
B31: Flujo de caja financiero | D31: =SUM(D9:D11)+D13+SUM(D14:D23)+D26+SUM(D27:D30) | E31: =SUM(E9:E11)+E13+SUM(E14:E23)+E26+SUM(E27:E30) | F31: =SUM(F9:F11)+F13+SUM(F14:F23)+F26+SUM(F27:F30) | G31: =SUM(G9:G11)+G13+SUM(G14:G23)+G26+SUM(G27:G30) | H31: =SUM(H9:H11)+H13+SUM(H14:H23)+H26+SUM(H27:H30) | I31: =SUM(I9:I11)+I13+SUM(I14:I23)+I26+SUM(I27:I30) | J31: =SUM(J9:J11)+J13+SUM(J14:J23)+J26+SUM(J27:J30) | K31: =SUM(K9:K11)+K13+SUM(K14:K23)+K26+SUM(K27:K30) | ... DE31: =SUM(DE9:DE11)+DE13+SUM(DE14:DE23)+DE26+SUM(DE27:DE30)
B32: Factor de actualizacion | D32: =IF(D8=0,0,1/(1+(1+p_ke)^(1/12)-1)^SUM($D8:D8)) | E32: =IF(E8=0,0,1/(1+(1+p_ke)^(1/12)-1)^SUM($D8:E8)) | F32: =IF(F8=0,0,1/(1+(1+p_ke)^(1/12)-1)^SUM($D8:F8)) | G32: =IF(G8=0,0,1/(1+(1+p_ke)^(1/12)-1)^SUM($D8:G8)) | H32: =IF(H8=0,0,1/(1+(1+p_ke)^(1/12)-1)^SUM($D8:H8)) | I32: =IF(I8=0,0,1/(1+(1+p_ke)^(1/12)-1)^SUM($D8:I8)) | J32: =IF(J8=0,0,1/(1+(1+p_ke)^(1/12)-1)^SUM($D8:J8)) | K32: =IF(K8=0,0,1/(1+(1+p_ke)^(1/12)-1)^SUM($D8:K8)) | ... DE32: =IF(DE8=0,0,1/(1+(1+p_ke)^(1/12)-1)^SUM($D8:DE8))
B34: VAN financiero | D34: =SUMPRODUCT(D31:DE31,D32:DE32)
