Workbook
Name p_ke: Inputs!$D$6
Name p_kd: Inputs!$D$7
Name p_wacc: Inputs!$D$8
Name p_tir: Inputs!$D$9
Name p_rcsd: Inputs!$D$10
Name p_crsd: Inputs!$D$11
Name p_ir: Inputs!$D$12
Name p_pt: Inputs!$D$13
Name p_arr: Inputs!$D$14
Name p_ipm: Inputs!$D$15
Name p_fx: Inputs!$D$16
Name p_ref: Inputs!$D$17
Name p_precio: Inputs!$D$18
Name p_margen_om: Inputs!$D$19

Sheet Resumen
B2: Resumen del modelo, APP autofinanciada por hitos
B3: No hay PPDI ni PPDMO: el proyecto se paga con la tarifa al usuario.
B6: Tarifa al usuario, S/ por kg DBO5 | D6: =p_precio
B7: Referencia mensual de ingreso | D7: =p_ref
B8: Ingreso tarifario, primer ano de operacion | D8: 1.2341551e+08
B9: Activo intangible al termino de obra | D9: ='Activo intangible'!$D$8
B10: Amortizacion lineal mensual | D10: ='Activo intangible'!$D$10
B11: Saldo final del intangible, debe ser cero | D11: ='Activo intangible'!$AE$16
B12: VAN financiero, debe ser cero | D12: =Flujo!$D$29
B13: Ke | D13: =p_ke
B14: Kd | D14: =p_kd
B15: WACC | D15: =p_wacc

Sheet Inputs
B2: Parametros del modelo
B3: Las celdas en ambar son de entrada. Las dos ultimas las resuelve el cierre.
B6: Ke, costo del patrimonio | D6: 0.11973267 | E6: CAPM en USD + riesgo pais + devaluacion
B7: Kd, costo de la deuda | D7: 0.10002309 | E7: soberano a vida media + spread
B8: WACC | D8: 0.098635786 | E8: despues de impuestos
B9: TIR objetivo del cierre | D9: 0.1197 | E9: Ke redondeado a 4 decimales, Control!M12
B10: Cobertura minima, RCSD | D10: 1.25 | E10: dimensiona la amortizacion
B11: Cuenta de reserva, CRSD | D11: 0.5 | E11: del servicio del ano siguiente
B12: Impuesto a la Renta | D12: 0.295
B13: Participacion de trabajadores | D13: 0.05
B14: Arrastre de perdidas | D14: 0.5 | E14: sistema B
B15: IPM, reajuste | D15: 0.0267 | E15: anual
B16: Tipo de cambio | D16: 3.3805 | E16: solo entra por los reembolsos en dolares
B17: PPDMO referencia mensual | D17: 12908504 | E17: S/ - LA CIERRA Solver
B18: Tarifa al usuario | D18: 31.109308 | E18: S/ por kg DBO5, derivada de la referencia
B19: Margen del operador | D19: 0.15 | E19: sobre todo el costo de O&M; aca no hay pata fija y variable

Sheet Hitos
B2: Hitos funcionales
B3: Sin PPDI los hitos solo reparten la inversion: no hay cuota que cobrar y no escalonan el inicio de la operacion.
B5: Hito | C5: % del CAPEX | D5: Inversion del hito
B6: Hito 1 | C6: 0.674423 | D6: ='Activo intangible'!$D$7*C6
B7: Hito 2 | C7: 0.0442 | D7: ='Activo intangible'!$D$7*C7
B8: Hito 3 | C8: 0.014198 | D8: ='Activo intangible'!$D$7*C8
B9: Hito 4 | C9: 0.267179 | D9: ='Activo intangible'!$D$7*C9
B10: Total | C10: =SUM(C6:C9) | D10: =SUM(D6:D9)

Sheet Activo intangible
B2: Activo intangible de la concesion
B3: CINIIF 12 p.17 y p.22. La amortizacion es gasto deducible y NO es caja.
B6: Inversion capitalizada | D6: 5.9055904e+08 | E6: CAPEX, otros del periodo D+C+PM y comisiones
B7: Intereses capitalizados | D7: 63241003 | E7: solo los del periodo de obra, NIC 23 via CINIIF 12 p.22
B8: Activo intangible al termino de obra | D8: =$D$6+$D$7
B9: Meses de operacion | D9: 238
B10: Amortizacion lineal mensual | D10: =$D$8/$D$9
B13: Ano | D13: 2025 | E13: 2026 | F13: 2027 | G13: 2028 | H13: 2029 | I13: 2030 | J13: 2031 | K13: 2032 | L13: 2033 | M13: 2034 | N13: 2035 | O13: 2036 | P13: 2037 | Q13: 2038 | R13: 2039 | S13: 2040 | T13: 2041 | U13: 2042 | V13: 2043 | W13: 2044 | X13: 2045 | Y13: 2046 | Z13: 2047 | AA13: 2048 | AB13: 2049 | AC13: 2050 | AD13: 2051 | AE13: 2052
B14: Meses de operacion del ano | D14: 0 | E14: 0 | F14: 0 | G14: 0 | H14: 0 | I14: 12 | J14: 12 | K14: 12 | L14: 12 | M14: 12 | N14: 12 | O14: 12 | P14: 12 | Q14: 12 | R14: 12 | S14: 12 | T14: 12 | U14: 12 | V14: 12 | W14: 12 | X14: 12 | Y14: 12 | Z14: 12 | AA14: 12 | AB14: 10 | AC14: 0 | AD14: 0 | AE14: 0
B15: Amortizacion del intangible | D15: =$D$10*D14 | E15: =$D$10*E14 | F15: =$D$10*F14 | G15: =$D$10*G14 | H15: =$D$10*H14 | I15: =$D$10*I14 | J15: =$D$10*J14 | K15: =$D$10*K14 | ... AE15: =$D$10*AE14
B16: Saldo del intangible | D16: =$D$8-D15 | E16: =D16-E15 | F16: =E16-F15 | G16: =F16-G15 | H16: =G16-H15 | I16: =H16-I15 | J16: =I16-J15 | K16: =J16-K15 | L16: =K16-L15 | ... AE16: =AD16-AE15
B18: Amortizacion acumulada | D18: =SUM($D$15:$AE$15)
B19: Saldo final, debe ser cero | D19: =$AE$16

Sheet Flujo
B2: Flujo de caja anual
B3: El VAN de la ultima fila es la celda que Solver lleva a cero.
B5: Ano | D5: 2025 | E5: 2026 | F5: 2027 | G5: 2028 | H5: 2029 | I5: 2030 | J5: 2031 | K5: 2032 | L5: 2033 | M5: 2034 | N5: 2035 | O5: 2036 | P5: 2037 | Q5: 2038 | R5: 2039 | S5: 2040 | T5: 2041 | U5: 2042 | V5: 2043 | W5: 2044 | X5: 2045 | Y5: 2046 | Z5: 2047 | AA5: 2048 | AB5: 2049 | AC5: 2050 | AD5: 2051 | AE5: 2052
B7: Ingreso tarifario al usuario | D7: =p_ref*0.0 | E7: =p_ref*0.0 | F7: =p_ref*0.0 | G7: =p_ref*0.0 | H7: =p_ref*0.0 | I7: =p_ref*9.560791754479322 | J7: =p_ref*10.018048674961099 | K7: =p_ref*10.499942555471089 | L7: =p_ref*11.10604009636353 | M7: =p_ref*11.667148169634194 | N7: =p_ref*12.19871302314162 | O7: =p_ref*12.757375862436476 | P7: =p_ref*13.344657550196267 | Q7: =p_ref*13.962132713843745 | R7: =p_ref*14.611462572941726 | S7: =p_ref*15.294436451923268 | T7: =p_ref*16.095599297709388 | U7: =p_ref*16.858664502137245 | V7: =p_ref*17.748896719911023 | W7: =p_ref*18.691407192127855 | X7: =p_ref*19.68948 | Y7: =p_ref*20.192360000000004 | Z7: =p_ref*20.70756 | AA7: =p_ref*21.344879999999996 | AB7: =p_ref*18.19679849640891 | AC7: =p_ref*0.0 | AD7: =p_ref*0.0 | AE7: =p_ref*0.0
B8: Pago por Obras | D8: 0 | E8: 0 | F8: 0 | G8: 0 | H8: 0 | I8: 0 | J8: 6738784.8 | K8: 0 | L8: 0 | M8: 0 | N8: 0 | O8: 0 | P8: 0 | Q8: 0 | R8: 0 | S8: 0 | T8: 0 | U8: 0 | V8: 0 | W8: 0 | X8: 0 | Y8: 0 | Z8: 0 | AA8: 0 | AB8: 0 | AC8: 0 | AD8: 0 | AE8: 0
B9: CAPEX | D9: -5374371.8 | E9: -24597552 | F9: -1.1508684e+08 | G9: -2.7059553e+08 | H9: -1.3920017e+08 | I9: 0 | J9: 0 | K9: 0 | L9: 0 | M9: 0 | N9: 0 | O9: 0 | P9: 0 | Q9: 0 | R9: 0 | S9: 0 | T9: 0 | U9: 0 | V9: 0 | W9: 0 | X9: 0 | Y9: 0 | Z9: 0 | AA9: 0 | AB9: 0 | AC9: 0 | AD9: 0 | AE9: 0
B10: Otros costos del periodo D+C+PM | D10: -4741865.3 | E10: -2619055.1 | F10: -2976119.7 | G10: -3475883 | H10: -3504061.8 | I10: 0 | J10: 0 | K10: 0 | L10: 0 | M10: 0 | N10: 0 | O10: 0 | P10: 0 | Q10: 0 | R10: 0 | S10: 0 | T10: 0 | U10: 0 | V10: 0 | W10: 0 | X10: 0 | Y10: 0 | Z10: 0 | AA10: 0 | AB10: 0 | AC10: 0 | AD10: 0 | AE10: 0
B11: Variacion de IGV del periodo D+C+PM | D11: -531330.44 | E11: 476308.42 | F11: -2439521.3 | G11: -1603943.4 | H11: 3915109.6 | I11: 183377.14 | J11: 0 | K11: 0 | L11: 0 | M11: 0 | N11: 0 | O11: 0 | P11: 0 | Q11: 0 | R11: 0 | S11: 0 | T11: 0 | U11: 0 | V11: 0 | W11: 0 | X11: 0 | Y11: 0 | Z11: 0 | AA11: 0 | AB11: 0 | AC11: 0 | AD11: 0 | AE11: 0
B12: Costos de cierre de la laguna SJS | D12: 0 | E12: 0 | F12: 0 | G12: 0 | H12: 0 | I12: -6738784.8 | J12: 0 | K12: 0 | L12: 0 | M12: 0 | N12: 0 | O12: 0 | P12: 0 | Q12: 0 | R12: 0 | S12: 0 | T12: 0 | U12: 0 | V12: 0 | W12: 0 | X12: 0 | Y12: 0 | Z12: 0 | AA12: 0 | AB12: 0 | AC12: 0 | AD12: 0 | AE12: 0
B13: Costos de operacion y mantenimiento | D13: 0 | E13: 0 | F13: 0 | G13: 0 | H13: 0 | I13: -58208696 | J13: -59374669 | K13: -60155937 | L13: -61830243 | M13: -63555824 | N13: -63623040 | O13: -65421949 | P13: -67327680 | Q13: -69201749 | R13: -71174318 | S13: -73920856 | T13: -76011263 | U13: -78156659 | V13: -80365049 | W13: -82667692 | X13: -83719126 | Y13: -86133142 | Z13: -88683405 | AA13: -91310040 | AB13: -79951487 | AC13: 0 | AD13: 0 | AE13: 0
B14: Reposiciones | D14: 0 | E14: 0 | F14: 0 | G14: 0 | H14: 0 | I14: 0 | J14: 0 | K14: 0 | L14: 0 | M14: 0 | N14: 0 | O14: 0 | P14: 0 | Q14: 0 | R14: 0 | S14: -213408.11 | T14: -169841.01 | U14: -72880.522 | V14: 0 | W14: -5260935.2 | X14: 0 | Y14: -6936190.9 | Z14: 0 | AA14: 0 | AB14: 0 | AC14: 0 | AD14: 0 | AE14: 0
B15: Variacion del capital de trabajo | D15: 0 | E15: 0 | F15: 0 | G15: 0 | H15: 0 | I15: -26470658 | J15: -1567480.2 | K15: -1352228 | L15: -1297703.1 | M15: -1666968 | N15: -1906700.3 | O15: -1869933 | P15: -1975246.3 | Q15: -2098848.7 | R15: -1737874.9 | S15: -1253359.9 | T15: -2411252.8 | U15: -2555810.5 | V15: -2992504.3 | W15: -3188076.7 | X15: -3509526.1 | Y15: -1128924.2 | Z15: -452524.16 | AA15: -1837825.7 | AB15: 61273445 | AC15: 0 | AD15: 0 | AE15: 0
B16: Otros del periodo operativo | D16: 0 | E16: 0 | F16: 0 | G16: 0 | H16: -10133000 | I16: 10133000 | J16: 0 | K16: 0 | L16: 0 | M16: 0 | N16: 0 | O16: 0 | P16: 0 | Q16: 0 | R16: 0 | S16: 0 | T16: 0 | U16: 0 | V16: 0 | W16: 0 | X16: 0 | Y16: 0 | Z16: 0 | AA16: 0 | AB16: 0 | AC16: 0 | AD16: 0 | AE16: 0
B17: Participacion de trabajadores | D17: 0 | E17: 0 | F17: 0 | G17: 0 | H17: 0 | I17: 0 | J17: 0 | K17: 0 | L17: 0 | M17: -38242.508 | N17: -459321.92 | O17: -839007.28 | P17: -1259412.6 | Q17: -1731415.6 | R17: -2253969.5 | S17: -2788741.2 | T17: -3480233.1 | U17: -4166677.8 | V17: -4968322 | W17: -5578097.3 | X17: -6773243.5 | Y17: -6730955.5 | Z17: -7282774.9 | AA17: -7562785.5 | AB17: -6373568 | AC17: 0 | AD17: 0 | AE17: 0
B18: Impuesto a la Renta | D18: 0 | E18: 0 | F18: 0 | G18: 0 | H18: 0 | I18: 0 | J18: 0 | K18: 0 | L18: 0 | M18: -107174.63 | N18: -1287249.7 | O18: -2351317.9 | P18: -3529503.9 | Q18: -4852292.2 | R18: -6316749.5 | S18: -7815447.2 | T18: -17473641 | U18: -23354229 | V18: -27847445 | W18: -31265235 | X18: -37964030 | Y18: -37727005 | Z18: -40819953 | AA18: -42389413 | AB18: -35723849 | AC18: 0 | AD18: 0 | AE18: 0
B19: Desembolsos de deuda | D19: 0 | E19: 0 | F19: 33313426 | G19: 2.9776691e+08 | H19: 2.2436618e+08 | I19: 0 | J19: 0 | K19: 0 | L19: 0 | M19: 0 | N19: 0 | O19: 0 | P19: 0 | Q19: 0 | R19: 0 | S19: 0 | T19: 0 | U19: 0 | V19: 0 | W19: 0 | X19: 0 | Y19: 0 | Z19: 0 | AA19: 0 | AB19: 0 | AC19: 0 | AD19: 0 | AE19: 0
... B24: Cuenta de reserva CRSD | D24: 0 | E24: 0 | F24: 0 | G24: 0 | H24: -27778738 | I24: -2267123.1 | J24: 433708.64 | K24: -2481612.2 | L24: -2001121.3 | M24: -1981441.3 | N24: -1602242.6 | O24: -1588516.7 | P24: -1671287.3 | Q24: -1913308 | R24: -1722908.2 | S24: 1285042.1 | T24: -436001.75 | U24: -1449800.8 | V24: -151873.4 | W24: 30903685 | X24: 14423538 | Y24: 0 | Z24: 0 | AA24: 0 | AB24: 0 | AC24: 0 | AD24: 0 | AE24: 0
B26: Flujo de caja financiero | D26: =SUM(D7:D24) | E26: =SUM(E7:E24) | F26: =SUM(F7:F24) | G26: =SUM(G7:G24) | H26: =SUM(H7:H24) | I26: =SUM(I7:I24) | J26: =SUM(J7:J24) | K26: =SUM(K7:K24) | ... AE26: =SUM(AE7:AE24)
B27: Periodo de descuento | D27: 0.16666667 | E27: 1.1666667 | F27: 2.1666667 | G27: 3.1666667 | H27: 4.1666667 | I27: 5.1666667 | J27: 6.1666667 | K27: 7.1666667 | L27: 8.1666667 | M27: 9.1666667 | N27: 10.166667 | O27: 11.166667 | P27: 12.166667 | Q27: 13.166667 | R27: 14.166667 | S27: 15.166667 | T27: 16.166667 | U27: 17.166667 | V27: 18.166667 | W27: 19.166667 | X27: 20.166667 | Y27: 21.166667 | Z27: 22.166667 | AA27: 23.166667 | AB27: 24 | AC27: 24 | AD27: 24 | AE27: 24
B29: VAN del flujo de caja financiero | D29: =SUMPRODUCT(D26:AE26,1/(1+p_tir)^D27:AE27)
B31: Memoria: amortizacion del intangible (no es caja) | D31: ='Activo intangible'!D15 | E31: ='Activo intangible'!E15 | F31: ='Activo intangible'!F15 | G31: ='Activo intangible'!G15 | H31: ='Activo intangible'!H15 | I31: ='Activo intangible'!I15 | J31: ='Activo intangible'!J15 | K31: ='Activo intangible'!K15 | ... AE31: ='Activo intangible'!AE15

Sheet Reparto de la tarifa
B2: Reparto de la tarifa
B3: De lo que recauda la tarifa, cuanto paga la operacion y cuanto repaga la inversion. Las dos partes suman el ingreso.
B5: Ano | D5: 2025 | E5: 2026 | F5: 2027 | G5: 2028 | H5: 2029 | I5: 2030 | J5: 2031 | K5: 2032 | L5: 2033 | M5: 2034 | N5: 2035 | O5: 2036 | P5: 2037 | Q5: 2038 | R5: 2039 | S5: 2040 | T5: 2041 | U5: 2042 | V5: 2043 | W5: 2044 | X5: 2045 | Y5: 2046 | Z5: 2047 | AA5: 2048 | AB5: 2049 | AC5: 2050 | AD5: 2051 | AE5: 2052
B7: Ingreso tarifario | D7: =Flujo!D7 | E7: =Flujo!E7 | F7: =Flujo!F7 | G7: =Flujo!G7 | H7: =Flujo!H7 | I7: =Flujo!I7 | J7: =Flujo!J7 | K7: =Flujo!K7 | ... AE7: =Flujo!AE7
B8: Costo de operacion y mantenimiento | D8: =-Flujo!D13 | E8: =-Flujo!E13 | F8: =-Flujo!F13 | G8: =-Flujo!G13 | H8: =-Flujo!H13 | I8: =-Flujo!I13 | J8: =-Flujo!J13 | K8: =-Flujo!K13 | ... AE8: =-Flujo!AE13
B9: Margen del operador | D9: =p_margen_om*D8 | E9: =p_margen_om*E8 | F9: =p_margen_om*F8 | G9: =p_margen_om*G8 | H9: =p_margen_om*H8 | I9: =p_margen_om*I8 | J9: =p_margen_om*J8 | K9: =p_margen_om*K8 | ... AE9: =p_margen_om*AE8
B10: Operacion y mantenimiento | D10: =D8+D9 | E10: =E8+E9 | F10: =F8+F9 | G10: =G8+G9 | H10: =H8+H9 | I10: =I8+I9 | J10: =J8+J9 | K10: =K8+K9 | ... AE10: =AE8+AE9
B11: Disponible para repagar la inversion | D11: =D7-D10 | E11: =E7-E10 | F11: =F7-F10 | G11: =G7-G10 | H11: =H7-H10 | I11: =I7-I10 | J11: =J7-J10 | K11: =K7-K10 | ... AE11: =AE7-AE10
B13: VAN del ingreso tarifario | D13: =SUMPRODUCT($D$7:$AE$7,1/(1+p_tir)^Flujo!$D$27:$AE$27)
B14: VAN del costo de O&M, sin margen | D14: =SUMPRODUCT($D$8:$AE$8,1/(1+p_tir)^Flujo!$D$27:$AE$27)
B15: VAN de la operacion, con margen | D15: =SUMPRODUCT($D$10:$AE$10,1/(1+p_tir)^Flujo!$D$27:$AE$27)
B16: VAN para la inversion | D16: =SUMPRODUCT($D$11:$AE$11,1/(1+p_tir)^Flujo!$D$27:$AE$27)
B17: Participacion de la operacion | D17: =$D$15/$D$13
B18: Participacion de la inversion | D18: =$D$16/$D$13
B19: Las dos partes menos el total, debe ser cero | D19: =$D$15+$D$16-$D$13
B20: Check del reparto | D20: =IF(ROUND($D$19,2)=0,"OK","ERROR")
