Workbook
Name p_ke: Inputs!$D$6
Name p_kd: Inputs!$D$7
Name p_wacc: Inputs!$D$8
Name p_tir: Inputs!$D$9
Name p_rcsd: Inputs!$D$10
Name p_crsd: Inputs!$D$11
Name p_ir: Inputs!$D$12
Name p_pt: Inputs!$D$13
Name p_arr: Inputs!$D$14
Name p_ipm: Inputs!$D$15
Name p_fx: Inputs!$D$16
Name p_cuotas: Inputs!$D$17
Name p_ppdi: Inputs!$D$18
Name p_ref: Inputs!$D$19

Sheet Resumen
B2: Resumen del modelo
B3: San Martin paga el PPDI por hitos funcionales y cierra todo el PPDMO a la vez.
B6: PPD Inversiones, anual | D6: =p_ppdi
B7: PPD Inversiones, cuota trimestral | D7: =p_ppdi/4
B8: PPD MO, referencia mensual | D8: =p_ref
B9: PPD MO fijo, anual | D9: =Hitos!E10*12
B10: Precio unitario, S/ miles por kg DBO | D10: 0.0021536821
B11: VAN financiero, debe ser cero | D11: =Flujo!$D$31
B12: Ke | D12: =p_ke
B13: Kd | D13: =p_kd
B14: WACC | D14: =p_wacc

Sheet Inputs
B2: Parametros del modelo
B3: Las celdas en ambar son de entrada. Las dos ultimas las resuelve el cierre.
B6: Ke, costo del patrimonio | D6: 0.12622649 | E6: CAPM en USD + riesgo pais + devaluacion
B7: Kd, costo de la deuda | D7: 0.10092957 | E7: soberano a vida media + spread
B8: WACC | D8: 0.097303479 | E8: despues de impuestos
B9: TIR objetivo del cierre | D9: 0.1262 | E9: Ke redondeado a 4 decimales, Control!M12
B10: Cobertura minima, RCSD | D10: 1.25 | E10: dimensiona la amortizacion
B11: Cuenta de reserva, CRSD | D11: 0.5 | E11: del servicio del ano siguiente
B12: Impuesto a la Renta | D12: 0.295
B13: Participacion de trabajadores | D13: 0.05
B14: Arrastre de perdidas | D14: 0.5 | E14: sistema B
B15: IPM, reajuste | D15: 0.0267 | E15: anual
B16: Tipo de cambio | D16: 0 | E16: solo entra por los reembolsos en dolares
B17: Cuotas del PPDI | D17: 60 | E17: trimestrales
B18: PPDI anual | D18: 32104.865 | E18: S/ - LA CIERRA Solver
B19: PPDMO referencia mensual | D19: 1474.958 | E19: S/ - LA CIERRA Solver

Sheet Hitos
B2: Hitos funcionales
B3: El PPDI se reparte por la participacion de cada hito en el CAPEX, y el PPDMO fijo por el VAN de su operacion y mantenimiento.
B5: Hito | C5: % del CAPEX | D5: Cuota trimestral del PPDI | E5: PPDMO fijo mensual
B6: Hito 1 | C6: 0.45 | D6: =p_ppdi*C6/4 | E6: 405.93536
B7: Hito 2 | C7: 0.2 | D7: =p_ppdi*C7/4 | E7: 180.41572
B8: Hito 3 | C8: 0.2 | D8: =p_ppdi*C8/4 | E8: 180.41572
B9: Hito 4 | C9: 0.15 | D9: =p_ppdi*C9/4 | E9: 135.31179
B10: Total | C10: =SUM(C6:C9) | D10: =SUM(D6:D9) | E10: =SUM(E6:E9)

Sheet Flujo
B2: Flujo de caja anual
B3: El VAN de la ultima fila es la celda que Solver lleva a cero.
B5: Ano | D5: 2027 | E5: 2028 | F5: 2029 | G5: 2030 | H5: 2031 | I5: 2032 | J5: 2033 | K5: 2034 | L5: 2035 | M5: 2036 | N5: 2037 | O5: 2038 | P5: 2039 | Q5: 2040 | R5: 2041 | S5: 2042 | T5: 2043 | U5: 2044 | V5: 2045 | W5: 2046 | X5: 2047 | Y5: 2048 | Z5: 2049 | AA5: 2050 | AB5: 2051 | AC5: 2052
B7: PPD Inversiones | D7: =p_ppdi*0.0 | E7: =p_ppdi*0.0 | F7: =p_ppdi*0.0 | G7: =p_ppdi*0.0 | H7: =p_ppdi*0.7500000000000001 | I7: =p_ppdi*1.0 | J7: =p_ppdi*1.0 | K7: =p_ppdi*1.0 | L7: =p_ppdi*1.0 | M7: =p_ppdi*1.0 | N7: =p_ppdi*1.0 | O7: =p_ppdi*1.0 | P7: =p_ppdi*1.0 | ... V7: =p_ppdi*1.0 | W7: =p_ppdi*0.25 | X7: =p_ppdi*0.0 | Y7: =p_ppdi*0.0 | Z7: =p_ppdi*0.0 | AA7: =p_ppdi*0.0 | AB7: =p_ppdi*0.0 | AC7: =p_ppdi*0.0
B8: PPD MO fijo | D8: =p_ref*0.0 | E8: =p_ref*0.0 | F8: =p_ref*0.0 | G8: =p_ref*0.0 | H8: =p_ref*6.090212837260705 | I8: =p_ref*8.306416941099005 | J8: =p_ref*8.54013227602211 | K8: =p_ref*8.781046097081305 | L8: =p_ref*9.006113463103452 | M8: =p_ref*9.236734121743755 | N8: =p_ref*9.473024276261844 | O8: =p_ref*9.715112361839417 | P8: =p_ref*9.963139045580236 | Q8: =p_ref*10.243476351459506 | R8: =p_ref*10.532424930473537 | S8: =p_ref*10.802426262206684 | T8: =p_ref*11.079063411660862 | U8: =p_ref*11.362477045939835 | V8: =p_ref*11.652832295991507 | W8: =p_ref*11.950306524685834 | X8: =p_ref*12.286549830369681 | Y8: =p_ref*12.633153574043789 | Z8: =p_ref*12.956999826713318 | AA8: =p_ref*13.288796828726023 | AB8: =p_ref*3.364047670551248 | AC8: =p_ref*0.0
B9: PPD MO variable | D9: =p_ref*0.0 | E9: =p_ref*0.0 | F9: =p_ref*0.0 | G9: =p_ref*0.0 | H9: =p_ref*3.867687162739295 | I9: =p_ref*5.3384245356078095 | J9: =p_ref*5.554493860225613 | K9: =p_ref*5.779718186657692 | L9: =p_ref*5.998992690016349 | M9: =p_ref*6.226440951628152 | N9: =p_ref*6.462351759637901 | O9: =p_ref*6.707030542233988 | P9: =p_ref*6.96080007014243 | Q9: =p_ref*7.242539130136988 | R9: =p_ref*7.5361991419559455 | S9: =p_ref*7.82214417842708 | T9: =p_ref*8.118729405374099 | U9: =p_ref*8.426331681668218 | V9: =p_ref*8.745356942381678 | W9: =p_ref*9.076232266655323 | X9: =p_ref*9.443587638805932 | Y9: =p_ref*9.826511275583695 | Z9: =p_ref*10.199351207002673 | AA9: =p_ref*10.586057967183692 | AB9: =p_ref*2.7120098345289936 | AC9: =p_ref*0.0
B10: Pago por Obras | D10: 0 | E10: 0 | F10: 0 | G10: 0 | H10: 0 | I10: 0 | J10: 0 | K10: 0 | L10: 0 | M10: 0 | N10: 0 | O10: 0 | P10: 0 | Q10: 0 | R10: 0 | S10: 0 | T10: 0 | U10: 0 | V10: 0 | W10: 0 | X10: 0 | Y10: 0 | Z10: 0 | AA10: 0 | AB10: 0 | AC10: 0
B11: CAPEX | D11: -4767.216 | E11: -34643.068 | F11: -82277.849 | G11: -68292.304 | H11: -10758.632 | I11: 0 | J11: 0 | K11: 0 | L11: 0 | M11: 0 | N11: 0 | O11: 0 | P11: 0 | Q11: 0 | R11: 0 | S11: 0 | T11: 0 | U11: 0 | V11: 0 | W11: 0 | X11: 0 | Y11: 0 | Z11: 0 | AA11: 0 | AB11: 0 | AC11: 0
B12: Otros costos del periodo D+C+PM | D12: -6232.2761 | E12: -773.71694 | F12: 0 | G12: 0 | H12: 0 | I12: 0 | J12: 0 | K12: 0 | L12: 0 | M12: 0 | N12: 0 | O12: 0 | P12: 0 | Q12: 0 | R12: 0 | S12: 0 | T12: 0 | U12: 0 | V12: 0 | W12: 0 | X12: 0 | Y12: 0 | Z12: 0 | AA12: 0 | AB12: 0 | AC12: 0
B13: Variacion de IGV del periodo D+C+PM | D13: 0 | E13: 0 | F13: 0 | G13: 0 | H13: 0 | I13: 0 | J13: 0 | K13: 0 | L13: 0 | M13: 0 | N13: 0 | O13: 0 | P13: 0 | Q13: 0 | R13: 0 | S13: 0 | T13: 0 | U13: 0 | V13: 0 | W13: 0 | X13: 0 | Y13: 0 | Z13: 0 | AA13: 0 | AB13: 0 | AC13: 0
B14: Costos de cierre de la laguna SJS | D14: 0 | E14: 0 | F14: 0 | G14: 0 | H14: 0 | I14: 0 | J14: 0 | K14: 0 | L14: 0 | M14: 0 | N14: 0 | O14: 0 | P14: 0 | Q14: 0 | R14: 0 | S14: 0 | T14: 0 | U14: 0 | V14: 0 | W14: 0 | X14: 0 | Y14: 0 | Z14: 0 | AA14: 0 | AB14: 0 | AC14: 0
B15: Costos de operacion y mantenimiento | D15: 0 | E15: 0 | F15: 0 | G15: 0 | H15: -7401.4395 | I15: -10136.979 | J15: -10447.214 | K15: -10767.276 | L15: -11097.489 | M15: -11438.186 | N15: -11789.711 | O15: -12152.422 | P15: -12526.687 | Q15: -12912.889 | R15: -13311.421 | S15: -13722.691 | T15: -14147.122 | U15: -14585.15 | V15: -15037.225 | W15: -15503.816 | X15: -15985.405 | Y15: -16482.492 | Z15: -16995.593 | AA15: -17525.244 | AB15: -4473.4544 | AC15: 0
B16: Reposiciones | D16: 0 | E16: 0 | F16: 0 | G16: 0 | H16: 0 | I16: 0 | J16: 0 | K16: 0 | L16: 0 | M16: 0 | N16: 0 | O16: 0 | P16: 0 | Q16: -5121.2104 | R16: 0 | S16: 0 | T16: 0 | U16: 0 | V16: -5842.3885 | W16: 0 | X16: 0 | Y16: 0 | Z16: 0 | AA16: -6665.1241 | AB16: 0 | AC16: 0
B17: Variacion del capital de trabajo | D17: 0 | E17: 0 | F17: 0 | G17: 0 | H17: -12404.67 | I17: 153.2007 | J17: -101.39132 | K17: -158.6031 | L17: -164.54281 | M17: -170.73842 | N17: -177.14916 | O17: -183.82475 | P17: -63.020593 | Q17: -127.18746 | R17: -198.23649 | S17: -205.76112 | T17: -213.52563 | U17: -221.58169 | V17: -229.98227 | W17: 7946.1869 | X17: -159.81581 | Y17: -248.23793 | Z17: -257.69767 | AA17: -267.48215 | AB17: 7454.0608 | AC17: 0
B18: Otros del periodo operativo | D18: 0 | E18: 0 | F18: 0 | G18: -1200 | H18: 1200 | I18: 0 | J18: 0 | K18: 0 | L18: 0 | M18: 0 | N18: 0 | O18: 0 | P18: 0 | Q18: 0 | R18: 0 | S18: 0 | T18: 0 | U18: 0 | V18: 0 | W18: 0 | X18: 0 | Y18: 0 | Z18: 0 | AA18: 0 | AB18: 0 | AC18: 0
B19: Participacion de trabajadores | D19: 0 | E19: 0 | F19: 0 | G19: 0 | H19: -462.08499 | I19: -567.18513 | J19: -664.74512 | K19: -765.52661 | L19: -869.39017 | M19: -981.24874 | N19: -1101.709 | O19: -1231.425 | P19: -1371.2328 | Q19: -1243.802 | R19: -1551.2373 | S19: -1655.3648 | T19: -1676.4172 | U19: -1698.102 | V19: -1428.3193 | W19: -539.51621 | X19: -803.28175 | Y19: -832.22853 | Z19: -857.95261 | AA19: -551.20204 | AB19: -224.42377 | AC19: 0
B20: Impuesto a la Renta | D20: 0 | E20: 0 | F20: 0 | G20: 0 | H20: -1294.9932 | I20: -1589.5363 | J20: -3129.7047 | K20: -4290.7767 | L20: -4872.9319 | M20: -5499.8992 | N20: -6175.0791 | O20: -6902.1374 | P20: -7685.7598 | Q20: -6971.5104 | R20: -8694.685 | S20: -9278.3196 | T20: -9396.3184 | U20: -9517.8617 | V20: -8005.7298 | W20: -3023.9884 | X20: -4502.3942 | Y20: -4664.6409 | Z20: -4808.8244 | AA20: -3089.4875 | AB20: -1257.8952 | AC20: 0
B21: Desembolsos de deuda | D21: 0 | E21: 0 | F21: 64382.861 | G21: 79338.187 | H21: 22016.147 | I21: 0 | J21: 0 | K21: 0 | L21: 0 | M21: 0 | N21: 0 | O21: 0 | P21: 0 | Q21: 0 | R21: 0 | S21: 0 | T21: 0 | U21: 0 | V21: 0 | W21: 0 | X21: 0 | Y21: 0 | Z21: 0 | AA21: 0 | AB21: 0 | AC21: 0
... B26: Cuenta de reserva CRSD | D26: 0 | E26: 0 | F26: 0 | G26: 0 | H26: -16035.974 | I26: 615.65669 | J26: 380.6374 | K26: 146.71426 | L26: 164.03425 | M26: 182.83992 | N26: 203.28008 | O26: 174.70526 | P26: 10141.528 | Q26: 4026.5774 | R26: 0 | S26: 0 | T26: 0 | U26: 0 | V26: 0 | W26: 0 | X26: 0 | Y26: 0 | Z26: 0 | AA26: 0 | AB26: 0 | AC26: 0
B28: Flujo de caja financiero | D28: =SUM(D7:D26) | E28: =SUM(E7:E26) | F28: =SUM(F7:F26) | G28: =SUM(G7:G26) | H28: =SUM(H7:H26) | I28: =SUM(I7:I26) | J28: =SUM(J7:J26) | K28: =SUM(K7:K26) | ... AC28: =SUM(AC7:AC26)
B29: Periodo de descuento | D29: 0.91666667 | E29: 1.9166667 | F29: 2.9166667 | G29: 3.9166667 | H29: 4.9166667 | I29: 5.9166667 | J29: 6.9166667 | K29: 7.9166667 | L29: 8.9166667 | M29: 9.9166667 | N29: 10.916667 | O29: 11.916667 | P29: 12.916667 | Q29: 13.916667 | R29: 14.916667 | S29: 15.916667 | T29: 16.916667 | U29: 17.916667 | V29: 18.916667 | W29: 19.916667 | X29: 20.916667 | Y29: 21.916667 | Z29: 22.916667 | AA29: 23.916667 | AB29: 24.166667 | AC29: 24.166667
B31: VAN del flujo de caja financiero | D31: =SUMPRODUCT(D28:AC28,1/(1+p_tir)^D29:AC29)

Sheet Activo financiero
B2: Activo financiero del PPDI
B3: CINIIF 12 p.16: el cobro es incondicional, asi que la obra es cuenta por cobrar. Se reconoce por el servicio de construccion, no por la necesidad de financiamiento.
B5: Ano | D5: 2027 | E5: 2028 | F5: 2029 | G5: 2030 | H5: 2031 | I5: 2032 | J5: 2033 | K5: 2034 | L5: 2035 | M5: 2036 | N5: 2037 | O5: 2038 | P5: 2039 | Q5: 2040 | R5: 2041 | S5: 2042 | T5: 2043 | U5: 2044 | V5: 2045 | W5: 2046 | X5: 2047 | Y5: 2048 | Z5: 2049 | AA5: 2050 | AB5: 2051 | AC5: 2052
B7: Servicio de construccion (CAPEX) | D7: =-Flujo!D11 | E7: =-Flujo!E11 | F7: =-Flujo!F11 | G7: =-Flujo!G11 | H7: =-Flujo!H11 | I7: =-Flujo!I11 | J7: =-Flujo!J11 | K7: =-Flujo!K11 | ... AC7: =-Flujo!AC11
B8: Otros costos del periodo D+C+PM | D8: =-Flujo!D12 | E8: =-Flujo!E12 | F8: =-Flujo!F12 | G8: =-Flujo!G12 | H8: =-Flujo!H12 | I8: =-Flujo!I12 | J8: =-Flujo!J12 | K8: =-Flujo!K12 | ... AC8: =-Flujo!AC12
B9: PPD Inversiones cobrado | D9: =-Flujo!D7 | E9: =-Flujo!E7 | F9: =-Flujo!F7 | G9: =-Flujo!G7 | H9: =-Flujo!H7 | I9: =-Flujo!I7 | J9: =-Flujo!J7 | K9: =-Flujo!K7 | ... AC9: =-Flujo!AC7
B10: Total del periodo | D10: =SUM(D7:D9) | E10: =SUM(E7:E9) | F10: =SUM(F7:F9) | G10: =SUM(G7:G9) | H10: =SUM(H7:H9) | I10: =SUM(I7:I9) | J10: =SUM(J7:J9) | K10: =SUM(K7:K9) | ... AC10: =SUM(AC7:AC9)
B12: Tasa implicita anual | D12: =IFERROR(IRR($D$10:$AC$10),0)
B14: Saldo inicial del activo | D14: 0 | E14: =D16 | F14: =E16 | G14: =F16 | H14: =G16 | I14: =H16 | J14: =I16 | K14: =J16 | L14: =K16 | ... AC14: =AB16
B15: Ingreso financiero devengado | D15: =D14*$D$12 | E15: =E14*$D$12 | F15: =F14*$D$12 | G15: =G14*$D$12 | H15: =H14*$D$12 | I15: =I14*$D$12 | J15: =J14*$D$12 | K15: =K14*$D$12 | ... AC15: =AC14*$D$12
B16: Saldo final del activo | D16: =D14+D10+D15 | E16: =E14+E10+E15 | F16: =F14+F10+F15 | G16: =G14+G10+G15 | H16: =H14+H10+H15 | I16: =I14+I10+I15 | J16: =J14+J10+J15 | K16: =K14+K10+K15 | ... AC16: =AC14+AC10+AC15
B18: Saldo maximo del activo | D18: =MAX($D$16:$AC$16)
B19: Ingreso financiero acumulado | D19: =SUM($D$15:$AC$15)
B20: Saldo final, debe ser cero | D20: =AC16
B21: Check AF | D21: =IF(ROUND(AC16,2)=0,"OK","ERROR")
B22: Anos con saldo negativo | D22: =SUMPRODUCT(--(ROUND($D$16:$AC$16,2)<0))
