Workbook
Name p_costo_obra: Inputs!$D$6
Name p_tamano_deuda: Inputs!$D$7
Name p_kd: Inputs!$D$8
Name p_spread: Inputs!$D$9
Name p_ke: Inputs!$D$10
Name p_wacc: Inputs!$D$11
Name p_pagos: Inputs!$D$12
Name p_ipm: Inputs!$D$13
Name p_gatillo: Inputs!$D$14
Name p_ipc: Inputs!$D$15
Name p_ir: Inputs!$D$16
Name p_part: Inputs!$D$17
Name p_superv: Inputs!$D$18
Name p_igv: Inputs!$D$19
Name p_tarifa_usuario: Inputs!$D$20
Name p_margen_om: Inputs!$D$21

Sheet Resumen
B2: Resumen del modelo, APP autofinanciada
B3: S/ miles sin IGV. No hay PPDI ni PPDMO: el proyecto se paga con la tarifa al usuario.
B6: Tarifa al usuario, S/ por kg DBO5 | D6: =p_tarifa_usuario
B7: Ingreso tarifario, primer mes de operacion anualizado | D7: =SUMPRODUCT(Ingresos!$D$15:$LI$15,Ingresos!$D$14:$LI$14)*12
B8: Ingreso tarifario, promedio mensual de la operacion | D8: =SUMPRODUCT(Ingresos!$D$7:$LI$7,Ingresos!$D$14:$LI$14)/SUM(Ingresos!$D$7:$LI$7)
B9: Tarifa que paga la operacion con su margen, S/ por kg DBO5 | D9: =p_tarifa_usuario*'Reparto de la tarifa'!$D$26
B10: Tarifa que repaga la inversion, S/ por kg DBO5 | D10: =p_tarifa_usuario*'Reparto de la tarifa'!$D$27
B11: VAN del ingreso tarifario | D11: ='Reparto de la tarifa'!$D$22
B12: del que va a la operacion | D12: ='Reparto de la tarifa'!$D$24
B13: del que repaga la inversion | D13: ='Reparto de la tarifa'!$D$25
B14: Activo intangible al termino de obra | D14: ='Activo intangible'!$D$8
B15: Amortizacion lineal mensual | D15: ='Activo intangible'!$D$9
B16: Meses de operacion | D16: ='Activo intangible'!$D$7
B17: Saldo final del intangible, debe ser cero | D17: ='Activo intangible'!$LI$18
B18: VAN financiero, debe ser cero | D18: =Flujo!$D$29
B19: WACC | D19: =p_wacc
B20: Kd | D20: =p_kd
B21: Ke | D21: =p_ke

Sheet Inputs
B2: Parametros del modelo
B3: Las celdas en ambar son de entrada. Las dos ultimas las resuelve el cierre.
B6: Costo de obra a financiar | D6: 261144.81 | E6: S/ miles
B7: Tamano de deuda | D7: 0.8 | E7: % del costo de obra
B8: Kd, costo de la deuda | D8: 0.10092957 | E8: soberano a vida media + spread
B9: Spread de deuda | D9: 0.035 | E9: sondeo de mercado
B10: Ke, costo del patrimonio | D10: 0.12622649 | E10: CAPM en USD + riesgo pais + devaluacion
B11: WACC | D11: 0.097303479 | E11: despues de impuestos
B12: Numero de pagos de la deuda | D12: 144 | E12: meses
B13: IPM, reajuste de ingresos | D13: 0.0267 | E13: anual
B14: Gatillo del reajuste | D14: 0.03 | E14: acumulado que dispara el ajuste
B15: IPC, reajuste de costos | D15: 0.02 | E15: anual, sin gatillo
B16: Tasa de Impuesto a la Renta | D16: 0.295
B17: Participacion de trabajadores | D17: 0.05
B18: Supervision del regulador | D18: 0.01 | E18: % del ingreso tarifario
B19: IGV | D19: 0.18 | E19: lo paga el usuario sobre la tarifa
B20: Tarifa al usuario | D20: 9.4608605 | E20: S/ por kg DBO5 - LA CIERRA Buscar Objetivo
B21: Margen del operador | D21: 0.15 | E21: sobre todo el costo de O&M; aca no hay pata fija y variable

Sheet Deuda
B2: Deuda financiera
B3: Cuota constante: el servicio sale de PMT y la amortizacion es el residuo.
B6: Mes | D6: 2026-10-31 | E6: 2026-11-30 | F6: 2026-12-31 | G6: 2027-01-31 | H6: 2027-02-28 | I6: 2027-03-31 | J6: 2027-04-30 | K6: 2027-05-31 | L6: 2027-06-30 | M6: 2027-07-31 | N6: 2027-08-31 | O6: 2027-09-30 | P6: 2027-10-31 | Q6: 2027-11-30 | R6: 2027-12-31 | S6: 2028-01-31 | T6: 2028-02-29 | U6: 2028-03-31 | V6: 2028-04-30 | W6: 2028-05-31 | X6: 2028-06-30 | Y6: 2028-07-31 | Z6: 2028-08-31 | AA6: 2028-09-30 | AB6: 2028-10-31 | AC6: 2028-11-30 | AD6: 2028-12-31 | AE6: 2029-01-31 | AF6: 2029-02-28 | AG6: 2029-03-31 | AH6: 2029-04-30 | AI6: 2029-05-31 | AJ6: 2029-06-30 | AK6: 2029-07-31 | AL6: 2029-08-31 | AM6: 2029-09-30 | AN6: 2029-10-31 | AO6: 2029-11-30 | AP6: 2029-12-31 | AQ6: 2030-01-31 | AR6: 2030-02-28 | AS6: 2030-03-31 | AT6: 2030-04-30 | AU6: 2030-05-31 | AV6: 2030-06-30 | AW6: 2030-07-31 | AX6: 2030-08-31 | AY6: 2030-09-30 | AZ6: 2030-10-31 | BA6: 2030-11-30 | BB6: 2030-12-31 | BC6: 2031-01-31 | BD6: 2031-02-28 | BE6: 2031-03-31 | BF6: 2031-04-30 | BG6: 2031-05-31 | BH6: 2031-06-30 | BI6: 2031-07-31 | BJ6: 2031-08-31 | BK6: 2031-09-30 | BL6: 2031-10-31 | BM6: 2031-11-30 | BN6: 2031-12-31 | BO6: 2032-01-31 | BP6: 2032-02-29 | BQ6: 2032-03-31 | BR6: 2032-04-30 | BS6: 2032-05-31 | BT6: 2032-06-30 | BU6: 2032-07-31 | BV6: 2032-08-31 | BW6: 2032-09-30 | BX6: 2032-10-31 | BY6: 2032-11-30 | BZ6: 2032-12-31 | CA6: 2033-01-31 | CB6: 2033-02-28 | CC6: 2033-03-31 | CD6: 2033-04-30 | CE6: 2033-05-31 | CF6: 2033-06-30 | CG6: 2033-07-31 | CH6: 2033-08-31 | CI6: 2033-09-30 | CJ6: 2033-10-31 | CK6: 2033-11-30 | CL6: 2033-12-31 | CM6: 2034-01-31 | CN6: 2034-02-28 | CO6: 2034-03-31 | CP6: 2034-04-30 | CQ6: 2034-05-31 | CR6: 2034-06-30 | CS6: 2034-07-31 | CT6: 2034-08-31 | CU6: 2034-09-30 | CV6: 2034-10-31 | CW6: 2034-11-30 | CX6: 2034-12-31 | CY6: 2035-01-31 | CZ6: 2035-02-28 | DA6: 2035-03-31 | DB6: 2035-04-30 | DC6: 2035-05-31 | DD6: 2035-06-30 | DE6: 2035-07-31 | DF6: 2035-08-31 | DG6: 2035-09-30 | DH6: 2035-10-31 | DI6: 2035-11-30 | DJ6: 2035-12-31 | DK6: 2036-01-31 | DL6: 2036-02-29 | DM6: 2036-03-31 | DN6: 2036-04-30 | DO6: 2036-05-31 | DP6: 2036-06-30 | DQ6: 2036-07-31 | DR6: 2036-08-31 | DS6: 2036-09-30 | DT6: 2036-10-31 | DU6: 2036-11-30 | DV6: 2036-12-31 | DW6: 2037-01-31 | DX6: 2037-02-28 | DY6: 2037-03-31 | DZ6: 2037-04-30 | EA6: 2037-05-31 | EB6: 2037-06-30 | EC6: 2037-07-31 | ED6: 2037-08-31 | EE6: 2037-09-30 | EF6: 2037-10-31 | EG6: 2037-11-30 | EH6: 2037-12-31 | EI6: 2038-01-31 | EJ6: 2038-02-28 | EK6: 2038-03-31 | EL6: 2038-04-30 | EM6: 2038-05-31 | EN6: 2038-06-30 | EO6: 2038-07-31 | EP6: 2038-08-31 | EQ6: 2038-09-30 | ER6: 2038-10-31 | ES6: 2038-11-30 | ET6: 2038-12-31 | EU6: 2039-01-31 | EV6: 2039-02-28 | EW6: 2039-03-31 | EX6: 2039-04-30 | EY6: 2039-05-31 | EZ6: 2039-06-30 | FA6: 2039-07-31 | FB6: 2039-08-31 | FC6: 2039-09-30 | FD6: 2039-10-31 | FE6: 2039-11-30 | FF6: 2039-12-31 | FG6: 2040-01-31 | FH6: 2040-02-29 | FI6: 2040-03-31 | FJ6: 2040-04-30 | FK6: 2040-05-31 | FL6: 2040-06-30 | FM6: 2040-07-31 | FN6: 2040-08-31 | FO6: 2040-09-30 | FP6: 2040-10-31 | FQ6: 2040-11-30 | FR6: 2040-12-31 | FS6: 2041-01-31 | FT6: 2041-02-28 | FU6: 2041-03-31 | FV6: 2041-04-30 | FW6: 2041-05-31 | FX6: 2041-06-30 | FY6: 2041-07-31 | FZ6: 2041-08-31 | GA6: 2041-09-30 | GB6: 2041-10-31 | GC6: 2041-11-30 | GD6: 2041-12-31 | GE6: 2042-01-31 | GF6: 2042-02-28 | GG6: 2042-03-31 | GH6: 2042-04-30 | GI6: 2042-05-31 | GJ6: 2042-06-30 | GK6: 2042-07-31 | GL6: 2042-08-31 | GM6: 2042-09-30 | GN6: 2042-10-31 | GO6: 2042-11-30 | GP6: 2042-12-31 | GQ6: 2043-01-31 | GR6: 2043-02-28 | GS6: 2043-03-31 | GT6: 2043-04-30 | GU6: 2043-05-31 | GV6: 2043-06-30 | GW6: 2043-07-31 | GX6: 2043-08-31 | GY6: 2043-09-30 | GZ6: 2043-10-31 | HA6: 2043-11-30 | HB6: 2043-12-31 | HC6: 2044-01-31 | HD6: 2044-02-29 | HE6: 2044-03-31 | HF6: 2044-04-30 | HG6: 2044-05-31 | HH6: 2044-06-30 | HI6: 2044-07-31 | HJ6: 2044-08-31 | HK6: 2044-09-30 | HL6: 2044-10-31 | HM6: 2044-11-30 | HN6: 2044-12-31 | HO6: 2045-01-31 | HP6: 2045-02-28 | HQ6: 2045-03-31 | HR6: 2045-04-30 | HS6: 2045-05-31 | HT6: 2045-06-30 | HU6: 2045-07-31 | HV6: 2045-08-31 | HW6: 2045-09-30 | HX6: 2045-10-31 | HY6: 2045-11-30 | HZ6: 2045-12-31 | IA6: 2046-01-31 | IB6: 2046-02-28 | IC6: 2046-03-31 | ID6: 2046-04-30 | IE6: 2046-05-31 | IF6: 2046-06-30 | IG6: 2046-07-31 | IH6: 2046-08-31 | II6: 2046-09-30 | IJ6: 2046-10-31 | IK6: 2046-11-30 | IL6: 2046-12-31 | IM6: 2047-01-31 | IN6: 2047-02-28 | IO6: 2047-03-31 | IP6: 2047-04-30 | IQ6: 2047-05-31 | IR6: 2047-06-30 | IS6: 2047-07-31 | IT6: 2047-08-31 | IU6: 2047-09-30 | IV6: 2047-10-31 | IW6: 2047-11-30 | IX6: 2047-12-31 | IY6: 2048-01-31 | IZ6: 2048-02-29 | JA6: 2048-03-31 | JB6: 2048-04-30 | JC6: 2048-05-31 | JD6: 2048-06-30 | JE6: 2048-07-31 | JF6: 2048-08-31 | JG6: 2048-09-30 | JH6: 2048-10-31 | JI6: 2048-11-30 | JJ6: 2048-12-31 | JK6: 2049-01-31 | JL6: 2049-02-28 | JM6: 2049-03-31 | JN6: 2049-04-30 | JO6: 2049-05-31 | JP6: 2049-06-30 | JQ6: 2049-07-31 | JR6: 2049-08-31 | JS6: 2049-09-30 | JT6: 2049-10-31 | JU6: 2049-11-30 | JV6: 2049-12-31 | JW6: 2050-01-31 | JX6: 2050-02-28 | JY6: 2050-03-31 | JZ6: 2050-04-30 | KA6: 2050-05-31 | KB6: 2050-06-30 | KC6: 2050-07-31 | KD6: 2050-08-31 | KE6: 2050-09-30 | KF6: 2050-10-31 | KG6: 2050-11-30 | KH6: 2050-12-31 | KI6: 2051-01-31 | KJ6: 2051-02-28 | KK6: 2051-03-31 | KL6: 2051-04-30 | KM6: 2051-05-31 | KN6: 2051-06-30 | KO6: 2051-07-31 | KP6: 2051-08-31 | KQ6: 2051-09-30 | KR6: 2051-10-31 | KS6: 2051-11-30 | KT6: 2051-12-31 | KU6: 2052-01-31 | KV6: 2052-02-29 | KW6: 2052-03-31 | KX6: 2052-04-30 | KY6: 2052-05-31 | KZ6: 2052-06-30 | LA6: 2052-07-31 | LB6: 2052-08-31 | LC6: 2052-09-30 | LD6: 2052-10-31 | LE6: 2052-11-30 | LF6: 2052-12-31 | LG6: 2053-01-31 | LH6: 2053-02-28 | LI6: 2053-03-31
B7: Flag obra y puesta en marcha | D7: 0 | E7: 0 | F7: 0 | G7: 0 | H7: 0 | I7: 0 | J7: 0 | K7: 0 | L7: 0 | M7: 0 | N7: 0 | O7: 0 | P7: 0 | Q7: 0 | R7: 0 | S7: 0 | T7: 0 | U7: 0 | V7: 0 | W7: 0 | X7: 0 | Y7: 1 | Z7: 1 | AA7: 1 | AB7: 1 | AC7: 1 | AD7: 1 | AE7: 1 | AF7: 1 | AG7: 1 | AH7: 1 | AI7: 1 | AJ7: 1 | AK7: 1 | AL7: 1 | AM7: 1 | AN7: 1 | AO7: 1 | AP7: 1 | AQ7: 1 | AR7: 1 | AS7: 1 | AT7: 1 | AU7: 1 | AV7: 1 | AW7: 1 | AX7: 1 | AY7: 1 | AZ7: 0 | BA7: 0 | BB7: 0 | BC7: 0 | BD7: 0 | BE7: 0 | BF7: 0 | BG7: 0 | BH7: 0 | BI7: 0 | BJ7: 0 | BK7: 0 | BL7: 0 | BM7: 0 | BN7: 0 | BO7: 0 | BP7: 0 | BQ7: 0 | BR7: 0 | BS7: 0 | BT7: 0 | BU7: 0 | BV7: 0 | BW7: 0 | BX7: 0 | BY7: 0 | BZ7: 0 | CA7: 0 | CB7: 0 | CC7: 0 | CD7: 0 | CE7: 0 | CF7: 0 | CG7: 0 | CH7: 0 | CI7: 0 | CJ7: 0 | CK7: 0 | CL7: 0 | CM7: 0 | CN7: 0 | CO7: 0 | CP7: 0 | CQ7: 0 | CR7: 0 | CS7: 0 | CT7: 0 | CU7: 0 | CV7: 0 | CW7: 0 | CX7: 0 | CY7: 0 | CZ7: 0 | DA7: 0 | DB7: 0 | DC7: 0 | DD7: 0 | DE7: 0 | DF7: 0 | DG7: 0 | DH7: 0 | DI7: 0 | DJ7: 0 | DK7: 0 | DL7: 0 | DM7: 0 | DN7: 0 | DO7: 0 | DP7: 0 | DQ7: 0 | DR7: 0 | DS7: 0 | DT7: 0 | DU7: 0 | DV7: 0 | DW7: 0 | DX7: 0 | DY7: 0 | DZ7: 0 | EA7: 0 | EB7: 0 | EC7: 0 | ED7: 0 | EE7: 0 | EF7: 0 | EG7: 0 | EH7: 0 | EI7: 0 | EJ7: 0 | EK7: 0 | EL7: 0 | EM7: 0 | EN7: 0 | EO7: 0 | EP7: 0 | EQ7: 0 | ER7: 0 | ES7: 0 | ET7: 0 | EU7: 0 | EV7: 0 | EW7: 0 | EX7: 0 | EY7: 0 | EZ7: 0 | FA7: 0 | FB7: 0 | FC7: 0 | FD7: 0 | FE7: 0 | FF7: 0 | FG7: 0 | FH7: 0 | FI7: 0 | FJ7: 0 | FK7: 0 | FL7: 0 | FM7: 0 | FN7: 0 | FO7: 0 | FP7: 0 | FQ7: 0 | FR7: 0 | FS7: 0 | FT7: 0 | FU7: 0 | FV7: 0 | FW7: 0 | FX7: 0 | FY7: 0 | FZ7: 0 | GA7: 0 | GB7: 0 | GC7: 0 | GD7: 0 | GE7: 0 | GF7: 0 | GG7: 0 | GH7: 0 | GI7: 0 | GJ7: 0 | GK7: 0 | GL7: 0 | GM7: 0 | GN7: 0 | GO7: 0 | GP7: 0 | GQ7: 0 | GR7: 0 | GS7: 0 | GT7: 0 | GU7: 0 | GV7: 0 | GW7: 0 | GX7: 0 | GY7: 0 | GZ7: 0 | HA7: 0 | HB7: 0 | HC7: 0 | HD7: 0 | HE7: 0 | HF7: 0 | HG7: 0 | HH7: 0 | HI7: 0 | HJ7: 0 | HK7: 0 | HL7: 0 | HM7: 0 | HN7: 0 | HO7: 0 | HP7: 0 | HQ7: 0 | HR7: 0 | HS7: 0 | HT7: 0 | HU7: 0 | HV7: 0 | HW7: 0 | HX7: 0 | HY7: 0 | HZ7: 0 | IA7: 0 | IB7: 0 | IC7: 0 | ID7: 0 | IE7: 0 | IF7: 0 | IG7: 0 | IH7: 0 | II7: 0 | IJ7: 0 | IK7: 0 | IL7: 0 | IM7: 0 | IN7: 0 | IO7: 0 | IP7: 0 | IQ7: 0 | IR7: 0 | IS7: 0 | IT7: 0 | IU7: 0 | IV7: 0 | IW7: 0 | IX7: 0 | IY7: 0 | IZ7: 0 | JA7: 0 | JB7: 0 | JC7: 0 | JD7: 0 | JE7: 0 | JF7: 0 | JG7: 0 | JH7: 0 | JI7: 0 | JJ7: 0 | JK7: 0 | JL7: 0 | JM7: 0 | JN7: 0 | JO7: 0 | JP7: 0 | JQ7: 0 | JR7: 0 | JS7: 0 | JT7: 0 | JU7: 0 | JV7: 0 | JW7: 0 | JX7: 0 | JY7: 0 | JZ7: 0 | KA7: 0 | KB7: 0 | KC7: 0 | KD7: 0 | KE7: 0 | KF7: 0 | KG7: 0 | KH7: 0 | KI7: 0 | KJ7: 0 | KK7: 0 | KL7: 0 | KM7: 0 | KN7: 0 | KO7: 0 | KP7: 0 | KQ7: 0 | KR7: 0 | KS7: 0 | KT7: 0 | KU7: 0 | KV7: 0 | KW7: 0 | KX7: 0 | KY7: 0 | KZ7: 0 | LA7: 0 | LB7: 0 | LC7: 0 | LD7: 0 | LE7: 0 | LF7: 0 | LG7: 0 | LH7: 0 | LI7: 0
B8: Flag de pago de deuda | D8: 0 | E8: 0 | F8: 0 | G8: 0 | H8: 0 | I8: 0 | J8: 0 | K8: 0 | L8: 0 | M8: 0 | N8: 0 | O8: 0 | P8: 0 | Q8: 0 | R8: 0 | S8: 0 | T8: 0 | U8: 0 | V8: 0 | W8: 0 | X8: 0 | Y8: 0 | Z8: 0 | AA8: 0 | AB8: 0 | AC8: 0 | AD8: 0 | AE8: 0 | AF8: 0 | AG8: 0 | AH8: 0 | AI8: 0 | AJ8: 0 | AK8: 0 | AL8: 0 | AM8: 0 | AN8: 0 | AO8: 0 | AP8: 0 | AQ8: 0 | AR8: 0 | AS8: 0 | AT8: 0 | AU8: 0 | AV8: 0 | AW8: 0 | AX8: 0 | AY8: 0 | AZ8: 1 | BA8: 1 | BB8: 1 | BC8: 1 | BD8: 1 | BE8: 1 | BF8: 1 | BG8: 1 | BH8: 1 | BI8: 1 | BJ8: 1 | BK8: 1 | BL8: 1 | BM8: 1 | BN8: 1 | BO8: 1 | BP8: 1 | BQ8: 1 | BR8: 1 | BS8: 1 | BT8: 1 | BU8: 1 | BV8: 1 | BW8: 1 | BX8: 1 | BY8: 1 | BZ8: 1 | CA8: 1 | CB8: 1 | CC8: 1 | CD8: 1 | CE8: 1 | CF8: 1 | CG8: 1 | CH8: 1 | CI8: 1 | CJ8: 1 | CK8: 1 | CL8: 1 | CM8: 1 | CN8: 1 | CO8: 1 | CP8: 1 | CQ8: 1 | CR8: 1 | CS8: 1 | CT8: 1 | CU8: 1 | CV8: 1 | CW8: 1 | CX8: 1 | CY8: 1 | CZ8: 1 | DA8: 1 | DB8: 1 | DC8: 1 | DD8: 1 | DE8: 1 | DF8: 1 | DG8: 1 | DH8: 1 | DI8: 1 | DJ8: 1 | DK8: 1 | DL8: 1 | DM8: 1 | DN8: 1 | DO8: 1 | DP8: 1 | DQ8: 1 | DR8: 1 | DS8: 1 | DT8: 1 | DU8: 1 | DV8: 1 | DW8: 1 | DX8: 1 | DY8: 1 | DZ8: 1 | EA8: 1 | EB8: 1 | EC8: 1 | ED8: 1 | EE8: 1 | EF8: 1 | EG8: 1 | EH8: 1 | EI8: 1 | EJ8: 1 | EK8: 1 | EL8: 1 | EM8: 1 | EN8: 1 | EO8: 1 | EP8: 1 | EQ8: 1 | ER8: 1 | ES8: 1 | ET8: 1 | EU8: 1 | EV8: 1 | EW8: 1 | EX8: 1 | EY8: 1 | EZ8: 1 | FA8: 1 | FB8: 1 | FC8: 1 | FD8: 1 | FE8: 1 | FF8: 1 | FG8: 1 | FH8: 1 | FI8: 1 | FJ8: 1 | FK8: 1 | FL8: 1 | FM8: 1 | FN8: 1 | FO8: 1 | FP8: 1 | FQ8: 1 | FR8: 1 | FS8: 1 | FT8: 1 | FU8: 1 | FV8: 1 | FW8: 1 | FX8: 1 | FY8: 1 | FZ8: 1 | GA8: 1 | GB8: 1 | GC8: 1 | GD8: 1 | GE8: 1 | GF8: 1 | GG8: 1 | GH8: 1 | GI8: 1 | GJ8: 1 | GK8: 1 | GL8: 1 | GM8: 1 | GN8: 0 | GO8: 0 | GP8: 0 | GQ8: 0 | GR8: 0 | GS8: 0 | GT8: 0 | GU8: 0 | GV8: 0 | GW8: 0 | GX8: 0 | GY8: 0 | GZ8: 0 | HA8: 0 | HB8: 0 | HC8: 0 | HD8: 0 | HE8: 0 | HF8: 0 | HG8: 0 | HH8: 0 | HI8: 0 | HJ8: 0 | HK8: 0 | HL8: 0 | HM8: 0 | HN8: 0 | HO8: 0 | HP8: 0 | HQ8: 0 | HR8: 0 | HS8: 0 | HT8: 0 | HU8: 0 | HV8: 0 | HW8: 0 | HX8: 0 | HY8: 0 | HZ8: 0 | IA8: 0 | IB8: 0 | IC8: 0 | ID8: 0 | IE8: 0 | IF8: 0 | IG8: 0 | IH8: 0 | II8: 0 | IJ8: 0 | IK8: 0 | IL8: 0 | IM8: 0 | IN8: 0 | IO8: 0 | IP8: 0 | IQ8: 0 | IR8: 0 | IS8: 0 | IT8: 0 | IU8: 0 | IV8: 0 | IW8: 0 | IX8: 0 | IY8: 0 | IZ8: 0 | JA8: 0 | JB8: 0 | JC8: 0 | JD8: 0 | JE8: 0 | JF8: 0 | JG8: 0 | JH8: 0 | JI8: 0 | JJ8: 0 | JK8: 0 | JL8: 0 | JM8: 0 | JN8: 0 | JO8: 0 | JP8: 0 | JQ8: 0 | JR8: 0 | JS8: 0 | JT8: 0 | JU8: 0 | JV8: 0 | JW8: 0 | JX8: 0 | JY8: 0 | JZ8: 0 | KA8: 0 | KB8: 0 | KC8: 0 | KD8: 0 | KE8: 0 | KF8: 0 | KG8: 0 | KH8: 0 | KI8: 0 | KJ8: 0 | KK8: 0 | KL8: 0 | KM8: 0 | KN8: 0 | KO8: 0 | KP8: 0 | KQ8: 0 | KR8: 0 | KS8: 0 | KT8: 0 | KU8: 0 | KV8: 0 | KW8: 0 | KX8: 0 | KY8: 0 | KZ8: 0 | LA8: 0 | LB8: 0 | LC8: 0 | LD8: 0 | LE8: 0 | LF8: 0 | LG8: 0 | LH8: 0 | LI8: 0
B9: Inversion a financiarse | D9: 0 | E9: 0 | F9: 0 | G9: 0 | H9: 0 | I9: 0 | J9: 0 | K9: 0 | L9: 0 | M9: 0 | N9: 0 | O9: 0 | P9: 0 | Q9: 0 | R9: 0 | S9: 0 | T9: 0 | U9: 0 | V9: 0 | W9: 0 | X9: 0 | Y9: 42887.065 | Z9: 6255.7562 | AA9: 6266.0881 | AB9: 6276.4371 | AC9: 6286.8031 | AD9: 6297.1863 | AE9: 15790.504 | AF9: 15816.583 | AG9: 15842.705 | AH9: 15868.871 | AI9: 15642.805 | AJ9: 15633.192 | AK9: 13673.055 | AL9: 13671.281 | AM9: 13091.902 | AN9: 13113.525 | AO9: 14842.491 | AP9: 14831.203 | AQ9: 2451.2709 | AR9: 2455.3194 | AS9: 1600.067 | AT9: 1602.7096 | AU9: 188.97311 | AV9: 189.28521 | AW9: 189.59783 | AX9: 189.91097 | AY9: 190.22462 | AZ9: 0 | BA9: 0 | BB9: 0 | BC9: 0 | BD9: 0 | BE9: 0 | BF9: 0 | BG9: 0 | BH9: 0 | BI9: 0 | BJ9: 0 | BK9: 0 | BL9: 0 | BM9: 0 | BN9: 0 | BO9: 0 | BP9: 0 | BQ9: 0 | BR9: 0 | BS9: 0 | BT9: 0 | BU9: 0 | BV9: 0 | BW9: 0 | BX9: 0 | BY9: 0 | BZ9: 0 | CA9: 0 | CB9: 0 | CC9: 0 | CD9: 0 | CE9: 0 | CF9: 0 | CG9: 0 | CH9: 0 | CI9: 0 | CJ9: 0 | CK9: 0 | CL9: 0 | CM9: 0 | CN9: 0 | CO9: 0 | CP9: 0 | CQ9: 0 | CR9: 0 | CS9: 0 | CT9: 0 | CU9: 0 | CV9: 0 | CW9: 0 | CX9: 0 | CY9: 0 | CZ9: 0 | DA9: 0 | DB9: 0 | DC9: 0 | DD9: 0 | DE9: 0 | DF9: 0 | DG9: 0 | DH9: 0 | DI9: 0 | DJ9: 0 | DK9: 0 | DL9: 0 | DM9: 0 | DN9: 0 | DO9: 0 | DP9: 0 | DQ9: 0 | DR9: 0 | DS9: 0 | DT9: 0 | DU9: 0 | DV9: 0 | DW9: 0 | DX9: 0 | DY9: 0 | DZ9: 0 | EA9: 0 | EB9: 0 | EC9: 0 | ED9: 0 | EE9: 0 | EF9: 0 | EG9: 0 | EH9: 0 | EI9: 0 | EJ9: 0 | EK9: 0 | EL9: 0 | EM9: 0 | EN9: 0 | EO9: 0 | EP9: 0 | EQ9: 0 | ER9: 0 | ES9: 0 | ET9: 0 | EU9: 0 | EV9: 0 | EW9: 0 | EX9: 0 | EY9: 0 | EZ9: 0 | FA9: 0 | FB9: 0 | FC9: 0 | FD9: 0 | FE9: 0 | FF9: 0 | FG9: 0 | FH9: 0 | FI9: 0 | FJ9: 0 | FK9: 0 | FL9: 0 | FM9: 0 | FN9: 0 | FO9: 0 | FP9: 0 | FQ9: 0 | FR9: 0 | FS9: 0 | FT9: 0 | FU9: 0 | FV9: 0 | FW9: 0 | FX9: 0 | FY9: 0 | FZ9: 0 | GA9: 0 | GB9: 0 | GC9: 0 | GD9: 0 | GE9: 0 | GF9: 0 | GG9: 0 | GH9: 0 | GI9: 0 | GJ9: 0 | GK9: 0 | GL9: 0 | GM9: 0 | GN9: 0 | GO9: 0 | GP9: 0 | GQ9: 0 | GR9: 0 | GS9: 0 | GT9: 0 | GU9: 0 | GV9: 0 | GW9: 0 | GX9: 0 | GY9: 0 | GZ9: 0 | HA9: 0 | HB9: 0 | HC9: 0 | HD9: 0 | HE9: 0 | HF9: 0 | HG9: 0 | HH9: 0 | HI9: 0 | HJ9: 0 | HK9: 0 | HL9: 0 | HM9: 0 | HN9: 0 | HO9: 0 | HP9: 0 | HQ9: 0 | HR9: 0 | HS9: 0 | HT9: 0 | HU9: 0 | HV9: 0 | HW9: 0 | HX9: 0 | HY9: 0 | HZ9: 0 | IA9: 0 | IB9: 0 | IC9: 0 | ID9: 0 | IE9: 0 | IF9: 0 | IG9: 0 | IH9: 0 | II9: 0 | IJ9: 0 | IK9: 0 | IL9: 0 | IM9: 0 | IN9: 0 | IO9: 0 | IP9: 0 | IQ9: 0 | IR9: 0 | IS9: 0 | IT9: 0 | IU9: 0 | IV9: 0 | IW9: 0 | IX9: 0 | IY9: 0 | IZ9: 0 | JA9: 0 | JB9: 0 | JC9: 0 | JD9: 0 | JE9: 0 | JF9: 0 | JG9: 0 | JH9: 0 | JI9: 0 | JJ9: 0 | JK9: 0 | JL9: 0 | JM9: 0 | JN9: 0 | JO9: 0 | JP9: 0 | JQ9: 0 | JR9: 0 | JS9: 0 | JT9: 0 | JU9: 0 | JV9: 0 | JW9: 0 | JX9: 0 | JY9: 0 | JZ9: 0 | KA9: 0 | KB9: 0 | KC9: 0 | KD9: 0 | KE9: 0 | KF9: 0 | KG9: 0 | KH9: 0 | KI9: 0 | KJ9: 0 | KK9: 0 | KL9: 0 | KM9: 0 | KN9: 0 | KO9: 0 | KP9: 0 | KQ9: 0 | KR9: 0 | KS9: 0 | KT9: 0 | KU9: 0 | KV9: 0 | KW9: 0 | KX9: 0 | KY9: 0 | KZ9: 0 | LA9: 0 | LB9: 0 | LC9: 0 | LD9: 0 | LE9: 0 | LF9: 0 | LG9: 0 | LH9: 0 | LI9: 0
B10: Desembolsos | D10: =D7*D9*p_tamano_deuda | E10: =E7*E9*p_tamano_deuda | F10: =F7*F9*p_tamano_deuda | G10: =G7*G9*p_tamano_deuda | H10: =H7*H9*p_tamano_deuda | I10: =I7*I9*p_tamano_deuda | J10: =J7*J9*p_tamano_deuda | K10: =K7*K9*p_tamano_deuda | ... LI10: =LI7*LI9*p_tamano_deuda
B11: Tasa mensual | D11: =(1+p_kd)^(1/12)-1
B12: Saldo de obra capitalizado (base de la cuota) | D12: =0*(1+$D$11)+D10 | E12: =D12*(1+$D$11)+E10 | F12: =E12*(1+$D$11)+F10 | G12: =F12*(1+$D$11)+G10 | H12: =G12*(1+$D$11)+H10 | I12: =H12*(1+$D$11)+I10 | J12: =I12*(1+$D$11)+J10 | K12: =J12*(1+$D$11)+K10 | L12: =K12*(1+$D$11)+L10 | ... AY12: =AX12*(1+$D$11)+AY10 | AZ12: 0 | BA12: 0 | BB12: 0 | BC12: 0 | BD12: 0 | BE12: 0 | BF12: 0 | BG12: 0 | BH12: 0 | BI12: 0 | BJ12: 0 | BK12: 0 | BL12: 0 | BM12: 0 | BN12: 0 | BO12: 0 | BP12: 0 | BQ12: 0 | BR12: 0 | BS12: 0 | BT12: 0 | BU12: 0 | BV12: 0 | BW12: 0 | BX12: 0 | BY12: 0 | BZ12: 0 | CA12: 0 | CB12: 0 | CC12: 0 | CD12: 0 | CE12: 0 | CF12: 0 | CG12: 0 | CH12: 0 | CI12: 0 | CJ12: 0 | CK12: 0 | CL12: 0 | CM12: 0 | CN12: 0 | CO12: 0 | CP12: 0 | CQ12: 0 | CR12: 0 | CS12: 0 | CT12: 0 | CU12: 0 | CV12: 0 | CW12: 0 | CX12: 0 | CY12: 0 | CZ12: 0 | DA12: 0 | DB12: 0 | DC12: 0 | DD12: 0 | DE12: 0 | DF12: 0 | DG12: 0 | DH12: 0 | DI12: 0 | DJ12: 0 | DK12: 0 | DL12: 0 | DM12: 0 | DN12: 0 | DO12: 0 | DP12: 0 | DQ12: 0 | DR12: 0 | DS12: 0 | DT12: 0 | DU12: 0 | DV12: 0 | DW12: 0 | DX12: 0 | DY12: 0 | DZ12: 0 | EA12: 0 | EB12: 0 | EC12: 0 | ED12: 0 | EE12: 0 | EF12: 0 | EG12: 0 | EH12: 0 | EI12: 0 | EJ12: 0 | EK12: 0 | EL12: 0 | EM12: 0 | EN12: 0 | EO12: 0 | EP12: 0 | EQ12: 0 | ER12: 0 | ES12: 0 | ET12: 0 | EU12: 0 | EV12: 0 | EW12: 0 | EX12: 0 | EY12: 0 | EZ12: 0 | FA12: 0 | FB12: 0 | FC12: 0 | FD12: 0 | FE12: 0 | FF12: 0 | FG12: 0 | FH12: 0 | FI12: 0 | FJ12: 0 | FK12: 0 | FL12: 0 | FM12: 0 | FN12: 0 | FO12: 0 | FP12: 0 | FQ12: 0 | FR12: 0 | FS12: 0 | FT12: 0 | FU12: 0 | FV12: 0 | FW12: 0 | FX12: 0 | FY12: 0 | FZ12: 0 | GA12: 0 | GB12: 0 | GC12: 0 | GD12: 0 | GE12: 0 | GF12: 0 | GG12: 0 | GH12: 0 | GI12: 0 | GJ12: 0 | GK12: 0 | GL12: 0 | GM12: 0 | GN12: 0 | GO12: 0 | GP12: 0 | GQ12: 0 | GR12: 0 | GS12: 0 | GT12: 0 | GU12: 0 | GV12: 0 | GW12: 0 | GX12: 0 | GY12: 0 | GZ12: 0 | HA12: 0 | HB12: 0 | HC12: 0 | HD12: 0 | HE12: 0 | HF12: 0 | HG12: 0 | HH12: 0 | HI12: 0 | HJ12: 0 | HK12: 0 | HL12: 0 | HM12: 0 | HN12: 0 | HO12: 0 | HP12: 0 | HQ12: 0 | HR12: 0 | HS12: 0 | HT12: 0 | HU12: 0 | HV12: 0 | HW12: 0 | HX12: 0 | HY12: 0 | HZ12: 0 | IA12: 0 | IB12: 0 | IC12: 0 | ID12: 0 | IE12: 0 | IF12: 0 | IG12: 0 | IH12: 0 | II12: 0 | IJ12: 0 | IK12: 0 | IL12: 0 | IM12: 0 | IN12: 0 | IO12: 0 | IP12: 0 | IQ12: 0 | IR12: 0 | IS12: 0 | IT12: 0 | IU12: 0 | IV12: 0 | IW12: 0 | IX12: 0 | IY12: 0 | IZ12: 0 | JA12: 0 | JB12: 0 | JC12: 0 | JD12: 0 | JE12: 0 | JF12: 0 | JG12: 0 | JH12: 0 | JI12: 0 | JJ12: 0 | JK12: 0 | JL12: 0 | JM12: 0 | JN12: 0 | JO12: 0 | JP12: 0 | JQ12: 0 | JR12: 0 | JS12: 0 | JT12: 0 | JU12: 0 | JV12: 0 | JW12: 0 | JX12: 0 | JY12: 0 | JZ12: 0 | KA12: 0 | KB12: 0 | KC12: 0 | KD12: 0 | KE12: 0 | KF12: 0 | KG12: 0 | KH12: 0 | KI12: 0 | KJ12: 0 | KK12: 0 | KL12: 0 | KM12: 0 | KN12: 0 | KO12: 0 | KP12: 0 | KQ12: 0 | KR12: 0 | KS12: 0 | KT12: 0 | KU12: 0 | KV12: 0 | KW12: 0 | KX12: 0 | KY12: 0 | KZ12: 0 | LA12: 0 | LB12: 0 | LC12: 0 | LD12: 0 | LE12: 0 | LF12: 0 | LG12: 0 | LH12: 0 | LI12: 0
B13: Cuota constante | D13: =-PMT($D$11,p_pagos,AY12)
B14: Interes | D14: 0 | E14: =D17*$D$11 | F14: =E17*$D$11 | G14: =F17*$D$11 | H14: =G17*$D$11 | I14: =H17*$D$11 | J14: =I17*$D$11 | K14: =J17*$D$11 | L14: =K17*$D$11 | ... LI14: =LH17*$D$11
B15: Amortizacion | D15: =D16-D14 | E15: =E16-E14 | F15: =F16-F14 | G15: =G16-G14 | H15: =H16-H14 | I15: =I16-I14 | J15: =J16-J14 | K15: =K16-K14 | ... LI15: =LI16-LI14
B16: Servicio de deuda | D16: =D8*$D$13 | E16: =E8*$D$13 | F16: =F8*$D$13 | G16: =G8*$D$13 | H16: =H8*$D$13 | I16: =I8*$D$13 | J16: =J8*$D$13 | K16: =K8*$D$13 | ... LI16: =LI8*$D$13
B17: Saldo deudor | D17: =0+D10-D15 | E17: =D17+E10-E15 | F17: =E17+F10-F15 | G17: =F17+G10-G15 | H17: =G17+H10-H15 | I17: =H17+I10-I15 | J17: =I17+J10-J15 | K17: =J17+K10-K15 | L17: =K17+L10-L15 | ... LI17: =LH17+LI10-LI15

Sheet Ingresos
B2: Ingreso tarifario al usuario
B3: Mismo reajuste por IPM con gatillo que la pata variable; aqui es todo el ingreso del proyecto.
B6: Mes | D6: 2026-10-31 | E6: 2026-11-30 | F6: 2026-12-31 | G6: 2027-01-31 | H6: 2027-02-28 | I6: 2027-03-31 | J6: 2027-04-30 | K6: 2027-05-31 | L6: 2027-06-30 | M6: 2027-07-31 | N6: 2027-08-31 | O6: 2027-09-30 | P6: 2027-10-31 | Q6: 2027-11-30 | R6: 2027-12-31 | S6: 2028-01-31 | T6: 2028-02-29 | U6: 2028-03-31 | V6: 2028-04-30 | W6: 2028-05-31 | X6: 2028-06-30 | Y6: 2028-07-31 | Z6: 2028-08-31 | AA6: 2028-09-30 | AB6: 2028-10-31 | AC6: 2028-11-30 | AD6: 2028-12-31 | AE6: 2029-01-31 | AF6: 2029-02-28 | AG6: 2029-03-31 | AH6: 2029-04-30 | AI6: 2029-05-31 | AJ6: 2029-06-30 | AK6: 2029-07-31 | AL6: 2029-08-31 | AM6: 2029-09-30 | AN6: 2029-10-31 | AO6: 2029-11-30 | AP6: 2029-12-31 | AQ6: 2030-01-31 | AR6: 2030-02-28 | AS6: 2030-03-31 | AT6: 2030-04-30 | AU6: 2030-05-31 | AV6: 2030-06-30 | AW6: 2030-07-31 | AX6: 2030-08-31 | AY6: 2030-09-30 | AZ6: 2030-10-31 | BA6: 2030-11-30 | BB6: 2030-12-31 | BC6: 2031-01-31 | BD6: 2031-02-28 | BE6: 2031-03-31 | BF6: 2031-04-30 | BG6: 2031-05-31 | BH6: 2031-06-30 | BI6: 2031-07-31 | BJ6: 2031-08-31 | BK6: 2031-09-30 | BL6: 2031-10-31 | BM6: 2031-11-30 | BN6: 2031-12-31 | BO6: 2032-01-31 | BP6: 2032-02-29 | BQ6: 2032-03-31 | BR6: 2032-04-30 | BS6: 2032-05-31 | BT6: 2032-06-30 | BU6: 2032-07-31 | BV6: 2032-08-31 | BW6: 2032-09-30 | BX6: 2032-10-31 | BY6: 2032-11-30 | BZ6: 2032-12-31 | CA6: 2033-01-31 | CB6: 2033-02-28 | CC6: 2033-03-31 | CD6: 2033-04-30 | CE6: 2033-05-31 | CF6: 2033-06-30 | CG6: 2033-07-31 | CH6: 2033-08-31 | CI6: 2033-09-30 | CJ6: 2033-10-31 | CK6: 2033-11-30 | CL6: 2033-12-31 | CM6: 2034-01-31 | CN6: 2034-02-28 | CO6: 2034-03-31 | CP6: 2034-04-30 | CQ6: 2034-05-31 | CR6: 2034-06-30 | CS6: 2034-07-31 | CT6: 2034-08-31 | CU6: 2034-09-30 | CV6: 2034-10-31 | CW6: 2034-11-30 | CX6: 2034-12-31 | CY6: 2035-01-31 | CZ6: 2035-02-28 | DA6: 2035-03-31 | DB6: 2035-04-30 | DC6: 2035-05-31 | DD6: 2035-06-30 | DE6: 2035-07-31 | DF6: 2035-08-31 | DG6: 2035-09-30 | DH6: 2035-10-31 | DI6: 2035-11-30 | DJ6: 2035-12-31 | DK6: 2036-01-31 | DL6: 2036-02-29 | DM6: 2036-03-31 | DN6: 2036-04-30 | DO6: 2036-05-31 | DP6: 2036-06-30 | DQ6: 2036-07-31 | DR6: 2036-08-31 | DS6: 2036-09-30 | DT6: 2036-10-31 | DU6: 2036-11-30 | DV6: 2036-12-31 | DW6: 2037-01-31 | DX6: 2037-02-28 | DY6: 2037-03-31 | DZ6: 2037-04-30 | EA6: 2037-05-31 | EB6: 2037-06-30 | EC6: 2037-07-31 | ED6: 2037-08-31 | EE6: 2037-09-30 | EF6: 2037-10-31 | EG6: 2037-11-30 | EH6: 2037-12-31 | EI6: 2038-01-31 | EJ6: 2038-02-28 | EK6: 2038-03-31 | EL6: 2038-04-30 | EM6: 2038-05-31 | EN6: 2038-06-30 | EO6: 2038-07-31 | EP6: 2038-08-31 | EQ6: 2038-09-30 | ER6: 2038-10-31 | ES6: 2038-11-30 | ET6: 2038-12-31 | EU6: 2039-01-31 | EV6: 2039-02-28 | EW6: 2039-03-31 | EX6: 2039-04-30 | EY6: 2039-05-31 | EZ6: 2039-06-30 | FA6: 2039-07-31 | FB6: 2039-08-31 | FC6: 2039-09-30 | FD6: 2039-10-31 | FE6: 2039-11-30 | FF6: 2039-12-31 | FG6: 2040-01-31 | FH6: 2040-02-29 | FI6: 2040-03-31 | FJ6: 2040-04-30 | FK6: 2040-05-31 | FL6: 2040-06-30 | FM6: 2040-07-31 | FN6: 2040-08-31 | FO6: 2040-09-30 | FP6: 2040-10-31 | FQ6: 2040-11-30 | FR6: 2040-12-31 | FS6: 2041-01-31 | FT6: 2041-02-28 | FU6: 2041-03-31 | FV6: 2041-04-30 | FW6: 2041-05-31 | FX6: 2041-06-30 | FY6: 2041-07-31 | FZ6: 2041-08-31 | GA6: 2041-09-30 | GB6: 2041-10-31 | GC6: 2041-11-30 | GD6: 2041-12-31 | GE6: 2042-01-31 | GF6: 2042-02-28 | GG6: 2042-03-31 | GH6: 2042-04-30 | GI6: 2042-05-31 | GJ6: 2042-06-30 | GK6: 2042-07-31 | GL6: 2042-08-31 | GM6: 2042-09-30 | GN6: 2042-10-31 | GO6: 2042-11-30 | GP6: 2042-12-31 | GQ6: 2043-01-31 | GR6: 2043-02-28 | GS6: 2043-03-31 | GT6: 2043-04-30 | GU6: 2043-05-31 | GV6: 2043-06-30 | GW6: 2043-07-31 | GX6: 2043-08-31 | GY6: 2043-09-30 | GZ6: 2043-10-31 | HA6: 2043-11-30 | HB6: 2043-12-31 | HC6: 2044-01-31 | HD6: 2044-02-29 | HE6: 2044-03-31 | HF6: 2044-04-30 | HG6: 2044-05-31 | HH6: 2044-06-30 | HI6: 2044-07-31 | HJ6: 2044-08-31 | HK6: 2044-09-30 | HL6: 2044-10-31 | HM6: 2044-11-30 | HN6: 2044-12-31 | HO6: 2045-01-31 | HP6: 2045-02-28 | HQ6: 2045-03-31 | HR6: 2045-04-30 | HS6: 2045-05-31 | HT6: 2045-06-30 | HU6: 2045-07-31 | HV6: 2045-08-31 | HW6: 2045-09-30 | HX6: 2045-10-31 | HY6: 2045-11-30 | HZ6: 2045-12-31 | IA6: 2046-01-31 | IB6: 2046-02-28 | IC6: 2046-03-31 | ID6: 2046-04-30 | IE6: 2046-05-31 | IF6: 2046-06-30 | IG6: 2046-07-31 | IH6: 2046-08-31 | II6: 2046-09-30 | IJ6: 2046-10-31 | IK6: 2046-11-30 | IL6: 2046-12-31 | IM6: 2047-01-31 | IN6: 2047-02-28 | IO6: 2047-03-31 | IP6: 2047-04-30 | IQ6: 2047-05-31 | IR6: 2047-06-30 | IS6: 2047-07-31 | IT6: 2047-08-31 | IU6: 2047-09-30 | IV6: 2047-10-31 | IW6: 2047-11-30 | IX6: 2047-12-31 | IY6: 2048-01-31 | IZ6: 2048-02-29 | JA6: 2048-03-31 | JB6: 2048-04-30 | JC6: 2048-05-31 | JD6: 2048-06-30 | JE6: 2048-07-31 | JF6: 2048-08-31 | JG6: 2048-09-30 | JH6: 2048-10-31 | JI6: 2048-11-30 | JJ6: 2048-12-31 | JK6: 2049-01-31 | JL6: 2049-02-28 | JM6: 2049-03-31 | JN6: 2049-04-30 | JO6: 2049-05-31 | JP6: 2049-06-30 | JQ6: 2049-07-31 | JR6: 2049-08-31 | JS6: 2049-09-30 | JT6: 2049-10-31 | JU6: 2049-11-30 | JV6: 2049-12-31 | JW6: 2050-01-31 | JX6: 2050-02-28 | JY6: 2050-03-31 | JZ6: 2050-04-30 | KA6: 2050-05-31 | KB6: 2050-06-30 | KC6: 2050-07-31 | KD6: 2050-08-31 | KE6: 2050-09-30 | KF6: 2050-10-31 | KG6: 2050-11-30 | KH6: 2050-12-31 | KI6: 2051-01-31 | KJ6: 2051-02-28 | KK6: 2051-03-31 | KL6: 2051-04-30 | KM6: 2051-05-31 | KN6: 2051-06-30 | KO6: 2051-07-31 | KP6: 2051-08-31 | KQ6: 2051-09-30 | KR6: 2051-10-31 | KS6: 2051-11-30 | KT6: 2051-12-31 | KU6: 2052-01-31 | KV6: 2052-02-29 | KW6: 2052-03-31 | KX6: 2052-04-30 | KY6: 2052-05-31 | KZ6: 2052-06-30 | LA6: 2052-07-31 | LB6: 2052-08-31 | LC6: 2052-09-30 | LD6: 2052-10-31 | LE6: 2052-11-30 | LF6: 2052-12-31 | LG6: 2053-01-31 | LH6: 2053-02-28 | LI6: 2053-03-31
B7: Flag de operacion | D7: 0 | E7: 0 | F7: 0 | G7: 0 | H7: 0 | I7: 0 | J7: 0 | K7: 0 | L7: 0 | M7: 0 | N7: 0 | O7: 0 | P7: 0 | Q7: 0 | R7: 0 | S7: 0 | T7: 0 | U7: 0 | V7: 0 | W7: 0 | X7: 0 | Y7: 0 | Z7: 0 | AA7: 0 | AB7: 0 | AC7: 0 | AD7: 0 | AE7: 0 | AF7: 0 | AG7: 0 | AH7: 0 | AI7: 0 | AJ7: 0 | AK7: 0 | AL7: 0 | AM7: 0 | AN7: 0 | AO7: 0 | AP7: 0 | AQ7: 0 | AR7: 0 | AS7: 0 | AT7: 0 | AU7: 0 | AV7: 0 | AW7: 0 | AX7: 0 | AY7: 0 | AZ7: 1 | BA7: 1 | BB7: 1 | BC7: 1 | BD7: 1 | BE7: 1 | BF7: 1 | BG7: 1 | BH7: 1 | BI7: 1 | BJ7: 1 | BK7: 1 | BL7: 1 | BM7: 1 | BN7: 1 | BO7: 1 | BP7: 1 | BQ7: 1 | BR7: 1 | BS7: 1 | BT7: 1 | BU7: 1 | BV7: 1 | BW7: 1 | BX7: 1 | BY7: 1 | BZ7: 1 | CA7: 1 | CB7: 1 | CC7: 1 | CD7: 1 | CE7: 1 | CF7: 1 | CG7: 1 | CH7: 1 | CI7: 1 | CJ7: 1 | CK7: 1 | CL7: 1 | CM7: 1 | CN7: 1 | CO7: 1 | CP7: 1 | CQ7: 1 | CR7: 1 | CS7: 1 | CT7: 1 | CU7: 1 | CV7: 1 | CW7: 1 | CX7: 1 | CY7: 1 | CZ7: 1 | DA7: 1 | DB7: 1 | DC7: 1 | DD7: 1 | DE7: 1 | DF7: 1 | DG7: 1 | DH7: 1 | DI7: 1 | DJ7: 1 | DK7: 1 | DL7: 1 | DM7: 1 | DN7: 1 | DO7: 1 | DP7: 1 | DQ7: 1 | DR7: 1 | DS7: 1 | DT7: 1 | DU7: 1 | DV7: 1 | DW7: 1 | DX7: 1 | DY7: 1 | DZ7: 1 | EA7: 1 | EB7: 1 | EC7: 1 | ED7: 1 | EE7: 1 | EF7: 1 | EG7: 1 | EH7: 1 | EI7: 1 | EJ7: 1 | EK7: 1 | EL7: 1 | EM7: 1 | EN7: 1 | EO7: 1 | EP7: 1 | EQ7: 1 | ER7: 1 | ES7: 1 | ET7: 1 | EU7: 1 | EV7: 1 | EW7: 1 | EX7: 1 | EY7: 1 | EZ7: 1 | FA7: 1 | FB7: 1 | FC7: 1 | FD7: 1 | FE7: 1 | FF7: 1 | FG7: 1 | FH7: 1 | FI7: 1 | FJ7: 1 | FK7: 1 | FL7: 1 | FM7: 1 | FN7: 1 | FO7: 1 | FP7: 1 | FQ7: 1 | FR7: 1 | FS7: 1 | FT7: 1 | FU7: 1 | FV7: 1 | FW7: 1 | FX7: 1 | FY7: 1 | FZ7: 1 | GA7: 1 | GB7: 1 | GC7: 1 | GD7: 1 | GE7: 1 | GF7: 1 | GG7: 1 | GH7: 1 | GI7: 1 | GJ7: 1 | GK7: 1 | GL7: 1 | GM7: 1 | GN7: 1 | GO7: 1 | GP7: 1 | GQ7: 1 | GR7: 1 | GS7: 1 | GT7: 1 | GU7: 1 | GV7: 1 | GW7: 1 | GX7: 1 | GY7: 1 | GZ7: 1 | HA7: 1 | HB7: 1 | HC7: 1 | HD7: 1 | HE7: 1 | HF7: 1 | HG7: 1 | HH7: 1 | HI7: 1 | HJ7: 1 | HK7: 1 | HL7: 1 | HM7: 1 | HN7: 1 | HO7: 1 | HP7: 1 | HQ7: 1 | HR7: 1 | HS7: 1 | HT7: 1 | HU7: 1 | HV7: 1 | HW7: 1 | HX7: 1 | HY7: 1 | HZ7: 1 | IA7: 1 | IB7: 1 | IC7: 1 | ID7: 1 | IE7: 1 | IF7: 1 | IG7: 1 | IH7: 1 | II7: 1 | IJ7: 1 | IK7: 1 | IL7: 1 | IM7: 1 | IN7: 1 | IO7: 1 | IP7: 1 | IQ7: 1 | IR7: 1 | IS7: 1 | IT7: 1 | IU7: 1 | IV7: 1 | IW7: 1 | IX7: 1 | IY7: 1 | IZ7: 1 | JA7: 1 | JB7: 1 | JC7: 1 | JD7: 1 | JE7: 1 | JF7: 1 | JG7: 1 | JH7: 1 | JI7: 1 | JJ7: 1 | JK7: 1 | JL7: 1 | JM7: 1 | JN7: 1 | JO7: 1 | JP7: 1 | JQ7: 1 | JR7: 1 | JS7: 1 | JT7: 1 | JU7: 1 | JV7: 1 | JW7: 1 | JX7: 1 | JY7: 1 | JZ7: 1 | KA7: 1 | KB7: 1 | KC7: 1 | KD7: 1 | KE7: 1 | KF7: 1 | KG7: 1 | KH7: 1 | KI7: 1 | KJ7: 1 | KK7: 1 | KL7: 1 | KM7: 1 | KN7: 1 | KO7: 1 | KP7: 1 | KQ7: 1 | KR7: 1 | KS7: 1 | KT7: 1 | KU7: 1 | KV7: 1 | KW7: 1 | KX7: 1 | KY7: 1 | KZ7: 1 | LA7: 1 | LB7: 1 | LC7: 1 | LD7: 0 | LE7: 0 | LF7: 0 | LG7: 0 | LH7: 0 | LI7: 0
B8: Trimestre del mes | D8: 1 | E8: 1 | F8: 1 | G8: 2 | H8: 2 | I8: 2 | J8: 3 | K8: 3 | L8: 3 | M8: 4 | N8: 4 | O8: 4 | P8: 5 | Q8: 5 | R8: 5 | S8: 6 | T8: 6 | U8: 6 | V8: 7 | W8: 7 | X8: 7 | Y8: 8 | Z8: 8 | AA8: 8 | AB8: 9 | AC8: 9 | AD8: 9 | AE8: 10 | AF8: 10 | AG8: 10 | AH8: 11 | AI8: 11 | AJ8: 11 | AK8: 12 | AL8: 12 | AM8: 12 | AN8: 13 | AO8: 13 | AP8: 13 | AQ8: 14 | AR8: 14 | AS8: 14 | AT8: 15 | AU8: 15 | AV8: 15 | AW8: 16 | AX8: 16 | AY8: 16 | AZ8: 17 | BA8: 17 | BB8: 17 | BC8: 18 | BD8: 18 | BE8: 18 | BF8: 19 | BG8: 19 | BH8: 19 | BI8: 20 | BJ8: 20 | BK8: 20 | BL8: 21 | BM8: 21 | BN8: 21 | BO8: 22 | BP8: 22 | BQ8: 22 | BR8: 23 | BS8: 23 | BT8: 23 | BU8: 24 | BV8: 24 | BW8: 24 | BX8: 25 | BY8: 25 | BZ8: 25 | CA8: 26 | CB8: 26 | CC8: 26 | CD8: 27 | CE8: 27 | CF8: 27 | CG8: 28 | CH8: 28 | CI8: 28 | CJ8: 29 | CK8: 29 | CL8: 29 | CM8: 30 | CN8: 30 | CO8: 30 | CP8: 31 | CQ8: 31 | CR8: 31 | CS8: 32 | CT8: 32 | CU8: 32 | CV8: 33 | CW8: 33 | CX8: 33 | CY8: 34 | CZ8: 34 | DA8: 34 | DB8: 35 | DC8: 35 | DD8: 35 | DE8: 36 | DF8: 36 | DG8: 36 | DH8: 37 | DI8: 37 | DJ8: 37 | DK8: 38 | DL8: 38 | DM8: 38 | DN8: 39 | DO8: 39 | DP8: 39 | DQ8: 40 | DR8: 40 | DS8: 40 | DT8: 41 | DU8: 41 | DV8: 41 | DW8: 42 | DX8: 42 | DY8: 42 | DZ8: 43 | EA8: 43 | EB8: 43 | EC8: 44 | ED8: 44 | EE8: 44 | EF8: 45 | EG8: 45 | EH8: 45 | EI8: 46 | EJ8: 46 | EK8: 46 | EL8: 47 | EM8: 47 | EN8: 47 | EO8: 48 | EP8: 48 | EQ8: 48 | ER8: 49 | ES8: 49 | ET8: 49 | EU8: 50 | EV8: 50 | EW8: 50 | EX8: 51 | EY8: 51 | EZ8: 51 | FA8: 52 | FB8: 52 | FC8: 52 | FD8: 53 | FE8: 53 | FF8: 53 | FG8: 54 | FH8: 54 | FI8: 54 | FJ8: 55 | FK8: 55 | FL8: 55 | FM8: 56 | FN8: 56 | FO8: 56 | FP8: 57 | FQ8: 57 | FR8: 57 | FS8: 58 | FT8: 58 | FU8: 58 | FV8: 59 | FW8: 59 | FX8: 59 | FY8: 60 | FZ8: 60 | GA8: 60 | GB8: 61 | GC8: 61 | GD8: 61 | GE8: 62 | GF8: 62 | GG8: 62 | GH8: 63 | GI8: 63 | GJ8: 63 | GK8: 64 | GL8: 64 | GM8: 64 | GN8: 65 | GO8: 65 | GP8: 65 | GQ8: 66 | GR8: 66 | GS8: 66 | GT8: 67 | GU8: 67 | GV8: 67 | GW8: 68 | GX8: 68 | GY8: 68 | GZ8: 69 | HA8: 69 | HB8: 69 | HC8: 70 | HD8: 70 | HE8: 70 | HF8: 71 | HG8: 71 | HH8: 71 | HI8: 72 | HJ8: 72 | HK8: 72 | HL8: 73 | HM8: 73 | HN8: 73 | HO8: 74 | HP8: 74 | HQ8: 74 | HR8: 75 | HS8: 75 | HT8: 75 | HU8: 76 | HV8: 76 | HW8: 76 | HX8: 77 | HY8: 77 | HZ8: 77 | IA8: 78 | IB8: 78 | IC8: 78 | ID8: 79 | IE8: 79 | IF8: 79 | IG8: 80 | IH8: 80 | II8: 80 | IJ8: 81 | IK8: 81 | IL8: 81 | IM8: 82 | IN8: 82 | IO8: 82 | IP8: 83 | IQ8: 83 | IR8: 83 | IS8: 84 | IT8: 84 | IU8: 84 | IV8: 85 | IW8: 85 | IX8: 85 | IY8: 86 | IZ8: 86 | JA8: 86 | JB8: 87 | JC8: 87 | JD8: 87 | JE8: 88 | JF8: 88 | JG8: 88 | JH8: 89 | JI8: 89 | JJ8: 89 | JK8: 90 | JL8: 90 | JM8: 90 | JN8: 91 | JO8: 91 | JP8: 91 | JQ8: 92 | JR8: 92 | JS8: 92 | JT8: 93 | JU8: 93 | JV8: 93 | JW8: 94 | JX8: 94 | JY8: 94 | JZ8: 95 | KA8: 95 | KB8: 95 | KC8: 96 | KD8: 96 | KE8: 96 | KF8: 97 | KG8: 97 | KH8: 97 | KI8: 98 | KJ8: 98 | KK8: 98 | KL8: 99 | KM8: 99 | KN8: 99 | KO8: 100 | KP8: 100 | KQ8: 100 | KR8: 101 | KS8: 101 | KT8: 101 | KU8: 102 | KV8: 102 | KW8: 102 | KX8: 103 | KY8: 103 | KZ8: 103 | LA8: 104 | LB8: 104 | LC8: 104 | LD8: 105 | LE8: 105 | LF8: 105 | LG8: 106 | LH8: 106 | LI8: 106
B9: Produccion efectiva, kg DBO5 | D9: 0 | E9: 0 | F9: 0 | G9: 0 | H9: 0 | I9: 0 | J9: 0 | K9: 0 | L9: 0 | M9: 0 | N9: 0 | O9: 0 | P9: 0 | Q9: 0 | R9: 0 | S9: 0 | T9: 0 | U9: 0 | V9: 0 | W9: 0 | X9: 0 | Y9: 0 | Z9: 0 | AA9: 0 | AB9: 0 | AC9: 0 | AD9: 0 | AE9: 0 | AF9: 0 | AG9: 0 | AH9: 0 | AI9: 0 | AJ9: 0 | AK9: 0 | AL9: 0 | AM9: 0 | AN9: 0 | AO9: 0 | AP9: 0 | AQ9: 0 | AR9: 0 | AS9: 0 | AT9: 0 | AU9: 0 | AV9: 0 | AW9: 0 | AX9: 0 | AY9: 0 | AZ9: 558467.34 | BA9: 558467.34 | BB9: 558467.34 | BC9: 565769.15 | BD9: 565769.15 | BE9: 565769.15 | BF9: 565769.15 | BG9: 565769.15 | BH9: 565769.15 | BI9: 565769.15 | BJ9: 565769.15 | BK9: 565769.15 | BL9: 565769.15 | BM9: 565769.15 | BN9: 565769.15 | BO9: 571854 | BP9: 571854 | BQ9: 571854 | BR9: 571854 | BS9: 571854 | BT9: 571854 | BU9: 571854 | BV9: 571854 | BW9: 571854 | BX9: 571854 | BY9: 571854 | BZ9: 571854 | CA9: 576721.88 | CB9: 576721.88 | CC9: 576721.88 | CD9: 576721.88 | CE9: 576721.88 | CF9: 576721.88 | CG9: 576721.88 | CH9: 576721.88 | CI9: 576721.88 | CJ9: 576721.88 | CK9: 576721.88 | CL9: 576721.88 | CM9: 581589.76 | CN9: 581589.76 | CO9: 581589.76 | CP9: 581589.76 | CQ9: 581589.76 | CR9: 581589.76 | CS9: 581589.76 | CT9: 581589.76 | CU9: 581589.76 | CV9: 581589.76 | CW9: 581589.76 | CX9: 581589.76 | CY9: 586457.64 | CZ9: 586457.64 | DA9: 586457.64 | DB9: 586457.64 | DC9: 586457.64 | DD9: 586457.64 | DE9: 586457.64 | DF9: 586457.64 | DG9: 586457.64 | DH9: 586457.64 | DI9: 586457.64 | DJ9: 586457.64 | DK9: 591325.51 | DL9: 591325.51 | DM9: 591325.51 | DN9: 591325.51 | DO9: 591325.51 | DP9: 591325.51 | DQ9: 591325.51 | DR9: 591325.51 | DS9: 591325.51 | DT9: 591325.51 | DU9: 591325.51 | DV9: 591325.51 | DW9: 620532.78 | DX9: 620532.78 | DY9: 620532.78 | DZ9: 620532.78 | EA9: 620532.78 | EB9: 620532.78 | EC9: 620532.78 | ED9: 620532.78 | EE9: 620532.78 | EF9: 620532.78 | EG9: 620532.78 | EH9: 620532.78 | EI9: 626617.63 | EJ9: 626617.63 | EK9: 626617.63 | EL9: 626617.63 | EM9: 626617.63 | EN9: 626617.63 | EO9: 626617.63 | EP9: 626617.63 | EQ9: 626617.63 | ER9: 626617.63 | ES9: 626617.63 | ET9: 626617.63 | EU9: 632702.48 | EV9: 632702.48 | EW9: 632702.48 | EX9: 632702.48 | EY9: 632702.48 | EZ9: 632702.48 | FA9: 632702.48 | FB9: 632702.48 | FC9: 632702.48 | FD9: 632702.48 | FE9: 632702.48 | FF9: 632702.48 | FG9: 640004.3 | FH9: 640004.3 | FI9: 640004.3 | FJ9: 640004.3 | FK9: 640004.3 | FL9: 640004.3 | FM9: 640004.3 | FN9: 640004.3 | FO9: 640004.3 | FP9: 640004.3 | FQ9: 640004.3 | FR9: 640004.3 | FS9: 646089.14 | FT9: 646089.14 | FU9: 646089.14 | FV9: 646089.14 | FW9: 646089.14 | FX9: 646089.14 | FY9: 646089.14 | FZ9: 646089.14 | GA9: 646089.14 | GB9: 646089.14 | GC9: 646089.14 | GD9: 646089.14 | GE9: 653390.96 | GF9: 653390.96 | GG9: 653390.96 | GH9: 653390.96 | GI9: 653390.96 | GJ9: 653390.96 | GK9: 653390.96 | GL9: 653390.96 | GM9: 653390.96 | GN9: 653390.96 | GO9: 653390.96 | GP9: 653390.96 | GQ9: 659475.81 | GR9: 659475.81 | GS9: 659475.81 | GT9: 659475.81 | GU9: 659475.81 | GV9: 659475.81 | GW9: 659475.81 | GX9: 659475.81 | GY9: 659475.81 | GZ9: 659475.81 | HA9: 659475.81 | HB9: 659475.81 | HC9: 666777.63 | HD9: 666777.63 | HE9: 666777.63 | HF9: 666777.63 | HG9: 666777.63 | HH9: 666777.63 | HI9: 666777.63 | HJ9: 666777.63 | HK9: 666777.63 | HL9: 666777.63 | HM9: 666777.63 | HN9: 666777.63 | HO9: 674079.44 | HP9: 674079.44 | HQ9: 674079.44 | HR9: 674079.44 | HS9: 674079.44 | HT9: 674079.44 | HU9: 674079.44 | HV9: 674079.44 | HW9: 674079.44 | HX9: 674079.44 | HY9: 674079.44 | HZ9: 674079.44 | IA9: 681381.26 | IB9: 681381.26 | IC9: 681381.26 | ID9: 681381.26 | IE9: 681381.26 | IF9: 681381.26 | IG9: 681381.26 | IH9: 681381.26 | II9: 681381.26 | IJ9: 681381.26 | IK9: 681381.26 | IL9: 681381.26 | IM9: 688683.08 | IN9: 688683.08 | IO9: 688683.08 | IP9: 688683.08 | IQ9: 688683.08 | IR9: 688683.08 | IS9: 688683.08 | IT9: 688683.08 | IU9: 688683.08 | IV9: 688683.08 | IW9: 688683.08 | IX9: 688683.08 | IY9: 695984.9 | IZ9: 695984.9 | JA9: 695984.9 | JB9: 695984.9 | JC9: 695984.9 | JD9: 695984.9 | JE9: 695984.9 | JF9: 695984.9 | JG9: 695984.9 | JH9: 695984.9 | JI9: 695984.9 | JJ9: 695984.9 | JK9: 703286.71 | JL9: 703286.71 | JM9: 703286.71 | JN9: 703286.71 | JO9: 703286.71 | JP9: 703286.71 | JQ9: 703286.71 | JR9: 703286.71 | JS9: 703286.71 | JT9: 703286.71 | JU9: 703286.71 | JV9: 703286.71 | JW9: 711805.5 | JX9: 711805.5 | JY9: 711805.5 | JZ9: 711805.5 | KA9: 711805.5 | KB9: 711805.5 | KC9: 711805.5 | KD9: 711805.5 | KE9: 711805.5 | KF9: 711805.5 | KG9: 711805.5 | KH9: 711805.5 | KI9: 720324.29 | KJ9: 720324.29 | KK9: 720324.29 | KL9: 720324.29 | KM9: 720324.29 | KN9: 720324.29 | KO9: 720324.29 | KP9: 720324.29 | KQ9: 720324.29 | KR9: 720324.29 | KS9: 720324.29 | KT9: 720324.29 | KU9: 720324.29 | KV9: 720324.29 | KW9: 720324.29 | KX9: 720324.29 | KY9: 720324.29 | KZ9: 720324.29 | LA9: 720324.29 | LB9: 720324.29 | LC9: 720324.29 | LD9: 0 | LE9: 0 | LF9: 0 | LG9: 0 | LH9: 0 | LI9: 0
B10: IPM mensual | D10: =((1+p_ipm)^(1/12)-1)*D7 | E10: =((1+p_ipm)^(1/12)-1)*E7 | F10: =((1+p_ipm)^(1/12)-1)*F7 | G10: =((1+p_ipm)^(1/12)-1)*G7 | H10: =((1+p_ipm)^(1/12)-1)*H7 | I10: =((1+p_ipm)^(1/12)-1)*I7 | J10: =((1+p_ipm)^(1/12)-1)*J7 | K10: =((1+p_ipm)^(1/12)-1)*K7 | ... LI10: =((1+p_ipm)^(1/12)-1)*LI7
B11: Acumulado pendiente | D11: =IF($D10=0,0,$D10) | E11: =IF(E10=0,0,SUM($D10:E10)-SUM($D12:D12)) | F11: =IF(F10=0,0,SUM($D10:F10)-SUM($D12:E12)) | G11: =IF(G10=0,0,SUM($D10:G10)-SUM($D12:F12)) | H11: =IF(H10=0,0,SUM($D10:H10)-SUM($D12:G12)) | I11: =IF(I10=0,0,SUM($D10:I10)-SUM($D12:H12)) | J11: =IF(J10=0,0,SUM($D10:J10)-SUM($D12:I12)) | K11: =IF(K10=0,0,SUM($D10:K10)-SUM($D12:J12)) | L11: =IF(L10=0,0,SUM($D10:L10)-SUM($D12:K12)) | ... LI11: =IF(LI10=0,0,SUM($D10:LI10)-SUM($D12:LH12))
B12: Ajuste liberado | D12: =IF(D11>=p_gatillo,D11,0) | E12: =IF(E11>=p_gatillo,E11,0) | F12: =IF(F11>=p_gatillo,F11,0) | G12: =IF(G11>=p_gatillo,G11,0) | H12: =IF(H11>=p_gatillo,H11,0) | I12: =IF(I11>=p_gatillo,I11,0) | J12: =IF(J11>=p_gatillo,J11,0) | K12: =IF(K11>=p_gatillo,K11,0) | ... LI12: =IF(LI11>=p_gatillo,LI11,0)
B13: Factor de reajuste | D13: =TRUNC(IF(D7=0,1,1*(1+D12)*D7),5) | E13: =TRUNC(IF(E7=0,1,D13*(1+E12)*E7),5) | F13: =TRUNC(IF(F7=0,1,E13*(1+F12)*F7),5) | G13: =TRUNC(IF(G7=0,1,F13*(1+G12)*G7),5) | H13: =TRUNC(IF(H7=0,1,G13*(1+H12)*H7),5) | I13: =TRUNC(IF(I7=0,1,H13*(1+I12)*I7),5) | J13: =TRUNC(IF(J7=0,1,I13*(1+J12)*J7),5) | K13: =TRUNC(IF(K7=0,1,J13*(1+K12)*K7),5) | L13: =TRUNC(IF(L7=0,1,K13*(1+L12)*L7),5) | ... LI13: =TRUNC(IF(LI7=0,1,LH13*(1+LI12)*LI7),5)
B14: Ingreso tarifario mensual | D14: =IF(D7=0,0,p_tarifa_usuario*D9*D13)/1000 | E14: =IF(E7=0,0,p_tarifa_usuario*E9*E13)/1000 | F14: =IF(F7=0,0,p_tarifa_usuario*F9*F13)/1000 | G14: =IF(G7=0,0,p_tarifa_usuario*G9*G13)/1000 | H14: =IF(H7=0,0,p_tarifa_usuario*H9*H13)/1000 | I14: =IF(I7=0,0,p_tarifa_usuario*I9*I13)/1000 | J14: =IF(J7=0,0,p_tarifa_usuario*J9*J13)/1000 | K14: =IF(K7=0,0,p_tarifa_usuario*K9*K13)/1000 | ... LI14: =IF(LI7=0,0,p_tarifa_usuario*LI9*LI13)/1000
B15: Primer mes de operacion | D15: =IF(AND(D7=1,0=0),1,0) | E15: =IF(AND(E7=1,SUM($D7:D7)=0),1,0) | F15: =IF(AND(F7=1,SUM($D7:E7)=0),1,0) | G15: =IF(AND(G7=1,SUM($D7:F7)=0),1,0) | H15: =IF(AND(H7=1,SUM($D7:G7)=0),1,0) | I15: =IF(AND(I7=1,SUM($D7:H7)=0),1,0) | J15: =IF(AND(J7=1,SUM($D7:I7)=0),1,0) | K15: =IF(AND(K7=1,SUM($D7:J7)=0),1,0) | L15: =IF(AND(L7=1,SUM($D7:K7)=0),1,0) | ... LI15: =IF(AND(LI7=1,SUM($D7:LH7)=0),1,0)

Sheet Activo intangible
B2: Activo intangible de la concesion
B3: CINIIF 12 p.17: derecho a cobrar al usuario, no importe determinable del concedente. p.22: intereses de obra capitalizados.
B6: Mes | D6: 2026-10-31 | E6: 2026-11-30 | F6: 2026-12-31 | G6: 2027-01-31 | H6: 2027-02-28 | I6: 2027-03-31 | J6: 2027-04-30 | K6: 2027-05-31 | L6: 2027-06-30 | M6: 2027-07-31 | N6: 2027-08-31 | O6: 2027-09-30 | P6: 2027-10-31 | Q6: 2027-11-30 | R6: 2027-12-31 | S6: 2028-01-31 | T6: 2028-02-29 | U6: 2028-03-31 | V6: 2028-04-30 | W6: 2028-05-31 | X6: 2028-06-30 | Y6: 2028-07-31 | Z6: 2028-08-31 | AA6: 2028-09-30 | AB6: 2028-10-31 | AC6: 2028-11-30 | AD6: 2028-12-31 | AE6: 2029-01-31 | AF6: 2029-02-28 | AG6: 2029-03-31 | AH6: 2029-04-30 | AI6: 2029-05-31 | AJ6: 2029-06-30 | AK6: 2029-07-31 | AL6: 2029-08-31 | AM6: 2029-09-30 | AN6: 2029-10-31 | AO6: 2029-11-30 | AP6: 2029-12-31 | AQ6: 2030-01-31 | AR6: 2030-02-28 | AS6: 2030-03-31 | AT6: 2030-04-30 | AU6: 2030-05-31 | AV6: 2030-06-30 | AW6: 2030-07-31 | AX6: 2030-08-31 | AY6: 2030-09-30 | AZ6: 2030-10-31 | BA6: 2030-11-30 | BB6: 2030-12-31 | BC6: 2031-01-31 | BD6: 2031-02-28 | BE6: 2031-03-31 | BF6: 2031-04-30 | BG6: 2031-05-31 | BH6: 2031-06-30 | BI6: 2031-07-31 | BJ6: 2031-08-31 | BK6: 2031-09-30 | BL6: 2031-10-31 | BM6: 2031-11-30 | BN6: 2031-12-31 | BO6: 2032-01-31 | BP6: 2032-02-29 | BQ6: 2032-03-31 | BR6: 2032-04-30 | BS6: 2032-05-31 | BT6: 2032-06-30 | BU6: 2032-07-31 | BV6: 2032-08-31 | BW6: 2032-09-30 | BX6: 2032-10-31 | BY6: 2032-11-30 | BZ6: 2032-12-31 | CA6: 2033-01-31 | CB6: 2033-02-28 | CC6: 2033-03-31 | CD6: 2033-04-30 | CE6: 2033-05-31 | CF6: 2033-06-30 | CG6: 2033-07-31 | CH6: 2033-08-31 | CI6: 2033-09-30 | CJ6: 2033-10-31 | CK6: 2033-11-30 | CL6: 2033-12-31 | CM6: 2034-01-31 | CN6: 2034-02-28 | CO6: 2034-03-31 | CP6: 2034-04-30 | CQ6: 2034-05-31 | CR6: 2034-06-30 | CS6: 2034-07-31 | CT6: 2034-08-31 | CU6: 2034-09-30 | CV6: 2034-10-31 | CW6: 2034-11-30 | CX6: 2034-12-31 | CY6: 2035-01-31 | CZ6: 2035-02-28 | DA6: 2035-03-31 | DB6: 2035-04-30 | DC6: 2035-05-31 | DD6: 2035-06-30 | DE6: 2035-07-31 | DF6: 2035-08-31 | DG6: 2035-09-30 | DH6: 2035-10-31 | DI6: 2035-11-30 | DJ6: 2035-12-31 | DK6: 2036-01-31 | DL6: 2036-02-29 | DM6: 2036-03-31 | DN6: 2036-04-30 | DO6: 2036-05-31 | DP6: 2036-06-30 | DQ6: 2036-07-31 | DR6: 2036-08-31 | DS6: 2036-09-30 | DT6: 2036-10-31 | DU6: 2036-11-30 | DV6: 2036-12-31 | DW6: 2037-01-31 | DX6: 2037-02-28 | DY6: 2037-03-31 | DZ6: 2037-04-30 | EA6: 2037-05-31 | EB6: 2037-06-30 | EC6: 2037-07-31 | ED6: 2037-08-31 | EE6: 2037-09-30 | EF6: 2037-10-31 | EG6: 2037-11-30 | EH6: 2037-12-31 | EI6: 2038-01-31 | EJ6: 2038-02-28 | EK6: 2038-03-31 | EL6: 2038-04-30 | EM6: 2038-05-31 | EN6: 2038-06-30 | EO6: 2038-07-31 | EP6: 2038-08-31 | EQ6: 2038-09-30 | ER6: 2038-10-31 | ES6: 2038-11-30 | ET6: 2038-12-31 | EU6: 2039-01-31 | EV6: 2039-02-28 | EW6: 2039-03-31 | EX6: 2039-04-30 | EY6: 2039-05-31 | EZ6: 2039-06-30 | FA6: 2039-07-31 | FB6: 2039-08-31 | FC6: 2039-09-30 | FD6: 2039-10-31 | FE6: 2039-11-30 | FF6: 2039-12-31 | FG6: 2040-01-31 | FH6: 2040-02-29 | FI6: 2040-03-31 | FJ6: 2040-04-30 | FK6: 2040-05-31 | FL6: 2040-06-30 | FM6: 2040-07-31 | FN6: 2040-08-31 | FO6: 2040-09-30 | FP6: 2040-10-31 | FQ6: 2040-11-30 | FR6: 2040-12-31 | FS6: 2041-01-31 | FT6: 2041-02-28 | FU6: 2041-03-31 | FV6: 2041-04-30 | FW6: 2041-05-31 | FX6: 2041-06-30 | FY6: 2041-07-31 | FZ6: 2041-08-31 | GA6: 2041-09-30 | GB6: 2041-10-31 | GC6: 2041-11-30 | GD6: 2041-12-31 | GE6: 2042-01-31 | GF6: 2042-02-28 | GG6: 2042-03-31 | GH6: 2042-04-30 | GI6: 2042-05-31 | GJ6: 2042-06-30 | GK6: 2042-07-31 | GL6: 2042-08-31 | GM6: 2042-09-30 | GN6: 2042-10-31 | GO6: 2042-11-30 | GP6: 2042-12-31 | GQ6: 2043-01-31 | GR6: 2043-02-28 | GS6: 2043-03-31 | GT6: 2043-04-30 | GU6: 2043-05-31 | GV6: 2043-06-30 | GW6: 2043-07-31 | GX6: 2043-08-31 | GY6: 2043-09-30 | GZ6: 2043-10-31 | HA6: 2043-11-30 | HB6: 2043-12-31 | HC6: 2044-01-31 | HD6: 2044-02-29 | HE6: 2044-03-31 | HF6: 2044-04-30 | HG6: 2044-05-31 | HH6: 2044-06-30 | HI6: 2044-07-31 | HJ6: 2044-08-31 | HK6: 2044-09-30 | HL6: 2044-10-31 | HM6: 2044-11-30 | HN6: 2044-12-31 | HO6: 2045-01-31 | HP6: 2045-02-28 | HQ6: 2045-03-31 | HR6: 2045-04-30 | HS6: 2045-05-31 | HT6: 2045-06-30 | HU6: 2045-07-31 | HV6: 2045-08-31 | HW6: 2045-09-30 | HX6: 2045-10-31 | HY6: 2045-11-30 | HZ6: 2045-12-31 | IA6: 2046-01-31 | IB6: 2046-02-28 | IC6: 2046-03-31 | ID6: 2046-04-30 | IE6: 2046-05-31 | IF6: 2046-06-30 | IG6: 2046-07-31 | IH6: 2046-08-31 | II6: 2046-09-30 | IJ6: 2046-10-31 | IK6: 2046-11-30 | IL6: 2046-12-31 | IM6: 2047-01-31 | IN6: 2047-02-28 | IO6: 2047-03-31 | IP6: 2047-04-30 | IQ6: 2047-05-31 | IR6: 2047-06-30 | IS6: 2047-07-31 | IT6: 2047-08-31 | IU6: 2047-09-30 | IV6: 2047-10-31 | IW6: 2047-11-30 | IX6: 2047-12-31 | IY6: 2048-01-31 | IZ6: 2048-02-29 | JA6: 2048-03-31 | JB6: 2048-04-30 | JC6: 2048-05-31 | JD6: 2048-06-30 | JE6: 2048-07-31 | JF6: 2048-08-31 | JG6: 2048-09-30 | JH6: 2048-10-31 | JI6: 2048-11-30 | JJ6: 2048-12-31 | JK6: 2049-01-31 | JL6: 2049-02-28 | JM6: 2049-03-31 | JN6: 2049-04-30 | JO6: 2049-05-31 | JP6: 2049-06-30 | JQ6: 2049-07-31 | JR6: 2049-08-31 | JS6: 2049-09-30 | JT6: 2049-10-31 | JU6: 2049-11-30 | JV6: 2049-12-31 | JW6: 2050-01-31 | JX6: 2050-02-28 | JY6: 2050-03-31 | JZ6: 2050-04-30 | KA6: 2050-05-31 | KB6: 2050-06-30 | KC6: 2050-07-31 | KD6: 2050-08-31 | KE6: 2050-09-30 | KF6: 2050-10-31 | KG6: 2050-11-30 | KH6: 2050-12-31 | KI6: 2051-01-31 | KJ6: 2051-02-28 | KK6: 2051-03-31 | KL6: 2051-04-30 | KM6: 2051-05-31 | KN6: 2051-06-30 | KO6: 2051-07-31 | KP6: 2051-08-31 | KQ6: 2051-09-30 | KR6: 2051-10-31 | KS6: 2051-11-30 | KT6: 2051-12-31 | KU6: 2052-01-31 | KV6: 2052-02-29 | KW6: 2052-03-31 | KX6: 2052-04-30 | KY6: 2052-05-31 | KZ6: 2052-06-30 | LA6: 2052-07-31 | LB6: 2052-08-31 | LC6: 2052-09-30 | LD6: 2052-10-31 | LE6: 2052-11-30 | LF6: 2052-12-31 | LG6: 2053-01-31 | LH6: 2053-02-28 | LI6: 2053-03-31
B7: Meses de operacion | D7: =SUM($D$12:$LI$12)
B8: Base del intangible al termino de obra | D8: =SUM($D$16:$LI$16)
B9: Amortizacion lineal mensual | D9: =$D$8/$D$7
B10: Trimestre del mes | D10: 1 | E10: 1 | F10: 1 | G10: 2 | H10: 2 | I10: 2 | J10: 3 | K10: 3 | L10: 3 | M10: 4 | N10: 4 | O10: 4 | P10: 5 | Q10: 5 | R10: 5 | S10: 6 | T10: 6 | U10: 6 | V10: 7 | W10: 7 | X10: 7 | Y10: 8 | Z10: 8 | AA10: 8 | AB10: 9 | AC10: 9 | AD10: 9 | AE10: 10 | AF10: 10 | AG10: 10 | AH10: 11 | AI10: 11 | AJ10: 11 | AK10: 12 | AL10: 12 | AM10: 12 | AN10: 13 | AO10: 13 | AP10: 13 | AQ10: 14 | AR10: 14 | AS10: 14 | AT10: 15 | AU10: 15 | AV10: 15 | AW10: 16 | AX10: 16 | AY10: 16 | AZ10: 17 | BA10: 17 | BB10: 17 | BC10: 18 | BD10: 18 | BE10: 18 | BF10: 19 | BG10: 19 | BH10: 19 | BI10: 20 | BJ10: 20 | BK10: 20 | BL10: 21 | BM10: 21 | BN10: 21 | BO10: 22 | BP10: 22 | BQ10: 22 | BR10: 23 | BS10: 23 | BT10: 23 | BU10: 24 | BV10: 24 | BW10: 24 | BX10: 25 | BY10: 25 | BZ10: 25 | CA10: 26 | CB10: 26 | CC10: 26 | CD10: 27 | CE10: 27 | CF10: 27 | CG10: 28 | CH10: 28 | CI10: 28 | CJ10: 29 | CK10: 29 | CL10: 29 | CM10: 30 | CN10: 30 | CO10: 30 | CP10: 31 | CQ10: 31 | CR10: 31 | CS10: 32 | CT10: 32 | CU10: 32 | CV10: 33 | CW10: 33 | CX10: 33 | CY10: 34 | CZ10: 34 | DA10: 34 | DB10: 35 | DC10: 35 | DD10: 35 | DE10: 36 | DF10: 36 | DG10: 36 | DH10: 37 | DI10: 37 | DJ10: 37 | DK10: 38 | DL10: 38 | DM10: 38 | DN10: 39 | DO10: 39 | DP10: 39 | DQ10: 40 | DR10: 40 | DS10: 40 | DT10: 41 | DU10: 41 | DV10: 41 | DW10: 42 | DX10: 42 | DY10: 42 | DZ10: 43 | EA10: 43 | EB10: 43 | EC10: 44 | ED10: 44 | EE10: 44 | EF10: 45 | EG10: 45 | EH10: 45 | EI10: 46 | EJ10: 46 | EK10: 46 | EL10: 47 | EM10: 47 | EN10: 47 | EO10: 48 | EP10: 48 | EQ10: 48 | ER10: 49 | ES10: 49 | ET10: 49 | EU10: 50 | EV10: 50 | EW10: 50 | EX10: 51 | EY10: 51 | EZ10: 51 | FA10: 52 | FB10: 52 | FC10: 52 | FD10: 53 | FE10: 53 | FF10: 53 | FG10: 54 | FH10: 54 | FI10: 54 | FJ10: 55 | FK10: 55 | FL10: 55 | FM10: 56 | FN10: 56 | FO10: 56 | FP10: 57 | FQ10: 57 | FR10: 57 | FS10: 58 | FT10: 58 | FU10: 58 | FV10: 59 | FW10: 59 | FX10: 59 | FY10: 60 | FZ10: 60 | GA10: 60 | GB10: 61 | GC10: 61 | GD10: 61 | GE10: 62 | GF10: 62 | GG10: 62 | GH10: 63 | GI10: 63 | GJ10: 63 | GK10: 64 | GL10: 64 | GM10: 64 | GN10: 65 | GO10: 65 | GP10: 65 | GQ10: 66 | GR10: 66 | GS10: 66 | GT10: 67 | GU10: 67 | GV10: 67 | GW10: 68 | GX10: 68 | GY10: 68 | GZ10: 69 | HA10: 69 | HB10: 69 | HC10: 70 | HD10: 70 | HE10: 70 | HF10: 71 | HG10: 71 | HH10: 71 | HI10: 72 | HJ10: 72 | HK10: 72 | HL10: 73 | HM10: 73 | HN10: 73 | HO10: 74 | HP10: 74 | HQ10: 74 | HR10: 75 | HS10: 75 | HT10: 75 | HU10: 76 | HV10: 76 | HW10: 76 | HX10: 77 | HY10: 77 | HZ10: 77 | IA10: 78 | IB10: 78 | IC10: 78 | ID10: 79 | IE10: 79 | IF10: 79 | IG10: 80 | IH10: 80 | II10: 80 | IJ10: 81 | IK10: 81 | IL10: 81 | IM10: 82 | IN10: 82 | IO10: 82 | IP10: 83 | IQ10: 83 | IR10: 83 | IS10: 84 | IT10: 84 | IU10: 84 | IV10: 85 | IW10: 85 | IX10: 85 | IY10: 86 | IZ10: 86 | JA10: 86 | JB10: 87 | JC10: 87 | JD10: 87 | JE10: 88 | JF10: 88 | JG10: 88 | JH10: 89 | JI10: 89 | JJ10: 89 | JK10: 90 | JL10: 90 | JM10: 90 | JN10: 91 | JO10: 91 | JP10: 91 | JQ10: 92 | JR10: 92 | JS10: 92 | JT10: 93 | JU10: 93 | JV10: 93 | JW10: 94 | JX10: 94 | JY10: 94 | JZ10: 95 | KA10: 95 | KB10: 95 | KC10: 96 | KD10: 96 | KE10: 96 | KF10: 97 | KG10: 97 | KH10: 97 | KI10: 98 | KJ10: 98 | KK10: 98 | KL10: 99 | KM10: 99 | KN10: 99 | KO10: 100 | KP10: 100 | KQ10: 100 | KR10: 101 | KS10: 101 | KT10: 101 | KU10: 102 | KV10: 102 | KW10: 102 | KX10: 103 | KY10: 103 | KZ10: 103 | LA10: 104 | LB10: 104 | LC10: 104 | LD10: 105 | LE10: 105 | LF10: 105 | LG10: 106 | LH10: 106 | LI10: 106
B11: Flag anterior a la operacion | D11: 1 | E11: 1 | F11: 1 | G11: 1 | H11: 1 | I11: 1 | J11: 1 | K11: 1 | L11: 1 | M11: 1 | N11: 1 | O11: 1 | P11: 1 | Q11: 1 | R11: 1 | S11: 1 | T11: 1 | U11: 1 | V11: 1 | W11: 1 | X11: 1 | Y11: 1 | Z11: 1 | AA11: 1 | AB11: 1 | AC11: 1 | AD11: 1 | AE11: 1 | AF11: 1 | AG11: 1 | AH11: 1 | AI11: 1 | AJ11: 1 | AK11: 1 | AL11: 1 | AM11: 1 | AN11: 1 | AO11: 1 | AP11: 1 | AQ11: 1 | AR11: 1 | AS11: 1 | AT11: 1 | AU11: 1 | AV11: 1 | AW11: 1 | AX11: 1 | AY11: 1 | AZ11: 0 | BA11: 0 | BB11: 0 | BC11: 0 | BD11: 0 | BE11: 0 | BF11: 0 | BG11: 0 | BH11: 0 | BI11: 0 | BJ11: 0 | BK11: 0 | BL11: 0 | BM11: 0 | BN11: 0 | BO11: 0 | BP11: 0 | BQ11: 0 | BR11: 0 | BS11: 0 | BT11: 0 | BU11: 0 | BV11: 0 | BW11: 0 | BX11: 0 | BY11: 0 | BZ11: 0 | CA11: 0 | CB11: 0 | CC11: 0 | CD11: 0 | CE11: 0 | CF11: 0 | CG11: 0 | CH11: 0 | CI11: 0 | CJ11: 0 | CK11: 0 | CL11: 0 | CM11: 0 | CN11: 0 | CO11: 0 | CP11: 0 | CQ11: 0 | CR11: 0 | CS11: 0 | CT11: 0 | CU11: 0 | CV11: 0 | CW11: 0 | CX11: 0 | CY11: 0 | CZ11: 0 | DA11: 0 | DB11: 0 | DC11: 0 | DD11: 0 | DE11: 0 | DF11: 0 | DG11: 0 | DH11: 0 | DI11: 0 | DJ11: 0 | DK11: 0 | DL11: 0 | DM11: 0 | DN11: 0 | DO11: 0 | DP11: 0 | DQ11: 0 | DR11: 0 | DS11: 0 | DT11: 0 | DU11: 0 | DV11: 0 | DW11: 0 | DX11: 0 | DY11: 0 | DZ11: 0 | EA11: 0 | EB11: 0 | EC11: 0 | ED11: 0 | EE11: 0 | EF11: 0 | EG11: 0 | EH11: 0 | EI11: 0 | EJ11: 0 | EK11: 0 | EL11: 0 | EM11: 0 | EN11: 0 | EO11: 0 | EP11: 0 | EQ11: 0 | ER11: 0 | ES11: 0 | ET11: 0 | EU11: 0 | EV11: 0 | EW11: 0 | EX11: 0 | EY11: 0 | EZ11: 0 | FA11: 0 | FB11: 0 | FC11: 0 | FD11: 0 | FE11: 0 | FF11: 0 | FG11: 0 | FH11: 0 | FI11: 0 | FJ11: 0 | FK11: 0 | FL11: 0 | FM11: 0 | FN11: 0 | FO11: 0 | FP11: 0 | FQ11: 0 | FR11: 0 | FS11: 0 | FT11: 0 | FU11: 0 | FV11: 0 | FW11: 0 | FX11: 0 | FY11: 0 | FZ11: 0 | GA11: 0 | GB11: 0 | GC11: 0 | GD11: 0 | GE11: 0 | GF11: 0 | GG11: 0 | GH11: 0 | GI11: 0 | GJ11: 0 | GK11: 0 | GL11: 0 | GM11: 0 | GN11: 0 | GO11: 0 | GP11: 0 | GQ11: 0 | GR11: 0 | GS11: 0 | GT11: 0 | GU11: 0 | GV11: 0 | GW11: 0 | GX11: 0 | GY11: 0 | GZ11: 0 | HA11: 0 | HB11: 0 | HC11: 0 | HD11: 0 | HE11: 0 | HF11: 0 | HG11: 0 | HH11: 0 | HI11: 0 | HJ11: 0 | HK11: 0 | HL11: 0 | HM11: 0 | HN11: 0 | HO11: 0 | HP11: 0 | HQ11: 0 | HR11: 0 | HS11: 0 | HT11: 0 | HU11: 0 | HV11: 0 | HW11: 0 | HX11: 0 | HY11: 0 | HZ11: 0 | IA11: 0 | IB11: 0 | IC11: 0 | ID11: 0 | IE11: 0 | IF11: 0 | IG11: 0 | IH11: 0 | II11: 0 | IJ11: 0 | IK11: 0 | IL11: 0 | IM11: 0 | IN11: 0 | IO11: 0 | IP11: 0 | IQ11: 0 | IR11: 0 | IS11: 0 | IT11: 0 | IU11: 0 | IV11: 0 | IW11: 0 | IX11: 0 | IY11: 0 | IZ11: 0 | JA11: 0 | JB11: 0 | JC11: 0 | JD11: 0 | JE11: 0 | JF11: 0 | JG11: 0 | JH11: 0 | JI11: 0 | JJ11: 0 | JK11: 0 | JL11: 0 | JM11: 0 | JN11: 0 | JO11: 0 | JP11: 0 | JQ11: 0 | JR11: 0 | JS11: 0 | JT11: 0 | JU11: 0 | JV11: 0 | JW11: 0 | JX11: 0 | JY11: 0 | JZ11: 0 | KA11: 0 | KB11: 0 | KC11: 0 | KD11: 0 | KE11: 0 | KF11: 0 | KG11: 0 | KH11: 0 | KI11: 0 | KJ11: 0 | KK11: 0 | KL11: 0 | KM11: 0 | KN11: 0 | KO11: 0 | KP11: 0 | KQ11: 0 | KR11: 0 | KS11: 0 | KT11: 0 | KU11: 0 | KV11: 0 | KW11: 0 | KX11: 0 | KY11: 0 | KZ11: 0 | LA11: 0 | LB11: 0 | LC11: 0 | LD11: 0 | LE11: 0 | LF11: 0 | LG11: 0 | LH11: 0 | LI11: 0
B12: Flag de operacion | D12: 0 | E12: 0 | F12: 0 | G12: 0 | H12: 0 | I12: 0 | J12: 0 | K12: 0 | L12: 0 | M12: 0 | N12: 0 | O12: 0 | P12: 0 | Q12: 0 | R12: 0 | S12: 0 | T12: 0 | U12: 0 | V12: 0 | W12: 0 | X12: 0 | Y12: 0 | Z12: 0 | AA12: 0 | AB12: 0 | AC12: 0 | AD12: 0 | AE12: 0 | AF12: 0 | AG12: 0 | AH12: 0 | AI12: 0 | AJ12: 0 | AK12: 0 | AL12: 0 | AM12: 0 | AN12: 0 | AO12: 0 | AP12: 0 | AQ12: 0 | AR12: 0 | AS12: 0 | AT12: 0 | AU12: 0 | AV12: 0 | AW12: 0 | AX12: 0 | AY12: 0 | AZ12: 1 | BA12: 1 | BB12: 1 | BC12: 1 | BD12: 1 | BE12: 1 | BF12: 1 | BG12: 1 | BH12: 1 | BI12: 1 | BJ12: 1 | BK12: 1 | BL12: 1 | BM12: 1 | BN12: 1 | BO12: 1 | BP12: 1 | BQ12: 1 | BR12: 1 | BS12: 1 | BT12: 1 | BU12: 1 | BV12: 1 | BW12: 1 | BX12: 1 | BY12: 1 | BZ12: 1 | CA12: 1 | CB12: 1 | CC12: 1 | CD12: 1 | CE12: 1 | CF12: 1 | CG12: 1 | CH12: 1 | CI12: 1 | CJ12: 1 | CK12: 1 | CL12: 1 | CM12: 1 | CN12: 1 | CO12: 1 | CP12: 1 | CQ12: 1 | CR12: 1 | CS12: 1 | CT12: 1 | CU12: 1 | CV12: 1 | CW12: 1 | CX12: 1 | CY12: 1 | CZ12: 1 | DA12: 1 | DB12: 1 | DC12: 1 | DD12: 1 | DE12: 1 | DF12: 1 | DG12: 1 | DH12: 1 | DI12: 1 | DJ12: 1 | DK12: 1 | DL12: 1 | DM12: 1 | DN12: 1 | DO12: 1 | DP12: 1 | DQ12: 1 | DR12: 1 | DS12: 1 | DT12: 1 | DU12: 1 | DV12: 1 | DW12: 1 | DX12: 1 | DY12: 1 | DZ12: 1 | EA12: 1 | EB12: 1 | EC12: 1 | ED12: 1 | EE12: 1 | EF12: 1 | EG12: 1 | EH12: 1 | EI12: 1 | EJ12: 1 | EK12: 1 | EL12: 1 | EM12: 1 | EN12: 1 | EO12: 1 | EP12: 1 | EQ12: 1 | ER12: 1 | ES12: 1 | ET12: 1 | EU12: 1 | EV12: 1 | EW12: 1 | EX12: 1 | EY12: 1 | EZ12: 1 | FA12: 1 | FB12: 1 | FC12: 1 | FD12: 1 | FE12: 1 | FF12: 1 | FG12: 1 | FH12: 1 | FI12: 1 | FJ12: 1 | FK12: 1 | FL12: 1 | FM12: 1 | FN12: 1 | FO12: 1 | FP12: 1 | FQ12: 1 | FR12: 1 | FS12: 1 | FT12: 1 | FU12: 1 | FV12: 1 | FW12: 1 | FX12: 1 | FY12: 1 | FZ12: 1 | GA12: 1 | GB12: 1 | GC12: 1 | GD12: 1 | GE12: 1 | GF12: 1 | GG12: 1 | GH12: 1 | GI12: 1 | GJ12: 1 | GK12: 1 | GL12: 1 | GM12: 1 | GN12: 1 | GO12: 1 | GP12: 1 | GQ12: 1 | GR12: 1 | GS12: 1 | GT12: 1 | GU12: 1 | GV12: 1 | GW12: 1 | GX12: 1 | GY12: 1 | GZ12: 1 | HA12: 1 | HB12: 1 | HC12: 1 | HD12: 1 | HE12: 1 | HF12: 1 | HG12: 1 | HH12: 1 | HI12: 1 | HJ12: 1 | HK12: 1 | HL12: 1 | HM12: 1 | HN12: 1 | HO12: 1 | HP12: 1 | HQ12: 1 | HR12: 1 | HS12: 1 | HT12: 1 | HU12: 1 | HV12: 1 | HW12: 1 | HX12: 1 | HY12: 1 | HZ12: 1 | IA12: 1 | IB12: 1 | IC12: 1 | ID12: 1 | IE12: 1 | IF12: 1 | IG12: 1 | IH12: 1 | II12: 1 | IJ12: 1 | IK12: 1 | IL12: 1 | IM12: 1 | IN12: 1 | IO12: 1 | IP12: 1 | IQ12: 1 | IR12: 1 | IS12: 1 | IT12: 1 | IU12: 1 | IV12: 1 | IW12: 1 | IX12: 1 | IY12: 1 | IZ12: 1 | JA12: 1 | JB12: 1 | JC12: 1 | JD12: 1 | JE12: 1 | JF12: 1 | JG12: 1 | JH12: 1 | JI12: 1 | JJ12: 1 | JK12: 1 | JL12: 1 | JM12: 1 | JN12: 1 | JO12: 1 | JP12: 1 | JQ12: 1 | JR12: 1 | JS12: 1 | JT12: 1 | JU12: 1 | JV12: 1 | JW12: 1 | JX12: 1 | JY12: 1 | JZ12: 1 | KA12: 1 | KB12: 1 | KC12: 1 | KD12: 1 | KE12: 1 | KF12: 1 | KG12: 1 | KH12: 1 | KI12: 1 | KJ12: 1 | KK12: 1 | KL12: 1 | KM12: 1 | KN12: 1 | KO12: 1 | KP12: 1 | KQ12: 1 | KR12: 1 | KS12: 1 | KT12: 1 | KU12: 1 | KV12: 1 | KW12: 1 | KX12: 1 | KY12: 1 | KZ12: 1 | LA12: 1 | LB12: 1 | LC12: 1 | LD12: 0 | LE12: 0 | LF12: 0 | LG12: 0 | LH12: 0 | LI12: 0
B13: Servicio de construccion del periodo | D13: 9871.0611 | E13: 1436.3191 | F13: 1438.6913 | G13: 1441.0674 | H13: 1443.4474 | I13: 1445.8314 | J13: 1456.5526 | K13: 1458.9445 | L13: 1461.3403 | M13: 1381.0649 | N13: 1383.3321 | O13: 1385.603 | P13: 49.876039 | Q13: 49.94465 | R13: 50.013374 | S13: 133.57997 | T13: 8.3333333 | U13: 8.3333333 | V13: 8.3333333 | W13: 8.3333333 | X13: 8.3333333 | Y13: 47218.558 | Z13: 6404.7806 | AA13: 6410.9541 | AB13: 6417.1378 | AC13: 6423.3317 | AD13: 6429.5359 | AE13: 15912.374 | AF13: 15927.957 | AG13: 15943.566 | AH13: 15959.2 | AI13: 15722.754 | AJ13: 15702.765 | AK13: 13733.555 | AL13: 13722.708 | AM13: 13134.641 | AN13: 13147.561 | AO13: 14866.677 | AP13: 14845.547 | AQ13: 2463.9882 | AR13: 2466.4073 | AS13: 1610.093 | AT13: 1611.6721 | AU13: 197.81015 | AV13: 197.99664 | AW13: 198.18343 | AX13: 198.37054 | AY13: 198.55795 | AZ13: 0 | BA13: 0 | BB13: 0 | BC13: 0 | BD13: 0 | BE13: 0 | BF13: 0 | BG13: 0 | BH13: 0 | BI13: 0 | BJ13: 0 | BK13: 0 | BL13: 0 | BM13: 0 | BN13: 0 | BO13: 0 | BP13: 0 | BQ13: 0 | BR13: 0 | BS13: 0 | BT13: 0 | BU13: 0 | BV13: 0 | BW13: 0 | BX13: 0 | BY13: 0 | BZ13: 0 | CA13: 0 | CB13: 0 | CC13: 0 | CD13: 0 | CE13: 0 | CF13: 0 | CG13: 0 | CH13: 0 | CI13: 0 | CJ13: 0 | CK13: 0 | CL13: 0 | CM13: 0 | CN13: 0 | CO13: 0 | CP13: 0 | CQ13: 0 | CR13: 0 | CS13: 0 | CT13: 0 | CU13: 0 | CV13: 0 | CW13: 0 | CX13: 0 | CY13: 0 | CZ13: 0 | DA13: 0 | DB13: 0 | DC13: 0 | DD13: 0 | DE13: 0 | DF13: 0 | DG13: 0 | DH13: 0 | DI13: 0 | DJ13: 0 | DK13: 0 | DL13: 0 | DM13: 0 | DN13: 0 | DO13: 0 | DP13: 0 | DQ13: 0 | DR13: 0 | DS13: 0 | DT13: 0 | DU13: 0 | DV13: 0 | DW13: 0 | DX13: 0 | DY13: 0 | DZ13: 0 | EA13: 0 | EB13: 0 | EC13: 0 | ED13: 0 | EE13: 0 | EF13: 0 | EG13: 0 | EH13: 0 | EI13: 0 | EJ13: 0 | EK13: 0 | EL13: 0 | EM13: 0 | EN13: 0 | EO13: 0 | EP13: 0 | EQ13: 0 | ER13: 0 | ES13: 0 | ET13: 0 | EU13: 0 | EV13: 0 | EW13: 0 | EX13: 0 | EY13: 0 | EZ13: 0 | FA13: 0 | FB13: 0 | FC13: 0 | FD13: 0 | FE13: 0 | FF13: 0 | FG13: 0 | FH13: 0 | FI13: 0 | FJ13: 0 | FK13: 0 | FL13: 0 | FM13: 0 | FN13: 0 | FO13: 0 | FP13: 0 | FQ13: 0 | FR13: 0 | FS13: 0 | FT13: 0 | FU13: 0 | FV13: 0 | FW13: 0 | FX13: 0 | FY13: 0 | FZ13: 0 | GA13: 0 | GB13: 0 | GC13: 0 | GD13: 0 | GE13: 0 | GF13: 0 | GG13: 0 | GH13: 0 | GI13: 0 | GJ13: 0 | GK13: 0 | GL13: 0 | GM13: 0 | GN13: 0 | GO13: 0 | GP13: 0 | GQ13: 0 | GR13: 0 | GS13: 0 | GT13: 0 | GU13: 0 | GV13: 0 | GW13: 0 | GX13: 0 | GY13: 0 | GZ13: 0 | HA13: 0 | HB13: 0 | HC13: 0 | HD13: 0 | HE13: 0 | HF13: 0 | HG13: 0 | HH13: 0 | HI13: 0 | HJ13: 0 | HK13: 0 | HL13: 0 | HM13: 0 | HN13: 0 | HO13: 0 | HP13: 0 | HQ13: 0 | HR13: 0 | HS13: 0 | HT13: 0 | HU13: 0 | HV13: 0 | HW13: 0 | HX13: 0 | HY13: 0 | HZ13: 0 | IA13: 0 | IB13: 0 | IC13: 0 | ID13: 0 | IE13: 0 | IF13: 0 | IG13: 0 | IH13: 0 | II13: 0 | IJ13: 0 | IK13: 0 | IL13: 0 | IM13: 0 | IN13: 0 | IO13: 0 | IP13: 0 | IQ13: 0 | IR13: 0 | IS13: 0 | IT13: 0 | IU13: 0 | IV13: 0 | IW13: 0 | IX13: 0 | IY13: 0 | IZ13: 0 | JA13: 0 | JB13: 0 | JC13: 0 | JD13: 0 | JE13: 0 | JF13: 0 | JG13: 0 | JH13: 0 | JI13: 0 | JJ13: 0 | JK13: 0 | JL13: 0 | JM13: 0 | JN13: 0 | JO13: 0 | JP13: 0 | JQ13: 0 | JR13: 0 | JS13: 0 | JT13: 0 | JU13: 0 | JV13: 0 | JW13: 0 | JX13: 0 | JY13: 0 | JZ13: 0 | KA13: 0 | KB13: 0 | KC13: 0 | KD13: 0 | KE13: 0 | KF13: 0 | KG13: 0 | KH13: 0 | KI13: 0 | KJ13: 0 | KK13: 0 | KL13: 0 | KM13: 0 | KN13: 0 | KO13: 0 | KP13: 0 | KQ13: 0 | KR13: 0 | KS13: 0 | KT13: 0 | KU13: 0 | KV13: 0 | KW13: 0 | KX13: 0 | KY13: 0 | KZ13: 0 | LA13: 0 | LB13: 0 | LC13: 0 | LD13: 0 | LE13: 0 | LF13: 0 | LG13: 0 | LH13: 0 | LI13: 0
B14: Interes de la deuda del periodo | D14: 0 | E14: 0 | F14: 0 | G14: 0 | H14: 0 | I14: 0 | J14: 0 | K14: 0 | L14: 0 | M14: 0 | N14: 0 | O14: 0 | P14: 0 | Q14: 0 | R14: 0 | S14: 0 | T14: 0 | U14: 0 | V14: 0 | W14: 0 | X14: 0 | Y14: 0 | Z14: 276.02446 | AA14: 318.50763 | AB14: 361.39908 | AC14: 404.7022 | AD14: 448.42042 | AE14: 492.55718 | AF14: 598.14875 | AG14: 704.75767 | AH14: 812.39238 | AI14: 921.06143 | AJ14: 1029.1498 | AK14: 1138.0458 | AL14: 1235.2023 | AM14: 1333.1291 | AN14: 1428.1147 | AO14: 1524.0037 | AP14: 1631.7919 | AQ14: 1740.3745 | AR14: 1770.1526 | AS14: 1800.1963 | AT14: 1824.9772 | AU14: 1849.9744 | AV14: 1866.0739 | AW14: 1882.3049 | AX14: 1898.6685 | AY14: 1915.1658 | AZ14: 1931.7978 | BA14: 1924.6371 | BB14: 1917.4188 | BC14: 1910.1425 | BD14: 1902.8076 | BE14: 1895.4138 | BF14: 1887.9604 | BG14: 1880.4471 | BH14: 1872.8733 | BI14: 1865.2386 | BJ14: 1857.5425 | BK14: 1849.7844 | BL14: 1841.964 | BM14: 1834.0806 | BN14: 1826.1338 | BO14: 1818.1231 | BP14: 1810.0479 | BQ14: 1801.9077 | BR14: 1793.7021 | BS14: 1785.4305 | BT14: 1777.0923 | BU14: 1768.687 | BV14: 1760.2141 | BW14: 1751.673 | BX14: 1743.0633 | BY14: 1734.3842 | BZ14: 1725.6354 | CA14: 1716.8161 | CB14: 1707.9259 | CC14: 1698.9642 | CD14: 1689.9304 | CE14: 1680.8239 | CF14: 1671.6441 | CG14: 1662.3905 | CH14: 1653.0624 | CI14: 1643.6593 | CJ14: 1634.1806 | CK14: 1624.6256 | CL14: 1614.9937 | CM14: 1605.2843 | CN14: 1595.4968 | CO14: 1585.6306 | CP14: 1575.685 | CQ14: 1565.6594 | CR14: 1555.5531 | CS14: 1545.3656 | CT14: 1535.096 | CU14: 1524.7439 | CV14: 1514.3084 | CW14: 1503.789 | CX14: 1493.185 | CY14: 1482.4957 | CZ14: 1471.7203 | DA14: 1460.8583 | DB14: 1449.9089 | DC14: 1438.8714 | DD14: 1427.7451 | DE14: 1416.5293 | DF14: 1405.2233 | DG14: 1393.8263 | DH14: 1382.3376 | DI14: 1370.7565 | DJ14: 1359.0822 | DK14: 1347.314 | DL14: 1335.4511 | DM14: 1323.4928 | DN14: 1311.4383 | DO14: 1299.2868 | DP14: 1287.0375 | DQ14: 1274.6897 | DR14: 1262.2426 | DS14: 1249.6953 | DT14: 1237.047 | DU14: 1224.2971 | DV14: 1211.4445 | DW14: 1198.4885 | DX14: 1185.4283 | DY14: 1172.2631 | DZ14: 1158.9919 | EA14: 1145.6139 | EB14: 1132.1284 | EC14: 1118.5343 | ED14: 1104.8309 | EE14: 1091.0172 | EF14: 1077.0924 | EG14: 1063.0555 | EH14: 1048.9058 | EI14: 1034.6421 | EJ14: 1020.2638 | EK14: 1005.7698 | EL14: 991.15913 | EM14: 976.43094 | EN14: 961.58427 | EO14: 946.61816 | EP14: 931.53164 | EQ14: 916.32375 | ER14: 900.99352 | ES14: 885.53994 | ET14: 869.96205 | EU14: 854.25882 | EV14: 838.42927 | EW14: 822.47236 | EX14: 806.38708 | EY14: 790.17239 | EZ14: 773.82725 | FA14: 757.35062 | FB14: 740.74142 | FC14: 723.99861 | FD14: 707.12109 | FE14: 690.1078 | FF14: 672.95763 | FG14: 655.66949 | FH14: 638.24226 | FI14: 620.67483 | FJ14: 602.96607 | FK14: 585.11484 | FL14: 567.11999 | FM14: 548.98038 | FN14: 530.69483 | FO14: 512.26217 | FP14: 493.68121 | FQ14: 474.95077 | FR14: 456.06965 | FS14: 437.03662 | FT14: 417.85047 | FU14: 398.50997 | FV14: 379.01387 | FW14: 359.36092 | FX14: 339.54986 | FY14: 319.57942 | FZ14: 299.44832 | GA14: 279.15526 | GB14: 258.69894 | GC14: 238.07804 | GD14: 217.29125 | GE14: 196.33723 | GF14: 175.21463 | GG14: 153.9221 | GH14: 132.45827 | GI14: 110.82175 | GJ14: 89.011174 | GK14: 67.025126 | GL14: 44.862198 | GM14: 22.520968 | GN14: -2.2463106e-12 | GO14: -2.2643823e-12 | GP14: -2.2825995e-12 | GQ14: -2.3009632e-12 | GR14: -2.3194747e-12 | GS14: -2.3381351e-12 | GT14: -2.3569456e-12 | GU14: -2.3759075e-12 | GV14: -2.3950219e-12 | GW14: -2.4142901e-12 | GX14: -2.4337133e-12 | GY14: -2.4532927e-12 | GZ14: -2.4730297e-12 | HA14: -2.4929255e-12 | HB14: -2.5129813e-12 | HC14: -2.5331985e-12 | HD14: -2.5535783e-12 | HE14: -2.5741221e-12 | HF14: -2.5948311e-12 | HG14: -2.6157068e-12 | HH14: -2.6367504e-12 | HI14: -2.6579633e-12 | HJ14: -2.6793469e-12 | HK14: -2.7009025e-12 | HL14: -2.7226315e-12 | HM14: -2.7445354e-12 | HN14: -2.7666154e-12 | HO14: -2.7888731e-12 | HP14: -2.8113099e-12 | HQ14: -2.8339271e-12 | HR14: -2.8567263e-12 | HS14: -2.879709e-12 | HT14: -2.9028765e-12 | HU14: -2.9262304e-12 | HV14: -2.9497722e-12 | HW14: -2.9735034e-12 | HX14: -2.9974256e-12 | HY14: -3.0215401e-12 | HZ14: -3.0458487e-12 | IA14: -3.0703529e-12 | IB14: -3.0950541e-12 | IC14: -3.1199542e-12 | ID14: -3.1450545e-12 | IE14: -3.1703568e-12 | IF14: -3.1958626e-12 | IG14: -3.2215736e-12 | IH14: -3.2474915e-12 | II14: -3.2736179e-12 | IJ14: -3.2999544e-12 | IK14: -3.3265029e-12 | IL14: -3.3532649e-12 | IM14: -3.3802423e-12 | IN14: -3.4074366e-12 | IO14: -3.4348498e-12 | IP14: -3.4624835e-12 | IQ14: -3.4903395e-12 | IR14: -3.5184196e-12 | IS14: -3.5467256e-12 | IT14: -3.5752594e-12 | IU14: -3.6040227e-12 | IV14: -3.6330174e-12 | IW14: -3.6622454e-12 | IX14: -3.6917085e-12 | IY14: -3.7214086e-12 | IZ14: -3.7513477e-12 | JA14: -3.7815277e-12 | JB14: -3.8119504e-12 | JC14: -3.842618e-12 | JD14: -3.8735322e-12 | JE14: -3.9046951e-12 | JF14: -3.9361088e-12 | JG14: -3.9677751e-12 | JH14: -3.9996963e-12 | JI14: -4.0318742e-12 | JJ14: -4.064311e-12 | JK14: -4.0970088e-12 | JL14: -4.1299696e-12 | JM14: -4.1631956e-12 | JN14: -4.196689e-12 | JO14: -4.2304517e-12 | JP14: -4.2644861e-12 | JQ14: -4.2987943e-12 | JR14: -4.3333785e-12 | JS14: -4.368241e-12 | JT14: -4.4033839e-12 | JU14: -4.4388095e-12 | JV14: -4.4745202e-12 | JW14: -4.5105181e-12 | JX14: -4.5468057e-12 | JY14: -4.5833852e-12 | JZ14: -4.620259e-12 | KA14: -4.6574294e-12 | KB14: -4.6948989e-12 | KC14: -4.7326698e-12 | KD14: -4.7707446e-12 | KE14: -4.8091257e-12 | KF14: -4.8478155e-12 | KG14: -4.8868167e-12 | KH14: -4.9261316e-12 | KI14: -4.9657628e-12 | KJ14: -5.0057128e-12 | KK14: -5.0459843e-12 | KL14: -5.0865797e-12 | KM14: -5.1275017e-12 | KN14: -5.168753e-12 | KO14: -5.2103361e-12 | KP14: -5.2522537e-12 | KQ14: -5.2945086e-12 | KR14: -5.3371035e-12 | KS14: -5.380041e-12 | KT14: -5.4233239e-12 | KU14: -5.4669551e-12 | KV14: -5.5109373e-12 | KW14: -5.5552733e-12 | KX14: -5.599966e-12 | KY14: -5.6450183e-12 | KZ14: -5.690433e-12 | LA14: -5.7362131e-12 | LB14: -5.7823614e-12 | LC14: -5.8288811e-12 | LD14: -5.875775e-12 | LE14: -5.9230462e-12 | LF14: -5.9706977e-12 | LG14: -6.0187325e-12 | LH14: -6.0671538e-12 | LI14: -6.1159646e-12
B15: Interes capitalizado (solo obra, p.22) | D15: =D14*D11 | E15: =E14*E11 | F15: =F14*F11 | G15: =G14*G11 | H15: =H14*H11 | I15: =I14*I11 | J15: =J14*J11 | K15: =K14*K11 | ... LI15: =LI14*LI11
B16: Adicion al intangible | D16: =D13*D11+D15 | E16: =E13*E11+E15 | F16: =F13*F11+F15 | G16: =G13*G11+G15 | H16: =H13*H11+H15 | I16: =I13*I11+I15 | J16: =J13*J11+J15 | K16: =K13*K11+K15 | ... LI16: =LI13*LI11+LI15
B17: Amortizacion del intangible | D17: =$D$9*D12 | E17: =$D$9*E12 | F17: =$D$9*F12 | G17: =$D$9*G12 | H17: =$D$9*H12 | I17: =$D$9*I12 | J17: =$D$9*J12 | K17: =$D$9*K12 | ... LI17: =$D$9*LI12
B18: Saldo del intangible | D18: =0+D16-D17 | E18: =D18+E16-E17 | F18: =E18+F16-F17 | G18: =F18+G16-G17 | H18: =G18+H16-H17 | I18: =H18+I16-I17 | J18: =I18+J16-J17 | K18: =J18+K16-K17 | L18: =K18+L16-L17 | ... LI18: =LH18+LI16-LI17
B20: Inversion capitalizada | D20: =SUMPRODUCT($D$11:$LI$11,$D$13:$LI$13)
B21: Intereses capitalizados | D21: =SUM($D$15:$LI$15)
B22: Amortizacion acumulada | D22: =SUM($D$17:$LI$17)
B23: Saldo final, debe ser cero | D23: =$LI$18

Sheet Flujo
B2: Flujo de caja financiero
B3: El VAN de la ultima fila es la celda que Buscar Objetivo lleva a cero.
B6: Ano | D6: 2026 | E6: 2027 | F6: 2027 | G6: 2027 | H6: 2027 | I6: 2028 | J6: 2028 | K6: 2028 | L6: 2028 | M6: 2029 | N6: 2029 | O6: 2029 | P6: 2029 | Q6: 2030 | R6: 2030 | S6: 2030 | T6: 2030 | U6: 2031 | V6: 2031 | W6: 2031 | X6: 2031 | Y6: 2032 | Z6: 2032 | AA6: 2032 | AB6: 2032 | AC6: 2033 | AD6: 2033 | AE6: 2033 | AF6: 2033 | AG6: 2034 | AH6: 2034 | AI6: 2034 | AJ6: 2034 | AK6: 2035 | AL6: 2035 | AM6: 2035 | AN6: 2035 | AO6: 2036 | AP6: 2036 | AQ6: 2036 | AR6: 2036 | AS6: 2037 | AT6: 2037 | AU6: 2037 | AV6: 2037 | AW6: 2038 | AX6: 2038 | AY6: 2038 | AZ6: 2038 | BA6: 2039 | BB6: 2039 | BC6: 2039 | BD6: 2039 | BE6: 2040 | BF6: 2040 | BG6: 2040 | BH6: 2040 | BI6: 2041 | BJ6: 2041 | BK6: 2041 | BL6: 2041 | BM6: 2042 | BN6: 2042 | BO6: 2042 | BP6: 2042 | BQ6: 2043 | BR6: 2043 | BS6: 2043 | BT6: 2043 | BU6: 2044 | BV6: 2044 | BW6: 2044 | BX6: 2044 | BY6: 2045 | BZ6: 2045 | CA6: 2045 | CB6: 2045 | CC6: 2046 | CD6: 2046 | CE6: 2046 | CF6: 2046 | CG6: 2047 | CH6: 2047 | CI6: 2047 | CJ6: 2047 | CK6: 2048 | CL6: 2048 | CM6: 2048 | CN6: 2048 | CO6: 2049 | CP6: 2049 | CQ6: 2049 | CR6: 2049 | CS6: 2050 | CT6: 2050 | CU6: 2050 | CV6: 2050 | CW6: 2051 | CX6: 2051 | CY6: 2051 | CZ6: 2051 | DA6: 2052 | DB6: 2052 | DC6: 2052 | DD6: 2052 | DE6: 2053
B7: Trimestre | D7: 1 | E7: 2 | F7: 3 | G7: 4 | H7: 5 | I7: 6 | J7: 7 | K7: 8 | L7: 9 | M7: 10 | N7: 11 | O7: 12 | P7: 13 | Q7: 14 | R7: 15 | S7: 16 | T7: 17 | U7: 18 | V7: 19 | W7: 20 | X7: 21 | Y7: 22 | Z7: 23 | AA7: 24 | AB7: 25 | AC7: 26 | AD7: 27 | AE7: 28 | AF7: 29 | AG7: 30 | AH7: 31 | AI7: 32 | AJ7: 33 | AK7: 34 | AL7: 35 | AM7: 36 | AN7: 37 | AO7: 38 | AP7: 39 | AQ7: 40 | AR7: 41 | AS7: 42 | AT7: 43 | AU7: 44 | AV7: 45 | AW7: 46 | AX7: 47 | AY7: 48 | AZ7: 49 | BA7: 50 | BB7: 51 | BC7: 52 | BD7: 53 | BE7: 54 | BF7: 55 | BG7: 56 | BH7: 57 | BI7: 58 | BJ7: 59 | BK7: 60 | BL7: 61 | BM7: 62 | BN7: 63 | BO7: 64 | BP7: 65 | BQ7: 66 | BR7: 67 | BS7: 68 | BT7: 69 | BU7: 70 | BV7: 71 | BW7: 72 | BX7: 73 | BY7: 74 | BZ7: 75 | CA7: 76 | CB7: 77 | CC7: 78 | CD7: 79 | CE7: 80 | CF7: 81 | CG7: 82 | CH7: 83 | CI7: 84 | CJ7: 85 | CK7: 86 | CL7: 87 | CM7: 88 | CN7: 89 | CO7: 90 | CP7: 91 | CQ7: 92 | CR7: 93 | CS7: 94 | CT7: 95 | CU7: 96 | CV7: 97 | CW7: 98 | CX7: 99 | CY7: 100 | CZ7: 101 | DA7: 102 | DB7: 103 | DC7: 104 | DD7: 105 | DE7: 106
B8: Meses vivos | D8: 3 | E8: 3 | F8: 3 | G8: 3 | H8: 3 | I8: 3 | J8: 3 | K8: 3 | L8: 3 | M8: 3 | N8: 3 | O8: 3 | P8: 3 | Q8: 3 | R8: 3 | S8: 3 | T8: 3 | U8: 3 | V8: 3 | W8: 3 | X8: 3 | Y8: 3 | Z8: 3 | AA8: 3 | AB8: 3 | AC8: 3 | AD8: 3 | AE8: 3 | AF8: 3 | AG8: 3 | AH8: 3 | AI8: 3 | AJ8: 3 | AK8: 3 | AL8: 3 | AM8: 3 | AN8: 3 | AO8: 3 | AP8: 3 | AQ8: 3 | AR8: 3 | AS8: 3 | AT8: 3 | AU8: 3 | AV8: 3 | AW8: 3 | AX8: 3 | AY8: 3 | AZ8: 3 | BA8: 3 | BB8: 3 | BC8: 3 | BD8: 3 | BE8: 3 | BF8: 3 | BG8: 3 | BH8: 3 | BI8: 3 | BJ8: 3 | BK8: 3 | BL8: 3 | BM8: 3 | BN8: 3 | BO8: 3 | BP8: 3 | BQ8: 3 | BR8: 3 | BS8: 3 | BT8: 3 | BU8: 3 | BV8: 3 | BW8: 3 | BX8: 3 | BY8: 3 | BZ8: 3 | CA8: 3 | CB8: 3 | CC8: 3 | CD8: 3 | CE8: 3 | CF8: 3 | CG8: 3 | CH8: 3 | CI8: 3 | CJ8: 3 | CK8: 3 | CL8: 3 | CM8: 3 | CN8: 3 | CO8: 3 | CP8: 3 | CQ8: 3 | CR8: 3 | CS8: 3 | CT8: 3 | CU8: 3 | CV8: 3 | CW8: 3 | CX8: 3 | CY8: 3 | CZ8: 3 | DA8: 3 | DB8: 3 | DC8: 3 | DD8: 3 | DE8: 0
B9: Ingreso tarifario | D9: =SUMPRODUCT((Ingresos!$D$8:$LI$8=D7+0)*Ingresos!$D$14:$LI$14) | E9: =SUMPRODUCT((Ingresos!$D$8:$LI$8=E7+0)*Ingresos!$D$14:$LI$14) | F9: =SUMPRODUCT((Ingresos!$D$8:$LI$8=F7+0)*Ingresos!$D$14:$LI$14) | G9: =SUMPRODUCT((Ingresos!$D$8:$LI$8=G7+0)*Ingresos!$D$14:$LI$14) | H9: =SUMPRODUCT((Ingresos!$D$8:$LI$8=H7+0)*Ingresos!$D$14:$LI$14) | I9: =SUMPRODUCT((Ingresos!$D$8:$LI$8=I7+0)*Ingresos!$D$14:$LI$14) | J9: =SUMPRODUCT((Ingresos!$D$8:$LI$8=J7+0)*Ingresos!$D$14:$LI$14) | K9: =SUMPRODUCT((Ingresos!$D$8:$LI$8=K7+0)*Ingresos!$D$14:$LI$14) | ... DE9: =SUMPRODUCT((Ingresos!$D$8:$LI$8=DE7+0)*Ingresos!$D$14:$LI$14)
B10: Supervision del regulador | D10: =-p_superv*D9 | E10: =-p_superv*E9 | F10: =-p_superv*F9 | G10: =-p_superv*G9 | H10: =-p_superv*H9 | I10: =-p_superv*I9 | J10: =-p_superv*J9 | K10: =-p_superv*K9 | ... DE10: =-p_superv*DE9
B11: Costo fijo (del motor) | D11: 0 | E11: 0 | F11: 0 | G11: 0 | H11: 0 | I11: 0 | J11: 0 | K11: 0 | L11: 0 | M11: 0 | N11: 0 | O11: 0 | P11: 0 | Q11: 0 | R11: 0 | S11: 0 | T11: -2185.32 | U11: -2196.17 | V11: -2207.07 | W11: -2218.02 | X11: -2229.03 | Y11: -2240.1 | Z11: -2251.21 | AA11: -2262.38 | AB11: -2273.61 | AC11: -2284.89 | AD11: -2296.23 | AE11: -2307.63 | AF11: -2319.08 | AG11: -2330.59 | AH11: -2342.16 | AI11: -2353.78 | AJ11: -2365.47 | AK11: -2377.2 | AL11: -2389 | AM11: -2400.87 | AN11: -2412.78 | AO11: -2424.75 | AP11: -2436.78 | AQ11: -2448.88 | AR11: -2461.03 | AS11: -2473.24 | AT11: -2485.52 | AU11: -2497.85 | AV11: -2510.25 | AW11: -2522.71 | AX11: -2535.23 | AY11: -2547.81 | AZ11: -2560.45 | BA11: -2573.17 | BB11: -2585.94 | BC11: -2598.77 | BD11: -2611.66 | BE11: -2624.62 | BF11: -2637.66 | BG11: -2650.74 | BH11: -2663.89 | BI11: -2677.12 | BJ11: -2690.4 | BK11: -2703.76 | BL11: -2717.17 | BM11: -2730.66 | BN11: -2744.22 | BO11: -2757.83 | BP11: -2771.52 | BQ11: -2785.27 | BR11: -2799.09 | BS11: -2812.99 | BT11: -2826.95 | BU11: -2840.98 | BV11: -2855.07 | BW11: -2869.25 | BX11: -2883.49 | BY11: -2897.8 | BZ11: -2912.19 | CA11: -2926.62 | CB11: -2941.15 | CC11: -2955.76 | CD11: -2970.43 | CE11: -2985.16 | CF11: -2999.97 | CG11: -3014.88 | CH11: -3029.83 | CI11: -3044.87 | CJ11: -3059.98 | CK11: -3075.16 | CL11: -3090.42 | CM11: -3105.76 | CN11: -3121.18 | CO11: -3136.67 | CP11: -3152.23 | CQ11: -3167.88 | CR11: -3183.6 | CS11: -3199.41 | CT11: -3215.28 | CU11: -3231.24 | CV11: -3247.27 | CW11: -3263.39 | CX11: -3279.58 | CY11: -3295.86 | CZ11: -3312.22 | DA11: -3328.65 | DB11: -3345.18 | DC11: -3361.77 | DD11: 0 | DE11: 0
B12: Costo variable (del motor) | D12: 0 | E12: 0 | F12: 0 | G12: 0 | H12: 0 | I12: 0 | J12: 0 | K12: 0 | L12: 0 | M12: 0 | N12: 0 | O12: 0 | P12: 0 | Q12: 0 | R12: 0 | S12: 0 | T12: -4129.23 | U12: -4195.86 | V12: -4216.68 | W12: -4237.62 | X12: -4258.65 | Y12: -4319.01 | Z12: -4340.44 | AA12: -4361.99 | AB12: -4383.63 | AC12: -4437.39 | AD12: -4459.42 | AE12: -4481.56 | AF12: -4503.79 | AG12: -4558.8 | AH12: -4581.42 | AI12: -4604.16 | AJ12: -4627 | AK12: -4683.28 | AL12: -4706.52 | AM12: -4729.87 | AN12: -4753.36 | AO12: -4810.9 | AP12: -4834.79 | AQ12: -4858.78 | AR12: -4882.9 | AS12: -5115.01 | AT12: -5140.39 | AU12: -5165.91 | AV12: -5191.54 | AW12: -5261.49 | AX12: -5287.6 | AY12: -5313.85 | AZ12: -5340.22 | BA12: -5411.77 | BB12: -5438.64 | BC12: -5465.62 | BD12: -5492.76 | BE12: -5575.17 | BF12: -5602.84 | BG12: -5630.64 | BH12: -5658.58 | BI12: -5733.55 | BJ12: -5762.01 | BK12: -5790.61 | BL12: -5819.34 | BM12: -5905.6 | BN12: -5934.91 | BO12: -5964.36 | BP12: -5993.97 | BQ12: -6072.48 | BR12: -6102.63 | BS12: -6132.91 | BT12: -6163.35 | BU12: -6253.64 | BV12: -6284.68 | BW12: -6315.87 | BX12: -6347.21 | BY12: -6439.6 | BZ12: -6471.57 | CA12: -6503.68 | CB12: -6535.96 | CC12: -6630.51 | CD12: -6663.41 | CE12: -6696.49 | CF12: -6729.72 | CG12: -6826.48 | CH12: -6860.35 | CI12: -6894.4 | CJ12: -6928.62 | CK12: -7027.63 | CL12: -7062.49 | CM12: -7097.55 | CN12: -7132.78 | CO12: -7234.08 | CP12: -7269.99 | CQ12: -7306.07 | CR12: -7342.32 | CS12: -7457.2 | CT12: -7494.21 | CU12: -7531.41 | CV12: -7568.79 | CW12: -7686.36 | CX12: -7724.5 | CY12: -7762.83 | CZ12: -7801.36 | DA12: -7840.08 | DB12: -7878.99 | DC12: -7918.09 | DD12: 0 | DE12: 0
B13: Gastos SPV (del motor) | D13: 0 | E13: 0 | F13: 0 | G13: 0 | H13: 0 | I13: 0 | J13: 0 | K13: 0 | L13: 0 | M13: 0 | N13: 0 | O13: 0 | P13: 0 | Q13: 0 | R13: 0 | S13: 0 | T13: -491.07 | U13: -493.5 | V13: -495.94 | W13: -498.4 | X13: -500.88 | Y13: -503.37 | Z13: -505.86 | AA13: -508.38 | AB13: -510.9 | AC13: -513.43 | AD13: -515.98 | AE13: -518.54 | AF13: -521.11 | AG13: -523.7 | AH13: -526.29 | AI13: -528.9 | AJ13: -531.54 | AK13: -534.17 | AL13: -536.83 | AM13: -539.49 | AN13: -542.16 | AO13: -544.86 | AP13: -547.56 | AQ13: -550.28 | AR13: -553.01 | AS13: -555.76 | AT13: -558.51 | AU13: -561.28 | AV13: -564.06 | AW13: -566.87 | AX13: -569.68 | AY13: -572.51 | AZ13: -575.35 | BA13: -578.21 | BB13: -581.07 | BC13: -583.95 | BD13: -586.86 | BE13: -589.78 | BF13: -592.7 | BG13: -595.64 | BH13: -598.59 | BI13: -601.56 | BJ13: -604.56 | BK13: -607.55 | BL13: -610.57 | BM13: -613.6 | BN13: -616.65 | BO13: -619.71 | BP13: -622.78 | BQ13: -625.87 | BR13: -628.97 | BS13: -632.1 | BT13: -635.23 | BU13: -638.39 | BV13: -641.56 | BW13: -644.74 | BX13: -647.94 | BY13: -651.15 | BZ13: -654.39 | CA13: -657.63 | CB13: -660.9 | CC13: -664.18 | CD13: -667.47 | CE13: -670.79 | CF13: -674.12 | CG13: -677.46 | CH13: -680.83 | CI13: -684.2 | CJ13: -687.6 | CK13: -691.02 | CL13: -694.44 | CM13: -697.89 | CN13: -701.35 | CO13: -704.83 | CP13: -708.33 | CQ13: -711.84 | CR13: -715.38 | CS13: -718.93 | CT13: -722.49 | CU13: -726.09 | CV13: -729.69 | CW13: -733.31 | CX13: -736.94 | CY13: -740.61 | CZ13: -744.27 | DA13: -747.97 | DB13: -751.69 | DC13: -755.42 | DD13: 0 | DE13: 0
B14: Seguros (del motor) | D14: 0 | E14: 0 | F14: 0 | G14: 0 | H14: 0 | I14: 0 | J14: 0 | K14: 0 | L14: 0 | M14: 0 | N14: 0 | O14: 0 | P14: 0 | Q14: 0 | R14: 0 | S14: 0 | T14: -178.20478 | U14: -178.20478 | V14: -178.20478 | W14: -178.20478 | X14: -178.20478 | Y14: -178.20478 | Z14: -178.20478 | AA14: -178.20478 | AB14: -178.20478 | AC14: -178.20478 | AD14: -178.20478 | AE14: -178.20478 | AF14: -178.20478 | AG14: -178.20478 | AH14: -178.20478 | AI14: -178.20478 | AJ14: -178.20478 | AK14: -178.20478 | AL14: -178.20478 | AM14: -178.20478 | AN14: -178.20478 | AO14: -178.20478 | AP14: -178.20478 | AQ14: -178.20478 | AR14: -178.20478 | AS14: -178.20478 | AT14: -178.20478 | AU14: -178.20478 | AV14: -178.20478 | AW14: -178.20478 | AX14: -178.20478 | AY14: -178.20478 | AZ14: -178.20478 | BA14: -178.20478 | BB14: -178.20478 | BC14: -178.20478 | BD14: -178.20478 | BE14: -178.20478 | BF14: -178.20478 | BG14: -178.20478 | BH14: -178.20478 | BI14: -178.20478 | BJ14: -178.20478 | BK14: -178.20478 | BL14: -178.20478 | BM14: -178.20478 | BN14: -178.20478 | BO14: -178.20478 | BP14: -178.20478 | BQ14: -178.20478 | BR14: -178.20478 | BS14: -178.20478 | BT14: -178.20478 | BU14: -178.20478 | BV14: -178.20478 | BW14: -178.20478 | BX14: -178.20478 | BY14: -178.20478 | BZ14: -178.20478 | CA14: -178.20478 | CB14: -178.20478 | CC14: -178.20478 | CD14: -178.20478 | CE14: -178.20478 | CF14: -178.20478 | CG14: -178.20478 | CH14: -178.20478 | CI14: -178.20478 | CJ14: -178.20478 | CK14: -178.20478 | CL14: -178.20478 | CM14: -178.20478 | CN14: -178.20478 | CO14: -178.20478 | CP14: -178.20478 | CQ14: -178.20478 | CR14: -178.20478 | CS14: -178.20478 | CT14: -178.20478 | CU14: -178.20478 | CV14: -178.20478 | CW14: -178.20478 | CX14: -178.20478 | CY14: -178.20478 | CZ14: -178.20478 | DA14: -178.20478 | DB14: -178.20478 | DC14: -178.20478 | DD14: 0 | DE14: 0
B15: Fianzas (del motor) | D15: 0 | E15: 0 | F15: 0 | G15: 0 | H15: 0 | I15: 0 | J15: 0 | K15: 0 | L15: 0 | M15: 0 | N15: 0 | O15: 0 | P15: 0 | Q15: 0 | R15: 0 | S15: 0 | T15: -191.57902 | U15: -191.57902 | V15: -191.57902 | W15: -191.57902 | X15: -191.57902 | Y15: -191.57902 | Z15: -191.57902 | AA15: -191.57902 | AB15: -52.323497 | AC15: -52.323497 | AD15: -52.323497 | AE15: -52.323497 | AF15: -52.323497 | AG15: -52.323497 | AH15: -52.323497 | AI15: -52.323497 | AJ15: -52.323497 | AK15: -52.323497 | AL15: -52.323497 | AM15: -52.323497 | AN15: -52.323497 | AO15: -52.323497 | AP15: -52.323497 | AQ15: -52.323497 | AR15: -52.323497 | AS15: -52.323497 | AT15: -52.323497 | AU15: -52.323497 | AV15: -52.323497 | AW15: -52.323497 | AX15: -52.323497 | AY15: -52.323497 | AZ15: -52.323497 | BA15: -52.323497 | BB15: -52.323497 | BC15: -52.323497 | BD15: -52.323497 | BE15: -52.323497 | BF15: -52.323497 | BG15: -52.323497 | BH15: -52.323497 | BI15: -52.323497 | BJ15: -52.323497 | BK15: -52.323497 | BL15: -52.323497 | BM15: -52.323497 | BN15: -52.323497 | BO15: -52.323497 | BP15: -52.323497 | BQ15: -52.323497 | BR15: -52.323497 | BS15: -52.323497 | BT15: -52.323497 | BU15: -52.323497 | BV15: -52.323497 | BW15: -52.323497 | BX15: -52.323497 | BY15: -52.323497 | BZ15: -52.323497 | CA15: -52.323497 | CB15: -52.323497 | CC15: -52.323497 | CD15: -52.323497 | CE15: -52.323497 | CF15: -52.323497 | CG15: -52.323497 | CH15: -52.323497 | CI15: -52.323497 | CJ15: -52.323497 | CK15: -52.323497 | CL15: -52.323497 | CM15: -52.323497 | CN15: -52.323497 | CO15: -52.323497 | CP15: -52.323497 | CQ15: -52.323497 | CR15: -52.323497 | CS15: -52.323497 | CT15: -52.323497 | CU15: -52.323497 | CV15: -52.323497 | CW15: -52.323497 | CX15: -52.323497 | CY15: -52.323497 | CZ15: -52.323497 | DA15: -52.323497 | DB15: -52.323497 | DC15: -52.323497 | DD15: -418.58798 | DE15: 0
B16: Gastos de promocion (del motor) | D16: 0 | E16: 0 | F16: 0 | G16: 0 | H16: 0 | I16: 0 | J16: 0 | K16: 0 | L16: 0 | M16: 0 | N16: 0 | O16: 0 | P16: 0 | Q16: 0 | R16: 0 | S16: 0 | T16: 0 | U16: 0 | V16: 0 | W16: 0 | X16: 0 | Y16: 0 | Z16: 0 | AA16: 0 | AB16: 0 | AC16: 0 | AD16: 0 | AE16: 0 | AF16: 0 | AG16: 0 | AH16: 0 | AI16: 0 | AJ16: 0 | AK16: 0 | AL16: 0 | AM16: 0 | AN16: 0 | AO16: 0 | AP16: 0 | AQ16: 0 | AR16: 0 | AS16: 0 | AT16: 0 | AU16: 0 | AV16: 0 | AW16: 0 | AX16: 0 | AY16: 0 | AZ16: 0 | BA16: 0 | BB16: 0 | BC16: 0 | BD16: 0 | BE16: 0 | BF16: 0 | BG16: 0 | BH16: 0 | BI16: 0 | BJ16: 0 | BK16: 0 | BL16: 0 | BM16: 0 | BN16: 0 | BO16: 0 | BP16: 0 | BQ16: 0 | BR16: 0 | BS16: 0 | BT16: 0 | BU16: 0 | BV16: 0 | BW16: 0 | BX16: 0 | BY16: 0 | BZ16: 0 | CA16: 0 | CB16: 0 | CC16: 0 | CD16: 0 | CE16: 0 | CF16: 0 | CG16: 0 | CH16: 0 | CI16: 0 | CJ16: 0 | CK16: 0 | CL16: 0 | CM16: 0 | CN16: 0 | CO16: 0 | CP16: 0 | CQ16: 0 | CR16: 0 | CS16: 0 | CT16: 0 | CU16: 0 | CV16: 0 | CW16: 0 | CX16: 0 | CY16: 0 | CZ16: 0 | DA16: 0 | DB16: 0 | DC16: 0 | DD16: 0 | DE16: 0
B17: Fideicomiso (del motor) | D17: 0 | E17: 0 | F17: 0 | G17: 0 | H17: 0 | I17: 0 | J17: 0 | K17: 0 | L17: 0 | M17: 0 | N17: 0 | O17: 0 | P17: 0 | Q17: 0 | R17: 0 | S17: 0 | T17: -25 | U17: -25 | V17: -25 | W17: -25 | X17: -25 | Y17: -25 | Z17: -25 | AA17: -25 | AB17: -25 | AC17: -25 | AD17: -25 | AE17: -25 | AF17: -25 | AG17: -25 | AH17: -25 | AI17: -25 | AJ17: -25 | AK17: -25 | AL17: -25 | AM17: -25 | AN17: -25 | AO17: -25 | AP17: -25 | AQ17: -25 | AR17: -25 | AS17: -25 | AT17: -25 | AU17: -25 | AV17: -25 | AW17: -25 | AX17: -25 | AY17: -25 | AZ17: -25 | BA17: -25 | BB17: -25 | BC17: -25 | BD17: -25 | BE17: -25 | BF17: -25 | BG17: -25 | BH17: -25 | BI17: -25 | BJ17: -25 | BK17: -25 | BL17: -25 | BM17: -25 | BN17: -25 | BO17: -25 | BP17: -25 | BQ17: -25 | BR17: -25 | BS17: -25 | BT17: -25 | BU17: -25 | BV17: -25 | BW17: -25 | BX17: -25 | BY17: -25 | BZ17: -25 | CA17: -25 | CB17: -25 | CC17: -25 | CD17: -25 | CE17: -25 | CF17: -25 | CG17: -25 | CH17: -25 | CI17: -25 | CJ17: -25 | CK17: -25 | CL17: -25 | CM17: -25 | CN17: -25 | CO17: -25 | CP17: -25 | CQ17: -25 | CR17: -25 | CS17: -25 | CT17: -25 | CU17: -25 | CV17: -25 | CW17: -25 | CX17: -25 | CY17: -25 | CZ17: -25 | DA17: -25 | DB17: -25 | DC17: -25 | DD17: -200 | DE17: 0
B18: Amortizacion del intangible (no es caja) | D18: =SUMPRODUCT(('Activo intangible'!$D$10:$LI$10=D7+0),'Activo intangible'!$D$17:$LI$17) | E18: =SUMPRODUCT(('Activo intangible'!$D$10:$LI$10=E7+0),'Activo intangible'!$D$17:$LI$17) | F18: =SUMPRODUCT(('Activo intangible'!$D$10:$LI$10=F7+0),'Activo intangible'!$D$17:$LI$17) | G18: =SUMPRODUCT(('Activo intangible'!$D$10:$LI$10=G7+0),'Activo intangible'!$D$17:$LI$17) | H18: =SUMPRODUCT(('Activo intangible'!$D$10:$LI$10=H7+0),'Activo intangible'!$D$17:$LI$17) | I18: =SUMPRODUCT(('Activo intangible'!$D$10:$LI$10=I7+0),'Activo intangible'!$D$17:$LI$17) | J18: =SUMPRODUCT(('Activo intangible'!$D$10:$LI$10=J7+0),'Activo intangible'!$D$17:$LI$17) | K18: =SUMPRODUCT(('Activo intangible'!$D$10:$LI$10=K7+0),'Activo intangible'!$D$17:$LI$17) | ... DE18: =SUMPRODUCT(('Activo intangible'!$D$10:$LI$10=DE7+0),'Activo intangible'!$D$17:$LI$17)
B19: Intereses de operacion | D19: 0 | E19: 0 | F19: 0 | G19: 0 | H19: 0 | I19: 0 | J19: 0 | K19: 0 | L19: 0 | M19: 0 | N19: 0 | O19: 0 | P19: 0 | Q19: 0 | R19: 0 | S19: 0 | T19: 5773.8537 | U19: 5708.3639 | V19: 5641.2807 | W19: 5572.5655 | X19: 5502.1783 | Y19: 5430.0787 | Z19: 5356.2249 | AA19: 5280.5742 | AB19: 5203.0829 | AC19: 5123.7063 | AD19: 5042.3984 | AE19: 4959.1123 | AF19: 4873.7999 | AG19: 4786.4118 | AH19: 4696.8976 | AI19: 4605.2054 | AJ19: 4511.2825 | AK19: 4415.0743 | AL19: 4316.5255 | AM19: 4215.5789 | AN19: 4112.1763 | AO19: 4006.258 | AP19: 3897.7626 | AQ19: 3786.6276 | AR19: 3672.7886 | AS19: 3556.1799 | AT19: 3436.7342 | AU19: 3314.3823 | AV19: 3189.0536 | AW19: 3060.6757 | AX19: 2929.1743 | AY19: 2794.4736 | AZ19: 2656.4955 | BA19: 2515.1605 | BB19: 2370.3867 | BC19: 2222.0906 | BD19: 2070.1865 | BE19: 1914.5866 | BF19: 1755.2009 | BG19: 1591.9374 | BH19: 1424.7016 | BI19: 1253.3971 | BJ19: 1077.9246 | BK19: 898.183 | BL19: 714.06823 | BM19: 525.47396 | BN19: 332.29119 | BO19: 134.40829 | BP19: -6.7932924e-12 | BQ19: -6.9585731e-12 | BR19: -7.127875e-12 | BS19: -7.3012961e-12 | BT19: -7.4789365e-12 | BU19: -7.6608989e-12 | BV19: -7.8472884e-12 | BW19: -8.0382128e-12 | BX19: -8.2337823e-12 | BY19: -8.4341101e-12 | BZ19: -8.6393118e-12 | CA19: -8.8495061e-12 | CB19: -9.0648144e-12 | CC19: -9.2853612e-12 | CD19: -9.5112738e-12 | CE19: -9.7426829e-12 | CF19: -9.9797222e-12 | CG19: -1.0222529e-11 | CH19: -1.0471243e-11 | CI19: -1.0726008e-11 | CJ19: -1.0986971e-11 | CK19: -1.1254284e-11 | CL19: -1.1528101e-11 | CM19: -1.1808579e-11 | CN19: -1.2095882e-11 | CO19: -1.2390174e-11 | CP19: -1.2691627e-11 | CQ19: -1.3000414e-11 | CR19: -1.3316714e-11 | CS19: -1.3640709e-11 | CT19: -1.3972587e-11 | CU19: -1.431254e-11 | CV19: -1.4660764e-11 | CW19: -1.501746e-11 | CX19: -1.5382834e-11 | CY19: -1.5757098e-11 | CZ19: -1.6140468e-11 | DA19: -1.6533166e-11 | DB19: -1.6935417e-11 | DC19: -1.7347456e-11 | DD19: 0 | DE19: 0
B20: Utilidad antes de impuestos | D20: =D9+D10+SUM(D11:D17)-D18-D19 | E20: =E9+E10+SUM(E11:E17)-E18-E19 | F20: =F9+F10+SUM(F11:F17)-F18-F19 | G20: =G9+G10+SUM(G11:G17)-G18-G19 | H20: =H9+H10+SUM(H11:H17)-H18-H19 | I20: =I9+I10+SUM(I11:I17)-I18-I19 | J20: =J9+J10+SUM(J11:J17)-J18-J19 | K20: =K9+K10+SUM(K11:K17)-K18-K19 | ... DE20: =DE9+DE10+SUM(DE11:DE17)-DE18-DE19
B21: Participacion e Impuesto a la Renta (del motor) | D21: 0 | E21: 0 | F21: 0 | G21: 0 | H21: 0 | I21: 0 | J21: 0 | K21: 0 | L21: 0 | M21: 0 | N21: 0 | O21: 0 | P21: 0 | Q21: 0 | R21: 0 | S21: 0 | T21: 0 | U21: 0 | V21: 0 | W21: 0 | X21: 0 | Y21: 0 | Z21: 0 | AA21: 0 | AB21: 0 | AC21: 0 | AD21: 0 | AE21: 0 | AF21: -251.25602 | AG21: 0 | AH21: 0 | AI21: 0 | AJ21: -2312.165 | AK21: 0 | AL21: 0 | AM21: 0 | AN21: -3383.812 | AO21: 0 | AP21: 0 | AQ21: 0 | AR21: -4526.2978 | AS21: 0 | AT21: 0 | AU21: 0 | AV21: -6576.8624 | AW21: 0 | AX21: 0 | AY21: 0 | AZ21: -7943.9896 | BA21: 0 | BB21: 0 | BC21: 0 | BD21: -9403.7459 | BE21: 0 | BF21: 0 | BG21: 0 | BH21: -11163.965 | BI21: 0 | BJ21: 0 | BK21: 0 | BL21: -12844.881 | BM21: 0 | BN21: 0 | BO21: 0 | BP21: -14669.61 | BQ21: 0 | BR21: 0 | BS21: 0 | BT21: -15828.646 | BU21: 0 | BV21: 0 | BW21: 0 | BX21: -16739.248 | BY21: 0 | BZ21: 0 | CA21: 0 | CB21: -17682.342 | CC21: 0 | CD21: 0 | CE21: 0 | CF21: -18658.776 | CG21: 0 | CH21: 0 | CI21: 0 | CJ21: -19869.958 | CK21: 0 | CL21: 0 | CM21: 0 | CN21: -20930.951 | CO21: 0 | CP21: 0 | CQ21: 0 | CR21: -22029.212 | CS21: 0 | CT21: 0 | CU21: 0 | CV21: -23225.656 | CW21: 0 | CX21: 0 | CY21: 0 | CZ21: -24465.08 | DA21: 0 | DB21: 0 | DC21: 0 | DD21: -18629.404 | DE21: 0
B22: CAPEX de caja | D22: -12746.071 | E22: -4330.3462 | F22: -4376.8374 | G22: -4150.0001 | H22: -149.83406 | I22: -150.24664 | J22: -25 | K22: -60034.293 | L22: -19270.005 | M22: -47783.897 | N22: -47384.719 | O22: -40590.904 | P22: -42859.785 | Q22: -6540.4886 | R22: -2007.4789 | S22: -595.11193 | T22: 0 | U22: 0 | V22: 0 | W22: 0 | X22: 0 | Y22: 0 | Z22: 0 | AA22: 0 | AB22: 0 | AC22: 0 | AD22: 0 | AE22: 0 | AF22: 0 | AG22: 0 | AH22: 0 | AI22: 0 | AJ22: 0 | AK22: 0 | AL22: 0 | AM22: 0 | AN22: 0 | AO22: 0 | AP22: 0 | AQ22: 0 | AR22: 0 | AS22: 0 | AT22: 0 | AU22: 0 | AV22: 0 | AW22: 0 | AX22: 0 | AY22: 0 | AZ22: 0 | BA22: 0 | BB22: 0 | BC22: 0 | BD22: 0 | BE22: 0 | BF22: 0 | BG22: 0 | BH22: 0 | BI22: 0 | BJ22: 0 | BK22: 0 | BL22: 0 | BM22: 0 | BN22: 0 | BO22: 0 | BP22: 0 | BQ22: 0 | BR22: 0 | BS22: 0 | BT22: 0 | BU22: 0 | BV22: 0 | BW22: 0 | BX22: 0 | BY22: 0 | BZ22: 0 | CA22: 0 | CB22: 0 | CC22: 0 | CD22: 0 | CE22: 0 | CF22: 0 | CG22: 0 | CH22: 0 | CI22: 0 | CJ22: 0 | CK22: 0 | CL22: 0 | CM22: 0 | CN22: 0 | CO22: 0 | CP22: 0 | CQ22: 0 | CR22: 0 | CS22: 0 | CT22: 0 | CU22: 0 | CV22: 0 | CW22: 0 | CX22: 0 | CY22: 0 | CZ22: 0 | DA22: 0 | DB22: 0 | DC22: 0 | DD22: 0 | DE22: 0
B23: Efecto neto del IGV | D23: -258.96443 | E23: -1.2852227 | F23: -2.7916012 | G23: 13.632703 | H23: 240.40614 | I23: 7.5024074 | J23: 0 | K23: -1127.8959 | L23: -5.59767 | M23: -1718.1934 | N23: 37.712467 | O23: 457.43208 | P23: -313.07405 | Q23: 2381.6044 | R23: 253.94072 | S23: -0.16909372 | T23: 35.740432 | U23: 0 | V23: 0 | W23: 0 | X23: 0 | Y23: 0 | Z23: 0 | AA23: 0 | AB23: 0 | AC23: 0 | AD23: 0 | AE23: 0 | AF23: 0 | AG23: 0 | AH23: 0 | AI23: 0 | AJ23: 0 | AK23: 0 | AL23: 0 | AM23: 0 | AN23: 0 | AO23: 0 | AP23: 0 | AQ23: 0 | AR23: 0 | AS23: 0 | AT23: 0 | AU23: 0 | AV23: 0 | AW23: 0 | AX23: 0 | AY23: 0 | AZ23: 0 | BA23: 0 | BB23: 0 | BC23: 0 | BD23: 0 | BE23: 0 | BF23: 0 | BG23: 0 | BH23: 0 | BI23: 0 | BJ23: 0 | BK23: 0 | BL23: 0 | BM23: 0 | BN23: 0 | BO23: 0 | BP23: 0 | BQ23: 0 | BR23: 0 | BS23: 0 | BT23: 0 | BU23: 0 | BV23: 0 | BW23: 0 | BX23: 0 | BY23: 0 | BZ23: 0 | CA23: 0 | CB23: 0 | CC23: 0 | CD23: 0 | CE23: 0 | CF23: 0 | CG23: 0 | CH23: 0 | CI23: 0 | CJ23: 0 | CK23: 0 | CL23: 0 | CM23: 0 | CN23: 0 | CO23: 0 | CP23: 0 | CQ23: 0 | CR23: 0 | CS23: 0 | CT23: 0 | CU23: 0 | CV23: 0 | CW23: 0 | CX23: 0 | CY23: 0 | CZ23: 0 | DA23: 0 | DB23: 0 | DC23: 0 | DD23: 0 | DE23: 0
B24: Desembolsos de deuda | D24: 0 | E24: 0 | F24: 0 | G24: 0 | H24: 0 | I24: 0 | J24: 0 | K24: 44327.128 | L24: 15088.341 | M24: 37959.834 | N24: 37715.894 | O24: 32348.991 | P24: 34229.775 | Q24: 5205.3258 | R24: 1584.7744 | S24: 455.78674 | T24: 0 | U24: 0 | V24: 0 | W24: 0 | X24: 0 | Y24: 0 | Z24: 0 | AA24: 0 | AB24: 0 | AC24: 0 | AD24: 0 | AE24: 0 | AF24: 0 | AG24: 0 | AH24: 0 | AI24: 0 | AJ24: 0 | AK24: 0 | AL24: 0 | AM24: 0 | AN24: 0 | AO24: 0 | AP24: 0 | AQ24: 0 | AR24: 0 | AS24: 0 | AT24: 0 | AU24: 0 | AV24: 0 | AW24: 0 | AX24: 0 | AY24: 0 | AZ24: 0 | BA24: 0 | BB24: 0 | BC24: 0 | BD24: 0 | BE24: 0 | BF24: 0 | BG24: 0 | BH24: 0 | BI24: 0 | BJ24: 0 | BK24: 0 | BL24: 0 | BM24: 0 | BN24: 0 | BO24: 0 | BP24: 0 | BQ24: 0 | BR24: 0 | BS24: 0 | BT24: 0 | BU24: 0 | BV24: 0 | BW24: 0 | BX24: 0 | BY24: 0 | BZ24: 0 | CA24: 0 | CB24: 0 | CC24: 0 | CD24: 0 | CE24: 0 | CF24: 0 | CG24: 0 | CH24: 0 | CI24: 0 | CJ24: 0 | CK24: 0 | CL24: 0 | CM24: 0 | CN24: 0 | CO24: 0 | CP24: 0 | CQ24: 0 | CR24: 0 | CS24: 0 | CT24: 0 | CU24: 0 | CV24: 0 | CW24: 0 | CX24: 0 | CY24: 0 | CZ24: 0 | DA24: 0 | DB24: 0 | DC24: 0 | DD24: 0 | DE24: 0
B25: Servicio de deuda | D25: 0 | E25: 0 | F25: 0 | G25: 0 | H25: 0 | I25: 0 | J25: 0 | K25: 0 | L25: 0 | M25: 0 | N25: 0 | O25: 0 | P25: 0 | Q25: 0 | R25: 0 | S25: 0 | T25: -8465.5858 | U25: -8465.5858 | V25: -8465.5858 | W25: -8465.5858 | X25: -8465.5858 | Y25: -8465.5858 | Z25: -8465.5858 | AA25: -8465.5858 | AB25: -8465.5858 | AC25: -8465.5858 | AD25: -8465.5858 | AE25: -8465.5858 | AF25: -8465.5858 | AG25: -8465.5858 | AH25: -8465.5858 | AI25: -8465.5858 | AJ25: -8465.5858 | AK25: -8465.5858 | AL25: -8465.5858 | AM25: -8465.5858 | AN25: -8465.5858 | AO25: -8465.5858 | AP25: -8465.5858 | AQ25: -8465.5858 | AR25: -8465.5858 | AS25: -8465.5858 | AT25: -8465.5858 | AU25: -8465.5858 | AV25: -8465.5858 | AW25: -8465.5858 | AX25: -8465.5858 | AY25: -8465.5858 | AZ25: -8465.5858 | BA25: -8465.5858 | BB25: -8465.5858 | BC25: -8465.5858 | BD25: -8465.5858 | BE25: -8465.5858 | BF25: -8465.5858 | BG25: -8465.5858 | BH25: -8465.5858 | BI25: -8465.5858 | BJ25: -8465.5858 | BK25: -8465.5858 | BL25: -8465.5858 | BM25: -8465.5858 | BN25: -8465.5858 | BO25: -8465.5858 | BP25: 0 | BQ25: 0 | BR25: 0 | BS25: 0 | BT25: 0 | BU25: 0 | BV25: 0 | BW25: 0 | BX25: 0 | BY25: 0 | BZ25: 0 | CA25: 0 | CB25: 0 | CC25: 0 | CD25: 0 | CE25: 0 | CF25: 0 | CG25: 0 | CH25: 0 | CI25: 0 | CJ25: 0 | CK25: 0 | CL25: 0 | CM25: 0 | CN25: 0 | CO25: 0 | CP25: 0 | CQ25: 0 | CR25: 0 | CS25: 0 | CT25: 0 | CU25: 0 | CV25: 0 | CW25: 0 | CX25: 0 | CY25: 0 | CZ25: 0 | DA25: 0 | DB25: 0 | DC25: 0 | DD25: 0 | DE25: 0
B26: Flujo de caja financiero | D26: =D9+D10+SUM(D11:D17)+D21+SUM(D22:D25) | E26: =E9+E10+SUM(E11:E17)+E21+SUM(E22:E25) | F26: =F9+F10+SUM(F11:F17)+F21+SUM(F22:F25) | G26: =G9+G10+SUM(G11:G17)+G21+SUM(G22:G25) | H26: =H9+H10+SUM(H11:H17)+H21+SUM(H22:H25) | I26: =I9+I10+SUM(I11:I17)+I21+SUM(I22:I25) | J26: =J9+J10+SUM(J11:J17)+J21+SUM(J22:J25) | K26: =K9+K10+SUM(K11:K17)+K21+SUM(K22:K25) | ... DE26: =DE9+DE10+SUM(DE11:DE17)+DE21+SUM(DE22:DE25)
B27: Factor de actualizacion | D27: =IF(D8=0,0,1/(1+(1+p_ke)^(1/12)-1)^SUM($D8:D8)) | E27: =IF(E8=0,0,1/(1+(1+p_ke)^(1/12)-1)^SUM($D8:E8)) | F27: =IF(F8=0,0,1/(1+(1+p_ke)^(1/12)-1)^SUM($D8:F8)) | G27: =IF(G8=0,0,1/(1+(1+p_ke)^(1/12)-1)^SUM($D8:G8)) | H27: =IF(H8=0,0,1/(1+(1+p_ke)^(1/12)-1)^SUM($D8:H8)) | I27: =IF(I8=0,0,1/(1+(1+p_ke)^(1/12)-1)^SUM($D8:I8)) | J27: =IF(J8=0,0,1/(1+(1+p_ke)^(1/12)-1)^SUM($D8:J8)) | K27: =IF(K8=0,0,1/(1+(1+p_ke)^(1/12)-1)^SUM($D8:K8)) | ... DE27: =IF(DE8=0,0,1/(1+(1+p_ke)^(1/12)-1)^SUM($D8:DE8))
B29: VAN financiero | D29: =SUMPRODUCT(D26:DE26,D27:DE27)

Sheet Reparto de la tarifa
B2: Reparto de la tarifa
B3: De lo que recauda la tarifa, cuanto paga la operacion y cuanto repaga la inversion. Las dos partes suman el ingreso.
B6: Ano | D6: =Flujo!D6 | E6: =Flujo!E6 | F6: =Flujo!F6 | G6: =Flujo!G6 | H6: =Flujo!H6 | I6: =Flujo!I6 | J6: =Flujo!J6 | K6: =Flujo!K6 | ... DE6: =Flujo!DE6
B7: Trimestre | D7: =Flujo!D7 | E7: =Flujo!E7 | F7: =Flujo!F7 | G7: =Flujo!G7 | H7: =Flujo!H7 | I7: =Flujo!I7 | J7: =Flujo!J7 | K7: =Flujo!K7 | ... DE7: =Flujo!DE7
B9: Ingreso tarifario | D9: =Flujo!D9 | E9: =Flujo!E9 | F9: =Flujo!F9 | G9: =Flujo!G9 | H9: =Flujo!H9 | I9: =Flujo!I9 | J9: =Flujo!J9 | K9: =Flujo!K9 | ... DE9: =Flujo!DE9
B10: Costo de operacion y mantenimiento, con supervision | D10: =-(Flujo!D10+SUM(Flujo!D11:D17)) | E10: =-(Flujo!E10+SUM(Flujo!E11:E17)) | F10: =-(Flujo!F10+SUM(Flujo!F11:F17)) | G10: =-(Flujo!G10+SUM(Flujo!G11:G17)) | H10: =-(Flujo!H10+SUM(Flujo!H11:H17)) | I10: =-(Flujo!I10+SUM(Flujo!I11:I17)) | J10: =-(Flujo!J10+SUM(Flujo!J11:J17)) | K10: =-(Flujo!K10+SUM(Flujo!K11:K17)) | ... DE10: =-(Flujo!DE10+SUM(Flujo!DE11:DE17))
B11: Margen del operador | D11: =p_margen_om*D10 | E11: =p_margen_om*E10 | F11: =p_margen_om*F10 | G11: =p_margen_om*G10 | H11: =p_margen_om*H10 | I11: =p_margen_om*I10 | J11: =p_margen_om*J10 | K11: =p_margen_om*K10 | ... DE11: =p_margen_om*DE10
B12: Operacion y mantenimiento | D12: =D10+D11 | E12: =E10+E11 | F12: =F10+F11 | G12: =G10+G11 | H12: =H10+H11 | I12: =I10+I11 | J12: =J10+J11 | K12: =K10+K11 | ... DE12: =DE10+DE11
B13: Disponible para repagar la inversion | D13: =D9-D12 | E13: =E9-E12 | F13: =F9-F12 | G13: =G9-G12 | H13: =H9-H12 | I13: =I9-I12 | J13: =J9-J12 | K13: =K9-K12 | ... DE13: =DE9-DE12
B15: Produccion facturada, kg DBO5 | D15: =SUMPRODUCT((Ingresos!$D$8:$LI$8=D7+0)*Ingresos!$D$9:$LI$9) | E15: =SUMPRODUCT((Ingresos!$D$8:$LI$8=E7+0)*Ingresos!$D$9:$LI$9) | F15: =SUMPRODUCT((Ingresos!$D$8:$LI$8=F7+0)*Ingresos!$D$9:$LI$9) | G15: =SUMPRODUCT((Ingresos!$D$8:$LI$8=G7+0)*Ingresos!$D$9:$LI$9) | H15: =SUMPRODUCT((Ingresos!$D$8:$LI$8=H7+0)*Ingresos!$D$9:$LI$9) | I15: =SUMPRODUCT((Ingresos!$D$8:$LI$8=I7+0)*Ingresos!$D$9:$LI$9) | J15: =SUMPRODUCT((Ingresos!$D$8:$LI$8=J7+0)*Ingresos!$D$9:$LI$9) | K15: =SUMPRODUCT((Ingresos!$D$8:$LI$8=K7+0)*Ingresos!$D$9:$LI$9) | ... DE15: =SUMPRODUCT((Ingresos!$D$8:$LI$8=DE7+0)*Ingresos!$D$9:$LI$9)
B16: Tarifa unitaria del trimestre | D16: =IF(D15=0,0,D9/D15*1000) | E16: =IF(E15=0,0,E9/E15*1000) | F16: =IF(F15=0,0,F9/F15*1000) | G16: =IF(G15=0,0,G9/G15*1000) | H16: =IF(H15=0,0,H9/H15*1000) | I16: =IF(I15=0,0,I9/I15*1000) | J16: =IF(J15=0,0,J9/J15*1000) | K16: =IF(K15=0,0,K9/K15*1000) | ... DE16: =IF(DE15=0,0,DE9/DE15*1000)
B17: de la operacion, con margen | D17: =IF(D15=0,0,D12/D15*1000) | E17: =IF(E15=0,0,E12/E15*1000) | F17: =IF(F15=0,0,F12/F15*1000) | G17: =IF(G15=0,0,G12/G15*1000) | H17: =IF(H15=0,0,H12/H15*1000) | I17: =IF(I15=0,0,I12/I15*1000) | J17: =IF(J15=0,0,J12/J15*1000) | K17: =IF(K15=0,0,K12/K15*1000) | ... DE17: =IF(DE15=0,0,DE12/DE15*1000)
B18: de la inversion | D18: =IF(D15=0,0,D13/D15*1000) | E18: =IF(E15=0,0,E13/E15*1000) | F18: =IF(F15=0,0,F13/F15*1000) | G18: =IF(G15=0,0,G13/G15*1000) | H18: =IF(H15=0,0,H13/H15*1000) | I18: =IF(I15=0,0,I13/I15*1000) | J18: =IF(J15=0,0,J13/J15*1000) | K18: =IF(K15=0,0,K13/K15*1000) | ... DE18: =IF(DE15=0,0,DE13/DE15*1000)
B20: Factor de actualizacion | D20: =Flujo!D27 | E20: =Flujo!E27 | F20: =Flujo!F27 | G20: =Flujo!G27 | H20: =Flujo!H27 | I20: =Flujo!I27 | J20: =Flujo!J27 | K20: =Flujo!K27 | ... DE20: =Flujo!DE27
B22: VAN del ingreso tarifario | D22: =SUMPRODUCT($D$9:$DE$9,$D$20:$DE$20)
B23: VAN del costo de O&M, sin margen | D23: =SUMPRODUCT($D$10:$DE$10,$D$20:$DE$20)
B24: VAN de la operacion, con margen | D24: =SUMPRODUCT($D$12:$DE$12,$D$20:$DE$20)
B25: VAN para la inversion | D25: =SUMPRODUCT($D$13:$DE$13,$D$20:$DE$20)
B26: Participacion de la operacion | D26: =$D$24/$D$22
B27: Participacion de la inversion | D27: =$D$25/$D$22
B28: Las dos partes menos el total, debe ser cero | D28: =$D$24+$D$25-$D$22
B29: Check del reparto | D29: =IF(ROUND($D$28,2)=0,"OK","ERROR")
